Workbook
Name \0: #REF!
Name \0: #REF!
Name \0: #REF!
Name \0: #REF!
Name \0: #REF!
Name \0: #REF!
Name \0: #REF!
Name \0: #REF!
Name \1: #REF!
Name \1: #REF!
Name \1: #REF!
Name \1: #REF!
Name \1: #REF!
Name \1: #REF!
Name \1: #REF!
Name \1: #REF!
Name \a: #REF!
Name \a: #REF!
Name \a: #REF!
Name \a: #REF!
Name \a: #REF!
Name \a: #REF!
Name \a: #REF!
Name \a: #REF!
Name \a: #REF!
Name \a: #REF!
Name \b: #REF!
Name \b: #REF!
Name \b: #REF!
Name \b: #REF!
Name \b: #REF!
Name \b: #REF!
Name \b: #REF!
Name \b: #REF!
Name \b: #REF!
Name \b: #REF!
Name \b11_567891011: #REF!
Name \b11_567891011: #REF!
Name \b11_567891011: #REF!
Name \b11_567891011: #REF!
Name \b11_567891011: #REF!
Name \b11_567891011: #REF!
Name \b11_567891011: #REF!
Name \b12_567891011: #REF!
Name \b12_567891011: #REF!
Name \b12_567891011: #REF!
Name \b12_567891011: #REF!
Name \b12_567891011: #REF!
Name \b12_567891011: #REF!
Name \b12_567891011: #REF!
Name \b13_567891011: #REF!
Name \b13_567891011: #REF!
Name \b13_567891011: #REF!
Name \b13_567891011: #REF!
Name \b13_567891011: #REF!
Name \b13_567891011: #REF!
Name \b13_567891011: #REF!
Name \b14_567891011: #REF!
Name \b14_567891011: #REF!
Name \b14_567891011: #REF!

Sheet RANK
B2: ="NILAI KINERJA UP3 TOLITOLI S.D "&[0]!A&" 2023" -> #REF!
B4: RANK | C4: UNIT | D4: ="NKO S.D "&[0]!A -> #REF!
B5: 1 | C5: =VLOOKUP(B5,$G$5:$I$9,2,FALSE) -> ULP BANGKIR | D5: =VLOOKUP(B5,$G$5:$I$9,3,FALSE) -> 105.33 | G5: =RANK(I5,$I$5:$I$9) -> 5 | H5: ULP TOLITOLI | I5: =ULP!L58 -> 99.36
B6: 2 | C6: =VLOOKUP(B6,$G$5:$I$9,2,FALSE) -> ULP KOTARAYA | D6: =VLOOKUP(B6,$G$5:$I$9,3,FALSE) -> 103.59 | G6: =RANK(I6,$I$5:$I$9) -> 4 | H6: ULP LEOK | I6: =ULP!W58 -> 99.74
B7: 3 | C7: =VLOOKUP(B7,$G$5:$I$9,2,FALSE) -> ULP MOUTONG | D7: =VLOOKUP(B7,$G$5:$I$9,3,FALSE) -> 100.84 | G7: =RANK(I7,$I$5:$I$9) -> 1 | H7: ULP BANGKIR | I7: =ULP!AH58 -> 105.33
B8: 4 | C8: =VLOOKUP(B8,$G$5:$I$9,2,FALSE) -> ULP LEOK | D8: =VLOOKUP(B8,$G$5:$I$9,3,FALSE) -> 99.74 | G8: =RANK(I8,$I$5:$I$9) -> 3 | H8: ULP MOUTONG | I8: =ULP!AS58 -> 100.84
B9: 5 | C9: =VLOOKUP(B9,$G$5:$I$9,2,FALSE) -> ULP TOLITOLI | D9: =VLOOKUP(B9,$G$5:$I$9,3,FALSE) -> 99.36 | G9: =RANK(I9,$I$5:$I$9) -> 2 | H9: ULP KOTARAYA | I9: =ULP!BD58 -> 103.59
C10: UP3 TOLITOLI | D10: ='UP3'!J70 -> 102.5

Sheet CHECKLIST
B3: NO | C3: KPI | D3: ULP TOLITOLI | E3: ULP LEOK | F3: ULP BANGKIR | G3: ULP MOUTONG | H3: ULP KOTARAYA
C4: Key Performance Indicators
B5: 1 | C5: Penjualan dan Pendapatan Tenaga Listrik
C6: a. Penjualan Tenaga listrik | D6: =ULP!K11 -> 110 | E6: =ULP!V11 -> 110 | F6: =ULP!AG11 -> 110 | G6: =ULP!AR11 -> 110 | H6: =ULP!BC11 -> 110
C7: b. Pendapatan Penjualan Tenaga Listrik | D7: =ULP!K12 -> 110 | E7: =ULP!V12 -> 110 | F7: =ULP!AG12 -> 110 | G7: =ULP!AR12 -> 110 | H7: =ULP!BC12 -> 110
B8: 2 | C8: Pengendalian Piutang Rata-Rata Tunggakan | D8: =ULP!#REF! -> #REF! | E8: =ULP!#REF! -> #REF! | F8: =ULP!#REF! -> #REF! | G8: =ULP!#REF! -> #REF! | H8: =ULP!#REF! -> #REF!
B9: 3 | C9: Susut Jaringan (Tanpa E-Min) | D9: =ULP!#REF! -> #REF! | E9: =ULP!#REF! -> #REF! | F9: =ULP!#REF! -> #REF! | G9: =ULP!#REF! -> #REF! | H9: =ULP!#REF! -> #REF!
C10: Performance Indikator
B11: 4 | C11: Peningkatan Pelayanan
C12: a. Response Time Atas Keluhan | D12: =ULP!K21 -> 108 | E12: =ULP!V21 -> 110 | F12: =ULP!AG21 -> 110 | G12: =ULP!AR21 -> 110 | H12: =ULP!BC21 -> 110
C13: b. Recovery Time Atas Keluhan | D13: =ULP!K22 -> 110 | E13: =ULP!V22 -> 110 | F13: =ULP!AG22 -> 110 | G13: =ULP!AR22 -> 110 | H13: =ULP!BC22 -> 110
C14: c. Response Time Atas Gangguan | D14: =ULP!K23 -> 50 | E14: =ULP!V23 -> 110 | F14: =ULP!AG23 -> 110 | G14: =ULP!AR23 -> 110 | H14: =ULP!BC23 -> 110
C15: d. Recovery Time Atas Gangguan | D15: =ULP!K24 -> 107.5 | E15: =ULP!V24 -> 107.5 | F15: =ULP!AG24 -> 107.5 | G15: =ULP!AR24 -> 107.5 | H15: =ULP!BC24 -> 107.5
B16: 5 | C16: Jumlah Pengguna Aktif Aplikasi "PLN Mobile" | D16: =ULP!K26 -> 110 | E16: =ULP!V26 -> 110 | F16: =ULP!AG26 -> 110 | G16: =ULP!AR26 -> 110 | H16: =ULP!BC26 -> 110
B17: 6 | C17: Peningkatan Keandalan Jaringan
C18: a. SAIDI sesuai kewenangannya | D18: =ULP!K28 -> 110 | E18: =ULP!V28 -> 110 | F18: =ULP!AG28 -> 110 | G18: =ULP!AR28 -> 110 | H18: =ULP!BC28 -> 110
C19: b. SAIFI sesuai kewenangannya | D19: =ULP!K32 -> 110 | E19: =ULP!V32 -> 110 | F19: =ULP!AG32 -> 110 | G19: =ULP!AR32 -> 110 | H19: =ULP!BC32 -> 110
B20: 7 | C20: Percepatan Penyambungan Pelanggan
C21: - PB/PD Paskem TR Tanpa Perluasan Jaringan | D21: =ULP!K46 -> 100 | E21: =ULP!V46 -> 100 | F21: =ULP!AG46 -> 100 | G21: =ULP!AR46 -> 100 | H21: =ULP!BC46 -> 100
B22: 8 | C22: Organization Capital Readiness (OCR) | D22: =ULP!K48 -> 110 | E22: =ULP!V48 -> 110 | F22: =ULP!AG48 -> 110 | G22: =ULP!AR48 -> 87.576702 | H22: =ULP!BC48 -> 95.137952
B23: 9 | C23: Maturity Level Kepatuhan | D23: =ULP!#REF! -> #REF! | E23: =ULP!#REF! -> #REF! | F23: =ULP!#REF! -> #REF! | G23: =ULP!#REF! -> #REF! | H23: =ULP!#REF! -> #REF!
B24: 10 | C24: Pengelolaan Revenue Assurence
C25: a. Update Data Pelanggan | D25: =ULP!#REF! -> #REF! | E25: =ULP!#REF! -> #REF! | F25: =ULP!#REF! -> #REF! | G25: =ULP!#REF! -> #REF! | H25: =ULP!#REF! -> #REF!
C26: b. Migrasi VKRN 41 dan VKRN 42 | D26: =ULP!K49 -> 87.808336 | E26: =ULP!V49 -> 110 | F26: =ULP!AG49 -> 110 | G26: =ULP!AR49 -> 89.565676 | H26: =ULP!BC49 -> 83.117018
B27: 11 | C27: Migrasi LPB | D27: =ULP!K53 -> 0 | E27: =ULP!V53 -> 0 | F27: =ULP!AG53 -> 0 | G27: =ULP!AR53 -> 0 | H27: =ULP!BC53 -> 0
B28: 12 | C28: Eksekusi Program Peningkatan Keandalan dan Efisiensi Distribusi (NNC)
C29: a. Eksekusi Program Keandalan Distribusi | D29: =ULP!K56 -> 0 | E29: =ULP!V56 -> 0 | F29: =ULP!AG56 -> 0 | G29: =ULP!AR56 -> 0 | H29: =ULP!BC56 -> 0
C30: b. Eksekusi P2TL | D30: =ULP!#REF! -> #REF! | E30: =ULP!#REF! -> #REF! | F30: =ULP!#REF! -> #REF! | G30: =ULP!#REF! -> #REF! | H30: =ULP!#REF! -> #REF!
B31: 13 | C31: Kepatuhan
C32: a. Keselamatan Ketenagalistrikan
C33: b. Pengelolaan Lingkungan Hidup
C34: c. Ketepatan Penyampaian Laporan dan Akurasi Data Kinerja
C35: d.Pemenuhan TMP
B36: TOTAL PENILAIAN | D36: =ULP!L58 -> 99.36 | E36: =RANK!D6 -> 103.59 | F36: =ULP!AH58 -> 105.33 | G36: =ULP!AS58 -> 100.84 | H36: =ULP!BD58 -> 103.59

Sheet scoreboard
B2: KPI | C2: Target | D2: Real
A3: Key Performance Indicators
B4: Pertumbuhan Penjualan Tenaga Listrik | C4: ='UP3'!G9 -> 0 | D4: ='UP3'!H9 -> 0 | E4: =D4/C4 -> #DIV/0! | F4: =IF(E4>1,1,E4) -> #DIV/0! | G4: =1-F4 -> #DIV/0!
B5: Delta Daya Tersambung | C5: ='UP3'!G10 -> 210.5 | D5: ='UP3'!H10 -> 159.21376 | E5: =D5/C5 -> 0.75635988 | F5: =IF(E5>1,1,E5) -> 0.75635988 | G5: =1-F5 -> 0.24364012
B6: kWh Jual Multiguna Non Backfeeding | C6: ='UP3'!G17 -> 0 | D6: ='UP3'!H17 -> 0 | E6: =D6/C6 -> #DIV/0! | F6: =IF(E6>1,1,E6) -> #DIV/0! | G6: =1-F6 -> #DIV/0!
B7: Pertumbuhan Penjualan Layanan Khusus | C7: ='UP3'!#REF! -> #REF! | D7: ='UP3'!#REF! -> #REF! | E7: =D7/C7 -> #REF! | F7: =IF(E7>1,1,E7) -> #REF! | G7: =1-F7 -> #REF!
B8: Penambahan Pelanggan Premium | C8: ='UP3'!G18 -> 0 | D8: ='UP3'!H18 -> 0 | E8: =D8/C8 -> #DIV/0! | F8: =IF(E8>1,1,E8) -> #DIV/0! | G8: =1-F8 -> #DIV/0!
B9: Susut Jaringan (Tanpa E-Min) | C9: ='UP3'!G19 -> 134 | D9: ='UP3'!H19 -> 98 | E9: =2-(D9/C9) -> 1.2686567 | F9: =IF(E9>1,1,E9) -> 1 | G9: =1-F9 -> 0
B10: SAIDI sesuai kewenangannya | C10: ='UP3'!G21 -> 5 | D10: ='UP3'!H21 -> 3 | E10: =2-(D10/C10) -> 1.4 | F10: =IF(E10>1,1,E10) -> 1 | G10: =1-F10 -> 0
B11: SAIFI sesuai kewenangannya | C11: ='UP3'!G22 -> 0 | D11: ='UP3'!H22 -> 0 | E11: =2-(D11/C11) -> #DIV/0! | F11: =IF(E11>1,1,E11) -> #DIV/0! | G11: =1-F11 -> #DIV/0!
B12: Energy Not Served | C12: ='UP3'!G24 -> 0.04 | D12: ='UP3'!H24 -> 0 | E12: =2-(D12/C12) -> 2 | F12: =IF(E12>1,1,E12) -> 1 | G12: =1-F12 -> 0
B13: Implementasi PLN Mobile | C13: ='UP3'!G25 -> 4.9 | D13: 100 | E13: =D13/C13 -> 20.408163 | F13: =IF(E13>1,1,E13) -> 1 | G13: =1-F13 -> 0
B14: Jumlah Komplain Pelanggan | C14: ='UP3'!#REF! -> #REF! | D14: ='UP3'!#REF! -> #REF! | E14: =D14/C14 -> #REF! | F14: 0 | G14: =1-F14 -> 1
B15: Aging Complaint | C15: ='UP3'!G33 -> 0 | D15: ='UP3'!H33 -> 0 | E15: =2-(D15/C15) -> #DIV/0! | F15: =IF(E15>1,1,E15) -> #DIV/0! | G15: =1-F15 -> #DIV/0!
B16: Rata-Rata Rasio Tunggakan | C16: ='UP3'!G38 -> 798 | D16: ='UP3'!H38 -> 814 | E16: =2-(D16/C16) -> 0.97994987 | F16: =IF(E16>1,1,E16) -> 0.97994987 | G16: =1-F16 -> 0.020050125
B17: Jumlah ULP NIHIL | C17: ='UP3'!G41 -> 13233.896 | D17: ='UP3'!H41 -> 64005.7 | E17: =D17/C17 -> 4.8364971 | F17: =IF(E17>1,1,E17) -> 1 | G17: =1-F17 -> 0
B18: Migrasi LPB pelanggan menunggak berulang | C18: ='UP3'!G42 -> 0 | D18: ='UP3'!H42 -> 0 | E18: =D18/C18 -> #DIV/0! | F18: =IF(E18>1,1,E18) -> #DIV/0! | G18: =1-F18 -> #DIV/0!
B19: BPP - Opex Non Fuel | C19: ='UP3'!G46 -> 1175 | D19: ='UP3'!H46 -> 1001.412 | E19: =2-(D19/C19) -> 1.1477345 | F19: =IF(E19>1,1,E19) -> 1 | G19: =1-F19 -> 0
B20: CF Pembangkit Non BBM | C20: ='UP3'!G50 -> 95-100 | D20: ='UP3'!H50 -> 96 | E20: =D20/C20 -> #VALUE! | F20: =IF(E20>1,1,E20) -> #VALUE! | G20: =1-F20 -> #VALUE!
B21: SFC PLTD PLN | C21: ='UP3'!G51 -> 0 | D21: ='UP3'!H51 -> 0 | E21: =2-(D21/C21) -> #DIV/0! | F21: =IF(E21>1,1,E21) -> #DIV/0! | G21: =1-F21 -> #DIV/0!
B22: ='UP3'!B53 -> Manajemen SDM, Komunikasi, dan TJSL | C22: ='UP3'!G53 -> 0 | D22: ='UP3'!H53 -> 0 | E22: =D22/C22 -> #DIV/0! | F22: =E22 -> #DIV/0! | G22: =1-F22 -> #DIV/0! | AO22: 264116
B23: ='UP3'!B55 -> b. Produktivitas Unit | C23: ='UP3'!G55 -> 100 | D23: ='UP3'!H55 -> 90 | E23: =D23/C23 -> 0.9 | F23: =IF(E23>1,1,E23) -> 0.9 | G23: =1-F23 -> 0.1 | AO23: =AO22-39 -> 264077
B24: ='UP3'!B56 -> c. Pengelolaan Komunikasi dan TJSL | C24: ='UP3'!G56 -> 100 | D24: ='UP3'!H56 -> 110 | E24: 100 | F24: =IF(E24>1,1,E24) -> 1 | G24: =1-F24 -> 0
B25: ='UP3'!B60 -> b. Maturity Level Gudang | C25: ='UP3'!G60 -> 3.5 | D25: ='UP3'!H60 -> 3.5 | E25: 100 | F25: =IF(E25>1,1,E25) -> 1 | G25: =1-F25 -> 0
B26: ='UP3'!B61 -> c. Maturity Level Sustainbility | C26: ='UP3'!G61 -> 100 | D26: ='UP3'!H61 -> 110 | E26: =D26/C26 -> 1.1 | F26: =IF(E26>1,1,E26) -> 1 | G26: =1-F26 -> 0
B27: ='UP3'!B62 -> d. Implementasi Roadmap Perbaikan Penerapan Manajemen Risiko dan Pencapaian Perlakuan Risiko | C27: ='UP3'!G62 -> 100 | D27: ='UP3'!H62 -> 100 | E27: =D27/C27 -> 1 | F27: =IF(E27>1,1,E27) -> 1 | G27: =1-F27 -> 0
B28: ='UP3'!B63 -> Kepatuhan : | C28: ='UP3'!G63 -> 0 | D28: ='UP3'!H63 -> 0 | E28: =D28/C28 -> #DIV/0! | F28: =IF(E28>1,1,E28) -> #DIV/0! | G28: =1-F28 -> #DIV/0!
B29: ='UP3'!B64 -> a. Pengelolaan K3, Keamanan dan Lingkungan Hidup | C29: ='UP3'!G64 -> 0 | D29: ='UP3'!H64 -> 0 | E29: 100 | F29: =IF(E29>1,1,E29) -> 1 | G29: =1-F29 -> 0
B30: ='UP3'!B66 -> c. Ketepatan penyampaian pelaporan dan Akurasi Data Kinerja | C30: ='UP3'!G66 -> 0 | D30: ='UP3'!H66 -> 0 | E30: 100 | F30: =IF(E30>1,1,E30) -> 1 | G30: =1-F30 -> 0
B39: SAIDI | C39: ='UP3'!G21 -> 5 | D39: ='UP3'!H21 -> 3 | E39: =2-(D39/C39) -> 1.4 | F39: =IF(E39>1,1,E39) -> 1 | G39: =1-F39 -> 0
B40: Rasio Tunggakan | C40: ='UP3'!G38 -> 798 | D40: ='UP3'!H38 -> 814 | E40: =2-(D40/C40) -> 0.97994987 | F40: =IF(E40>1,1,E40) -> 0.97994987 | G40: =1-F40 -> 0.020050125
B41: Multiguna | C41: ='UP3'!G17 -> 0 | D41: ='UP3'!H17 -> 0 | E41: =D41/C41 -> #DIV/0! | F41: =IF(E41>1,1,E41) -> #DIV/0! | G41: =1-F41 -> #DIV/0!
B42: RE 99 % | C42: ='UP3'!G55 -> 100 | D42: ='UP3'!H55 -> 90 | E42: =D42/C42 -> 0.9 | F42: =IF(E42>1,1,E42) -> 0.9 | G42: =1-F42 -> 0.1
B43: Komplain Pelanggan | C43: ='UP3'!#REF! -> #REF! | D43: ='UP3'!#REF! -> #REF! | E43: =D43/C43 -> #REF! | F43: 0 | G43: =1-F43 -> 1

Sheet TRACK
B2: Unit | C2: Nilai Kinerja Organisasi (NKO)
C3: Jan | D3: Feb | E3: Mar | F3: Apr | G3: May | H3: Jun | I3: Jul | J3: Aug | K3: Sep | L3: Oct | M3: Nov | N3: Dec
B4: ULP Tolitoli Khusus
B5: ULP Leok
B6: ULP Bangkir
B7: ULP Kotaraya
B8: UP3 Tolitoli | C8: =DETAIL!J43 -> #REF! | D8: =DETAIL!P43 -> #REF! | E8: =DETAIL!V43 -> #REF! | F8: =DETAIL!AB43 -> #REF!

Sheet DETAIL
B1: KONTRAK MANAJEMEN 2022
B2: PT PLN (PERSERO) UIW SULUTTENGGO
B3: UP3 TOLITOLI
A4: NO | B4: KPI | D4: SATUAN | F4: JAN | L4: FEB | R4: MAR | X4: APRIL | AD4: MEI
F5: BOBOT | G5: TARGET | H5: REAL | I5: PENCAPAIAN | J5: NILAI | L5: BOBOT | M5: TARGET | N5: REAL | O5: PENCAPAIAN | P5: NILAI | R5: BOBOT | S5: TARGET | T5: REAL | U5: PENCAPAIAN | V5: NILAI | X5: BOBOT | Y5: TARGET | Z5: REAL | AA5: PENCAPAIAN | AB5: NILAI | AD5: BOBOT | AE5: TARGET | AF5: REAL | AG5: PENCAPAIAN | AH5: NILAI
A6: 1 | B6: 2 | D6: 3 | F6: 4 | G6: 6 | H6: 7 | I6: 8 | J6: 9 | L6: 4 | M6: 6 | N6: 7 | O6: 8 | P6: 9 | R6: 4 | S6: 6 | T6: 7 | U6: 8 | V6: 9 | X6: 4 | Y6: 6 | Z6: 7 | AA6: 8 | AB6: 9 | AD6: 4 | AE6: 6 | AF6: 7 | AG6: 8 | AH6: 9
A7: =T.UP3!A7 -> I | B7: =T.UP3!B7 -> Key Performance Indikator | F7: =SUM(F8:F10) -> 28 | J7: =SUM(J8:J10) -> 15.4 | L7: =SUM(L8:L10) -> 28 | P7: =SUM(P8:P10) -> 15.4 | R7: =SUM(R8:R10) -> 28 | V7: =SUM(V8:V10) -> 15.126234 | X7: =SUM(X8:X10) -> 28 | AB7: =SUM(AB8:AB10) -> 14.159757 | AD7: =SUM(AD8:AD10) -> 28 | AH7: =SUM(AH8:AH10) -> 13.806863
A8: =T.UP3!A8 -> 1 | B8: =T.UP3!B8 -> Penjualan Tenaga Listrik | C8: =T.UP3!C8 -> ñ | D8: =T.UP3!D8 -> GWh | F8: =IF(H8="N/A",0,T.UP3!$F$8) -> 14 | G8: =VLOOKUP($B$8,T.UP3!$B$4:$T$70,MATCH(DETAIL!$F$4,T.UP3!$B$5:$T$5,0),FALSE) -> 18.74 | H8: =VLOOKUP($B$8,'R.UP3'!$B$4:$S$54,MATCH(DETAIL!$F$4,'R.UP3'!$B$5:$S$5,0),FALSE) -> 22.980831 | I8: =IF(OR(G8="N/A",H8="N/A"),"N/A",IF(AND(G8=0,H8=0),0,H8/G8*100)) -> 122.62983 | J8: =IF(OR(I8="N/A",I8<0),0,IF(I8>110,F8*110/100,F8*I8/100)) -> 15.4 | L8: =IF(N8="N/A",0,T.UP3!$F$8) -> 14 | M8: =VLOOKUP($B$8,T.UP3!$B$4:$T$70,MATCH(DETAIL!$L$4,T.UP3!$B$5:$T$5,0),FALSE) -> 36.55 | N8: =VLOOKUP($B$8,'R.UP3'!$B$4:$S$54,MATCH(DETAIL!$L$4,'R.UP3'!$B$5:$S$5,0),FALSE) -> 42.202826 | O8: =IF(OR(M8="N/A",N8="N/A"),"N/A",IF(AND(M8=0,N8=0),0,N8/M8*100)) -> 115.46601 | P8: =IF(OR(O8="N/A",O8<0),0,IF(O8>110,L8*110/100,L8*O8/100)) -> 15.4 | R8: =IF(T8="N/A",0,T.UP3!$F$8) -> 14 | S8: =VLOOKUP($B$8,T.UP3!$B$4:$T$70,MATCH(DETAIL!$R$4,T.UP3!$B$5:$T$5,0),FALSE) -> 56.39 | T8: =VLOOKUP($B$8,'R.UP3'!$B$4:$S$54,MATCH(DETAIL!$R$4,'R.UP3'!$B$5:$S$5,0),FALSE) -> 60.926308 | U8: =IF(OR(S8="N/A",T8="N/A"),"N/A",IF(AND(S8=0,T8=0),0,T8/S8*100)) -> 108.04453 | V8: =IF(OR(U8="N/A",U8<0),0,IF(U8>110,R8*110/100,R8*U8/100)) -> 15.126234 | X8: =IF(Z8="N/A",0,T.UP3!$F$8) -> 14 | Y8: =VLOOKUP($B$8,T.UP3!$B$4:$T$70,MATCH(DETAIL!$X$4,T.UP3!$B$5:$T$5,0),FALSE) -> 75.55 | Z8: =VLOOKUP($B$8,'R.UP3'!$B$4:$S$54,MATCH(DETAIL!$X$4,'R.UP3'!$B$5:$S$5,0),FALSE) -> 76.412119 | AA8: =IF(OR(Y8="N/A",Z8="N/A"),"N/A",IF(AND(Y8=0,Z8=0),0,Z8/Y8*100)) -> 101.14112 | AB8: =IF(OR(AA8="N/A",AA8<0),0,IF(AA8>110,X8*110/100,X8*AA8/100)) -> 14.159757 | AD8: =IF(AF8="N/A",0,T.UP3!$F$8) -> 14 | AE8: =VLOOKUP($B$8,T.UP3!$B$4:$T$70,MATCH(DETAIL!$AD$4,T.UP3!$B$5:$T$5,0),FALSE) -> 95.22 | AF8: =VLOOKUP($B$8,'R.UP3'!$B$4:$S$54,MATCH(DETAIL!$AD$4,'R.UP3'!$B$5:$S$5,0),FALSE) -> 93.906393 | AG8: =IF(OR(AE8="N/A",AF8="N/A"),"N/A",IF(AND(AE8=0,AF8=0),0,AF8/AE8*100)) -> 98.620451 | AH8: =IF(OR(AG8="N/A",AG8<0),0,IF(AG8>110,AD8*110/100,AD8*AG8/100)) -> 13.806863
A9: =T.UP3!A9 -> 2 | B9: =T.UP3!B9 -> Keandalan Sistem | C9: =T.UP3!C9 -> 0 | D9: =T.UP3!D9 -> 0 | F9: =IF(H9="N/A",0,T.UP3!$F$9) -> 14 | G9: =VLOOKUP($B$9,T.UP3!$B$4:$T$70,MATCH(DETAIL!$F$4,T.UP3!$B$5:$T$5,0),FALSE) -> 0 | H9: =VLOOKUP($B$9,'R.UP3'!$B$4:$S$54,MATCH(DETAIL!$F$4,'R.UP3'!$B$5:$S$5,0),FALSE) -> 0 | I9: =IF(OR(G9="N/A",H9="N/A"),"N/A",IF(AND(G9=0,H9=0),0,(2-H9/G9)*100)) -> 0 | J9: =IF(OR(I9="N/A",I9<0),0,IF(I9>110,F9*110/100,F9*I9/100)) -> 0 | L9: =IF(N9="N/A",0,T.UP3!$F$9) -> 14 | M9: =VLOOKUP($B$9,T.UP3!$B$4:$T$70,MATCH(DETAIL!$L$4,T.UP3!$B$5:$T$5,0),FALSE) -> 0 | N9: =VLOOKUP($B$9,'R.UP3'!$B$4:$S$54,MATCH(DETAIL!$L$4,'R.UP3'!$B$5:$S$5,0),FALSE) -> 0 | O9: =IF(OR(M9="N/A",N9="N/A"),"N/A",IF(AND(M9=0,N9=0),0,(2-N9/M9)*100)) -> 0 | P9: =IF(OR(O9="N/A",O9<0),0,IF(O9>110,L9*110/100,L9*O9/100)) -> 0 | R9: =IF(T9="N/A",0,T.UP3!$F$9) -> 14 | S9: =VLOOKUP($B$9,T.UP3!$B$4:$T$70,MATCH(DETAIL!$R$4,T.UP3!$B$5:$T$5,0),FALSE) -> 0 | T9: =VLOOKUP($B$9,'R.UP3'!$B$4:$S$54,MATCH(DETAIL!$R$4,'R.UP3'!$B$5:$S$5,0),FALSE) -> 0 | U9: =IF(OR(S9="N/A",T9="N/A"),"N/A",IF(AND(S9=0,T9=0),0,(2-T9/S9)*100)) -> 0 | V9: =IF(OR(U9="N/A",U9<0),0,IF(U9>110,R9*110/100,R9*U9/100)) -> 0 | X9: =IF(Z9="N/A",0,T.UP3!$F$9) -> 14 | Y9: =VLOOKUP($B$9,T.UP3!$B$4:$T$70,MATCH(DETAIL!$X$4,T.UP3!$B$5:$T$5,0),FALSE) -> 0 | Z9: =VLOOKUP($B$9,'R.UP3'!$B$4:$S$54,MATCH(DETAIL!$X$4,'R.UP3'!$B$5:$S$5,0),FALSE) -> 0 | AA9: =IF(OR(Y9="N/A",Z9="N/A"),"N/A",IF(AND(Y9=0,Z9=0),0,(2-Z9/Y9)*100)) -> 0 | AB9: =IF(OR(AA9="N/A",AA9<0),0,IF(AA9>110,X9*110/100,X9*AA9/100)) -> 0 | AD9: =IF(AF9="N/A",0,T.UP3!$F$9) -> 14 | AE9: =VLOOKUP($B$9,T.UP3!$B$4:$T$70,MATCH(DETAIL!$AD$4,T.UP3!$B$5:$T$5,0),FALSE) -> 0 | AF9: =VLOOKUP($B$9,'R.UP3'!$B$4:$S$54,MATCH(DETAIL!$AD$4,'R.UP3'!$B$5:$S$5,0),FALSE) -> 0 | AG9: =IF(OR(AE9="N/A",AF9="N/A"),"N/A",IF(AND(AE9=0,AF9=0),0,(2-AF9/AE9)*100)) -> 0 | AH9: =IF(OR(AG9="N/A",AG9<0),0,IF(AG9>110,AD9*110/100,AD9*AG9/100)) -> 0
A10: =T.UP3!A10 -> 0 | B10: =T.UP3!B10 -> a. SAIDI Sesuai Kewenangannya | C10: =T.UP3!C10 -> ò | D10: =T.UP3!D10 -> Menit/Plg | F10: =IF(H10="N/A",0,T.UP3!$F$10) -> 0 | G10: =VLOOKUP($B$10,T.UP3!$B$4:$T$70,MATCH(DETAIL!$F$4,T.UP3!$B$5:$T$5,0),FALSE) -> 23.39 | H10: =VLOOKUP($B$10,'R.UP3'!$B$4:$S$54,MATCH(DETAIL!$F$4,'R.UP3'!$B$5:$S$5,0),FALSE) -> 12.366709 | I10: =IF(OR(G10="N/A",H10="N/A"),"N/A",IF(AND(G10=0,H10=0),0,H10/G10*100)) -> 52.871777 | J10: =IF(OR(I10="N/A",I10<0),0,IF(I10>110,F10*110/100,F10*I10/100)) -> 0 | L10: =IF(N10="N/A",0,T.UP3!$F$10) -> 0 | M10: =VLOOKUP($B$10,T.UP3!$B$4:$T$70,MATCH(DETAIL!$L$4,T.UP3!$B$5:$T$5,0),FALSE) -> 46.78 | N10: =VLOOKUP($B$10,'R.UP3'!$B$4:$S$54,MATCH(DETAIL!$L$4,'R.UP3'!$B$5:$S$5,0),FALSE) -> 14.217818 | O10: =IF(OR(M10="N/A",N10="N/A"),"N/A",IF(AND(M10=0,N10=0),0,N10/M10*100)) -> 30.392942 | P10: =IF(OR(O10="N/A",O10<0),0,IF(O10>110,L10*110/100,L10*O10/100)) -> 0 | R10: =IF(T10="N/A",0,T.UP3!$F$10) -> 0 | S10: =VLOOKUP($B$10,T.UP3!$B$4:$T$70,MATCH(DETAIL!$R$4,T.UP3!$B$5:$T$5,0),FALSE) -> 70.17 | T10: =VLOOKUP($B$10,'R.UP3'!$B$4:$S$54,MATCH(DETAIL!$R$4,'R.UP3'!$B$5:$S$5,0),FALSE) -> 15.90799 | U10: =IF(OR(S10="N/A",T10="N/A"),"N/A",IF(AND(S10=0,T10=0),0,T10/S10*100)) -> 22.670642 | V10: =IF(OR(U10="N/A",U10<0),0,IF(U10>110,R10*110/100,R10*U10/100)) -> 0 | X10: =IF(Z10="N/A",0,T.UP3!$F$10) -> 0 | Y10: =VLOOKUP($B$10,T.UP3!$B$4:$T$70,MATCH(DETAIL!$X$4,T.UP3!$B$5:$T$5,0),FALSE) -> 93.56 | Z10: =VLOOKUP($B$10,'R.UP3'!$B$4:$S$54,MATCH(DETAIL!$X$4,'R.UP3'!$B$5:$S$5,0),FALSE) -> 30.880917 | AA10: =IF(OR(Y10="N/A",Z10="N/A"),"N/A",IF(AND(Y10=0,Z10=0),0,Z10/Y10*100)) -> 33.006538 | AB10: =IF(OR(AA10="N/A",AA10<0),0,IF(AA10>110,X10*110/100,X10*AA10/100)) -> 0 | AD10: =IF(AF10="N/A",0,T.UP3!$F$10) -> 0 | AE10: =VLOOKUP($B$10,T.UP3!$B$4:$T$70,MATCH(DETAIL!$AD$4,T.UP3!$B$5:$T$5,0),FALSE) -> 116.95 | AF10: =VLOOKUP($B$10,'R.UP3'!$B$4:$S$54,MATCH(DETAIL!$AD$4,'R.UP3'!$B$5:$S$5,0),FALSE) -> 82.702127 | AG10: =IF(OR(AE10="N/A",AF10="N/A"),"N/A",IF(AND(AE10=0,AF10=0),0,AF10/AE10*100)) -> 70.715799 | AH10: =IF(OR(AG10="N/A",AG10<0),0,IF(AG10>110,AD10*110/100,AD10*AG10/100)) -> 0
A11: =T.UP3!A17 -> II | B11: =T.UP3!B17 -> Perfomance Indicators | F11: =SUM(F12:F41) -> #REF! | J11: =SUM(J12:J41) -> #REF! | L11: =SUM(L12:L41) -> #REF! | P11: =SUM(P12:P41) -> #REF! | R11: =SUM(R12:R41) -> #REF! | V11: =SUM(V12:V41) -> #REF! | X11: =SUM(X12:X41) -> #REF! | AB11: =SUM(AB12:AB41) -> #REF! | AD11: =SUM(AD12:AD41) -> #REF! | AH11: =SUM(AH12:AH41) -> #REF!
A12: =T.UP3!A18 -> 4 | B12: =T.UP3!B18 -> Keandalan Jaringan Distribusi | C12: =T.UP3!C18 -> 0 | D12: =T.UP3!D18 -> 0 | F12: =IF(H12="N/A",0,T.UP3!$F$18) -> 6 | G12: =VLOOKUP($B$12,T.UP3!$B$4:$T$70,MATCH(DETAIL!$F$4,T.UP3!$B$5:$T$5,0),FALSE) -> 0 | H12: =VLOOKUP($B$12,'R.UP3'!$B$4:$S$54,MATCH(DETAIL!$F$4,'R.UP3'!$B$5:$S$5,0),FALSE) -> 0 | I12: =IF(OR(G12="N/A",H12="N/A"),"N/A",IF(AND(G12=0,H12=0),0,(2-H12/G12)*100)) -> 0 | J12: =IF(I12="N/A",0,IF(I12>110,F12*110/100,F12*I12/100)) -> 0 | L12: =IF(N12="N/A",0,T.UP3!$F$18) -> 6 | M12: =VLOOKUP($B$12,T.UP3!$B$4:$T$70,MATCH(DETAIL!$L$4,T.UP3!$B$5:$T$5,0),FALSE) -> 0 | N12: =VLOOKUP($B$12,'R.UP3'!$B$4:$S$54,MATCH(DETAIL!$L$4,'R.UP3'!$B$5:$S$5,0),FALSE) -> 0 | O12: =IF(OR(M12="N/A",N12="N/A"),"N/A",IF(AND(M12=0,N12=0),0,(2-N12/M12)*100)) -> 0 | P12: =IF(O12="N/A",0,IF(O12>110,L12*110/100,L12*O12/100)) -> 0 | R12: =IF(T12="N/A",0,T.UP3!$F$18) -> 6 | S12: =VLOOKUP($B$12,T.UP3!$B$4:$T$70,MATCH(DETAIL!$R$4,T.UP3!$B$5:$T$5,0),FALSE) -> 0 | T12: =VLOOKUP($B$12,'R.UP3'!$B$4:$S$54,MATCH(DETAIL!$R$4,'R.UP3'!$B$5:$S$5,0),FALSE) -> 0 | U12: =IF(OR(S12="N/A",T12="N/A"),"N/A",IF(AND(S12=0,T12=0),0,(2-T12/S12)*100)) -> 0 | V12: =IF(U12="N/A",0,IF(U12>110,R12*110/100,R12*U12/100)) -> 0 | X12: =IF(Z12="N/A",0,T.UP3!$F$18) -> 6 | Y12: =VLOOKUP($B$12,T.UP3!$B$4:$T$70,MATCH(DETAIL!$X$4,T.UP3!$B$5:$T$5,0),FALSE) -> 0 | Z12: =VLOOKUP($B$12,'R.UP3'!$B$4:$S$54,MATCH(DETAIL!$X$4,'R.UP3'!$B$5:$S$5,0),FALSE) -> 0 | AA12: =IF(OR(Y12="N/A",Z12="N/A"),"N/A",IF(AND(Y12=0,Z12=0),0,(2-Z12/Y12)*100)) -> 0 | AB12: =IF(AA12="N/A",0,IF(AA12>110,X12*110/100,X12*AA12/100)) -> 0 | AD12: =IF(AF12="N/A",0,T.UP3!$F$18) -> 6 | AE12: =VLOOKUP($B$12,T.UP3!$B$4:$T$70,MATCH(DETAIL!$AD$4,T.UP3!$B$5:$T$5,0),FALSE) -> 0 | AF12: =VLOOKUP($B$12,'R.UP3'!$B$4:$S$54,MATCH(DETAIL!$AD$4,'R.UP3'!$B$5:$S$5,0),FALSE) -> 0 | AG12: =IF(OR(AE12="N/A",AF12="N/A"),"N/A",IF(AND(AE12=0,AF12=0),0,(2-AF12/AE12)*100)) -> 0 | AH12: =IF(AG12="N/A",0,IF(AG12>110,AD12*110/100,AD12*AG12/100)) -> 0
A13: =T.UP3!A19 -> 0 | B13: =T.UP3!B19 -> a. Gangguan TM > 5 Menit | C13: =T.UP3!C19 -> ò | D13: =T.UP3!D19 -> Kali | F13: =IF(H13="N/A",0,T.UP3!$F$19) -> 0 | G13: =VLOOKUP($B$13,T.UP3!$B$4:$T$70,MATCH(DETAIL!$F$4,T.UP3!$B$5:$T$5,0),FALSE) -> 15 | H13: =VLOOKUP($B$13,'R.UP3'!$B$4:$S$54,MATCH(DETAIL!$F$4,'R.UP3'!$B$5:$S$5,0),FALSE) -> 5 | I13: =IF(OR(G13="N/A",H13="N/A"),"N/A",IF(AND(G13=0,H13=0),0,(2-H13/G13)*100)) -> 166.66667 | J13: =IF(I13="N/A",0,IF(I13>110,F13*110/100,F13*I13/100)) -> 0 | L13: =IF(N13="N/A",0,T.UP3!$F$19) -> 0 | M13: =VLOOKUP($B$13,T.UP3!$B$4:$T$70,MATCH(DETAIL!$L$4,T.UP3!$B$5:$T$5,0),FALSE) -> 29 | N13: =VLOOKUP($B$13,'R.UP3'!$B$4:$S$54,MATCH(DETAIL!$L$4,'R.UP3'!$B$5:$S$5,0),FALSE) -> 10 | O13: =IF(OR(M13="N/A",N13="N/A"),"N/A",IF(AND(M13=0,N13=0),0,(2-N13/M13)*100)) -> 165.51724 | P13: =IF(O13="N/A",0,IF(O13>110,L13*110/100,L13*O13/100)) -> 0 | R13: =IF(T13="N/A",0,T.UP3!$F$19) -> 0 | S13: =VLOOKUP($B$13,T.UP3!$B$4:$T$70,MATCH(DETAIL!$R$4,T.UP3!$B$5:$T$5,0),FALSE) -> 45 | T13: =VLOOKUP($B$13,'R.UP3'!$B$4:$S$54,MATCH(DETAIL!$R$4,'R.UP3'!$B$5:$S$5,0),FALSE) -> 32 | U13: =IF(OR(S13="N/A",T13="N/A"),"N/A",IF(AND(S13=0,T13=0),0,(2-T13/S13)*100)) -> 128.88889 | V13: =IF(U13="N/A",0,IF(U13>110,R13*110/100,R13*U13/100)) -> 0 | X13: =IF(Z13="N/A",0,T.UP3!$F$19) -> 0 | Y13: =VLOOKUP($B$13,T.UP3!$B$4:$T$70,MATCH(DETAIL!$X$4,T.UP3!$B$5:$T$5,0),FALSE) -> 59 | Z13: =VLOOKUP($B$13,'R.UP3'!$B$4:$S$54,MATCH(DETAIL!$X$4,'R.UP3'!$B$5:$S$5,0),FALSE) -> 40 | AA13: =IF(OR(Y13="N/A",Z13="N/A"),"N/A",IF(AND(Y13=0,Z13=0),0,(2-Z13/Y13)*100)) -> 132.20339 | AB13: =IF(AA13="N/A",0,IF(AA13>110,X13*110/100,X13*AA13/100)) -> 0 | AD13: =IF(AF13="N/A",0,T.UP3!$F$19) -> 0 | AE13: =VLOOKUP($B$13,T.UP3!$B$4:$T$70,MATCH(DETAIL!$AD$4,T.UP3!$B$5:$T$5,0),FALSE) -> 74 | AF13: =VLOOKUP($B$13,'R.UP3'!$B$4:$S$54,MATCH(DETAIL!$AD$4,'R.UP3'!$B$5:$S$5,0),FALSE) -> 66 | AG13: =IF(OR(AE13="N/A",AF13="N/A"),"N/A",IF(AND(AE13=0,AF13=0),0,(2-AF13/AE13)*100)) -> 110.81081 | AH13: =IF(AG13="N/A",0,IF(AG13>110,AD13*110/100,AD13*AG13/100)) -> 0
A14: =T.UP3!A20 -> 0 | B14: =T.UP3!B20 -> b. Gangguan TM ≤ 5 Menit | C14: =T.UP3!C20 -> ò | D14: =T.UP3!D20 -> Kali | F14: =IF(H14="N/A",0,T.UP3!$F$20) -> 0 | G14: =VLOOKUP($B$14,T.UP3!$B$4:$T$70,MATCH(DETAIL!$F$4,T.UP3!$B$5:$T$5,0),FALSE) -> 17 | H14: =VLOOKUP($B$14,'R.UP3'!$B$4:$S$54,MATCH(DETAIL!$F$4,'R.UP3'!$B$5:$S$5,0),FALSE) -> 1 | I14: =IF(OR(G14="N/A",H14="N/A"),"N/A",IF(AND(G14=0,H14=0),0,(2-H14/G14)*100)) -> 194.11765 | J14: =IF(I14="N/A",0,IF(I14>110,F14*110/100,F14*I14/100)) -> 0 | L14: =IF(N14="N/A",0,T.UP3!$F$20) -> 0 | M14: =VLOOKUP($B$14,T.UP3!$B$4:$T$70,MATCH(DETAIL!$L$4,T.UP3!$B$5:$T$5,0),FALSE) -> 31 | N14: =VLOOKUP($B$14,'R.UP3'!$B$4:$S$54,MATCH(DETAIL!$L$4,'R.UP3'!$B$5:$S$5,0),FALSE) -> 18 | O14: =IF(OR(M14="N/A",N14="N/A"),"N/A",IF(AND(M14=0,N14=0),0,(2-N14/M14)*100)) -> 141.93548 | P14: =IF(O14="N/A",0,IF(O14>110,L14*110/100,L14*O14/100)) -> 0 | R14: =IF(T14="N/A",0,T.UP3!$F$20) -> 0 | S14: =VLOOKUP($B$14,T.UP3!$B$4:$T$70,MATCH(DETAIL!$R$4,T.UP3!$B$5:$T$5,0),FALSE) -> 48 | T14: =VLOOKUP($B$14,'R.UP3'!$B$4:$S$54,MATCH(DETAIL!$R$4,'R.UP3'!$B$5:$S$5,0),FALSE) -> 21 | U14: =IF(OR(S14="N/A",T14="N/A"),"N/A",IF(AND(S14=0,T14=0),0,(2-T14/S14)*100)) -> 156.25 | V14: =IF(U14="N/A",0,IF(U14>110,R14*110/100,R14*U14/100)) -> 0 | X14: =IF(Z14="N/A",0,T.UP3!$F$20) -> 0 | Y14: =VLOOKUP($B$14,T.UP3!$B$4:$T$70,MATCH(DETAIL!$X$4,T.UP3!$B$5:$T$5,0),FALSE) -> 65 | Z14: =VLOOKUP($B$14,'R.UP3'!$B$4:$S$54,MATCH(DETAIL!$X$4,'R.UP3'!$B$5:$S$5,0),FALSE) -> 22 | AA14: =IF(OR(Y14="N/A",Z14="N/A"),"N/A",IF(AND(Y14=0,Z14=0),0,(2-Z14/Y14)*100)) -> 166.15385 | AB14: =IF(AA14="N/A",0,IF(AA14>110,X14*110/100,X14*AA14/100)) -> 0 | AD14: =IF(AF14="N/A",0,T.UP3!$F$20) -> 0 | AE14: =VLOOKUP($B$14,T.UP3!$B$4:$T$70,MATCH(DETAIL!$AD$4,T.UP3!$B$5:$T$5,0),FALSE) -> 79 | AF14: =VLOOKUP($B$14,'R.UP3'!$B$4:$S$54,MATCH(DETAIL!$AD$4,'R.UP3'!$B$5:$S$5,0),FALSE) -> 57 | AG14: =IF(OR(AE14="N/A",AF14="N/A"),"N/A",IF(AND(AE14=0,AF14=0),0,(2-AF14/AE14)*100)) -> 127.8481 | AH14: =IF(AG14="N/A",0,IF(AG14>110,AD14*110/100,AD14*AG14/100)) -> 0
A15: =T.UP3!A21 -> 0 | B15: =T.UP3!B21 -> c. Kerusakan Peralatan Distribusi (PHB TM dan Trafo) Sesuai Kewenangan
B16: =T.UP3!B22 -> Peningkatan Layanan | C16: =T.UP3!C22 -> 0 | D16: =T.UP3!D22 -> 0 | F16: =IF(H16="N/A",0,T.UP3!$F$22) -> 6 | G16: =VLOOKUP($B$16,T.UP3!$B$4:$T$70,MATCH(DETAIL!$F$4,T.UP3!$B$5:$T$5,0),FALSE) -> 0 | H16: =VLOOKUP($B$16,'R.UP3'!$B$4:$S$54,MATCH(DETAIL!$F$4,'R.UP3'!$B$5:$S$5,0),FALSE) -> 0 | I16: =IF(OR(G16="N/A",H16="N/A"),"N/A",IF(AND(G16=0,H16=0),0,(2-H16/G16)*100)) -> 0 | J16: =IF(I16="N/A",0,IF(I16>110,F16*110/100,F16*I16/100)) -> 0 | L16: =IF(N16="N/A",0,T.UP3!$F$22) -> 6 | M16: =VLOOKUP($B$16,T.UP3!$B$4:$T$70,MATCH(DETAIL!$L$4,T.UP3!$B$5:$T$5,0),FALSE) -> 0 | N16: =VLOOKUP($B$16,'R.UP3'!$B$4:$S$54,MATCH(DETAIL!$L$4,'R.UP3'!$B$5:$S$5,0),FALSE) -> 0 | O16: =IF(OR(M16="N/A",N16="N/A"),"N/A",IF(AND(M16=0,N16=0),0,(2-N16/M16)*100)) -> 0 | P16: =IF(O16="N/A",0,IF(O16>110,L16*110/100,L16*O16/100)) -> 0 | R16: =IF(T16="N/A",0,T.UP3!$F$22) -> 6 | S16: =VLOOKUP($B$16,T.UP3!$B$4:$T$70,MATCH(DETAIL!$R$4,T.UP3!$B$5:$T$5,0),FALSE) -> 0 | T16: =VLOOKUP($B$16,'R.UP3'!$B$4:$S$54,MATCH(DETAIL!$R$4,'R.UP3'!$B$5:$S$5,0),FALSE) -> 0 | U16: =IF(OR(S16="N/A",T16="N/A"),"N/A",IF(AND(S16=0,T16=0),0,(2-T16/S16)*100)) -> 0 | V16: =IF(U16="N/A",0,IF(U16>110,R16*110/100,R16*U16/100)) -> 0 | X16: =IF(Z16="N/A",0,T.UP3!$F$22) -> 6 | Y16: =VLOOKUP($B$16,T.UP3!$B$4:$T$70,MATCH(DETAIL!$X$4,T.UP3!$B$5:$T$5,0),FALSE) -> 0 | Z16: =VLOOKUP($B$16,'R.UP3'!$B$4:$S$54,MATCH(DETAIL!$X$4,'R.UP3'!$B$5:$S$5,0),FALSE) -> 0 | AA16: =IF(OR(Y16="N/A",Z16="N/A"),"N/A",IF(AND(Y16=0,Z16=0),0,(2-Z16/Y16)*100)) -> 0 | AB16: =IF(AA16="N/A",0,IF(AA16>110,X16*110/100,X16*AA16/100)) -> 0 | AD16: =IF(AF16="N/A",0,T.UP3!$F$22) -> 6 | AE16: =VLOOKUP($B$16,T.UP3!$B$4:$T$70,MATCH(DETAIL!$AD$4,T.UP3!$B$5:$T$5,0),FALSE) -> 0 | AF16: =VLOOKUP($B$16,'R.UP3'!$B$4:$S$54,MATCH(DETAIL!$AD$4,'R.UP3'!$B$5:$S$5,0),FALSE) -> 0 | AG16: =IF(OR(AE16="N/A",AF16="N/A"),"N/A",IF(AND(AE16=0,AF16=0),0,(2-AF16/AE16)*100)) -> 0 | AH16: =IF(AG16="N/A",0,IF(AG16>110,AD16*110/100,AD16*AG16/100)) -> 0
B17: =T.UP3!B24 -> b. Pengaduan Gangguan Berulang pada PLN Mobile | C17: =T.UP3!C24 -> ò | D17: =T.UP3!D24 -> % | F17: =IF(H17="N/A",0,T.UP3!$F$24) -> 0 | G17: =VLOOKUP($B$17,T.UP3!$B$4:$T$70,MATCH(DETAIL!$F$4,T.UP3!$B$5:$T$5,0),FALSE) -> 0.04 | H17: =VLOOKUP($B$17,'R.UP3'!$B$4:$S$54,MATCH(DETAIL!$F$4,'R.UP3'!$B$5:$S$5,0),FALSE) -> 0 | I17: =IF(OR(G17="N/A",H17="N/A"),"N/A",IF(AND(G17=0,H17=0),0,(2-H17/G17)*100)) -> 200 | J17: =IF(I17="N/A",0,IF(I17>110,F17*110/100,F17*I17/100)) -> 0 | L17: =IF(N17="N/A",0,T.UP3!$F$24) -> 0 | M17: =VLOOKUP($B$17,T.UP3!$B$4:$T$70,MATCH(DETAIL!$L$4,T.UP3!$B$5:$T$5,0),FALSE) -> 0.04 | N17: =VLOOKUP($B$17,'R.UP3'!$B$4:$S$54,MATCH(DETAIL!$L$4,'R.UP3'!$B$5:$S$5,0),FALSE) -> 0 | O17: =IF(OR(M17="N/A",N17="N/A"),"N/A",IF(AND(M17=0,N17=0),0,(2-N17/M17)*100)) -> 200 | P17: =IF(O17="N/A",0,IF(O17>110,L17*110/100,L17*O17/100)) -> 0 | R17: =IF(T17="N/A",0,T.UP3!$F$24) -> 0 | S17: =VLOOKUP($B$17,T.UP3!$B$4:$T$70,MATCH(DETAIL!$R$4,T.UP3!$B$5:$T$5,0),FALSE) -> 0.04 | T17: =VLOOKUP($B$17,'R.UP3'!$B$4:$S$54,MATCH(DETAIL!$R$4,'R.UP3'!$B$5:$S$5,0),FALSE) -> 0 | U17: =IF(OR(S17="N/A",T17="N/A"),"N/A",IF(AND(S17=0,T17=0),0,(2-T17/S17)*100)) -> 200 | V17: =IF(U17="N/A",0,IF(U17>110,R17*110/100,R17*U17/100)) -> 0 | X17: =IF(Z17="N/A",0,T.UP3!$F$24) -> 0 | Y17: =VLOOKUP($B$17,T.UP3!$B$4:$T$70,MATCH(DETAIL!$X$4,T.UP3!$B$5:$T$5,0),FALSE) -> 0.04 | Z17: =VLOOKUP($B$17,'R.UP3'!$B$4:$S$54,MATCH(DETAIL!$X$4,'R.UP3'!$B$5:$S$5,0),FALSE) -> 0 | AA17: =IF(OR(Y17="N/A",Z17="N/A"),"N/A",IF(AND(Y17=0,Z17=0),0,(2-Z17/Y17)*100)) -> 200 | AB17: =IF(AA17="N/A",0,IF(AA17>110,X17*110/100,X17*AA17/100)) -> 0 | AD17: =IF(AF17="N/A",0,T.UP3!$F$24) -> 0 | AE17: =VLOOKUP($B$17,T.UP3!$B$4:$T$70,MATCH(DETAIL!$AD$4,T.UP3!$B$5:$T$5,0),FALSE) -> 0.04 | AF17: =VLOOKUP($B$17,'R.UP3'!$B$4:$S$54,MATCH(DETAIL!$AD$4,'R.UP3'!$B$5:$S$5,0),FALSE) -> 0 | AG17: =IF(OR(AE17="N/A",AF17="N/A"),"N/A",IF(AND(AE17=0,AF17=0),0,(2-AF17/AE17)*100)) -> 200 | AH17: =IF(AG17="N/A",0,IF(AG17>110,AD17*110/100,AD17*AG17/100)) -> 0
A18: =T.UP3!A25 -> 0 | B18: =T.UP3!B25 -> c. Rating PLN Mobile | C18: =T.UP3!C25 -> ñ | D18: =T.UP3!D25 -> Rating | F18: =IF(H18="N/A",0,T.UP3!$F$25) -> 0 | G18: =VLOOKUP($B$18,T.UP3!$B$4:$T$70,MATCH(DETAIL!$F$4,T.UP3!$B$5:$T$5,0),FALSE) -> 4.9 | H18: =VLOOKUP($B$18,'R.UP3'!$B$4:$S$54,MATCH(DETAIL!$F$4,'R.UP3'!$B$5:$S$5,0),FALSE) -> 4.91 | I18: =IF(OR(G18="N/A",H18="N/A"),"N/A",IF(AND(G18=0,H18=0),0,H18/G18*100)) -> 100.20408 | J18: =IF(I18="N/A",0,IF(I18>110,F18*110/100,F18*I18/100)) -> 0 | L18: =IF(N18="N/A",0,T.UP3!$F$25) -> 0 | M18: =VLOOKUP($B$18,T.UP3!$B$4:$T$70,MATCH(DETAIL!$L$4,T.UP3!$B$5:$T$5,0),FALSE) -> 4.9 | N18: =VLOOKUP($B$18,'R.UP3'!$B$4:$S$54,MATCH(DETAIL!$L$4,'R.UP3'!$B$5:$S$5,0),FALSE) -> 4.91 | O18: =IF(OR(M18="N/A",N18="N/A"),"N/A",IF(AND(M18=0,N18=0),0,N18/M18*100)) -> 100.20408 | P18: =IF(O18="N/A",0,IF(O18>110,L18*110/100,L18*O18/100)) -> 0 | R18: =IF(T18="N/A",0,T.UP3!$F$25) -> 0 | S18: =VLOOKUP($B$18,T.UP3!$B$4:$T$70,MATCH(DETAIL!$R$4,T.UP3!$B$5:$T$5,0),FALSE) -> 4.9 | T18: =VLOOKUP($B$18,'R.UP3'!$B$4:$S$54,MATCH(DETAIL!$R$4,'R.UP3'!$B$5:$S$5,0),FALSE) -> 4.91 | U18: =IF(OR(S18="N/A",T18="N/A"),"N/A",IF(AND(S18=0,T18=0),0,T18/S18*100)) -> 100.20408 | V18: =IF(U18="N/A",0,IF(U18>110,R18*110/100,R18*U18/100)) -> 0 | X18: =IF(Z18="N/A",0,T.UP3!$F$25) -> 0 | Y18: =VLOOKUP($B$18,T.UP3!$B$4:$T$70,MATCH(DETAIL!$X$4,T.UP3!$B$5:$T$5,0),FALSE) -> 4.9 | Z18: =VLOOKUP($B$18,'R.UP3'!$B$4:$S$54,MATCH(DETAIL!$X$4,'R.UP3'!$B$5:$S$5,0),FALSE) -> 4.91 | AA18: =IF(OR(Y18="N/A",Z18="N/A"),"N/A",IF(AND(Y18=0,Z18=0),0,Z18/Y18*100)) -> 100.20408 | AB18: =IF(AA18="N/A",0,IF(AA18>110,X18*110/100,X18*AA18/100)) -> 0 | AD18: =IF(AF18="N/A",0,T.UP3!$F$25) -> 0 | AE18: =VLOOKUP($B$18,T.UP3!$B$4:$T$70,MATCH(DETAIL!$AD$4,T.UP3!$B$5:$T$5,0),FALSE) -> 4.9 | AF18: =VLOOKUP($B$18,'R.UP3'!$B$4:$S$54,MATCH(DETAIL!$AD$4,'R.UP3'!$B$5:$S$5,0),FALSE) -> 4.9 | AG18: =IF(OR(AE18="N/A",AF18="N/A"),"N/A",IF(AND(AE18=0,AF18=0),0,AF18/AE18*100)) -> 100 | AH18: =IF(AG18="N/A",0,IF(AG18>110,AD18*110/100,AD18*AG18/100)) -> 0
A19: =T.UP3!#REF! -> #REF! | B19: =T.UP3!#REF! -> #REF!
B20: =T.UP3!B26 -> d. Jumlah Kali Transaksi Keuangan melalui PLN Mobile | C20: =T.UP3!C26 -> ñ | D20: =T.UP3!D26 -> Kali Transaksi | F20: =IF(H20="N/A",0,T.UP3!$F$26) -> 0 | G20: =VLOOKUP($B$20,T.UP3!$B$4:$T$70,MATCH(DETAIL!$F$4,T.UP3!$B$5:$T$5,0),FALSE) -> 5386 | H20: =VLOOKUP($B$20,'R.UP3'!$B$4:$S$54,MATCH(DETAIL!$F$4,'R.UP3'!$B$5:$S$5,0),FALSE) -> 2781 | I20: =IF(OR(G20="N/A",H20="N/A"),"N/A",IF(AND(G20=0,H20=0),0,IF(H20<0,0,(2-H20/G20)*100))) -> 148.36613 | J20: =IF(OR(I20="N/A",I20<0),0,IF(I20>110,F20*110/100,F20*I20/100)) -> 0 | L20: =IF(N20="N/A",0,T.UP3!$F$26) -> 0 | M20: =VLOOKUP($B$20,T.UP3!$B$4:$T$70,MATCH(DETAIL!$L$4,T.UP3!$B$5:$T$5,0),FALSE) -> 10253 | N20: =VLOOKUP($B$20,'R.UP3'!$B$4:$S$54,MATCH(DETAIL!$L$4,'R.UP3'!$B$5:$S$5,0),FALSE) -> 6163 | O20: =IF(OR(M20="N/A",N20="N/A"),"N/A",IF(AND(M20=0,N20=0),0,IF(N20<0,0,(2-N20/M20)*100))) -> 139.89076 | P20: =IF(OR(O20="N/A",O20<0),0,IF(O20>110,L20*110/100,L20*O20/100)) -> 0 | R20: =IF(T20="N/A",0,T.UP3!$F$26) -> 0 | S20: =VLOOKUP($B$20,T.UP3!$B$4:$T$70,MATCH(DETAIL!$R$4,T.UP3!$B$5:$T$5,0),FALSE) -> 15641 | T20: =VLOOKUP($B$20,'R.UP3'!$B$4:$S$54,MATCH(DETAIL!$R$4,'R.UP3'!$B$5:$S$5,0),FALSE) -> 16349 | U20: =IF(OR(S20="N/A",T20="N/A"),"N/A",IF(AND(S20=0,T20=0),0,IF(T20<0,0,(2-T20/S20)*100))) -> 95.473435 | V20: =IF(OR(U20="N/A",U20<0),0,IF(U20>110,R20*110/100,R20*U20/100)) -> 0 | X20: =IF(Z20="N/A",0,T.UP3!$F$26) -> 0 | Y20: =VLOOKUP($B$20,T.UP3!$B$4:$T$70,MATCH(DETAIL!$X$4,T.UP3!$B$5:$T$5,0),FALSE) -> 20855 | Z20: =VLOOKUP($B$20,'R.UP3'!$B$4:$S$54,MATCH(DETAIL!$X$4,'R.UP3'!$B$5:$S$5,0),FALSE) -> 26667 | AA20: =IF(OR(Y20="N/A",Z20="N/A"),"N/A",IF(AND(Y20=0,Z20=0),0,IF(Z20<0,0,(2-Z20/Y20)*100))) -> 72.131383 | AB20: =IF(OR(AA20="N/A",AA20<0),0,IF(AA20>110,X20*110/100,X20*AA20/100)) -> 0 | AD20: =IF(AF20="N/A",0,T.UP3!$F$26) -> 0 | AE20: =VLOOKUP($B$20,T.UP3!$B$4:$T$70,MATCH(DETAIL!$AD$4,T.UP3!$B$5:$T$5,0),FALSE) -> 26242 | AF20: =VLOOKUP($B$20,'R.UP3'!$B$4:$S$54,MATCH(DETAIL!$AD$4,'R.UP3'!$B$5:$S$5,0),FALSE) -> 36549 | AG20: =IF(OR(AE20="N/A",AF20="N/A"),"N/A",IF(AND(AE20=0,AF20=0),0,IF(AF20<0,0,(2-AF20/AE20)*100))) -> 60.723268 | AH20: =IF(OR(AG20="N/A",AG20<0),0,IF(AG20>110,AD20*110/100,AD20*AG20/100)) -> 0
B21: =T.UP3!#REF! -> #REF! | C21: =T.UP3!#REF! -> #REF! | D21: =T.UP3!#REF! -> #REF! | F21: =IF(H21="N/A",0,T.UP3!#REF!) -> #REF! | G21: =VLOOKUP($B$21,T.UP3!$B$4:$T$70,MATCH(DETAIL!$F$4,T.UP3!$B$5:$T$5,0),FALSE) -> #REF! | H21: =VLOOKUP($B$21,'R.UP3'!$B$4:$S$54,MATCH(DETAIL!$F$4,'R.UP3'!$B$5:$S$5,0),FALSE) -> #REF! | I21: =IF(OR(G21="N/A",H21="N/A"),"N/A",IF(AND(G21=0,H21=0),0,(2-H21/G21)*100)) -> #REF! | J21: =IF(OR(I21="N/A",I21<0),0,IF(I21>110,F21*110/100,F21*I21/100)) -> #REF! | L21: =IF(N21="N/A",0,T.UP3!#REF!) -> #REF! | M21: =VLOOKUP($B$21,T.UP3!$B$4:$T$70,MATCH(DETAIL!$L$4,T.UP3!$B$5:$T$5,0),FALSE) -> #REF! | N21: =VLOOKUP($B$21,'R.UP3'!$B$4:$S$54,MATCH(DETAIL!$L$4,'R.UP3'!$B$5:$S$5,0),FALSE) -> #REF! | O21: =IF(OR(M21="N/A",N21="N/A"),"N/A",IF(AND(M21=0,N21=0),0,(2-N21/M21)*100)) -> #REF! | P21: =IF(OR(O21="N/A",O21<0),0,IF(O21>110,L21*110/100,L21*O21/100)) -> #REF! | R21: =IF(T21="N/A",0,T.UP3!#REF!) -> #REF! | S21: =VLOOKUP($B$21,T.UP3!$B$4:$T$70,MATCH(DETAIL!$R$4,T.UP3!$B$5:$T$5,0),FALSE) -> #REF! | T21: =VLOOKUP($B$21,'R.UP3'!$B$4:$S$54,MATCH(DETAIL!$R$4,'R.UP3'!$B$5:$S$5,0),FALSE) -> #REF! | U21: =IF(OR(S21="N/A",T21="N/A"),"N/A",IF(AND(S21=0,T21=0),0,(2-T21/S21)*100)) -> #REF! | V21: =IF(OR(U21="N/A",U21<0),0,IF(U21>110,R21*110/100,R21*U21/100)) -> #REF! | X21: =IF(Z21="N/A",0,T.UP3!#REF!) -> #REF! | Y21: =VLOOKUP($B$21,T.UP3!$B$4:$T$70,MATCH(DETAIL!$X$4,T.UP3!$B$5:$T$5,0),FALSE) -> #REF! | Z21: =VLOOKUP($B$21,'R.UP3'!$B$4:$S$54,MATCH(DETAIL!$X$4,'R.UP3'!$B$5:$S$5,0),FALSE) -> #REF! | AA21: =IF(OR(Y21="N/A",Z21="N/A"),"N/A",IF(AND(Y21=0,Z21=0),0,(2-Z21/Y21)*100)) -> #REF! | AB21: =IF(OR(AA21="N/A",AA21<0),0,IF(AA21>110,X21*110/100,X21*AA21/100)) -> #REF! | AD21: =IF(AF21="N/A",0,T.UP3!#REF!) -> #REF! | AE21: =VLOOKUP($B$21,T.UP3!$B$4:$T$70,MATCH(DETAIL!$AD$4,T.UP3!$B$5:$T$5,0),FALSE) -> #REF! | AF21: =VLOOKUP($B$21,'R.UP3'!$B$4:$S$54,MATCH(DETAIL!$AD$4,'R.UP3'!$B$5:$S$5,0),FALSE) -> #REF! | AG21: =IF(OR(AE21="N/A",AF21="N/A"),"N/A",IF(AND(AE21=0,AF21=0),0,(2-AF21/AE21)*100)) -> #REF! | AH21: =IF(OR(AG21="N/A",AG21<0),0,IF(AG21>110,AD21*110/100,AD21*AG21/100)) -> #REF!
A22: =T.UP3!A38 -> 0 | B22: =T.UP3!B38 -> b. Penambahan Jumlah Pelanggan | C22: =T.UP3!C38 -> ñ | D22: =T.UP3!D38 -> Pelanggan | F22: =IF(H22="N/A",0,T.UP3!$F$38) -> 2 | G22: =VLOOKUP($B$22,T.UP3!$B$4:$T$70,MATCH(DETAIL!$F$4,T.UP3!$B$5:$T$5,0),FALSE) -> 631 | H22: =VLOOKUP($B$22,'R.UP3'!$B$4:$S$54,MATCH(DETAIL!$F$4,'R.UP3'!$B$5:$S$5,0),FALSE) -> 498 | I22: =IF(OR(G22="N/A",H22="N/A"),"N/A",IF(AND(G22=0,H22=0),0,H22/G22*100)) -> 78.922345 | J22: =IF(OR(I22="N/A",I22<0),0,IF(I22>110,F22*110/100,F22*I22/100)) -> 1.5784469 | L22: =IF(N22="N/A",0,T.UP3!$F$38) -> 2 | M22: =VLOOKUP($B$22,T.UP3!$B$4:$T$70,MATCH(DETAIL!$L$4,T.UP3!$B$5:$T$5,0),FALSE) -> 1283 | N22: =VLOOKUP($B$22,'R.UP3'!$B$4:$S$54,MATCH(DETAIL!$L$4,'R.UP3'!$B$5:$S$5,0),FALSE) -> 965 | O22: =IF(OR(M22="N/A",N22="N/A"),"N/A",IF(AND(M22=0,N22=0),0,N22/M22*100)) -> 75.214341 | P22: =IF(OR(O22="N/A",O22<0),0,IF(O22>110,L22*110/100,L22*O22/100)) -> 1.5042868 | R22: =IF(T22="N/A",0,T.UP3!$F$38) -> 2 | S22: =VLOOKUP($B$22,T.UP3!$B$4:$T$70,MATCH(DETAIL!$R$4,T.UP3!$B$5:$T$5,0),FALSE) -> 1968 | T22: =VLOOKUP($B$22,'R.UP3'!$B$4:$S$54,MATCH(DETAIL!$R$4,'R.UP3'!$B$5:$S$5,0),FALSE) -> 1364 | U22: =IF(OR(S22="N/A",T22="N/A"),"N/A",IF(AND(S22=0,T22=0),0,T22/S22*100)) -> 69.308943 | V22: =IF(OR(U22="N/A",U22<0),0,IF(U22>110,R22*110/100,R22*U22/100)) -> 1.3861789 | X22: =IF(Z22="N/A",0,T.UP3!$F$38) -> 2 | Y22: =VLOOKUP($B$22,T.UP3!$B$4:$T$70,MATCH(DETAIL!$X$4,T.UP3!$B$5:$T$5,0),FALSE) -> 2626 | Z22: =VLOOKUP($B$22,'R.UP3'!$B$4:$S$54,MATCH(DETAIL!$X$4,'R.UP3'!$B$5:$S$5,0),FALSE) -> 1792 | AA22: =IF(OR(Y22="N/A",Z22="N/A"),"N/A",IF(AND(Y22=0,Z22=0),0,Z22/Y22*100)) -> 68.24067 | AB22: =IF(OR(AA22="N/A",AA22<0),0,IF(AA22>110,X22*110/100,X22*AA22/100)) -> 1.3648134 | AD22: =IF(AF22="N/A",0,T.UP3!$F$38) -> 2 | AE22: =VLOOKUP($B$22,T.UP3!$B$4:$T$70,MATCH(DETAIL!$AD$4,T.UP3!$B$5:$T$5,0),FALSE) -> 3639 | AF22: =VLOOKUP($B$22,'R.UP3'!$B$4:$S$54,MATCH(DETAIL!$AD$4,'R.UP3'!$B$5:$S$5,0),FALSE) -> 2153 | AG22: =IF(OR(AE22="N/A",AF22="N/A"),"N/A",IF(AND(AE22=0,AF22=0),0,AF22/AE22*100)) -> 59.164606 | AH22: =IF(OR(AG22="N/A",AG22<0),0,IF(AG22>110,AD22*110/100,AD22*AG22/100)) -> 1.1832921
A23: =T.UP3!A41 -> 0 | B23: =T.UP3!B41 -> e. Penambahan Jumlah Pelanggan Rumah Tangga Lisdes | C23: =T.UP3!C41 -> ñ | D23: =T.UP3!D41 -> Pelanggan | F23: =IF(H23="N/A",0,T.UP3!$F$41) -> 1.5 | G23: =VLOOKUP($B$23,T.UP3!$B$4:$T$70,MATCH(DETAIL!$F$4,T.UP3!$B$5:$T$5,0),FALSE) -> 3 | H23: =VLOOKUP($B$23,'R.UP3'!$B$4:$S$54,MATCH(DETAIL!$F$4,'R.UP3'!$B$5:$S$5,0),FALSE) -> 50 | I23: =IF(OR(G23="N/A",H23="N/A"),"N/A",IF(AND(G23=0,H23=0),0,H23/G23*100)) -> 1666.6667 | J23: =IF(OR(I23="N/A",I23<0),0,IF(I23>110,F23*110/100,F23*I23/100)) -> 1.65 | L23: =IF(N23="N/A",0,T.UP3!$F$41) -> 1.5 | M23: =VLOOKUP($B$23,T.UP3!$B$4:$T$70,MATCH(DETAIL!$L$4,T.UP3!$B$5:$T$5,0),FALSE) -> 4 | N23: =VLOOKUP($B$23,'R.UP3'!$B$4:$S$54,MATCH(DETAIL!$L$4,'R.UP3'!$B$5:$S$5,0),FALSE) -> 71 | O23: =IF(OR(M23="N/A",N23="N/A"),"N/A",IF(AND(M23=0,N23=0),0,N23/M23*100)) -> 1775 | P23: =IF(OR(O23="N/A",O23<0),0,IF(O23>110,L23*110/100,L23*O23/100)) -> 1.65 | R23: =IF(T23="N/A",0,T.UP3!$F$41) -> 1.5 | S23: =VLOOKUP($B$23,T.UP3!$B$4:$T$70,MATCH(DETAIL!$R$4,T.UP3!$B$5:$T$5,0),FALSE) -> 4 | T23: =VLOOKUP($B$23,'R.UP3'!$B$4:$S$54,MATCH(DETAIL!$R$4,'R.UP3'!$B$5:$S$5,0),FALSE) -> 87 | U23: =IF(OR(S23="N/A",T23="N/A"),"N/A",IF(AND(S23=0,T23=0),0,T23/S23*100)) -> 2175 | V23: =IF(OR(U23="N/A",U23<0),0,IF(U23>110,R23*110/100,R23*U23/100)) -> 1.65 | X23: =IF(Z23="N/A",0,T.UP3!$F$41) -> 1.5 | Y23: =VLOOKUP($B$23,T.UP3!$B$4:$T$70,MATCH(DETAIL!$X$4,T.UP3!$B$5:$T$5,0),FALSE) -> 4 | Z23: =VLOOKUP($B$23,'R.UP3'!$B$4:$S$54,MATCH(DETAIL!$X$4,'R.UP3'!$B$5:$S$5,0),FALSE) -> 113 | AA23: =IF(OR(Y23="N/A",Z23="N/A"),"N/A",IF(AND(Y23=0,Z23=0),0,Z23/Y23*100)) -> 2825 | AB23: =IF(OR(AA23="N/A",AA23<0),0,IF(AA23>110,X23*110/100,X23*AA23/100)) -> 1.65 | AD23: =IF(AF23="N/A",0,T.UP3!$F$41) -> 1.5 | AE23: =VLOOKUP($B$23,T.UP3!$B$4:$T$70,MATCH(DETAIL!$AD$4,T.UP3!$B$5:$T$5,0),FALSE) -> 8 | AF23: =VLOOKUP($B$23,'R.UP3'!$B$4:$S$54,MATCH(DETAIL!$AD$4,'R.UP3'!$B$5:$S$5,0),FALSE) -> 134 | AG23: =IF(OR(AE23="N/A",AF23="N/A"),"N/A",IF(AND(AE23=0,AF23=0),0,AF23/AE23*100)) -> 1675 | AH23: =IF(OR(AG23="N/A",AG23<0),0,IF(AG23>110,AD23*110/100,AD23*AG23/100)) -> 1.65
A24: =T.UP3!A43 -> 10 | B24: =T.UP3!B43 -> Pengelolaan Pembacaan Meter | C24: =T.UP3!C43 -> 0 | D24: =T.UP3!D43 -> 0 | F24: =IF(H24="N/A",0,T.UP3!$F$43) -> 4 | G24: =VLOOKUP($B$24,T.UP3!$B$4:$T$70,MATCH(DETAIL!$F$4,T.UP3!$B$5:$T$5,0),FALSE) -> 0 | H24: =VLOOKUP($B$24,'R.UP3'!$B$4:$S$54,MATCH(DETAIL!$F$4,'R.UP3'!$B$5:$S$5,0),FALSE) -> 0 | I24: =IF(OR(G24="N/A",H24="N/A"),"N/A",IF(AND(G24=0,H24=0),0,H24/G24*100)) -> 0 | J24: =IF(OR(I24="N/A",I24<0),0,IF(I24>110,F24*110/100,F24*I24/100)) -> 0 | L24: =IF(N24="N/A",0,T.UP3!$F$43) -> 4 | M24: =VLOOKUP($B$24,T.UP3!$B$4:$T$70,MATCH(DETAIL!$L$4,T.UP3!$B$5:$T$5,0),FALSE) -> 0 | N24: =VLOOKUP($B$24,'R.UP3'!$B$4:$S$54,MATCH(DETAIL!$L$4,'R.UP3'!$B$5:$S$5,0),FALSE) -> 0 | O24: =IF(OR(M24="N/A",N24="N/A"),"N/A",IF(AND(M24=0,N24=0),0,N24/M24*100)) -> 0 | P24: =IF(OR(O24="N/A",O24<0),0,IF(O24>110,L24*110/100,L24*O24/100)) -> 0 | R24: =IF(T24="N/A",0,T.UP3!$F$43) -> 4 | S24: =VLOOKUP($B$24,T.UP3!$B$4:$T$70,MATCH(DETAIL!$R$4,T.UP3!$B$5:$T$5,0),FALSE) -> 0 | T24: =VLOOKUP($B$24,'R.UP3'!$B$4:$S$54,MATCH(DETAIL!$R$4,'R.UP3'!$B$5:$S$5,0),FALSE) -> 0 | U24: =IF(OR(S24="N/A",T24="N/A"),"N/A",IF(AND(S24=0,T24=0),0,T24/S24*100)) -> 0 | V24: =IF(OR(U24="N/A",U24<0),0,IF(U24>110,R24*110/100,R24*U24/100)) -> 0 | X24: =IF(Z24="N/A",0,T.UP3!$F$43) -> 4 | Y24: =VLOOKUP($B$24,T.UP3!$B$4:$T$70,MATCH(DETAIL!$X$4,T.UP3!$B$5:$T$5,0),FALSE) -> 0 | Z24: =VLOOKUP($B$24,'R.UP3'!$B$4:$S$54,MATCH(DETAIL!$X$4,'R.UP3'!$B$5:$S$5,0),FALSE) -> 0 | AA24: =IF(OR(Y24="N/A",Z24="N/A"),"N/A",IF(AND(Y24=0,Z24=0),0,Z24/Y24*100)) -> 0 | AB24: =IF(OR(AA24="N/A",AA24<0),0,IF(AA24>110,X24*110/100,X24*AA24/100)) -> 0 | AD24: =IF(AF24="N/A",0,T.UP3!$F$43) -> 4 | AE24: =VLOOKUP($B$24,T.UP3!$B$4:$T$70,MATCH(DETAIL!$AD$4,T.UP3!$B$5:$T$5,0),FALSE) -> 0 | AF24: =VLOOKUP($B$24,'R.UP3'!$B$4:$S$54,MATCH(DETAIL!$AD$4,'R.UP3'!$B$5:$S$5,0),FALSE) -> 0 | AG24: =IF(OR(AE24="N/A",AF24="N/A"),"N/A",IF(AND(AE24=0,AF24=0),0,AF24/AE24*100)) -> 0 | AH24: =IF(OR(AG24="N/A",AG24<0),0,IF(AG24>110,AD24*110/100,AD24*AG24/100)) -> 0
A25: =T.UP3!A44 -> 0 | B25: =T.UP3!B44 -> a. Jumlah Pengguna Swa Cam
B26: =T.UP3!#REF! -> #REF! | C26: =T.UP3!#REF! -> #REF! | D26: =T.UP3!#REF! -> #REF! | F26: =IF(H26="N/A",0,T.UP3!#REF!) -> #REF! | G26: =VLOOKUP($B$26,T.UP3!$B$4:$T$70,MATCH(DETAIL!$F$4,T.UP3!$B$5:$T$5,0),FALSE) -> #REF! | H26: =VLOOKUP($B$26,'R.UP3'!$B$4:$S$54,MATCH(DETAIL!$F$4,'R.UP3'!$B$5:$S$5,0),FALSE) -> #REF! | I26: =IF(OR(G26="N/A",H26="N/A"),"N/A",IF(AND(G26=0,H26=0),0,H26/G26*100)) -> #REF! | J26: =IF(OR(I26="N/A",I26<0),0,IF(I26>110,F26*110/100,F26*I26/100)) -> #REF! | L26: =IF(N26="N/A",0,T.UP3!#REF!) -> #REF! | M26: =VLOOKUP($B$26,T.UP3!$B$4:$T$70,MATCH(DETAIL!$L$4,T.UP3!$B$5:$T$5,0),FALSE) -> #REF! | N26: =VLOOKUP($B$26,'R.UP3'!$B$4:$S$54,MATCH(DETAIL!$L$4,'R.UP3'!$B$5:$S$5,0),FALSE) -> #REF! | O26: =IF(OR(M26="N/A",N26="N/A"),"N/A",IF(AND(M26=0,N26=0),0,N26/M26*100)) -> #REF! | P26: =IF(OR(O26="N/A",O26<0),0,IF(O26>110,L26*110/100,L26*O26/100)) -> #REF! | R26: =IF(T26="N/A",0,T.UP3!#REF!) -> #REF! | S26: =VLOOKUP($B$26,T.UP3!$B$4:$T$70,MATCH(DETAIL!$R$4,T.UP3!$B$5:$T$5,0),FALSE) -> #REF! | T26: =VLOOKUP($B$26,'R.UP3'!$B$4:$S$54,MATCH(DETAIL!$R$4,'R.UP3'!$B$5:$S$5,0),FALSE) -> #REF! | U26: =IF(OR(S26="N/A",T26="N/A"),"N/A",IF(AND(S26=0,T26=0),0,T26/S26*100)) -> #REF! | V26: =IF(OR(U26="N/A",U26<0),0,IF(U26>110,R26*110/100,R26*U26/100)) -> #REF! | X26: =IF(Z26="N/A",0,T.UP3!#REF!) -> #REF! | Y26: =VLOOKUP($B$26,T.UP3!$B$4:$T$70,MATCH(DETAIL!$X$4,T.UP3!$B$5:$T$5,0),FALSE) -> #REF! | Z26: =VLOOKUP($B$26,'R.UP3'!$B$4:$S$54,MATCH(DETAIL!$X$4,'R.UP3'!$B$5:$S$5,0),FALSE) -> #REF! | AA26: =IF(OR(Y26="N/A",Z26="N/A"),"N/A",IF(AND(Y26=0,Z26=0),0,Z26/Y26*100)) -> #REF! | AB26: =IF(OR(AA26="N/A",AA26<0),0,IF(AA26>110,X26*110/100,X26*AA26/100)) -> #REF! | AD26: =IF(AF26="N/A",0,T.UP3!#REF!) -> #REF! | AE26: =VLOOKUP($B$26,T.UP3!$B$4:$T$70,MATCH(DETAIL!$AD$4,T.UP3!$B$5:$T$5,0),FALSE) -> #REF! | AF26: =VLOOKUP($B$26,'R.UP3'!$B$4:$S$54,MATCH(DETAIL!$AD$4,'R.UP3'!$B$5:$S$5,0),FALSE) -> #REF! | AG26: =IF(OR(AE26="N/A",AF26="N/A"),"N/A",IF(AND(AE26=0,AF26=0),0,AF26/AE26*100)) -> #REF! | AH26: =IF(OR(AG26="N/A",AG26<0),0,IF(AG26>110,AD26*110/100,AD26*AG26/100)) -> #REF!
B27: =T.UP3!B47 -> a. Pencapaian Rata-Rata Saldo Tanggal 20 diluar Konsumen Instansi (Kementerian & Lembaga)
B28: =T.UP3!B51 -> a. Pengendalian Penggunaan Anggaran Investasi sesuai RKAP | C28: =T.UP3!C51 -> ó | D28: =T.UP3!D51 -> % | F28: =IF(H28="N/A",0,T.UP3!$F$51) -> 0 | G28: =VLOOKUP($B$28,T.UP3!$B$4:$T$70,MATCH(DETAIL!$F$4,T.UP3!$B$5:$T$5,0),FALSE) -> 95-100 | H28: =VLOOKUP($B$28,'R.UP3'!$B$4:$S$54,MATCH(DETAIL!$F$4,'R.UP3'!$B$5:$S$5,0),FALSE) -> 100 | I28: =IF(OR(G28="N/A",H28="N/A"),"N/A",IF(AND(G28=0,H28=0),0,(2-H28/G28)*100)) -> #VALUE! | J28: =IF(OR(I28="N/A",I28<0),0,IF(I28>110,F28*110/100,F28*I28/100)) -> #VALUE! | L28: =IF(N28="N/A",0,T.UP3!$F$51) -> 0 | M28: =VLOOKUP($B$28,T.UP3!$B$4:$T$70,MATCH(DETAIL!$L$4,T.UP3!$B$5:$T$5,0),FALSE) -> 95-100 | N28: =VLOOKUP($B$28,'R.UP3'!$B$4:$S$54,MATCH(DETAIL!$L$4,'R.UP3'!$B$5:$S$5,0),FALSE) -> 100 | O28: =IF(OR(M28="N/A",N28="N/A"),"N/A",IF(AND(M28=0,N28=0),0,(2-N28/M28)*100)) -> #VALUE! | P28: =IF(OR(O28="N/A",O28<0),0,IF(O28>110,L28*110/100,L28*O28/100)) -> #VALUE! | R28: =IF(T28="N/A",0,T.UP3!$F$51) -> 0 | S28: =VLOOKUP($B$28,T.UP3!$B$4:$T$70,MATCH(DETAIL!$R$4,T.UP3!$B$5:$T$5,0),FALSE) -> 95-100 | T28: =VLOOKUP($B$28,'R.UP3'!$B$4:$S$54,MATCH(DETAIL!$R$4,'R.UP3'!$B$5:$S$5,0),FALSE) -> 39.55 | U28: =IF(OR(S28="N/A",T28="N/A"),"N/A",IF(AND(S28=0,T28=0),0,(2-T28/S28)*100)) -> #VALUE! | V28: =IF(OR(U28="N/A",U28<0),0,IF(U28>110,R28*110/100,R28*U28/100)) -> #VALUE! | X28: =IF(Z28="N/A",0,T.UP3!$F$51) -> 0 | Y28: =VLOOKUP($B$28,T.UP3!$B$4:$T$70,MATCH(DETAIL!$X$4,T.UP3!$B$5:$T$5,0),FALSE) -> 95-100 | Z28: =VLOOKUP($B$28,'R.UP3'!$B$4:$S$54,MATCH(DETAIL!$X$4,'R.UP3'!$B$5:$S$5,0),FALSE) -> 58.86 | AA28: =IF(OR(Y28="N/A",Z28="N/A"),"N/A",IF(AND(Y28=0,Z28=0),0,(2-Z28/Y28)*100)) -> #VALUE! | AB28: =IF(OR(AA28="N/A",AA28<0),0,IF(AA28>110,X28*110/100,X28*AA28/100)) -> #VALUE! | AD28: =IF(AF28="N/A",0,T.UP3!$F$51) -> 0 | AE28: =VLOOKUP($B$28,T.UP3!$B$4:$T$70,MATCH(DETAIL!$AD$4,T.UP3!$B$5:$T$5,0),FALSE) -> 95-100 | AF28: =VLOOKUP($B$28,'R.UP3'!$B$4:$S$54,MATCH(DETAIL!$AD$4,'R.UP3'!$B$5:$S$5,0),FALSE) -> 71.11 | AG28: =IF(OR(AE28="N/A",AF28="N/A"),"N/A",IF(AND(AE28=0,AF28=0),0,(2-AF28/AE28)*100)) -> #VALUE! | AH28: =IF(OR(AG28="N/A",AG28<0),0,IF(AG28>110,AD28*110/100,AD28*AG28/100)) -> #VALUE!
B29: =T.UP3!#REF! -> #REF! | C29: =T.UP3!#REF! -> #REF! | D29: =T.UP3!#REF! -> #REF! | F29: =IF(H29="N/A",0,T.UP3!#REF!) -> #REF! | G29: =VLOOKUP($B$29,T.UP3!$B$4:$T$70,MATCH(DETAIL!$F$4,T.UP3!$B$5:$T$5,0),FALSE) -> #REF! | H29: =VLOOKUP($B$29,'R.UP3'!$B$4:$S$54,MATCH(DETAIL!$F$4,'R.UP3'!$B$5:$S$5,0),FALSE) -> #REF! | I29: =IF(OR(G29="N/A",H29="N/A"),"N/A",IF(AND(G29=0,H29=0),0,(2-H29/G29)*100)) -> #REF! | J29: =IF(OR(I29="N/A",I29<0),0,IF(I29>110,F29*110/100,F29*I29/100)) -> #REF! | L29: =IF(N29="N/A",0,T.UP3!#REF!) -> #REF! | M29: =VLOOKUP($B$29,T.UP3!$B$4:$T$70,MATCH(DETAIL!$L$4,T.UP3!$B$5:$T$5,0),FALSE) -> #REF! | N29: =VLOOKUP($B$29,'R.UP3'!$B$4:$S$54,MATCH(DETAIL!$L$4,'R.UP3'!$B$5:$S$5,0),FALSE) -> #REF! | O29: =IF(OR(M29="N/A",N29="N/A"),"N/A",IF(AND(M29=0,N29=0),0,(2-N29/M29)*100)) -> #REF! | P29: =IF(OR(O29="N/A",O29<0),0,IF(O29>110,L29*110/100,L29*O29/100)) -> #REF! | R29: =IF(T29="N/A",0,T.UP3!#REF!) -> #REF! | S29: =VLOOKUP($B$29,T.UP3!$B$4:$T$70,MATCH(DETAIL!$R$4,T.UP3!$B$5:$T$5,0),FALSE) -> #REF! | T29: =VLOOKUP($B$29,'R.UP3'!$B$4:$S$54,MATCH(DETAIL!$R$4,'R.UP3'!$B$5:$S$5,0),FALSE) -> #REF! | U29: =IF(OR(S29="N/A",T29="N/A"),"N/A",IF(AND(S29=0,T29=0),0,(2-T29/S29)*100)) -> #REF! | V29: =IF(OR(U29="N/A",U29<0),0,IF(U29>110,R29*110/100,R29*U29/100)) -> #REF! | X29: =IF(Z29="N/A",0,T.UP3!#REF!) -> #REF! | Y29: =VLOOKUP($B$29,T.UP3!$B$4:$T$70,MATCH(DETAIL!$X$4,T.UP3!$B$5:$T$5,0),FALSE) -> #REF! | Z29: =VLOOKUP($B$29,'R.UP3'!$B$4:$S$54,MATCH(DETAIL!$X$4,'R.UP3'!$B$5:$S$5,0),FALSE) -> #REF! | AA29: =IF(OR(Y29="N/A",Z29="N/A"),"N/A",IF(AND(Y29=0,Z29=0),0,(2-Z29/Y29)*100)) -> #REF! | AB29: =IF(OR(AA29="N/A",AA29<0),0,IF(AA29>110,X29*110/100,X29*AA29/100)) -> #REF! | AD29: =IF(AF29="N/A",0,T.UP3!#REF!) -> #REF! | AE29: =VLOOKUP($B$29,T.UP3!$B$4:$T$70,MATCH(DETAIL!$AD$4,T.UP3!$B$5:$T$5,0),FALSE) -> #REF! | AF29: =VLOOKUP($B$29,'R.UP3'!$B$4:$S$54,MATCH(DETAIL!$AD$4,'R.UP3'!$B$5:$S$5,0),FALSE) -> #REF! | AG29: =IF(OR(AE29="N/A",AF29="N/A"),"N/A",IF(AND(AE29=0,AF29=0),0,(2-AF29/AE29)*100)) -> #REF! | AH29: =IF(OR(AG29="N/A",AG29<0),0,IF(AG29>110,AD29*110/100,AD29*AG29/100)) -> #REF!
B30: =T.UP3!#REF! -> #REF! | C30: =T.UP3!#REF! -> #REF! | D30: =T.UP3!#REF! -> #REF! | F30: =IF(H30="N/A",0,T.UP3!#REF!) -> #REF! | G30: =VLOOKUP($B$30,T.UP3!$B$4:$T$70,MATCH(DETAIL!$F$4,T.UP3!$B$5:$T$5,0),FALSE) -> #REF! | H30: =VLOOKUP($B$30,'R.UP3'!$B$4:$S$54,MATCH(DETAIL!$F$4,'R.UP3'!$B$5:$S$5,0),FALSE) -> #REF! | I30: =IF(OR(G30="N/A",H30="N/A"),"N/A",IF(AND(G30=0,H30=0),0,(2-H30/G30)*100)) -> #REF! | J30: =IF(OR(I30="N/A",I30<0),0,IF(I30>110,F30*110/100,F30*I30/100)) -> #REF! | L30: =IF(N30="N/A",0,T.UP3!#REF!) -> #REF! | M30: =VLOOKUP($B$30,T.UP3!$B$4:$T$70,MATCH(DETAIL!$L$4,T.UP3!$B$5:$T$5,0),FALSE) -> #REF! | N30: =VLOOKUP($B$30,'R.UP3'!$B$4:$S$54,MATCH(DETAIL!$L$4,'R.UP3'!$B$5:$S$5,0),FALSE) -> #REF! | O30: =IF(OR(M30="N/A",N30="N/A"),"N/A",IF(AND(M30=0,N30=0),0,(2-N30/M30)*100)) -> #REF! | P30: =IF(OR(O30="N/A",O30<0),0,IF(O30>110,L30*110/100,L30*O30/100)) -> #REF! | R30: =IF(T30="N/A",0,T.UP3!#REF!) -> #REF! | S30: =VLOOKUP($B$30,T.UP3!$B$4:$T$70,MATCH(DETAIL!$R$4,T.UP3!$B$5:$T$5,0),FALSE) -> #REF! | T30: =VLOOKUP($B$30,'R.UP3'!$B$4:$S$54,MATCH(DETAIL!$R$4,'R.UP3'!$B$5:$S$5,0),FALSE) -> #REF! | U30: =IF(OR(S30="N/A",T30="N/A"),"N/A",IF(AND(S30=0,T30=0),0,(2-T30/S30)*100)) -> #REF! | V30: =IF(OR(U30="N/A",U30<0),0,IF(U30>110,R30*110/100,R30*U30/100)) -> #REF! | X30: =IF(Z30="N/A",0,T.UP3!#REF!) -> #REF! | Y30: =VLOOKUP($B$30,T.UP3!$B$4:$T$70,MATCH(DETAIL!$X$4,T.UP3!$B$5:$T$5,0),FALSE) -> #REF! | Z30: =VLOOKUP($B$30,'R.UP3'!$B$4:$S$54,MATCH(DETAIL!$X$4,'R.UP3'!$B$5:$S$5,0),FALSE) -> #REF! | AA30: =IF(OR(Y30="N/A",Z30="N/A"),"N/A",IF(AND(Y30=0,Z30=0),0,(2-Z30/Y30)*100)) -> #REF! | AB30: =IF(OR(AA30="N/A",AA30<0),0,IF(AA30>110,X30*110/100,X30*AA30/100)) -> #REF! | AD30: =IF(AF30="N/A",0,T.UP3!#REF!) -> #REF! | AE30: =VLOOKUP($B$30,T.UP3!$B$4:$T$70,MATCH(DETAIL!$AD$4,T.UP3!$B$5:$T$5,0),FALSE) -> #REF! | AF30: =VLOOKUP($B$30,'R.UP3'!$B$4:$S$54,MATCH(DETAIL!$AD$4,'R.UP3'!$B$5:$S$5,0),FALSE) -> #REF! | AG30: =IF(OR(AE30="N/A",AF30="N/A"),"N/A",IF(AND(AE30=0,AF30=0),0,(2-AF30/AE30)*100)) -> #REF! | AH30: =IF(OR(AG30="N/A",AG30<0),0,IF(AG30>110,AD30*110/100,AD30*AG30/100)) -> #REF!
B31: =T.UP3!#REF! -> #REF! | C31: =T.UP3!#REF! -> #REF! | D31: =T.UP3!#REF! -> #REF! | F31: =IF(H31="N/A",0,T.UP3!#REF!) -> #REF! | G31: =VLOOKUP($B$31,T.UP3!$B$4:$T$70,MATCH(DETAIL!$F$4,T.UP3!$B$5:$T$5,0),FALSE) -> #REF! | H31: =VLOOKUP($B$31,'R.UP3'!$B$4:$S$54,MATCH(DETAIL!$F$4,'R.UP3'!$B$5:$S$5,0),FALSE) -> #REF! | I31: =IF(OR(G31="N/A",H31="N/A"),"N/A",IF(AND(G31=0,H31=0),0,H31/G31*100)) -> #REF! | J31: =IF(OR(I31="N/A",I31<0),0,IF(I31>110,F31*110/100,F31*I31/100)) -> #REF! | L31: =IF(N31="N/A",0,T.UP3!#REF!) -> #REF! | M31: =VLOOKUP($B$31,T.UP3!$B$4:$T$70,MATCH(DETAIL!$L$4,T.UP3!$B$5:$T$5,0),FALSE) -> #REF! | N31: =VLOOKUP($B$31,'R.UP3'!$B$4:$S$54,MATCH(DETAIL!$L$4,'R.UP3'!$B$5:$S$5,0),FALSE) -> #REF! | O31: =IF(OR(M31="N/A",N31="N/A"),"N/A",IF(AND(M31=0,N31=0),0,N31/M31*100)) -> #REF! | P31: =IF(OR(O31="N/A",O31<0),0,IF(O31>110,L31*110/100,L31*O31/100)) -> #REF! | R31: =IF(T31="N/A",0,T.UP3!#REF!) -> #REF! | S31: =VLOOKUP($B$31,T.UP3!$B$4:$T$70,MATCH(DETAIL!$R$4,T.UP3!$B$5:$T$5,0),FALSE) -> #REF! | T31: =VLOOKUP($B$31,'R.UP3'!$B$4:$S$54,MATCH(DETAIL!$R$4,'R.UP3'!$B$5:$S$5,0),FALSE) -> #REF! | U31: =IF(OR(S31="N/A",T31="N/A"),"N/A",IF(AND(S31=0,T31=0),0,T31/S31*100)) -> #REF! | V31: =IF(OR(U31="N/A",U31<0),0,IF(U31>110,R31*110/100,R31*U31/100)) -> #REF! | X31: =IF(Z31="N/A",0,T.UP3!#REF!) -> #REF! | Y31: =VLOOKUP($B$31,T.UP3!$B$4:$T$70,MATCH(DETAIL!$X$4,T.UP3!$B$5:$T$5,0),FALSE) -> #REF! | Z31: =VLOOKUP($B$31,'R.UP3'!$B$4:$S$54,MATCH(DETAIL!$X$4,'R.UP3'!$B$5:$S$5,0),FALSE) -> #REF! | AA31: =IF(OR(Y31="N/A",Z31="N/A"),"N/A",IF(AND(Y31=0,Z31=0),0,Z31/Y31*100)) -> #REF! | AB31: =IF(OR(AA31="N/A",AA31<0),0,IF(AA31>110,X31*110/100,X31*AA31/100)) -> #REF! | AD31: =IF(AF31="N/A",0,T.UP3!#REF!) -> #REF! | AE31: =VLOOKUP($B$31,T.UP3!$B$4:$T$70,MATCH(DETAIL!$AD$4,T.UP3!$B$5:$T$5,0),FALSE) -> #REF! | AF31: =VLOOKUP($B$31,'R.UP3'!$B$4:$S$54,MATCH(DETAIL!$AD$4,'R.UP3'!$B$5:$S$5,0),FALSE) -> #REF! | AG31: =IF(OR(AE31="N/A",AF31="N/A"),"N/A",IF(AND(AE31=0,AF31=0),0,AF31/AE31*100)) -> #REF! | AH31: =IF(OR(AG31="N/A",AG31<0),0,IF(AG31>110,AD31*110/100,AD31*AG31/100)) -> #REF!
B32: =T.UP3!B52 -> b. Usulan Penghapusan ATTB | C32: =T.UP3!C52 -> ñ | D32: =T.UP3!D52 -> Rp. Milyar | F32: =IF(H32="N/A",0,T.UP3!$F$52) -> 0 | G32: =VLOOKUP($B$32,T.UP3!$B$4:$T$70,MATCH(DETAIL!$F$4,T.UP3!$B$5:$T$5,0),FALSE) -> 0 | H32: =VLOOKUP($B$32,'R.UP3'!$B$4:$S$54,MATCH(DETAIL!$F$4,'R.UP3'!$B$5:$S$5,0),FALSE) -> 0 | I32: =IF(OR(G32="N/A",H32="N/A"),"N/A",IF(AND(G32=0,H32=0),0,H32/G32*100)) -> 0 | J32: =IF(OR(I32="N/A",I32<0),0,IF(I32>110,F32*110/100,F32*I32/100)) -> 0 | L32: =IF(N32="N/A",0,T.UP3!$F$52) -> 0 | M32: =VLOOKUP($B$32,T.UP3!$B$4:$T$70,MATCH(DETAIL!$L$4,T.UP3!$B$5:$T$5,0),FALSE) -> 0 | N32: =VLOOKUP($B$32,'R.UP3'!$B$4:$S$54,MATCH(DETAIL!$L$4,'R.UP3'!$B$5:$S$5,0),FALSE) -> 0 | O32: =IF(OR(M32="N/A",N32="N/A"),"N/A",IF(AND(M32=0,N32=0),0,N32/M32*100)) -> 0 | P32: =IF(OR(O32="N/A",O32<0),0,IF(O32>110,L32*110/100,L32*O32/100)) -> 0 | R32: =IF(T32="N/A",0,T.UP3!$F$52) -> 0 | S32: =VLOOKUP($B$32,T.UP3!$B$4:$T$70,MATCH(DETAIL!$R$4,T.UP3!$B$5:$T$5,0),FALSE) -> 0 | T32: =VLOOKUP($B$32,'R.UP3'!$B$4:$S$54,MATCH(DETAIL!$R$4,'R.UP3'!$B$5:$S$5,0),FALSE) -> 0 | U32: =IF(OR(S32="N/A",T32="N/A"),"N/A",IF(AND(S32=0,T32=0),0,T32/S32*100)) -> 0 | V32: =IF(OR(U32="N/A",U32<0),0,IF(U32>110,R32*110/100,R32*U32/100)) -> 0 | X32: =IF(Z32="N/A",0,T.UP3!$F$52) -> 0 | Y32: =VLOOKUP($B$32,T.UP3!$B$4:$T$70,MATCH(DETAIL!$X$4,T.UP3!$B$5:$T$5,0),FALSE) -> 0 | Z32: =VLOOKUP($B$32,'R.UP3'!$B$4:$S$54,MATCH(DETAIL!$X$4,'R.UP3'!$B$5:$S$5,0),FALSE) -> 0 | AA32: =IF(OR(Y32="N/A",Z32="N/A"),"N/A",IF(AND(Y32=0,Z32=0),0,Z32/Y32*100)) -> 0 | AB32: =IF(OR(AA32="N/A",AA32<0),0,IF(AA32>110,X32*110/100,X32*AA32/100)) -> 0 | AD32: =IF(AF32="N/A",0,T.UP3!$F$52) -> 0 | AE32: =VLOOKUP($B$32,T.UP3!$B$4:$T$70,MATCH(DETAIL!$AD$4,T.UP3!$B$5:$T$5,0),FALSE) -> 0 | AF32: =VLOOKUP($B$32,'R.UP3'!$B$4:$S$54,MATCH(DETAIL!$AD$4,'R.UP3'!$B$5:$S$5,0),FALSE) -> 0 | AG32: =IF(OR(AE32="N/A",AF32="N/A"),"N/A",IF(AND(AE32=0,AF32=0),0,AF32/AE32*100)) -> 0 | AH32: =IF(OR(AG32="N/A",AG32<0),0,IF(AG32>110,AD32*110/100,AD32*AG32/100)) -> 0
B33: =T.UP3!#REF! -> #REF! | C33: =T.UP3!#REF! -> #REF! | D33: =T.UP3!#REF! -> #REF! | F33: =IF(H33="N/A",0,T.UP3!#REF!) -> #REF! | G33: =VLOOKUP($B$33,T.UP3!$B$4:$T$70,MATCH(DETAIL!$F$4,T.UP3!$B$5:$T$5,0),FALSE) -> #REF! | H33: =VLOOKUP($B$33,'R.UP3'!$B$4:$S$54,MATCH(DETAIL!$F$4,'R.UP3'!$B$5:$S$5,0),FALSE) -> #REF! | I33: =IF(OR(G33="N/A",H33="N/A"),"N/A",IF(AND(G33=0,H33=0),0,H33/G33*100)) -> #REF! | J33: =IF(OR(I33="N/A",I33<0),0,IF(I33>110,F33*110/100,F33*I33/100)) -> #REF! | L33: =IF(N33="N/A",0,T.UP3!#REF!) -> #REF! | M33: =VLOOKUP($B$33,T.UP3!$B$4:$T$70,MATCH(DETAIL!$L$4,T.UP3!$B$5:$T$5,0),FALSE) -> #REF! | N33: =VLOOKUP($B$33,'R.UP3'!$B$4:$S$54,MATCH(DETAIL!$L$4,'R.UP3'!$B$5:$S$5,0),FALSE) -> #REF! | O33: =IF(OR(M33="N/A",N33="N/A"),"N/A",IF(AND(M33=0,N33=0),0,N33/M33*100)) -> #REF! | P33: =IF(OR(O33="N/A",O33<0),0,IF(O33>110,L33*110/100,L33*O33/100)) -> #REF! | R33: =IF(T33="N/A",0,T.UP3!#REF!) -> #REF! | S33: =VLOOKUP($B$33,T.UP3!$B$4:$T$70,MATCH(DETAIL!$R$4,T.UP3!$B$5:$T$5,0),FALSE) -> #REF! | T33: =VLOOKUP($B$33,'R.UP3'!$B$4:$S$54,MATCH(DETAIL!$R$4,'R.UP3'!$B$5:$S$5,0),FALSE) -> #REF! | U33: =IF(OR(S33="N/A",T33="N/A"),"N/A",IF(AND(S33=0,T33=0),0,T33/S33*100)) -> #REF! | V33: =IF(OR(U33="N/A",U33<0),0,IF(U33>110,R33*110/100,R33*U33/100)) -> #REF! | X33: =IF(Z33="N/A",0,T.UP3!#REF!) -> #REF! | Y33: =VLOOKUP($B$33,T.UP3!$B$4:$T$70,MATCH(DETAIL!$X$4,T.UP3!$B$5:$T$5,0),FALSE) -> #REF! | Z33: =VLOOKUP($B$33,'R.UP3'!$B$4:$S$54,MATCH(DETAIL!$X$4,'R.UP3'!$B$5:$S$5,0),FALSE) -> #REF! | AA33: =IF(OR(Y33="N/A",Z33="N/A"),"N/A",IF(AND(Y33=0,Z33=0),0,Z33/Y33*100)) -> #REF! | AB33: =IF(OR(AA33="N/A",AA33<0),0,IF(AA33>110,X33*110/100,X33*AA33/100)) -> #REF! | AD33: =IF(AF33="N/A",0,T.UP3!#REF!) -> #REF! | AE33: =VLOOKUP($B$33,T.UP3!$B$4:$T$70,MATCH(DETAIL!$AD$4,T.UP3!$B$5:$T$5,0),FALSE) -> #REF! | AF33: =VLOOKUP($B$33,'R.UP3'!$B$4:$S$54,MATCH(DETAIL!$AD$4,'R.UP3'!$B$5:$S$5,0),FALSE) -> #REF! | AG33: =IF(OR(AE33="N/A",AF33="N/A"),"N/A",IF(AND(AE33=0,AF33=0),0,AF33/AE33*100)) -> #REF! | AH33: =IF(OR(AG33="N/A",AG33<0),0,IF(AG33>110,AD33*110/100,AD33*AG33/100)) -> #REF!
A34: =T.UP3!A53 -> 0 | B34: =T.UP3!B53 -> c. Usulan Penghapusan PRR
B35: =T.UP3!B55 -> a. HCR, OCR, dan Produktivitas Pegawai | C35: =T.UP3!C55 -> ñ | D35: =T.UP3!D55 -> % | F35: =IF(H35="N/A",0,T.UP3!$F$55) -> 0 | G35: =VLOOKUP($B$35,T.UP3!$B$4:$T$70,MATCH(DETAIL!$F$4,T.UP3!$B$5:$T$5,0),FALSE) -> 0 | H35: =VLOOKUP($B$35,'R.UP3'!$B$4:$S$54,MATCH(DETAIL!$F$4,'R.UP3'!$B$5:$S$5,0),FALSE) -> 100 | I35: =IF(OR(G35="N/A",H35="N/A"),"N/A",IF(AND(G35=0,H35=0),0,H35/G35*100)) -> #DIV/0! | J35: =IF(OR(I35="N/A",I35<0),0,IF(I35>110,F35*110/100,F35*I35/100)) -> #DIV/0! | L35: =IF(N35="N/A",0,T.UP3!$F$55) -> 0 | M35: =VLOOKUP($B$35,T.UP3!$B$4:$T$70,MATCH(DETAIL!$L$4,T.UP3!$B$5:$T$5,0),FALSE) -> 0 | N35: =VLOOKUP($B$35,'R.UP3'!$B$4:$S$54,MATCH(DETAIL!$L$4,'R.UP3'!$B$5:$S$5,0),FALSE) -> 100 | O35: =IF(OR(M35="N/A",N35="N/A"),"N/A",IF(AND(M35=0,N35=0),0,N35/M35*100)) -> #DIV/0! | P35: =IF(OR(O35="N/A",O35<0),0,IF(O35>110,L35*110/100,L35*O35/100)) -> #DIV/0! | R35: =IF(T35="N/A",0,T.UP3!$F$55) -> 0 | S35: =VLOOKUP($B$35,T.UP3!$B$4:$T$70,MATCH(DETAIL!$R$4,T.UP3!$B$5:$T$5,0),FALSE) -> 0 | T35: =VLOOKUP($B$35,'R.UP3'!$B$4:$S$54,MATCH(DETAIL!$R$4,'R.UP3'!$B$5:$S$5,0),FALSE) -> 100 | U35: =IF(OR(S35="N/A",T35="N/A"),"N/A",IF(AND(S35=0,T35=0),0,T35/S35*100)) -> #DIV/0! | V35: =IF(OR(U35="N/A",U35<0),0,IF(U35>110,R35*110/100,R35*U35/100)) -> #DIV/0! | X35: =IF(Z35="N/A",0,T.UP3!$F$55) -> 0 | Y35: =VLOOKUP($B$35,T.UP3!$B$4:$T$70,MATCH(DETAIL!$X$4,T.UP3!$B$5:$T$5,0),FALSE) -> 0 | Z35: =VLOOKUP($B$35,'R.UP3'!$B$4:$S$54,MATCH(DETAIL!$X$4,'R.UP3'!$B$5:$S$5,0),FALSE) -> 100 | AA35: =IF(OR(Y35="N/A",Z35="N/A"),"N/A",IF(AND(Y35=0,Z35=0),0,Z35/Y35*100)) -> #DIV/0! | AB35: =IF(OR(AA35="N/A",AA35<0),0,IF(AA35>110,X35*110/100,X35*AA35/100)) -> #DIV/0! | AD35: =IF(AF35="N/A",0,T.UP3!$F$55) -> 0 | AE35: =VLOOKUP($B$35,T.UP3!$B$4:$T$70,MATCH(DETAIL!$AD$4,T.UP3!$B$5:$T$5,0),FALSE) -> 0 | AF35: =VLOOKUP($B$35,'R.UP3'!$B$4:$S$54,MATCH(DETAIL!$AD$4,'R.UP3'!$B$5:$S$5,0),FALSE) -> 100 | AG35: =IF(OR(AE35="N/A",AF35="N/A"),"N/A",IF(AND(AE35=0,AF35=0),0,AF35/AE35*100)) -> #DIV/0! | AH35: =IF(OR(AG35="N/A",AG35<0),0,IF(AG35>110,AD35*110/100,AD35*AG35/100)) -> #DIV/0!
B36: =T.UP3!B56 -> b. Produktivitas Unit | C36: =T.UP3!C56 -> ñ | D36: =T.UP3!D56 -> % | F36: =IF(H36="N/A",0,T.UP3!$F$56) -> #N/A | G36: =VLOOKUP($B$36,T.UP3!$B$4:$T$70,MATCH(DETAIL!$F$4,T.UP3!$B$5:$T$5,0),FALSE) -> 0 | H36: =VLOOKUP($B$36,'R.UP3'!$B$4:$S$54,MATCH(DETAIL!$F$4,'R.UP3'!$B$5:$S$5,0),FALSE) -> #N/A | I36: =IF(OR(G36="N/A",H36="N/A"),"N/A",IF(AND(G36=0,H36=0),0,H36/G36*100)) -> #N/A | J36: =IF(OR(I36="N/A",I36<0),0,IF(I36>110,F36*110/100,F36*I36/100)) -> #N/A | L36: =IF(N36="N/A",0,T.UP3!$F$56) -> #N/A | M36: =VLOOKUP($B$36,T.UP3!$B$4:$T$70,MATCH(DETAIL!$L$4,T.UP3!$B$5:$T$5,0),FALSE) -> 0 | N36: =VLOOKUP($B$36,'R.UP3'!$B$4:$S$54,MATCH(DETAIL!$L$4,'R.UP3'!$B$5:$S$5,0),FALSE) -> #N/A | O36: =IF(OR(M36="N/A",N36="N/A"),"N/A",IF(AND(M36=0,N36=0),0,N36/M36*100)) -> #N/A | P36: =IF(OR(O36="N/A",O36<0),0,IF(O36>110,L36*110/100,L36*O36/100)) -> #N/A | R36: =IF(T36="N/A",0,T.UP3!$F$56) -> #N/A | S36: =VLOOKUP($B$36,T.UP3!$B$4:$T$70,MATCH(DETAIL!$R$4,T.UP3!$B$5:$T$5,0),FALSE) -> 0 | T36: =VLOOKUP($B$36,'R.UP3'!$B$4:$S$54,MATCH(DETAIL!$R$4,'R.UP3'!$B$5:$S$5,0),FALSE) -> #N/A | U36: =IF(OR(S36="N/A",T36="N/A"),"N/A",IF(AND(S36=0,T36=0),0,T36/S36*100)) -> #N/A | V36: =IF(OR(U36="N/A",U36<0),0,IF(U36>110,R36*110/100,R36*U36/100)) -> #N/A | X36: =IF(Z36="N/A",0,T.UP3!$F$56) -> #N/A | Y36: =VLOOKUP($B$36,T.UP3!$B$4:$T$70,MATCH(DETAIL!$X$4,T.UP3!$B$5:$T$5,0),FALSE) -> 0 | Z36: =VLOOKUP($B$36,'R.UP3'!$B$4:$S$54,MATCH(DETAIL!$X$4,'R.UP3'!$B$5:$S$5,0),FALSE) -> #N/A | AA36: =IF(OR(Y36="N/A",Z36="N/A"),"N/A",IF(AND(Y36=0,Z36=0),0,Z36/Y36*100)) -> #N/A | AB36: =IF(OR(AA36="N/A",AA36<0),0,IF(AA36>110,X36*110/100,X36*AA36/100)) -> #N/A | AD36: =IF(AF36="N/A",0,T.UP3!$F$56) -> #N/A | AE36: =VLOOKUP($B$36,T.UP3!$B$4:$T$70,MATCH(DETAIL!$AD$4,T.UP3!$B$5:$T$5,0),FALSE) -> 0 | AF36: =VLOOKUP($B$36,'R.UP3'!$B$4:$S$54,MATCH(DETAIL!$AD$4,'R.UP3'!$B$5:$S$5,0),FALSE) -> #N/A | AG36: =IF(OR(AE36="N/A",AF36="N/A"),"N/A",IF(AND(AE36=0,AF36=0),0,AF36/AE36*100)) -> #N/A | AH36: =IF(OR(AG36="N/A",AG36<0),0,IF(AG36>110,AD36*110/100,AD36*AG36/100)) -> #N/A
A37: =T.UP3!A61 -> 0 | B37: =T.UP3!B61 -> b. Maturity Level Gudang
B38: =T.UP3!B62 -> c. Maturity Level Sustainbility | F38: =IF(H38="N/A",0,T.UP3!$F$62) -> 0 | L38: =IF(N38="N/A",0,T.UP3!$F$62) -> 0 | R38: =IF(T38="N/A",0,T.UP3!$F$62) -> 0 | X38: =IF(Z38="N/A",0,T.UP3!$F$62) -> 0 | AD38: =IF(AF38="N/A",0,T.UP3!$F$62) -> 0
B39: =T.UP3!B63 -> d. Implementasi Roadmap Perbaikan Penerapan Manajemen Risiko dan Pencapaian Perlakuan Risiko | F39: =IF(H39="N/A",0,T.UP3!$F$63) -> 0 | L39: =IF(N39="N/A",0,T.UP3!$F$63) -> 0 | R39: =IF(T39="N/A",0,T.UP3!$F$63) -> 0 | X39: =IF(Z39="N/A",0,T.UP3!$F$63) -> 0 | AD39: =IF(AF39="N/A",0,T.UP3!$F$63) -> 0
B40: =T.UP3!B67 -> c. Ketepatan penyampaian pelaporan dan Akurasi Data Kinerja | F40: =IF(H40="N/A",0,T.UP3!$F$67) -> Max-10 | L40: =IF(N40="N/A",0,T.UP3!$F$67) -> Max-10 | R40: =IF(T40="N/A",0,T.UP3!$F$67) -> Max-10 | X40: =IF(Z40="N/A",0,T.UP3!$F$67) -> Max-10 | AD40: =IF(AF40="N/A",0,T.UP3!$F$67) -> Max-10
B41: =T.UP3!B69 -> e. Pencapaian Beyond RKAP | F41: =IF(H41="N/A",0,T.UP3!$F$69) -> Max-2 Max+2 | L41: =IF(N41="N/A",0,T.UP3!$F$69) -> Max-2 Max+2 | R41: =IF(T41="N/A",0,T.UP3!$F$69) -> Max-2 Max+2 | X41: =IF(Z41="N/A",0,T.UP3!$F$69) -> Max-2 Max+2 | AD41: =IF(AF41="N/A",0,T.UP3!$F$69) -> Max-2 Max+2
B42: TOTAL BOBOT | F42: =F7+F11 -> #REF! | J42: =J7+J11 -> #REF! | L42: =L7+L11 -> #REF! | P42: =P7+P11 -> #REF! | R42: =R7+R11 -> #REF! | V42: =V7+V11 -> #REF! | X42: =X7+X11 -> #REF! | AB42: =AB7+AB11 -> #REF! | AD42: =AD7+AD11 -> #REF! | AH42: =AH7+AH11 -> #REF!
B43: TOTAL BOBOT PROPORSIONAL | F43: 100 | J43: =F43/F42*J42 -> #REF! | L43: 100 | P43: =L43/L42*P42 -> #REF! | R43: 100 | V43: =R43/R42*V42 -> #REF! | X43: 100 | AB43: =X43/X42*AB42 -> #REF! | AD43: 100 | AH43: =AD43/AD42*AH42 -> #REF!

Sheet TREN
B2: UNIT | C2: NKO
C3: Januari | D3: Februari | E3: Maret | F3: April | G3: Mei | H3: Juni | I3: Juli | J3: Agustus | K3: September | L3: Oktober | M3: November | N3: Desember
B4: UP3 Tolitoli | C4: 80.4 | D4: 87.04 | E4: 93.39
B5: ULP Tolitoli Kota | C5: 75.72 | D5: 87.05 | E5: 93.36
B6: ULP Leok | C6: 66.71 | D6: 77.27 | E6: 90.08
B7: ULP Bangkir | C7: 74.87 | D7: 75.95 | E7: 87.94
B8: ULP Moutong | C8: 88.26 | D8: 86.77 | E8: 86.59
B9: ULP Kotaraya | C9: 65.25 | D9: 74.42 | E9: 79.99

Sheet KPI
B1: KONTRAK MANAJEMEN 2024
B2: PT PLN (PERSERO) UNIT INDUK DISTRIBUSI SULUTTENGGO
B3: UNIT PELAKSANA PELAYANAN PELANGGAN TOLITOLI
A5: 1 | B5: PENJUALAN DAN PENDAPATAN TENAGA LISTRIK
B6: TARGET | Q6: REALISASI BULANAN | AF6: REALISASI KOMULATIF
B7: Unit | D7: Jan | E7: Feb | F7: Mar | G7: Apr | H7: May | I7: Jun | J7: Jul | K7: Aug | L7: Sep | M7: Oct | N7: Nov | O7: Dec | Q7: Unit | S7: Jan | T7: Feb | U7: Mar | V7: Apr | W7: May | X7: Jun | Y7: Jul | Z7: Aug | AA7: Sep | AB7: Oct | AC7: Nov | AD7: Dec | AF7: Unit | AH7: Jan | AI7: Feb | AJ7: Mar | AK7: Apr | AL7: May | AM7: Jun | AN7: Jul | AO7: Aug | AP7: Sep | AQ7: Oct | AR7: Nov | AS7: Dec
B8: ULP Tolitoli | C8: Penjualan TL (GWh) | D8: 6.54 | E8: 12.76 | F8: 19.68 | G8: 26.37 | H8: 33.24 | I8: 39.7 | J8: 46.24 | K8: 52.96 | L8: 59.74 | M8: 66.82 | N8: 73.76 | O8: 80.8 | Q8: ULP Tolitoli | R8: Penjualan TL (GWh) | S8: 7.513838 | T8: 6.6075826 | U8: 6.2866504 | V8: 5.3273309 | W8: 6.0775352 | X8: 5.8227203 | Y8: 6.0798251 | Z8: 6.0595866 | AA8: 6.0901056 | AF8: ULP Tolitoli | AG8: Penjualan TL (GWh) | AH8: =IF(S8>1,S8,0) -> 7.513838 | AI8: =IF(T8>1,AH8+T8,0) -> 14.121421 | AJ8: =IF(U8>1,AI8+U8,0) -> 20.408071 | AK8: =IF(V8>1,AJ8+V8,0) -> 25.735402 | AL8: =IF(W8>1,AK8+W8,0) -> 31.812937 | AM8: =IF(X8>1,AL8+X8,0) -> 37.635657 | AN8: =IF(Y8>1,AM8+Y8,0) -> 43.715482 | AO8: =IF(Z8>1,AN8+Z8,0) -> 49.775069 | AP8: =IF(AA8>1,AO8+AA8,0) -> 55.865175 | ... AS8: =IF(AD8>1,AR8+AD8,0) -> 0
C9: Pendapatan TL (Rp) | R9: Pendapatan TL (Rp) | S9: 5758.6689 | T9: 4805.807 | U9: 5685.7965 | V9: 5644.9557 | W9: 6466.5394 | X9: 6206.7761 | Y9: 6472.3053 | Z9: 6395.7097 | AA9: 6431.5954 | AG9: Pendapatan TL (Rp) | AH9: =IF(S9>1,S9,0) -> 5758.6689 | AI9: =IF(T9>1,AH9+T9,0) -> 10564.476 | AJ9: =IF(U9>1,AI9+U9,0) -> 16250.272 | AK9: =IF(V9>1,AJ9+V9,0) -> 21895.228 | AL9: =IF(W9>1,AK9+W9,0) -> 28361.767 | AM9: =IF(X9>1,AL9+X9,0) -> 34568.544 | AN9: =IF(Y9>1,AM9+Y9,0) -> 41040.849 | AO9: =IF(Z9>1,AN9+Z9,0) -> 47436.559 | AP9: =IF(AA9>1,AO9+AA9,0) -> 53868.154 | ... AS9: =IF(AD9>1,AR9+AD9,0) -> 0
C10: Harga Jual (Rp/kWh) | R10: Harga Jual (Rp/kWh) | S10: =IF(S9=0,0,S9/S8) -> 766.40844 | T10: =IF(T9=0,0,T9/T8) -> 727.31698 | U10: =IF(U9=0,0,U9/U8) -> 904.42383 | V10: =IF(V9=0,0,V9/V8) -> 1059.6218 | W10: =IF(W9=0,0,W9/W8) -> 1064.0069 | X10: =IF(X9=0,0,X9/X8) -> 1065.9582 | Y10: =IF(Y9=0,0,Y9/Y8) -> 1064.5545 | Z10: =IF(Z9=0,0,Z9/Z8) -> 1055.4696 | ... AD10: =IF(AD9=0,0,AD9/AD8) -> 0 | AG10: Harga Jual (Rp/kWh) | AH10: =IF(AH9=0,0,AH9/AH8) -> 766.40844 | AI10: =IF(AI9=0,0,AI9/AI8) -> 748.11708 | AJ10: =IF(AJ9=0,0,AJ9/AJ8) -> 796.26695 | AK10: =IF(AK9=0,0,AK9/AK8) -> 850.78244 | AL10: =IF(AL9=0,0,AL9/AL8) -> 891.51679 | AM10: =IF(AM9=0,0,AM9/AM8) -> 918.50511 | AN10: =IF(AN9=0,0,AN9/AN8) -> 938.81725 | AO10: =IF(AO9=0,0,AO9/AO8) -> 953.01844 | ... AS10: =IF(AS9=0,0,AS9/AS8) -> 0
B11: ULP Leok | C11: Penjualan TL (GWh) | D11: 4.27 | E11: 8.33 | F11: 12.85 | G11: 17.22 | H11: 21.7 | I11: 25.92 | J11: 30.2 | K11: 34.58 | L11: 39.01 | M11: 43.63 | N11: 48.16 | O11: 52.76 | Q11: ULP Leok | R11: Penjualan TL (GWh) | S11: 5.0476842 | T11: 4.2129476 | U11: 4.296454 | V11: 3.7453335 | W11: 4.1215169 | X11: 4.263192 | Y11: 4.3133183 | Z11: 4.4597583 | AA11: 4.3609504 | AF11: ULP Leok | AG11: Penjualan TL (GWh) | AH11: =IF(S11>1,S11,0) -> 5.0476842 | AI11: =IF(T11>1,AH11+T11,0) -> 9.2606318 | AJ11: =IF(U11>1,AI11+U11,0) -> 13.557086 | AK11: =IF(V11>1,AJ11+V11,0) -> 17.302419 | AL11: =IF(W11>1,AK11+W11,0) -> 21.423936 | AM11: =IF(X11>1,AL11+X11,0) -> 25.687128 | AN11: =IF(Y11>1,AM11+Y11,0) -> 30.000447 | AO11: =IF(Z11>1,AN11+Z11,0) -> 34.460205 | AP11: =IF(AA11>1,AO11+AA11,0) -> 38.821155 | ... AS11: =IF(AD11>1,AR11+AD11,0) -> 0
C12: Pendapatan TL (Rp) | R12: Pendapatan TL (Rp) | S12: 3590.437 | T12: 2787.8467 | U12: 3850.8055 | V12: 3929.3757 | W12: 4350.1471 | X12: 4541.8532 | Y12: 4551.0917 | Z12: 4715.1307 | AA12: 4593.0558 | AG12: Pendapatan TL (Rp) | AH12: =IF(S12>1,S12,0) -> 3590.437 | AI12: =IF(T12>1,AH12+T12,0) -> 6378.2837 | AJ12: =IF(U12>1,AI12+U12,0) -> 10229.089 | AK12: =IF(V12>1,AJ12+V12,0) -> 14158.465 | AL12: =IF(W12>1,AK12+W12,0) -> 18508.612 | AM12: =IF(X12>1,AL12+X12,0) -> 23050.465 | AN12: =IF(Y12>1,AM12+Y12,0) -> 27601.557 | AO12: =IF(Z12>1,AN12+Z12,0) -> 32316.687 | AP12: =IF(AA12>1,AO12+AA12,0) -> 36909.743 | ... AS12: =IF(AD12>1,AR12+AD12,0) -> 0
C13: Harga Jual (Rp/kWh) | R13: Harga Jual (Rp/kWh) | S13: =IF(S12=0,0,S12/S11) -> 711.30382 | T13: =IF(T12=0,0,T12/T11) -> 661.73304 | U13: =IF(U12=0,0,U12/U11) -> 896.27528 | V13: =IF(V12=0,0,V12/V11) -> 1049.139 | W13: =IF(W12=0,0,W12/W11) -> 1055.4724 | X13: =IF(X12=0,0,X12/X11) -> 1065.3644 | Y13: =IF(Y12=0,0,Y12/Y11) -> 1055.1254 | Z13: =IF(Z12=0,0,Z12/Z11) -> 1057.2615 | ... AD13: =IF(AD12=0,0,AD12/AD11) -> 0 | AG13: Harga Jual (Rp/kWh) | AH13: =IF(AH12=0,0,AH12/AH11) -> 711.30382 | AI13: =IF(AI12=0,0,AI12/AI11) -> 688.75254 | AJ13: =IF(AJ12=0,0,AJ12/AJ11) -> 754.51976 | AK13: =IF(AK12=0,0,AK12/AK11) -> 818.29394 | AL13: =IF(AL12=0,0,AL12/AL11) -> 863.9221 | AM13: =IF(AM12=0,0,AM12/AM11) -> 897.35469 | AN13: =IF(AN12=0,0,AN12/AN11) -> 920.0382 | AO13: =IF(AO12=0,0,AO12/AO11) -> 937.79731 | ... AS13: =IF(AS12=0,0,AS12/AS11) -> 0
B14: ULP Bangkir | C14: Penjualan TL (GWh) | D14: 2.19 | E14: 4.28 | F14: 6.6 | G14: 8.84 | H14: 11.15 | I14: 13.31 | J14: 15.51 | K14: 17.76 | L14: 20.04 | M14: 22.41 | N14: 24.74 | O14: 27.1 | Q14: ULP Bangkir | R14: Penjualan TL (GWh) | S14: 3.3499516 | T14: 2.7952299 | U14: 2.4283223 | V14: 1.3904715 | W14: 1.718491 | X14: 1.9566386 | Y14: 2.0255426 | Z14: 2.1538006 | AA14: 2.2264042 | AF14: ULP Bangkir | AG14: Penjualan TL (GWh) | AH14: =IF(S14>1,S14,0) -> 3.3499516 | AI14: =IF(T14>1,AH14+T14,0) -> 6.1451815 | AJ14: =IF(U14>1,AI14+U14,0) -> 8.5735038 | AK14: =IF(V14>1,AJ14+V14,0) -> 9.9639754 | AL14: =IF(W14>1,AK14+W14,0) -> 11.682466 | AM14: =IF(X14>1,AL14+X14,0) -> 13.639105 | AN14: =IF(Y14>1,AM14+Y14,0) -> 15.664648 | AO14: =IF(Z14>1,AN14+Z14,0) -> 17.818448 | AP14: =IF(AA14>1,AO14+AA14,0) -> 20.044852 | ... AS14: =IF(AD14>1,AR14+AD14,0) -> 0
C15: Pendapatan TL (Rp) | R15: Pendapatan TL (Rp) | S15: 2094.2917 | T15: 1685.6909 | U15: 1628.1596 | V15: 1396.8175 | W15: 1668.0895 | X15: 1935.3136 | Y15: 1935.1123 | Z15: 2062.2802 | AA15: 2148.6193 | AG15: Pendapatan TL (Rp) | AH15: =IF(S15>1,S15,0) -> 2094.2917 | AI15: =IF(T15>1,AH15+T15,0) -> 3779.9825 | AJ15: =IF(U15>1,AI15+U15,0) -> 5408.1422 | AK15: =IF(V15>1,AJ15+V15,0) -> 6804.9597 | AL15: =IF(W15>1,AK15+W15,0) -> 8473.0492 | AM15: =IF(X15>1,AL15+X15,0) -> 10408.363 | AN15: =IF(Y15>1,AM15+Y15,0) -> 12343.475 | AO15: =IF(Z15>1,AN15+Z15,0) -> 14405.755 | AP15: =IF(AA15>1,AO15+AA15,0) -> 16554.375 | ... AS15: =IF(AD15>1,AR15+AD15,0) -> 0
C16: Harga Jual (Rp/kWh) | R16: Harga Jual (Rp/kWh) | S16: =IF(S15=0,0,S15/S14) -> 625.17072 | T16: =IF(T15=0,0,T15/T14) -> 603.05983 | U16: =IF(U15=0,0,U15/U14) -> 670.48745 | V16: =IF(V15=0,0,V15/V14) -> 1004.5639 | W16: =IF(W15=0,0,W15/W14) -> 970.67107 | X16: =IF(X15=0,0,X15/X14) -> 989.10122 | Y16: =IF(Y15=0,0,Y15/Y14) -> 955.35501 | Z16: =IF(Z15=0,0,Z15/Z14) -> 957.50749 | ... AD16: =IF(AD15=0,0,AD15/AD14) -> 0 | AG16: Harga Jual (Rp/kWh) | AH16: =IF(AH15=0,0,AH15/AH14) -> 625.17072 | AI16: =IF(AI15=0,0,AI15/AI14) -> 615.11324 | AJ16: =IF(AJ15=0,0,AJ15/AJ14) -> 630.79719 | AK16: =IF(AK15=0,0,AK15/AK14) -> 682.95629 | AL16: =IF(AL15=0,0,AL15/AL14) -> 725.27914 | AM16: =IF(AM15=0,0,AM15/AM14) -> 763.12653 | AN16: =IF(AN15=0,0,AN15/AN14) -> 787.98294 | AO16: =IF(AO15=0,0,AO15/AO14) -> 808.47418 | ... AS16: =IF(AS15=0,0,AS15/AS14) -> 0
B17: ULP Moutong | C17: Penjualan TL (GWh) | D17: 2.82 | E17: 5.5 | F17: 8.49 | G17: 11.37 | H17: 14.33 | I17: 17.11 | J17: 19.94 | K17: 22.83 | L17: 25.75 | M17: 28.8 | N17: 31.8 | O17: 34.83 | Q17: ULP Moutong | R17: Penjualan TL (GWh) | S17: 3.2428242 | T17: 2.5461385 | U17: 2.7160148 | V17: 2.4894414 | W17: 2.798196 | X17: 2.8152356 | Y17: 2.7164543 | Z17: 2.6185962 | AA17: 2.7242467 | AF17: ULP Moutong | AG17: Penjualan TL (GWh) | AH17: =IF(S17>1,S17,0) -> 3.2428242 | AI17: =IF(T17>1,AH17+T17,0) -> 5.7889627 | AJ17: =IF(U17>1,AI17+U17,0) -> 8.5049775 | AK17: =IF(V17>1,AJ17+V17,0) -> 10.994419 | AL17: =IF(W17>1,AK17+W17,0) -> 13.792615 | AM17: =IF(X17>1,AL17+X17,0) -> 16.60785 | AN17: =IF(Y17>1,AM17+Y17,0) -> 19.324305 | AO17: =IF(Z17>1,AN17+Z17,0) -> 21.942901 | AP17: =IF(AA17>1,AO17+AA17,0) -> 24.667148 | ... AS17: =IF(AD17>1,AR17+AD17,0) -> 0
C18: Pendapatan TL (Rp) | R18: Pendapatan TL (Rp) | S18: 1776.4605 | T18: 1336.4275 | U18: 1865.9663 | V18: 2166.6713 | W18: 2408.7867 | X18: 2391.1408 | Y18: 2329.8405 | Z18: 2143.2016 | AA18: 2273.9831 | AG18: Pendapatan TL (Rp) | AH18: =IF(S18>1,S18,0) -> 1776.4605 | AI18: =IF(T18>1,AH18+T18,0) -> 3112.8881 | AJ18: =IF(U18>1,AI18+U18,0) -> 4978.8544 | AK18: =IF(V18>1,AJ18+V18,0) -> 7145.5257 | AL18: =IF(W18>1,AK18+W18,0) -> 9554.3123 | AM18: =IF(X18>1,AL18+X18,0) -> 11945.453 | AN18: =IF(Y18>1,AM18+Y18,0) -> 14275.294 | AO18: =IF(Z18>1,AN18+Z18,0) -> 16418.495 | AP18: =IF(AA18>1,AO18+AA18,0) -> 18692.478 | ... AS18: =IF(AD18>1,AR18+AD18,0) -> 0
C19: Harga Jual (Rp/kWh) | R19: Harga Jual (Rp/kWh) | S19: =IF(S18=0,0,S18/S17) -> 547.81278 | T19: =IF(T18=0,0,T18/T17) -> 524.88406 | U19: =IF(U18=0,0,U18/U17) -> 687.02363 | V19: =IF(V18=0,0,V18/V17) -> 870.34436 | W19: =IF(W18=0,0,W18/W17) -> 860.83559 | X19: =IF(X18=0,0,X18/X17) -> 849.35726 | Y19: =IF(Y18=0,0,Y18/Y17) -> 857.67707 | Z19: =IF(Z18=0,0,Z18/Z17) -> 818.45438 | ... AD19: =IF(AD18=0,0,AD18/AD17) -> 0 | AG19: Harga Jual (Rp/kWh) | AH19: =IF(AH18=0,0,AH18/AH17) -> 547.81278 | AI19: =IF(AI18=0,0,AI18/AI17) -> 537.72813 | AJ19: =IF(AJ18=0,0,AJ18/AJ17) -> 585.40477 | AK19: =IF(AK18=0,0,AK18/AK17) -> 649.923 | AL19: =IF(AL18=0,0,AL18/AL17) -> 692.71218 | AM19: =IF(AM18=0,0,AM18/AM17) -> 719.26546 | AN19: =IF(AN18=0,0,AN18/AN17) -> 738.72224 | AO19: =IF(AO18=0,0,AO18/AO17) -> 748.23722 | ... AS19: =IF(AS18=0,0,AS18/AS17) -> 0
B20: ULP Kotaraya | C20: Penjualan TL (GWh) | D20: 2.91 | E20: 5.68 | F20: 8.77 | G20: 11.75 | H20: 14.81 | I20: 17.68 | J20: 20.6 | K20: 23.59 | L20: 26.61 | M20: 29.76 | N20: 32.86 | O20: 35.99 | Q20: ULP Kotaraya | R20: Penjualan TL (GWh) | S20: 3.8265327 | T20: 3.0600966 | U20: 2.9960408 | V20: 2.533233 | W20: 2.7785356 | X20: 2.8873877 | Y20: 3.0526141 | Z20: 2.9289135 | AA20: 2.8941228 | AF20: ULP Kotaraya | AG20: Penjualan TL (GWh) | AH20: =IF(S20>1,S20,0) -> 3.8265327 | AI20: =IF(T20>1,AH20+T20,0) -> 6.8866294 | AJ20: =IF(U20>1,AI20+U20,0) -> 9.8826701 | AK20: =IF(V20>1,AJ20+V20,0) -> 12.415903 | AL20: =IF(W20>1,AK20+W20,0) -> 15.194439 | AM20: =IF(X20>1,AL20+X20,0) -> 18.081826 | AN20: =IF(Y20>1,AM20+Y20,0) -> 21.13444 | AO20: =IF(Z20>1,AN20+Z20,0) -> 24.063354 | AP20: =IF(AA20>1,AO20+AA20,0) -> 26.957477 | ... AS20: =IF(AD20>1,AR20+AD20,0) -> 0
C21: Pendapatan TL (Rp) | R21: Pendapatan TL (Rp) | S21: 2338.0716 | T21: 1779.9429 | U21: 2315.2552 | V21: 2456.7947 | W21: 2671.1729 | X21: 2741.3748 | Y21: 3020.9704 | Z21: 2782.4471 | AA21: 2752.9711 | AG21: Pendapatan TL (Rp) | AH21: =IF(S21>1,S21,0) -> 2338.0716 | AI21: =IF(T21>1,AH21+T21,0) -> 4118.0145 | AJ21: =IF(U21>1,AI21+U21,0) -> 6433.2698 | AK21: =IF(V21>1,AJ21+V21,0) -> 8890.0645 | AL21: =IF(W21>1,AK21+W21,0) -> 11561.237 | AM21: =IF(X21>1,AL21+X21,0) -> 14302.612 | AN21: =IF(Y21>1,AM21+Y21,0) -> 17323.583 | AO21: =IF(Z21>1,AN21+Z21,0) -> 20106.03 | AP21: =IF(AA21>1,AO21+AA21,0) -> 22859.001 | ... AS21: =IF(AD21>1,AR21+AD21,0) -> 0
C22: Harga Jual (Rp/kWh) | R22: Harga Jual (Rp/kWh) | S22: =IF(S21=0,0,S21/S20) -> 611.0157 | T22: =IF(T21=0,0,T21/T20) -> 581.66233 | U22: =IF(U21=0,0,U21/U20) -> 772.77161 | V22: =IF(V21=0,0,V21/V20) -> 969.8258 | W22: =IF(W21=0,0,W21/W20) -> 961.35998 | X22: =IF(X21=0,0,X21/X20) -> 949.43082 | Y22: =IF(Y21=0,0,Y21/Y20) -> 989.63389 | Z22: =IF(Z21=0,0,Z21/Z20) -> 949.99292 | ... AD22: =IF(AD21=0,0,AD21/AD20) -> 0 | AG22: Harga Jual (Rp/kWh) | AH22: =IF(AH21=0,0,AH21/AH20) -> 611.0157 | AI22: =IF(AI21=0,0,AI21/AI20) -> 597.97244 | AJ22: =IF(AJ21=0,0,AJ21/AJ20) -> 650.96474 | AK22: =IF(AK21=0,0,AK21/AK20) -> 716.02238 | AL22: =IF(AL21=0,0,AL21/AL20) -> 760.88611 | AM22: =IF(AM21=0,0,AM21/AM20) -> 790.99378 | AN22: =IF(AN21=0,0,AN21/AN20) -> 819.68494 | AO22: =IF(AO21=0,0,AO21/AO20) -> 835.54561 | ... AS22: =IF(AS21=0,0,AS21/AS20) -> 0
B23: UP3 Tolitoli | C23: Penjualan TL (GWh) | D23: 18.74 | E23: 36.55 | F23: 56.39 | G23: 75.55 | H23: 95.22 | I23: 113.73 | J23: 132.49 | K23: 151.71 | L23: 171.15 | M23: 191.42 | N23: 211.32 | O23: 231.47 | Q23: UP3 Tolitoli | R23: Penjualan TL (GWh) | S23: =S8+S11+S14+S17+S20 -> 22.980831 | T23: =T8+T11+T14+T17+T20 -> 19.221995 | U23: =U8+U11+U14+U17+U20 -> 18.723482 | V23: =V8+V11+V14+V17+V20 -> 15.48581 | W23: =W8+W11+W14+W17+W20 -> 17.494275 | X23: =X8+X11+X14+X17+X20 -> 17.745174 | Y23: =Y8+Y11+Y14+Y17+Y20 -> 18.187754 | Z23: =Z8+Z11+Z14+Z17+Z20 -> 18.220655 | ... AD23: =AD8+AD11+AD14+AD17+AD20 -> 0 | AF23: UP3 Tolitoli | AG23: Penjualan TL (GWh) | AH23: =AH8+AH11+AH14+AH17+AH20 -> 22.980831 | AI23: =AI8+AI11+AI14+AI17+AI20 -> 42.202826 | AJ23: =AJ8+AJ11+AJ14+AJ17+AJ20 -> 60.926308 | AK23: =AK8+AK11+AK14+AK17+AK20 -> 76.412119 | AL23: =AK23+W23 -> 93.906393 | AM23: =AL23+X23 -> 111.65157 | AN23: =AM23+Y23 -> 129.83932 | AO23: =AN23+Z23 -> 148.05998 | AP23: =AO23+AA23 -> 166.35581 | AQ23: =AP23+AB23 -> 166.35581 | AR23: =AQ23+AC23 -> 166.35581 | AS23: =AR23+AD23 -> 166.35581
C24: Pendapatan TL (Rp) | R24: Pendapatan TL (Rp) | S24: =S9+S12+S15+S18+S21 -> 15557.93 | T24: =T9+T12+T15+T18+T21 -> 12395.715 | U24: =U9+U12+U15+U18+U21 -> 15345.983 | V24: =V9+V12+V15+V18+V21 -> 15594.615 | W24: =W9+W12+W15+W18+W21 -> 17564.736 | X24: =X9+X12+X15+X18+X21 -> 17816.459 | Y24: =Y9+Y12+Y15+Y18+Y21 -> 18309.32 | Z24: =Z9+Z12+Z15+Z18+Z21 -> 18098.769 | ... AD24: =AD9+AD12+AD15+AD18+AD21 -> 0 | AG24: Pendapatan TL (Rp) | AH24: =AH9+AH12+AH15+AH18+AH21 -> 15557.93 | AI24: =AI9+AI12+AI15+AI18+AI21 -> 27953.645 | AJ24: =AJ9+AJ12+AJ15+AJ18+AJ21 -> 43299.628 | AK24: =AK9+AK12+AK15+AK18+AK21 -> 58894.243 | AL24: =AL9+AL12+AL15+AL18+AL21 -> 76458.978 | AM24: =AM9+AM12+AM15+AM18+AM21 -> 94275.437 | AN24: =AN9+AN12+AN15+AN18+AN21 -> 112584.76 | AO24: =AO9+AO12+AO15+AO18+AO21 -> 130683.53 | ... AS24: =AS9+AS12+AS15+AS18+AS21 -> 0
C25: Harga Jual (Rp/kWh) | R25: Harga Jual (Rp/kWh) | S25: =IF(S24=0,0,S24/S23) -> 676.99597 | T25: =IF(T24=0,0,T24/T23) -> 644.8714 | U25: =IF(U24=0,0,U24/U23) -> 819.6116 | V25: =IF(V24=0,0,V24/V23) -> 1007.0261 | W25: =IF(W24=0,0,W24/W23) -> 1004.0277 | X25: =IF(X24=0,0,X24/X23) -> 1004.0171 | Y25: =IF(Y24=0,0,Y24/Y23) -> 1006.6839 | Z25: =IF(Z24=0,0,Z24/Z23) -> 993.31056 | ... AD25: =IF(AD24=0,0,AD24/AD23) -> 0 | AG25: Harga Jual (Rp/kWh) | AH25: =IF(AH24=0,0,AH24/AH23) -> 676.99597 | AI25: =IF(AI24=0,0,AI24/AI23) -> 662.36429 | AJ25: =IF(AJ24=0,0,AJ24/AJ23) -> 710.68852 | AK25: =IF(AK24=0,0,AK24/AK23) -> 770.7448 | AL25: =IF(AL24=0,0,AL24/AL23) -> 814.20418 | AM25: =IF(AM24=0,0,AM24/AM23) -> 844.37182 | AN25: =IF(AN24=0,0,AN24/AN23) -> 867.10833 | AO25: =IF(AO24=0,0,AO24/AO23) -> 882.63911 | ... AS25: =IF(AS24=0,0,AS24/AS23) -> 0
A27: 2 | B27: SAIDI | Q27: =B27 -> SAIDI | AF27: =B27 -> SAIDI
B28: TARGET | Q28: REALISASI BULANAN | AF28: REALISASI KOMULATIF
B29: Unit | D29: Jan | E29: Feb | F29: Mar | G29: Apr | H29: May | I29: Jun | J29: Jul | K29: Aug | L29: Sep | M29: Oct | N29: Nov | O29: Dec | Q29: Unit | S29: Jan | T29: Feb | U29: Mar | V29: Apr | W29: May | X29: Jun | Y29: Jul | Z29: Aug | AA29: Sep | AB29: Oct | AC29: Nov | AD29: Dec | AF29: Unit | AH29: Jan | AI29: Feb | AJ29: Mar | AK29: Apr | AL29: May | AM29: Jun | AN29: Jul | AO29: Aug | AP29: Sep | AQ29: Oct | AR29: Nov | AS29: Dec
B30: ULP Tolitoli | C30: Menit | Q30: ULP Tolitoli | R30: Menit | S30: =10022.05*60 -> 601323 | T30: =2078.37*60 -> 124702.2 | U30: =1465.67 *60 -> 87940.2 | V30: 1229737.2 | W30: =69028.87*60 -> 4141732.2 | X30: =62522.48*60 -> 3751348.8 | Y30: =10661.98*60 -> 639718.8 | Z30: =4656.82*60 -> 279409.2 | AA30: =12327.72*60 -> 739663.2 | AF30: ULP Tolitoli | AG30: Menit | AH30: =IF(S30=0,0,S30) -> 601323 | AI30: =IF(T30=0,0,AH30+T30) -> 726025.2 | AJ30: =IF(U30=0,0,AI30+U30) -> 813965.4 | AK30: =IF(V30=0,0,AJ30+V30) -> 2043702.6 | AL30: =IF(W30=0,0,AK30+W30) -> 6185434.8 | AM30: =IF(X30=0,0,AL30+X30) -> 9936783.6 | AN30: =IF(Y30=0,0,AM30+Y30) -> 10576502 | AO30: =IF(Z30=0,0,AN30+Z30) -> 10855912 | AP30: =IF(AA30=0,0,AO30+AA30) -> 11595575 | ... AS30: =IF(AD30=0,0,AR30+AD30) -> 0
C31: Pelanggan | R31: Pelanggan | S31: 46737 | T31: 46863 | U31: 46970 | V31: 47063 | W31: 47155 | X31: 47250 | Y31: 47346 | Z31: 47446 | AA31: 47552 | AG31: Pelanggan | AH31: =S31 -> 46737 | AI31: =T31 -> 46863 | AJ31: =U31 -> 46970 | AK31: =V31 -> 47063 | AL31: =W31 -> 47155 | AM31: =X31 -> 47250 | AN31: =Y31 -> 47346 | AO31: =Z31 -> 47446 | ... AS31: =AD31 -> 0
C32: SAIDI (Menit/Plg) | D32: 32.44 | E32: 64.87 | F32: 97.31 | G32: 129.75 | H32: 162.18 | I32: 194.62 | J32: 227.06 | K32: 259.49 | L32: 291.93 | M32: 324.37 | N32: 356.8 | O32: 389.24 | R32: SAIDI (Menit/Plg) | S32: =IF(S30=0,0,S30/S31) -> 12.866102 | T32: =IF(T30=0,0,T30/T31) -> 2.6609948 | U32: =IF(U30=0,0,U30/U31) -> 1.8722631 | V32: =IF(V30=0,0,V30/V31) -> 26.129596 | W32: =IF(W30=0,0,W30/W31) -> 87.832302 | X32: =IF(X30=0,0,X30/X31) -> 79.393625 | Y32: =IF(Y30=0,0,Y30/Y31) -> 13.51157 | Z32: =IF(Z30=0,0,Z30/Z31) -> 5.8889938 | ... AD32: =IF(AD30=0,0,AD30/AD31) -> 0 | AG32: SAIDI (Menit/Plg) | AH32: =IF(AH30=0,0,AH30/AH31) -> 12.866102 | AI32: =IF(AI30=0,0,AI30/AI31) -> 15.492504 | AJ32: =IF(AJ30=0,0,AJ30/AJ31) -> 17.329474 | AK32: =IF(AK30=0,0,AK30/AK31) -> 43.424826 | AL32: =IF(AL30=0,0,AL30/AL31) -> 131.17241 | AM32: =IF(AM30=0,0,AM30/AM31) -> 210.3023 | AN32: =IF(AN30=0,0,AN30/AN31) -> 223.38745 | AO32: =IF(AO30=0,0,AO30/AO31) -> 228.80562 | ... AS32: =IF(AS30=0,0,AS30/AS31) -> 0
B33: ULP Leok | C33: Menit | Q33: ULP Leok | R33: Menit | S33: =15737.08*60 -> 944224.8 | T33: =2447.04*60 -> 146822.4 | U33: =489.36*60 -> 29361.6 | V33: 461679 | W33: =27295.32*60 -> 1637719.2 | X33: =25701.84*60 -> 1542110.4 | Y33: 905589.6 | Z33: =185.44*60 -> 11126.4 | AA33: =7818.4*60 -> 469104 | AF33: ULP Leok | AG33: Menit | AH33: =IF(S33=0,0,S33) -> 944224.8 | AI33: =IF(T33=0,0,AH33+T33) -> 1091047.2 | AJ33: =IF(U33=0,0,AI33+U33) -> 1120408.8 | AK33: =IF(V33=0,0,AJ33+V33) -> 1582087.8 | AL33: =IF(W33=0,0,AK33+W33) -> 3219807 | AM33: =IF(X33=0,0,AL33+X33) -> 4761917.4 | AN33: =IF(Y33=0,0,AM33+Y33) -> 5667507 | AO33: =IF(Z33=0,0,AN33+Z33) -> 5678633.4 | AP33: =IF(AA33=0,0,AO33+AA33) -> 6147737.4 | ... AS33: =IF(AD33=0,0,AR33+AD33) -> 0
C34: Pelanggan | R34: Pelanggan | S34: 35785 | T34: 35893 | U34: 35986 | V34: 36089 | W34: 36170 | X34: 36277 | Y34: 36362 | Z34: 36498 | AA34: 36621 | AG34: Pelanggan | AH34: =S34 -> 35785 | AI34: =T34 -> 35893 | AJ34: =U34 -> 35986 | AK34: =V34 -> 36089 | AL34: =W34 -> 36170 | AM34: =X34 -> 36277 | AN34: =Y34 -> 36362 | AO34: =Z34 -> 36498 | ... AS34: =AD34 -> 0
C35: SAIDI (Menit/Plg) | D35: 25.22 | E35: 50.45 | F35: 75.67 | G35: 100.89 | H35: 126.12 | I35: 151.34 | J35: 176.56 | K35: 201.78 | L35: 227.01 | M35: 252.23 | N35: 277.45 | O35: 302.68 | R35: SAIDI (Menit/Plg) | S35: =IF(S33=0,0,S33/S34) -> 26.38605 | T35: =IF(T33=0,0,T33/T34) -> 4.090558 | U35: =IF(U33=0,0,U33/U34) -> 0.8159173 | V35: =IF(V33=0,0,V33/V34) -> 12.79279 | W35: =IF(W33=0,0,W33/W34) -> 45.278385 | X35: =IF(X33=0,0,X33/X34) -> 42.509314 | Y35: =IF(Y33=0,0,Y33/Y34) -> 24.904835 | Z35: =IF(Z33=0,0,Z33/Z34) -> 0.30484958 | ... AD35: =IF(AD33=0,0,AD33/AD34) -> 0 | AG35: SAIDI (Menit/Plg) | AH35: =IF(AH33=0,0,AH33/AH34) -> 26.38605 | AI35: =IF(AI33=0,0,AI33/AI34) -> 30.397214 | AJ35: =IF(AJ33=0,0,AJ33/AJ34) -> 31.134575 | AK35: =IF(AK33=0,0,AK33/AK34) -> 43.838505 | AL35: =IF(AL33=0,0,AL33/AL34) -> 89.018717 | AM35: =IF(AM33=0,0,AM33/AM34) -> 131.26547 | AN35: =IF(AN33=0,0,AN33/AN34) -> 155.86346 | AO35: =IF(AO33=0,0,AO33/AO34) -> 155.58752 | ... AS35: =IF(AS33=0,0,AS33/AS34) -> 0
B36: ULP Bangkir | C36: Menit | Q36: ULP Bangkir | R36: Menit | S36: =5491.21*60 -> 329472.6 | T36: =48.6*60 -> 2916 | U36: =1280.78*60 -> 76846.8 | V36: 319051.2 | W36: =6384.62*60 -> 383077.2 | X36: =5700.53*60 -> 342031.8 | Y36: 455848.2 | Z36: =111.76*60 -> 6705.6 | AA36: =4353.37*60 -> 261202.2 | AF36: ULP Bangkir | AG36: Menit | AH36: =IF(S36=0,0,S36) -> 329472.6 | AI36: =IF(T36=0,0,AH36+T36) -> 332388.6 | AJ36: =IF(U36=0,0,AI36+U36) -> 409235.4 | AK36: =IF(V36=0,0,AJ36+V36) -> 728286.6 | AL36: =IF(W36=0,0,AK36+W36) -> 1111363.8 | AM36: =IF(X36=0,0,AL36+X36) -> 1453395.6 | AN36: =IF(Y36=0,0,AM36+Y36) -> 1909243.8 | AO36: =IF(Z36=0,0,AN36+Z36) -> 1915949.4 | AP36: =IF(AA36=0,0,AO36+AA36) -> 2177151.6 | ... AS36: =IF(AD36=0,0,AR36+AD36) -> 0
C37: Pelanggan | R37: Pelanggan | S37: 21705 | T37: 21751 | U37: 21798 | V37: 21849 | W37: 21902 | X37: 21961 | Y37: 21999 | Z37: 22037 | AA37: 22094 | AG37: Pelanggan | AH37: =S37 -> 21705 | AI37: =T37 -> 21751 | AJ37: =U37 -> 21798 | AK37: =V37 -> 21849 | AL37: =W37 -> 21902 | AM37: =X37 -> 21961 | AN37: =Y37 -> 21999 | AO37: =Z37 -> 22037 | ... AS37: =AD37 -> 0
C38: SAIDI (Menit/Plg) | D38: 14.65 | E38: 29.3 | F38: 43.94 | G38: 58.59 | H38: 73.24 | I38: 87.89 | J38: 102.54 | K38: 117.18 | L38: 131.83 | M38: 146.48 | N38: 161.13 | O38: 175.78 | R38: SAIDI (Menit/Plg) | S38: =IF(S36=0,0,S36/S37) -> 15.179572 | T38: =IF(T36=0,0,T36/T37) -> 0.1340628 | U38: =IF(U36=0,0,U36/U37) -> 3.525406 | V38: =IF(V36=0,0,V36/V37) -> 14.602554 | W38: =IF(W36=0,0,W36/W37) -> 17.490512 | X38: =IF(X36=0,0,X36/X37) -> 15.574509 | Y38: =IF(Y36=0,0,Y36/Y37) -> 20.721315 | Z38: =IF(Z36=0,0,Z36/Z37) -> 0.30428824 | ... AD38: =IF(AD36=0,0,AD36/AD37) -> 0 | AG38: SAIDI (Menit/Plg) | AH38: =IF(AH36=0,0,AH36/AH37) -> 15.179572 | AI38: =IF(AI36=0,0,AI36/AI37) -> 15.281532 | AJ38: =IF(AJ36=0,0,AJ36/AJ37) -> 18.773988 | AK38: =IF(AK36=0,0,AK36/AK37) -> 33.33272 | AL38: =IF(AL36=0,0,AL36/AL37) -> 50.742571 | AM38: =IF(AM36=0,0,AM36/AM37) -> 66.180757 | AN38: =IF(AN36=0,0,AN36/AN37) -> 86.787754 | AO38: =IF(AO36=0,0,AO36/AO37) -> 86.942388 | ... AS38: =IF(AS36=0,0,AS36/AS37) -> 0
B39: ULP Moutong | C39: Menit | Q39: ULP Moutong | R39: Menit | S39: =350.31*60 -> 21018.6 | T39: =161.1*60 -> 9666 | U39: =405.5*60 -> 24330 | V39: 305365.8 | W39: =15357.66*60 -> 921459.6 | X39: =6832.02*60 -> 409921.2 | Y39: 388913.4 | Z39: =80.23*60 -> 4813.8 | AA39: =1512.09*60 -> 90725.4 | AF39: ULP Moutong | AG39: Menit | AH39: =IF(S39=0,0,S39) -> 21018.6 | AI39: =IF(T39=0,0,AH39+T39) -> 30684.6 | AJ39: =IF(U39=0,0,AI39+U39) -> 55014.6 | AK39: =IF(V39=0,0,AJ39+V39) -> 360380.4 | AL39: =IF(W39=0,0,AK39+W39) -> 1281840 | AM39: =IF(X39=0,0,AL39+X39) -> 1691761.2 | AN39: =IF(Y39=0,0,AM39+Y39) -> 2080674.6 | AO39: =IF(Z39=0,0,AN39+Z39) -> 2085488.4 | AP39: =IF(AA39=0,0,AO39+AA39) -> 2176213.8 | ... AS39: =IF(AD39=0,0,AR39+AD39) -> 0
C40: Pelanggan | R40: Pelanggan | S40: 22738 | T40: 22826 | U40: 22869 | V40: 22908 | W40: 22948 | X40: 23000 | Y40: 23047 | Z40: 23067 | AA40: 23111 | AG40: Pelanggan | AH40: =S40 -> 22738 | AI40: =T40 -> 22826 | AJ40: =U40 -> 22869 | AK40: =V40 -> 22908 | AL40: =W40 -> 22948 | AM40: =X40 -> 23000 | AN40: =Y40 -> 23047 | AO40: =Z40 -> 23067 | ... AS40: =AD40 -> 0
C41: SAIDI (Menit/Plg) | D41: 17.31 | E41: 34.62 | F41: 51.92 | G41: 69.23 | H41: 86.54 | I41: 103.85 | J41: 121.16 | K41: 138.47 | L41: 155.77 | M41: 173.08 | N41: 190.39 | O41: 207.7 | R41: SAIDI (Menit/Plg) | S41: =IF(S39=0,0,S39/S40) -> 0.92438209 | T41: =IF(T39=0,0,T39/T40) -> 0.42346447 | U41: =IF(U39=0,0,U39/U40) -> 1.0638856 | V41: =IF(V39=0,0,V39/V40) -> 13.330094 | W41: =IF(W39=0,0,W39/W40) -> 40.154244 | X41: =IF(X39=0,0,X39/X40) -> 17.822661 | Y41: =IF(Y39=0,0,Y39/Y40) -> 16.874795 | Z41: =IF(Z39=0,0,Z39/Z40) -> 0.20868774 | ... AD41: =IF(AD39=0,0,AD39/AD40) -> 0 | AG41: SAIDI (Menit/Plg) | AH41: =IF(AH39=0,0,AH39/AH40) -> 0.92438209 | AI41: =IF(AI39=0,0,AI39/AI40) -> 1.3442828 | AJ41: =IF(AJ39=0,0,AJ39/AJ40) -> 2.4056408 | AK41: =IF(AK39=0,0,AK39/AK40) -> 15.73164 | AL41: =IF(AL39=0,0,AL39/AL40) -> 55.858463 | AM41: =IF(AM39=0,0,AM39/AM40) -> 73.554835 | AN41: =IF(AN39=0,0,AN39/AN40) -> 90.279629 | AO41: =IF(AO39=0,0,AO39/AO40) -> 90.41004 | ... AS41: =IF(AS39=0,0,AS39/AS40) -> 0
B42: ULP Kotaraya | C42: Menit | Q42: ULP Kotaraya | R42: Menit | S42: =655.23*60 -> 39313.8 | T42: =203.77*60 -> 12226.2 | U42: =886.08*60 -> 53164.8 | V42: 53568.6 | W42: =18713.13*60 -> 1122787.8 | X42: =5220.36*60 -> 313221.6 | Y42: 1299536.4 | Z42: =7344.92*60 -> 440695.2 | AA42: =79.96*60 -> 4797.6 | AF42: ULP Kotaraya | AG42: Menit | AH42: =IF(S42=0,0,S42) -> 39313.8 | AI42: =IF(T42=0,0,AH42+T42) -> 51540 | AJ42: =IF(U42=0,0,AI42+U42) -> 104704.8 | AK42: =IF(V42=0,0,AJ42+V42) -> 158273.4 | AL42: =IF(W42=0,0,AK42+W42) -> 1281061.2 | AM42: =IF(X42=0,0,AL42+X42) -> 1594282.8 | AN42: =IF(Y42=0,0,AM42+Y42) -> 2893819.2 | AO42: =IF(Z42=0,0,AN42+Z42) -> 3334514.4 | AP42: =IF(AA42=0,0,AO42+AA42) -> 3339312 | ... AS42: =IF(AD42=0,0,AR42+AD42) -> 0
C43: Pelanggan | R43: Pelanggan | S43: 29532 | T43: 29631 | U43: 29740 | V43: 29882 | W43: 29977 | X43: 30072 | Y43: 30175 | Z43: 30244 | AA43: 30382 | AG43: Pelanggan | AH43: =S43 -> 29532 | AI43: =T43 -> 29631 | AJ43: =U43 -> 29740 | AK43: =V43 -> 29882 | AL43: =W43 -> 29977 | AM43: =X43 -> 30072 | AN43: =Y43 -> 30175 | AO43: =Z43 -> 30244 | ... AS43: =AD43 -> 0
C44: SAIDI (Menit/Plg) | D44: 17.89 | E44: 35.78 | F44: 53.68 | G44: 71.57 | H44: 89.46 | I44: 107.35 | J44: 125.25 | K44: 143.14 | L44: 161.03 | M44: 178.92 | N44: 196.81 | O44: 214.71 | R44: SAIDI (Menit/Plg) | S44: =IF(S42=0,0,S42/S43) -> 1.3312271 | T44: =IF(T42=0,0,T42/T43) -> 0.41261517 | U44: =IF(U42=0,0,U42/U43) -> 1.787653 | V44: =IF(V42=0,0,V42/V43) -> 1.7926712 | W44: =IF(W42=0,0,W42/W43) -> 37.454975 | X44: =IF(X42=0,0,X42/X43) -> 10.415722 | Y44: =IF(Y42=0,0,Y42/Y43) -> 43.066658 | Z44: =IF(Z42=0,0,Z42/Z43) -> 14.571327 | ... AD44: =IF(AD42=0,0,AD42/AD43) -> 0 | AG44: SAIDI (Menit/Plg) | AH44: =IF(AH42=0,0,AH42/AH43) -> 1.3312271 | AI44: =IF(AI42=0,0,AI42/AI43) -> 1.7393946 | AJ44: =IF(AJ42=0,0,AJ42/AJ43) -> 3.5206725 | AK44: =IF(AK42=0,0,AK42/AK43) -> 5.2966133 | AL44: =IF(AL42=0,0,AL42/AL43) -> 42.734803 | AM44: =IF(AM42=0,0,AM42/AM43) -> 53.015523 | AN44: =IF(AN42=0,0,AN42/AN43) -> 95.901216 | AO44: =IF(AO42=0,0,AO42/AO43) -> 110.25375 | ... AS44: =IF(AS42=0,0,AS42/AS43) -> 0
B45: UP3 Tolitoli | C45: Menit | Q45: UP3 Tolitoli | R45: Menit | S45: =S30+S33+S36+S39+S42 -> 1935352.8 | T45: =T30+T33+T36+T39+T42 -> 296332.8 | U45: =U30+U33+U36+U39+U42 -> 271643.4 | V45: =V30+V33+V36+V39+V42 -> 2369401.8 | W45: =W30+W33+W36+W39+W42 -> 8206776 | X45: =X30+X33+X36+X39+X42 -> 6358633.8 | Y45: =Y30+Y33+Y36+Y39+Y42 -> 3689606.4 | Z45: =Z30+Z33+Z36+Z39+Z42 -> 742750.2 | ... AD45: =AD30+AD33+AD36+AD39+AD42 -> 0 | AF45: UP3 Tolitoli | AG45: Menit | AH45: =AH30+AH33+AH36+AH39+AH42 -> 1935352.8 | AI45: =AI30+AI33+AI36+AI39+AI42 -> 2231685.6 | AJ45: =AJ30+AJ33+AJ36+AJ39+AJ42 -> 2503329 | AK45: =AK30+AK33+AK36+AK39+AK42 -> 4872730.8 | AL45: =AL30+AL33+AL36+AL39+AL42 -> 13079507 | AM45: =AM30+AM33+AM36+AM39+AM42 -> 19438141 | AN45: =AN30+AN33+AN36+AN39+AN42 -> 23127747 | AO45: =AO30+AO33+AO36+AO39+AO42 -> 23870497 | ... AS45: =AS30+AS33+AS36+AS39+AS42 -> 0
C46: Pelanggan | R46: Pelanggan | S46: =S31+S34+S37+S40+S43 -> 156497 | T46: =T31+T34+T37+T40+T43 -> 156964 | U46: =U31+U34+U37+U40+U43 -> 157363 | V46: =V31+V34+V37+V40+V43 -> 157791 | W46: =W31+W34+W37+W40+W43 -> 158152 | X46: =X31+X34+X37+X40+X43 -> 158560 | Y46: =Y31+Y34+Y37+Y40+Y43 -> 158929 | Z46: =Z31+Z34+Z37+Z40+Z43 -> 159292 | ... AD46: =AD31+AD34+AD37+AD40+AD43 -> 0 | AG46: Pelanggan | AH46: =AH31+AH34+AH37+AH40+AH43 -> 156497 | AI46: =AI31+AI34+AI37+AI40+AI43 -> 156964 | AJ46: =AJ31+AJ34+AJ37+AJ40+AJ43 -> 157363 | AK46: =AK31+AK34+AK37+AK40+AK43 -> 157791 | AL46: =AL31+AL34+AL37+AL40+AL43 -> 158152 | AM46: =AM31+AM34+AM37+AM40+AM43 -> 158560 | AN46: =AN31+AN34+AN37+AN40+AN43 -> 158929 | AO46: =AO31+AO34+AO37+AO40+AO43 -> 159292 | ... AS46: =AS31+AS34+AS37+AS40+AS43 -> 0
C47: SAIDI (Menit/Plg) | D47: 23.39 | E47: 46.78 | F47: 70.17 | G47: 93.56 | H47: 116.95 | I47: 140.34 | J47: 163.72 | K47: 187.11 | L47: 210.5 | M47: 233.89 | N47: 257.28 | O47: 280.67 | R47: SAIDI (Menit/Plg) | S47: =IF(S45=0,0,S45/S46) -> 12.366709 | T47: =IF(T45=0,0,T45/T46) -> 1.887903 | U47: =IF(U45=0,0,U45/U46) -> 1.7262215 | V47: =IF(V45=0,0,V45/V46) -> 15.016077 | W47: =IF(W45=0,0,W45/W46) -> 51.891699 | X47: =IF(X45=0,0,X45/X46) -> 40.102383 | Y47: =IF(Y45=0,0,Y45/Y46) -> 23.215438 | Z47: =IF(Z45=0,0,Z45/Z46) -> 4.6628217 | ... AD47: =IF(AD45=0,0,AD45/AD46) -> 0 | AG47: SAIDI (Menit/Plg) | AH47: =IF(AH45=0,0,AH45/AH46) -> 12.366709 | AI47: =IF(AI45=0,0,AI45/AI46) -> 14.217818 | AJ47: =IF(AJ45=0,0,AJ45/AJ46) -> 15.90799 | AK47: =IF(AK45=0,0,AK45/AK46) -> 30.880917 | AL47: =IF(AL45=0,0,AL45/AL46) -> 82.702127 | AM47: =IF(AM45=0,0,AM45/AM46) -> 122.5917 | AN47: =IF(AN45=0,0,AN45/AN46) -> 145.52251 | AO47: =IF(AO45=0,0,AO45/AO46) -> 149.85371 | ... AS47: =IF(AS45=0,0,AS45/AS46) -> 0
B49: SAIFI | Q49: =B49 -> SAIFI | AF49: =B49 -> SAIFI
B50: TARGET | Q50: REALISASI BULANAN | AF50: REALISASI KOMULATIF
B51: Unit | D51: Jan | E51: Feb | F51: Mar | G51: Apr | H51: May | I51: Jun | J51: Jul | K51: Aug | L51: Sep | M51: Oct | N51: Nov | O51: Dec | Q51: Unit | S51: Jan | T51: Feb | U51: Mar | V51: Apr | W51: May | X51: Jun | Y51: Jul | Z51: Aug | AA51: Sep | AB51: Oct | AC51: Nov | AD51: Dec | AF51: Unit | AH51: Jan | AI51: Feb | AJ51: Mar | AK51: Apr | AL51: May | AM51: Jun | AN51: Jul | AO51: Aug | AP51: Sep | AQ51: Oct | AR51: Nov | AS51: Dec
B52: ULP Tolitoli | C52: Kali | Q52: ULP Tolitoli | R52: Kali | S52: 5656 | T52: 588 | U52: 4394 | V52: 16438 | W52: 30518 | X52: 22601 | Y52: 12961 | Z52: 1463 | AA52: 15802 | AF52: ULP Tolitoli | AG52: Kali | AH52: =IF(S52=0,0,S52) -> 5656 | AI52: =IF(T52=0,0,AH52+T52) -> 6244 | AJ52: =IF(U52=0,0,AI52+U52) -> 10638 | AK52: =IF(V52=0,0,AJ52+V52) -> 27076 | AL52: =IF(W52=0,0,AK52+W52) -> 57594 | AM52: =IF(X52=0,0,AL52+X52) -> 80195 | AN52: =IF(Y52=0,0,AM52+Y52) -> 93156 | AO52: =IF(Z52=0,0,AN52+Z52) -> 94619 | AP52: =IF(AA52=0,0,AO52+AA52) -> 110421 | ... AS52: =IF(AD52=0,0,AR52+AD52) -> 0
C53: Pelanggan | R53: Pelanggan | S53: =S31 -> 46737 | T53: =T31 -> 46863 | U53: =U31 -> 46970 | V53: =V31 -> 47063 | W53: =W31 -> 47155 | X53: =X31 -> 47250 | Y53: =Y31 -> 47346 | Z53: =Z31 -> 47446 | ... AD53: =AD31 -> 0 | AG53: Pelanggan | AH53: =S53 -> 46737 | AI53: =T53 -> 46863 | AJ53: =U53 -> 46970 | AK53: =V53 -> 47063 | AL53: =W53 -> 47155 | AM53: =X53 -> 47250 | AN53: =Y53 -> 47346 | AO53: =Z53 -> 47446 | ... AS53: =AD53 -> 0
C54: SAIFI (Kali/Plg) | D54: 0.29 | E54: 0.59 | F54: 0.88 | G54: 1.18 | H54: 1.47 | I54: 1.76 | J54: 2.06 | K54: 2.35 | L54: 2.65 | M54: 2.94 | N54: 3.23 | O54: 3.53 | R54: SAIFI (Kali/Plg) | S54: =IF(S52=0,0,S52/S53) -> 0.12101761 | T54: =IF(T52=0,0,T52/T53) -> 0.012547212 | U54: =IF(U52=0,0,U52/U53) -> 0.093549074 | V54: =IF(V52=0,0,V52/V53) -> 0.3492765 | W54: =IF(W52=0,0,W52/W53) -> 0.64718482 | X54: =IF(X52=0,0,X52/X53) -> 0.47832804 | Y54: =IF(Y52=0,0,Y52/Y53) -> 0.27375069 | Z54: =IF(Z52=0,0,Z52/Z53) -> 0.030835055 | ... AD54: =IF(AD52=0,0,AD52/AD53) -> 0 | AG54: SAIFI (Menit/Plg) | AH54: =IF(AH52=0,0,AH52/AH53) -> 0.12101761 | AI54: =IF(AI52=0,0,AI52/AI53) -> 0.13323944 | AJ54: =IF(AJ52=0,0,AJ52/AJ53) -> 0.22648499 | AK54: =IF(AK52=0,0,AK52/AK53) -> 0.57531394 | AL54: =IF(AL52=0,0,AL52/AL53) -> 1.2213763 | AM54: =IF(AM52=0,0,AM52/AM53) -> 1.6972487 | AN54: =IF(AN52=0,0,AN52/AN53) -> 1.967558 | AO54: =IF(AO52=0,0,AO52/AO53) -> 1.9942461 | ... AS54: =IF(AS52=0,0,AS52/AS53) -> 0
B55: ULP Leok | C55: Kali | Q55: ULP Leok | R55: Kali | S55: 11743 | T55: 1524 | U55: 3191 | V55: 5084 | W55: 15127 | X55: 12709 | Y55: 10326 | Z55: 416 | AA55: 4445 | AF55: ULP Leok | AG55: Kali | AH55: =IF(S55=0,0,S55) -> 11743 | AI55: =IF(T55=0,0,AH55+T55) -> 13267 | AJ55: =IF(U55=0,0,AI55+U55) -> 16458 | AK55: =IF(V55=0,0,AJ55+V55) -> 21542 | AL55: =IF(W55=0,0,AK55+W55) -> 36669 | AM55: =IF(X55=0,0,AL55+X55) -> 49378 | AN55: =IF(Y55=0,0,AM55+Y55) -> 59704 | AO55: =IF(Z55=0,0,AN55+Z55) -> 60120 | AP55: =IF(AA55=0,0,AO55+AA55) -> 64565 | ... AS55: =IF(AD55=0,0,AR55+AD55) -> 0
C56: Pelanggan | R56: Pelanggan | S56: =S34 -> 35785 | T56: =T34 -> 35893 | U56: =U34 -> 35986 | V56: =V34 -> 36089 | W56: =W34 -> 36170 | X56: =X34 -> 36277 | Y56: =Y34 -> 36362 | Z56: =Z34 -> 36498 | ... AD56: =AD34 -> 0 | AG56: Pelanggan | AH56: =S56 -> 35785 | AI56: =T56 -> 35893 | AJ56: =U56 -> 35986 | AK56: =V56 -> 36089 | AL56: =W56 -> 36170 | AM56: =X56 -> 36277 | AN56: =Y56 -> 36362 | AO56: =Z56 -> 36498 | ... AS56: =AD56 -> 0
C57: SAIFI (Kali/Plg) | D57: 0.27 | E57: 0.53 | F57: 0.8 | G57: 1.07 | H57: 1.33 | I57: 1.6 | J57: 1.86 | K57: 2.13 | L57: 2.4 | M57: 2.66 | N57: 2.93 | O57: 3.2 | R57: SAIFI (Kali/Plg) | S57: =IF(S55=0,0,S55/S56) -> 0.32815425 | T57: =IF(T55=0,0,T55/T56) -> 0.042459532 | U57: =IF(U55=0,0,U55/U56) -> 0.088673373 | V57: =IF(V55=0,0,V55/V56) -> 0.14087395 | W57: =IF(W55=0,0,W55/W56) -> 0.41821952 | X57: =IF(X55=0,0,X55/X56) -> 0.35033217 | Y57: =IF(Y55=0,0,Y55/Y56) -> 0.28397778 | Z57: =IF(Z55=0,0,Z55/Z56) -> 0.011397885 | ... AD57: =IF(AD55=0,0,AD55/AD56) -> 0 | AG57: SAIFI (Menit/Plg) | AH57: =IF(AH55=0,0,AH55/AH56) -> 0.32815425 | AI57: =IF(AI55=0,0,AI55/AI56) -> 0.36962639 | AJ57: =IF(AJ55=0,0,AJ55/AJ56) -> 0.45734452 | AK57: =IF(AK55=0,0,AK55/AK56) -> 0.59691319 | AL57: =IF(AL55=0,0,AL55/AL56) -> 1.013796 | AM57: =IF(AM55=0,0,AM55/AM56) -> 1.3611379 | AN57: =IF(AN55=0,0,AN55/AN56) -> 1.6419339 | AO57: =IF(AO55=0,0,AO55/AO56) -> 1.6472135 | ... AS57: =IF(AS55=0,0,AS55/AS56) -> 0
B58: ULP Bangkir | C58: Kali | Q58: ULP Bangkir | R58: Kali | S58: 3224 | T58: 242 | U58: 3124 | V58: 2117 | W58: 9271 | X58: 7125 | Y58: 5974 | Z58: 252 | AA58: 4077 | AF58: ULP Bangkir | AG58: Kali | AH58: =IF(S58=0,0,S58) -> 3224 | AI58: =IF(T58=0,0,AH58+T58) -> 3466 | AJ58: =IF(U58=0,0,AI58+U58) -> 6590 | AK58: =IF(V58=0,0,AJ58+V58) -> 8707 | AL58: =IF(W58=0,0,AK58+W58) -> 17978 | AM58: =IF(X58=0,0,AL58+X58) -> 25103 | AN58: =IF(Y58=0,0,AM58+Y58) -> 31077 | AO58: =IF(Z58=0,0,AN58+Z58) -> 31329 | AP58: =IF(AA58=0,0,AO58+AA58) -> 35406 | ... AS58: =IF(AD58=0,0,AR58+AD58) -> 0
C59: Pelanggan | R59: Pelanggan | S59: =S37 -> 21705 | T59: =T37 -> 21751 | U59: =U37 -> 21798 | V59: =V37 -> 21849 | W59: =W37 -> 21902 | X59: =X37 -> 21961 | Y59: =Y37 -> 21999 | Z59: =Z37 -> 22037 | ... AD59: =AD37 -> 0 | AG59: Pelanggan | AH59: =S59 -> 21705 | AI59: =T59 -> 21751 | AJ59: =U59 -> 21798 | AK59: =V59 -> 21849 | AL59: =W59 -> 21902 | AM59: =X59 -> 21961 | AN59: =Y59 -> 21999 | AO59: =Z59 -> 22037 | ... AS59: =AD59 -> 0
C60: SAIFI (Kali/Plg) | D60: 0.23 | E60: 0.47 | F60: 0.7 | G60: 0.94 | H60: 1.17 | I60: 1.4 | J60: 1.64 | K60: 1.87 | L60: 2.1 | M60: 2.34 | N60: 2.57 | O60: 2.81 | R60: SAIFI (Kali/Plg) | S60: =IF(S58=0,0,S58/S59) -> 0.1485372 | T60: =IF(T58=0,0,T58/T59) -> 0.011125925 | U60: =IF(U58=0,0,U58/U59) -> 0.1433159 | V60: =IF(V58=0,0,V58/V59) -> 0.096892306 | W60: =IF(W58=0,0,W58/W59) -> 0.42329468 | X60: =IF(X58=0,0,X58/X59) -> 0.32443878 | Y60: =IF(Y58=0,0,Y58/Y59) -> 0.2715578 | Z60: =IF(Z58=0,0,Z58/Z59) -> 0.011435313 | ... AD60: =IF(AD58=0,0,AD58/AD59) -> 0 | AG60: SAIFI (Menit/Plg) | AH60: =IF(AH58=0,0,AH58/AH59) -> 0.1485372 | AI60: =IF(AI58=0,0,AI58/AI59) -> 0.159349 | AJ60: =IF(AJ58=0,0,AJ58/AJ59) -> 0.30232131 | AK60: =IF(AK58=0,0,AK58/AK59) -> 0.39850794 | AL60: =IF(AL58=0,0,AL58/AL59) -> 0.82083828 | AM60: =IF(AM58=0,0,AM58/AM59) -> 1.1430718 | AN60: =IF(AN58=0,0,AN58/AN59) -> 1.4126551 | AO60: =IF(AO58=0,0,AO58/AO59) -> 1.4216545 | ... AS60: =IF(AS58=0,0,AS58/AS59) -> 0
B61: ULP Moutong | C61: Kali | Q61: ULP Moutong | R61: Kali | S61: 424 | T61: 939 | U61: 2405 | V61: 3369 | W61: 6494 | X61: 4710 | Y61: 4748 | Z61: 171 | AA61: 1578 | AF61: ULP Moutong | AG61: Kali | AH61: =IF(S61=0,0,S61) -> 424 | AI61: =IF(T61=0,0,AH61+T61) -> 1363 | AJ61: =IF(U61=0,0,AI61+U61) -> 3768 | AK61: =IF(V61=0,0,AJ61+V61) -> 7137 | AL61: =IF(W61=0,0,AK61+W61) -> 13631 | AM61: =IF(X61=0,0,AL61+X61) -> 18341 | AN61: =IF(Y61=0,0,AM61+Y61) -> 23089 | AO61: =IF(Z61=0,0,AN61+Z61) -> 23260 | AP61: =IF(AA61=0,0,AO61+AA61) -> 24838 | ... AS61: =IF(AD61=0,0,AR61+AD61) -> 0
C62: Pelanggan | R62: Pelanggan | S62: =S40 -> 22738 | T62: =T40 -> 22826 | U62: =U40 -> 22869 | V62: =V40 -> 22908 | W62: =W40 -> 22948 | X62: =X40 -> 23000 | Y62: =Y40 -> 23047 | Z62: =Z40 -> 23067 | ... AD62: =AD40 -> 0 | AG62: Pelanggan | AH62: =S62 -> 22738 | AI62: =T62 -> 22826 | AJ62: =U62 -> 22869 | AK62: =V62 -> 22908 | AL62: =W62 -> 22948 | AM62: =X62 -> 23000 | AN62: =Y62 -> 23047 | AO62: =Z62 -> 23067 | ... AS62: =AD62 -> 0
C63: SAIFI (Kali/Plg) | D63: 0.17 | E63: 0.34 | F63: 0.51 | G63: 0.68 | H63: 0.85 | I63: 1.02 | J63: 1.19 | K63: 1.37 | L63: 1.54 | M63: 1.71 | N63: 1.88 | O63: 2.05 | R63: SAIFI (Kali/Plg) | S63: =IF(S61=0,0,S61/S62) -> 0.018647199 | T63: =IF(T61=0,0,T61/T62) -> 0.0411373 | U63: =IF(U61=0,0,U61/U62) -> 0.1051642 | V63: =IF(V61=0,0,V61/V62) -> 0.14706653 | W63: =IF(W61=0,0,W61/W62) -> 0.28298762 | X63: =IF(X61=0,0,X61/X62) -> 0.20478261 | Y63: =IF(Y61=0,0,Y61/Y62) -> 0.2060138 | Z63: =IF(Z61=0,0,Z61/Z62) -> 0.0074131877 | ... AD63: =IF(AD61=0,0,AD61/AD62) -> 0 | AG63: SAIFI (Menit/Plg) | AH63: =IF(AH61=0,0,AH61/AH62) -> 0.018647199 | AI63: =IF(AI61=0,0,AI61/AI62) -> 0.059712608 | AJ63: =IF(AJ61=0,0,AJ61/AJ62) -> 0.16476453 | AK63: =IF(AK61=0,0,AK61/AK62) -> 0.31155055 | AL63: =IF(AL61=0,0,AL61/AL62) -> 0.59399512 | AM63: =IF(AM61=0,0,AM61/AM62) -> 0.79743478 | AN63: =IF(AN61=0,0,AN61/AN62) -> 1.0018224 | AO63: =IF(AO61=0,0,AO61/AO62) -> 1.0083669 | ... AS63: =IF(AS61=0,0,AS61/AS62) -> 0
B64: ULP Kotaraya | C64: Kali | Q64: ULP Kotaraya | R64: Kali | S64: 1884 | T64: 548 | U64: 4685 | V64: 4588 | W64: 13583 | X64: 7160 | Y64: 8587 | Z64: 2924 | AA64: 169 | AF64: ULP Kotaraya | AG64: Kali | AH64: =IF(S64=0,0,S64) -> 1884 | AI64: =IF(T64=0,0,AH64+T64) -> 2432 | AJ64: =IF(U64=0,0,AI64+U64) -> 7117 | AK64: =IF(V64=0,0,AJ64+V64) -> 11705 | AL64: =IF(W64=0,0,AK64+W64) -> 25288 | AM64: =IF(X64=0,0,AL64+X64) -> 32448 | AN64: =IF(Y64=0,0,AM64+Y64) -> 41035 | AO64: =IF(Z64=0,0,AN64+Z64) -> 43959 | AP64: =IF(AA64=0,0,AO64+AA64) -> 44128 | ... AS64: =IF(AD64=0,0,AR64+AD64) -> 0
C65: Pelanggan | R65: Pelanggan | S65: =S43 -> 29532 | T65: =T43 -> 29631 | U65: =U43 -> 29740 | V65: =V43 -> 29882 | W65: =W43 -> 29977 | X65: =X43 -> 30072 | Y65: =Y43 -> 30175 | Z65: =Z43 -> 30244 | ... AD65: =AD43 -> 0 | AG65: Pelanggan | AH65: =S65 -> 29532 | AI65: =T65 -> 29631 | AJ65: =U65 -> 29740 | AK65: =V65 -> 29882 | AL65: =W65 -> 29977 | AM65: =X65 -> 30072 | AN65: =Y65 -> 30175 | AO65: =Z65 -> 30244 | ... AS65: =AD65 -> 0
C66: SAIFI (Kali/Plg) | D66: 0.22 | E66: 0.44 | F66: 0.65 | G66: 0.87 | H66: 1.09 | I66: 1.31 | J66: 1.53 | K66: 1.75 | L66: 1.96 | M66: 2.18 | N66: 2.4 | O66: 2.62 | R66: SAIFI (Kali/Plg) | S66: =IF(S64=0,0,S64/S65) -> 0.063795205 | T66: =IF(T64=0,0,T64/T65) -> 0.018494145 | U66: =IF(U64=0,0,U64/U65) -> 0.15753194 | V66: =IF(V64=0,0,V64/V65) -> 0.15353725 | W66: =IF(W64=0,0,W64/W65) -> 0.45311405 | X66: =IF(X64=0,0,X64/X65) -> 0.23809524 | Y66: =IF(Y64=0,0,Y64/Y65) -> 0.28457332 | Z66: =IF(Z64=0,0,Z64/Z65) -> 0.096680333 | ... AD66: =IF(AD64=0,0,AD64/AD65) -> 0 | AG66: SAIFI (Menit/Plg) | AH66: =IF(AH64=0,0,AH64/AH65) -> 0.063795205 | AI66: =IF(AI64=0,0,AI64/AI65) -> 0.082076204 | AJ66: =IF(AJ64=0,0,AJ64/AJ65) -> 0.23930733 | AK66: =IF(AK64=0,0,AK64/AK65) -> 0.39170738 | AL66: =IF(AL64=0,0,AL64/AL65) -> 0.84358008 | AM66: =IF(AM64=0,0,AM64/AM65) -> 1.0790104 | AN66: =IF(AN64=0,0,AN64/AN65) -> 1.3599006 | AO66: =IF(AO64=0,0,AO64/AO65) -> 1.4534784 | ... AS66: =IF(AS64=0,0,AS64/AS65) -> 0
B67: UP3 Tolitoli | C67: Kali | Q67: UP3 Tolitoli | R67: Kali | S67: =S52+S55+S58+S61+S64 -> 22931 | T67: =T52+T55+T58+T61+T64 -> 3841 | U67: =U52+U55+U58+U61+U64 -> 17799 | V67: =V52+V55+V58+V61+V64 -> 31596 | W67: =W52+W55+W58+W61+W64 -> 74993 | X67: =X52+X55+X58+X61+X64 -> 54305 | Y67: =Y52+Y55+Y58+Y61+Y64 -> 42596 | Z67: =Z52+Z55+Z58+Z61+Z64 -> 5226 | ... AD67: =AD52+AD55+AD58+AD61+AD64 -> 0 | AF67: UP3 Tolitoli | AG67: Kali | AH67: =IF(S67=0,0,S67) -> 22931 | AI67: =IF(T67=0,0,AH67+T67) -> 26772 | AJ67: =IF(U67=0,0,AI67+U67) -> 44571 | AK67: =IF(V67=0,0,AJ67+V67) -> 76167 | AL67: =IF(W67=0,0,AK67+W67) -> 151160 | AM67: =IF(X67=0,0,AL67+X67) -> 205465 | AN67: =IF(Y67=0,0,AM67+Y67) -> 248061 | AO67: =IF(Z67=0,0,AN67+Z67) -> 253287 | AP67: =IF(AA67=0,0,AO67+AA67) -> 279358 | ... AS67: =IF(AD67=0,0,AR67+AD67) -> 0
C68: Pelanggan | R68: Pelanggan | S68: =S53+S56+S59+S62+S65 -> 156497 | T68: =T53+T56+T59+T62+T65 -> 156964 | U68: =U53+U56+U59+U62+U65 -> 157363 | V68: =V53+V56+V59+V62+V65 -> 157791 | W68: =W53+W56+W59+W62+W65 -> 158152 | X68: =X53+X56+X59+X62+X65 -> 158560 | Y68: =Y53+Y56+Y59+Y62+Y65 -> 158929 | Z68: =Z53+Z56+Z59+Z62+Z65 -> 159292 | ... AD68: =AD53+AD56+AD59+AD62+AD65 -> 0 | AG68: Pelanggan | AH68: =S68 -> 156497 | AI68: =T68 -> 156964 | AJ68: =U68 -> 157363 | AK68: =V68 -> 157791 | AL68: =W68 -> 158152 | AM68: =X68 -> 158560 | AN68: =Y68 -> 158929 | AO68: =Z68 -> 159292 | ... AS68: =AD68 -> 0
C69: SAIFI (Kali/Plg) | D69: 0.25 | E69: 0.49 | F69: 0.74 | G69: 0.99 | H69: 1.24 | I69: 1.48 | J69: 1.73 | K69: 1.98 | L69: 2.22 | M69: 2.47 | N69: 2.72 | O69: 2.97 | R69: SAIFI (Kali/Plg) | S69: =IF(S67=0,0,S67/S68) -> 0.14652677 | T69: =IF(T67=0,0,T67/T68) -> 0.024470579 | U69: =IF(U67=0,0,U67/U68) -> 0.11310791 | V69: =IF(V67=0,0,V67/V68) -> 0.20023956 | W69: =IF(W67=0,0,W67/W68) -> 0.47418306 | X69: =IF(X67=0,0,X67/X68) -> 0.34248865 | Y69: =IF(Y67=0,0,Y67/Y68) -> 0.26801905 | Z69: =IF(Z67=0,0,Z67/Z68) -> 0.032807674 | ... AD69: =IF(AD67=0,0,AD67/AD68) -> 0 | AG69: SAIFI (Menit/Plg) | AH69: =IF(AH67=0,0,AH67/AH68) -> 0.14652677 | AI69: =IF(AI67=0,0,AI67/AI68) -> 0.1705614 | AJ69: =IF(AJ67=0,0,AJ67/AJ68) -> 0.28323685 | AK69: =IF(AK67=0,0,AK67/AK68) -> 0.48270814 | AL69: =IF(AL67=0,0,AL67/AL68) -> 0.95578937 | AM69: =IF(AM67=0,0,AM67/AM68) -> 1.2958186 | AN69: =IF(AN67=0,0,AN67/AN68) -> 1.560829 | AO69: =IF(AO67=0,0,AO67/AO68) -> 1.5900799 | ... AS69: =IF(AS67=0,0,AS67/AS68) -> 0
B71: ENS DISTRIBUSI | Q71: =B71 -> ENS DISTRIBUSI | AF71: =B71 -> ENS DISTRIBUSI
B72: TARGET | Q72: REALISASI BULANAN | AF72: REALISASI KOMULATIF
B73: Unit | D73: Jan | E73: Feb | F73: Mar | G73: Apr | H73: May | I73: Jun | J73: Jul | K73: Aug | L73: Sep | M73: Oct | N73: Nov | O73: Dec | Q73: Unit | S73: Jan | T73: Feb | U73: Mar | V73: Apr | W73: May | X73: Jun | Y73: Jul | Z73: Aug | AA73: Sep | AB73: Oct | AC73: Nov | AD73: Dec | AF73: Unit | AH73: Jan | AI73: Feb | AJ73: Mar | AK73: Apr | AL73: May | AM73: Jun | AN73: Jul | AO73: Aug | AP73: Sep | AQ73: Oct | AR73: Nov | AS73: Dec
B74: ULP Tolitoli | C74: MWh | D74: 4.04 | E74: 8.08 | F74: 12.12 | G74: 16.16 | H74: 20.19 | I74: 24.23 | J74: 28.27 | K74: 32.31 | L74: 36.35 | M74: 40.39 | N74: 44.43 | O74: 48.47 | Q74: ULP Tolitoli | R74: MWh | S74: =1709/1000 -> 1.709 | T74: =482/1000 -> 0.482 | U74: =228/1000 -> 0.228 | V74: 2.826 | W74: 6.701 | X74: 5.705 | Y74: 1.224 | Z74: 1.378 | AA74: 2.29 | AF74: ULP Tolitoli | AG74: MWh | AH74: =IF(S74=0,0,S74) -> 1.709 | AI74: =IF(T74=0,0,AH74+T74) -> 2.191 | AJ74: =IF(U74=0,0,AI74+U74) -> 2.419 | AK74: =IF(V74=0,0,AJ74+V74) -> 5.245 | AL74: =IF(W74=0,0,AK74+W74) -> 11.946 | AM74: =IF(X74=0,0,AL74+X74) -> 17.651 | AN74: =IF(Y74=0,0,AM74+Y74) -> 18.875 | AO74: =IF(Z74=0,0,AN74+Z74) -> 20.253 | AP74: =IF(AA74=0,0,AO74+AA74) -> 22.543 | ... AS74: =IF(AD74=0,0,AR74+AD74) -> 0
B75: ULP Leok | C75: MWh | D75: 2.45 | E75: 4.9 | F75: 7.35 | G75: 9.8 | H75: 12.25 | I75: 14.69 | J75: 17.14 | K75: 19.59 | L75: 22.04 | M75: 24.49 | N75: 26.94 | O75: 29.39 | Q75: ULP Leok | R75: MWh | S75: =2703/1000 -> 2.703 | T75: =652/1000 -> 0.652 | U75: =70/1000 -> 0.07 | V75: 1.277 | W75: 3.142 | X75: 2.836 | Y75: 1.826 | Z75: 0.022 | AA75: 1.483 | AF75: ULP Leok | AG75: MWh | AH75: =IF(S75=0,0,S75) -> 2.703 | AI75: =IF(T75=0,0,AH75+T75) -> 3.355 | AJ75: =IF(U74=0,0,AI75+U74) -> 3.583 | AK75: =IF(V75=0,0,AJ75+V75) -> 4.86 | AL75: =IF(W75=0,0,AK75+W75) -> 8.002 | AM75: =IF(X75=0,0,AL75+X75) -> 10.838 | AN75: =IF(Y75=0,0,AM75+Y75) -> 12.664 | AO75: =IF(Z75=0,0,AN75+Z75) -> 12.686 | AP75: =IF(AA75=0,0,AO75+AA75) -> 14.169 | AQ75: =IF(AB75=0,0,AP75+AB75) -> 0 | AR75: =IF(AC75=0,0,AQ75+AC75) -> 0 | AS75: =IF(AD75=0,0,AR75+AD75) -> 0
B76: ULP Bangkir | C76: MWh | D76: 0.59 | E76: 1.18 | F76: 1.77 | G76: 2.36 | H76: 2.95 | I76: 3.54 | J76: 4.13 | K76: 4.72 | L76: 5.31 | M76: 5.9 | N76: 6.49 | O76: 7.08 | Q76: ULP Bangkir | R76: MWh | S76: =796/1000 -> 0.796 | T76: =6/1000 -> 0.006 | U76: =253/1000 -> 0.253 | V76: 0.839 | W76: 0.648 | X76: 0.496 | Y76: 0.615 | Z76: 0.013 | AA76: 0.495 | AF76: ULP Bangkir | AG76: MWh | AH76: =IF(S76=0,0,S76) -> 0.796 | AI76: =IF(T76=0,0,AH76+T76) -> 0.802 | AJ76: =IF(U76=0,0,AI76+U76) -> 1.055 | AK76: =IF(V76=0,0,AJ76+V76) -> 1.894 | AL76: =IF(W76=0,0,AK76+W76) -> 2.542 | AM76: =IF(X76=0,0,AL76+X76) -> 3.038 | AN76: =IF(Y76=0,0,AM76+Y76) -> 3.653 | AO76: =IF(Z76=0,0,AN76+Z76) -> 3.666 | AP76: =IF(AA76=0,0,AO76+AA76) -> 4.161 | ... AS76: =IF(AD76=0,0,AR76+AD76) -> 0
B77: ULP Moutong | C77: MWh | D77: 0.86 | E77: 1.72 | F77: 2.58 | G77: 3.45 | H77: 4.31 | I77: 5.17 | J77: 6.03 | K77: 6.89 | L77: 7.75 | M77: 8.61 | N77: 9.47 | O77: 10.34 | Q77: ULP Moutong | R77: MWh | S77: =154/1000 -> 0.154 | T77: =21/1000 -> 0.021 | U77: =67/1000 -> 0.067 | V77: 0.645 | W77: 2.211 | X77: 1.03 | Y77: 0.865 | Z77: 0.009 | AA77: 0.262 | AF77: ULP Moutong | AG77: MWh | AH77: =IF(S77=0,0,S77) -> 0.154 | AI77: =IF(T77=0,0,AH77+T77) -> 0.175 | AJ77: =IF(U77=0,0,AI77+U77) -> 0.242 | AK77: =IF(V77=0,0,AJ77+V77) -> 0.887 | AL77: =IF(W77=0,0,AK77+W77) -> 3.098 | AM77: =IF(X77=0,0,AL77+X77) -> 4.128 | AN77: =IF(Y77=0,0,AM77+Y77) -> 4.993 | AO77: =IF(Z77=0,0,AN77+Z77) -> 5.002 | AP77: =IF(AA77=0,0,AO77+AA77) -> 5.264 | ... AS77: =IF(AD77=0,0,AR77+AD77) -> 0
B78: ULP Kotaraya | C78: MWh | D78: 1.05 | E78: 2.1 | F78: 3.15 | G78: 4.2 | H78: 5.25 | I78: 6.3 | J78: 7.35 | K78: 8.4 | L78: 9.45 | M78: 10.5 | N78: 11.55 | O78: 12.6 | Q78: ULP Kotaraya | R78: MWh | S78: =82/1000 -> 0.082 | T78: =24/1000 -> 0.024 | U78: =113/1000 -> 0.113 | V78: 0.087 | W78: 1.656 | X78: 0.462 | Y78: 1.789 | Z78: 0.586 | AA78: 0.004 | AF78: ULP Kotaraya | AG78: MWh | AH78: =IF(S78=0,0,S78) -> 0.082 | AI78: =IF(T78=0,0,AH78+T78) -> 0.106 | AJ78: =IF(U78=0,0,AI78+U78) -> 0.219 | AK78: =IF(V78=0,0,AJ78+V78) -> 0.306 | AL78: =IF(W78=0,0,AK78+W78) -> 1.962 | AM78: =IF(X78=0,0,AL78+X78) -> 2.424 | AN78: =IF(Y78=0,0,AM78+Y78) -> 4.213 | AO78: =IF(Z78=0,0,AN78+Z78) -> 4.799 | AP78: =IF(AA78=0,0,AO78+AA78) -> 4.803 | ... AS78: =IF(AD78=0,0,AR78+AD78) -> 0
B79: UP3 Tolitoli | C79: MWh | D79: 8.99 | E79: 17.98 | F79: 26.97 | G79: 35.96 | H79: 44.94 | I79: 53.93 | J79: 62.92 | K79: 71.91 | L79: 80.9 | M79: 89.89 | N79: 98.88 | O79: 107.87 | Q79: UP3 Tolitoli | R79: MWh | S79: =SUM(S74:S78) -> 5.444 | T79: =SUM(T74:T78) -> 1.185 | U79: =SUM(U74:U78) -> 0.731 | V79: =SUM(V74:V78) -> 5.674 | W79: =SUM(W74:W78) -> 14.358 | X79: =SUM(X74:X78) -> 10.529 | Y79: =SUM(Y74:Y78) -> 6.319 | Z79: =SUM(Z74:Z78) -> 2.008 | ... AD79: =SUM(AD74:AD78) -> 0 | AF79: UP3 Tolitoli | AG79: MWh | AH79: =IF(S79=0,0,S79) -> 5.444 | AI79: =IF(T79=0,0,AH79+T79) -> 6.629 | AJ79: =IF(U79=0,0,AI79+U79) -> 7.36 | AK79: =IF(V79=0,0,AJ79+V79) -> 13.034 | AL79: =IF(W79=0,0,AK79+W79) -> 27.392 | AM79: =IF(X79=0,0,AL79+X79) -> 37.921 | AN79: =IF(Y79=0,0,AM79+Y79) -> 44.24 | AO79: =IF(Z79=0,0,AN79+Z79) -> 46.248 | AP79: =IF(AA79=0,0,AO79+AA79) -> 50.782 | ... AS79: =IF(AD79=0,0,AR79+AD79) -> 0
A83: 3 | B83: SUSUT JARINGAN TANPA E-MIN (%) | Q83: =B83 -> SUSUT JARINGAN TANPA E-MIN (%) | AF83: =B83 -> SUSUT JARINGAN TANPA E-MIN (%)
B84: TARGET | Q84: REALISASI BULANAN | AF84: REALISASI KOMULATIF
B85: Unit | D85: Jan | E85: Feb | F85: Mar | G85: Apr | H85: May | I85: Jun | J85: Jul | K85: Aug | L85: Sep | M85: Oct | N85: Nov | O85: Dec | Q85: Unit | S85: Jan | T85: Feb | U85: Mar | V85: Apr | W85: May | X85: Jun | Y85: Jul | Z85: Aug | AA85: Sep | AB85: Oct | AC85: Nov | AD85: Dec | AF85: Unit | AH85: Jan | AI85: Feb | AJ85: Mar | AK85: Apr | AL85: May | AM85: Jun | AN85: Jul | AO85: Aug | AP85: Sep | AQ85: Oct | AR85: Nov | AS85: Dec
B86: ULP Tolitoli | C86: kWh Siap Salur (kWh) | Q86: ULP Tolitoli | R86: kWh Siap Salur (kWh) | S86: 7016666.3 | T86: 6257261.5 | U86: 6881436.7 | V86: 6762863.8 | W86: 7317520.2 | X86: 6412591 | Y86: 6791574.7 | Z86: 6576037.2 | AA86: 6699247 | AF86: ULP Tolitoli | AG86: kWh Siap Salur (kWh) | AH86: =IF(S86=0,0,S86) -> 7016666.3 | AI86: =IF(T86=0,0,AH86+T86) -> 13273928 | AJ86: =IF(U86=0,0,AI86+U86) -> 20155364 | AK86: =IF(V86=0,0,AJ86+V86) -> 26918228 | AL86: =IF(W86=0,0,AK86+W86) -> 34235748 | AM86: =IF(X86=0,0,AL86+X86) -> 40648339 | AN86: =IF(Y86=0,0,AM86+Y86) -> 47439914 | AO86: =IF(Z86=0,0,AN86+Z86) -> 54015951 | AP86: =IF(AA86=0,0,AO86+AA86) -> 60715198 | ... AS86: =IF(AD86=0,0,AR86+AD86) -> 0
C87: PSSD (kWh) | R87: PSSD (kWh) | S87: 60661.656 | T87: 60760.872 | U87: 60866.35 | V87: 60969.1 | W87: 61078.608 | X87: 61167.528 | Y87: 61281.72 | Z87: 61392.744 | AA87: 61476.448 | AG87: PSSD (kWh) | AH87: =IF(S87=0,0,S87) -> 60661.656 | AI87: =IF(T87=0,0,AH87+T87) -> 121422.53 | AJ87: =IF(U87=0,0,AI87+U87) -> 182288.88 | AK87: =IF(V87=0,0,AJ87+V87) -> 243257.98 | AL87: =IF(W87=0,0,AK87+W87) -> 304336.59 | AM87: =IF(X87=0,0,AL87+X87) -> 365504.11 | AN87: =IF(Y87=0,0,AM87+Y87) -> 426785.83 | AO87: =IF(Z87=0,0,AN87+Z87) -> 488178.58 | AP87: =IF(AA87=0,0,AO87+AA87) -> 549655.03 | ... AS87: =IF(AD87=0,0,AR87+AD87) -> 0
C88: Jual Tanpa E-min (kWh) | R88: Jual Tanpa E-min (kWh) | S88: 7471811 | T88: 6546925.6 | U88: 6242950 | V88: 5286155.9 | W88: 6041871.2 | X88: 5733166.3 | Y88: 5976394.1 | Z88: 5999696.6 | AA88: 6021804.6 | AG88: Jual Tanpa E-min (kWh) | AH88: =IF(S88=0,0,S88) -> 7471811 | AI88: =IF(T88=0,0,AH88+T88) -> 14018737 | AJ88: =IF(U88=0,0,AI88+U88) -> 20261687 | AK88: =IF(V88=0,0,AJ88+V88) -> 25547842 | AL88: =IF(W88=0,0,AK88+W88) -> 31589714 | AM88: =IF(X88=0,0,AL88+X88) -> 37322880 | AN88: =IF(Y88=0,0,AM88+Y88) -> 43299274 | AO88: =IF(Z88=0,0,AN88+Z88) -> 49298971 | AP88: =IF(AA88=0,0,AO88+AA88) -> 55320775 | ... AS88: =IF(AD88=0,0,AR88+AD88) -> 0
C89: Susut Jaringan (%) | D89: 10.36 | E89: 10.36 | F89: 10.36 | G89: 10.17 | H89: 9.98 | I89: 9.79 | J89: 9.72 | K89: 9.65 | L89: 9.58 | M89: 9.51 | N89: 9.44 | O89: 9.37 | R89: Susut Jaringan (%) | S89: =IF(S86=0,0,(S86-S87-S88)/S86*100) -> -7.3511602 | T89: =IF(T86=0,0,(T86-T87-T88)/T86*100) -> -5.6002929 | U89: =IF(U86=0,0,(U86-U87-U88)/U86*100) -> 8.3938914 | V89: =IF(V86=0,0,(V86-V87-V88)/V86*100) -> 20.934013 | W89: =IF(W86=0,0,(W86-W87-W88)/W86*100) -> 16.598116 | X89: =IF(X86=0,0,(X86-X87-X88)/X86*100) -> 9.6413014 | Y89: =IF(Y86=0,0,(Y86-Y87-Y88)/Y86*100) -> 11.100501 | Z89: =IF(Z86=0,0,(Z86-Z87-Z88)/Z86*100) -> 7.8306719 | ... AD89: =IF(AD86=0,0,(AD86-AD87-AD88)/AD86*100) -> 0 | AG89: Susut Jaringan (%) | AH89: =IF(AH86=0,0,(AH86-AH87-AH88)/AH86*100) -> -7.3511602 | AI89: =IF(AI86=0,0,(AI86-AI87-AI88)/AI86*100) -> -6.5258103 | AJ89: =IF(AJ86=0,0,(AJ86-AJ87-AJ88)/AJ86*100) -> -1.4319316 | AK89: =IF(AK86=0,0,(AK86-AK87-AK88)/AK86*100) -> 4.1872287 | AL89: =IF(AL86=0,0,(AL86-AL87-AL88)/AL86*100) -> 6.8399213 | AM89: =IF(AM86=0,0,(AM86-AM87-AM88)/AM86*100) -> 7.2818608 | AN89: =IF(AN86=0,0,(AN86-AN87-AN88)/AN86*100) -> 7.8285435 | AO89: =IF(AO86=0,0,(AO86-AO87-AO88)/AO86*100) -> 7.8288026 | ... AS89: =IF(AS86=0,0,(AS86-AS87-AS88)/AS86*100) -> 0
B90: ULP Leok | C90: kWh Siap Salur (kWh) | Q90: ULP Leok | R90: kWh Siap Salur (kWh) | S90: 4449874.2 | T90: 4442618.1 | U90: 5102551.2 | V90: 4774566.5 | W90: 5045961.4 | X90: 4823509.5 | Y90: 5143693.7 | Z90: 5066765 | AA90: 5057536 | AF90: ULP Leok | AG90: kWh Siap Salur (kWh) | AH90: =IF(S90=0,0,S90) -> 4449874.2 | AI90: =IF(T90=0,0,AH90+T90) -> 8892492.3 | AJ90: =IF(U90=0,0,AI90+U90) -> 13995044 | AK90: =IF(V90=0,0,AJ90+V90) -> 18769610 | AL90: =IF(W90=0,0,AK90+W90) -> 23815572 | AM90: =IF(X90=0,0,AL90+X90) -> 28639081 | AN90: =IF(Y90=0,0,AM90+Y90) -> 33782775 | AO90: =IF(Z90=0,0,AN90+Z90) -> 38849540 | AP90: =IF(AA90=0,0,AO90+AA90) -> 43907076 | ... AS90: =IF(AD90=0,0,AR90+AD90) -> 0
C91: PSSD (kWh) | R91: PSSD (kWh) | S91: 46063.44 | T91: 46566.792 | U91: 46670.04 | V91: 46805.76 | W91: 46901.952 | X91: 46965.6 | Y91: 47043.288 | Z91: 47267.064 | AA91: 47372.968 | AG91: PSSD (kWh) | AH91: =IF(S91=0,0,S91) -> 46063.44 | AI91: =IF(T91=0,0,AH91+T91) -> 92630.232 | AJ91: =IF(U91=0,0,AI91+U91) -> 139300.27 | AK91: =IF(V91=0,0,AJ91+V91) -> 186106.03 | AL91: =IF(W91=0,0,AK91+W91) -> 233007.98 | AM91: =IF(X91=0,0,AL91+X91) -> 279973.58 | AN91: =IF(Y91=0,0,AM91+Y91) -> 327016.87 | AO91: =IF(Z91=0,0,AN91+Z91) -> 374283.94 | AP91: =IF(AA91=0,0,AO91+AA91) -> 421656.9 | ... AS91: =IF(AD91=0,0,AR91+AD91) -> 0
C92: Jual Tanpa E-min (kWh) | R92: Jual Tanpa E-min (kWh) | S92: 5024820.2 | T92: 4188626.6 | U92: 4270932 | V92: 3722369.5 | W92: 4101468.9 | X92: 4242295 | Y92: 4293714.3 | Z92: 4437258.3 | AA92: 4337942.4 | AG92: Jual Tanpa E-min (kWh) | AH92: =IF(S92=0,0,S92) -> 5024820.2 | AI92: =IF(T92=0,0,AH92+T92) -> 9213446.8 | AJ92: =IF(U92=0,0,AI92+U92) -> 13484379 | AK92: =IF(V92=0,0,AJ92+V92) -> 17206748 | AL92: =IF(W92=0,0,AK92+W92) -> 21308217 | AM92: =IF(X92=0,0,AL92+X92) -> 25550512 | AN92: =IF(Y92=0,0,AM92+Y92) -> 29844227 | AO92: =IF(Z92=0,0,AN92+Z92) -> 34281485 | AP92: =IF(AA92=0,0,AO92+AA92) -> 38619427 | ... AS92: =IF(AD92=0,0,AR92+AD92) -> 0
C93: Susut Jaringan (%) | D93: 11.44 | E93: 11.44 | F93: 11.44 | G93: 11.23 | H93: 11.03 | I93: 10.82 | J93: 10.74 | K93: 10.66 | L93: 10.58 | M93: 10.51 | N93: 10.43 | O93: 10.35 | R93: Susut Jaringan (%) | S93: =IF(S90=0,0,(S90-S91-S92)/S90*100) -> -13.955662 | T93: =IF(T90=0,0,(T90-T91-T92)/T90*100) -> 4.6689738 | U93: =IF(U90=0,0,(U90-U91-U92)/U90*100) -> 15.383465 | V93: =IF(V90=0,0,(V90-V91-V92)/V90*100) -> 21.057226 | W93: =IF(W90=0,0,(W90-W91-W92)/W90*100) -> 17.788297 | X93: =IF(X90=0,0,(X90-X91-X92)/X90*100) -> 11.075937 | Y93: =IF(Y90=0,0,(Y90-Y91-Y92)/Y90*100) -> 15.610107 | Z93: =IF(Z90=0,0,(Z90-Z91-Z92)/Z90*100) -> 11.491349 | ... AD93: =IF(AD90=0,0,(AD90-AD91-AD92)/AD90*100) -> 0 | AG93: Susut Jaringan (%) | AH93: =IF(AH90=0,0,(AH90-AH91-AH92)/AH90*100) -> -13.955662 | AI93: =IF(AI90=0,0,(AI90-AI91-AI92)/AI90*100) -> -4.6509426 | AJ93: =IF(AJ90=0,0,(AJ90-AJ91-AJ92)/AJ90*100) -> 2.6535427 | AK93: =IF(AK90=0,0,(AK90-AK91-AK92)/AK90*100) -> 7.3350256 | AL93: =IF(AL90=0,0,(AL90-AL91-AL92)/AL90*100) -> 9.5498289 | AM93: =IF(AM90=0,0,(AM90-AM91-AM92)/AM90*100) -> 9.8068621 | AN93: =IF(AN90=0,0,(AN90-AN91-AN92)/AN90*100) -> 10.690452 | AO93: =IF(AO90=0,0,(AO90-AO91-AO92)/AO90*100) -> 10.794905 | ... AS93: =IF(AS90=0,0,(AS90-AS91-AS92)/AS90*100) -> 0
B94: ULP Bangkir | C94: kWh Siap Salur (kWh) | Q94: ULP Bangkir | R94: kWh Siap Salur (kWh) | S94: 2368984.2 | T94: 2194537.2 | U94: 2397068.1 | V94: 2108800.3 | W94: 2218709 | X94: 2233892.4 | Y94: 2369124 | Z94: 2441233.3 | AA94: 2505917.9 | AF94: ULP Bangkir | AG94: kWh Siap Salur (kWh) | AH94: =IF(S94=0,0,S94) -> 2368984.2 | AI94: =IF(T94=0,0,AH94+T94) -> 4563521.4 | AJ94: =IF(U94=0,0,AI94+U94) -> 6960589.5 | AK94: =IF(V94=0,0,AJ94+V94) -> 9069389.8 | AL94: =IF(W94=0,0,AK94+W94) -> 11288099 | AM94: =IF(X94=0,0,AL94+X94) -> 13521991 | AN94: =IF(Y94=0,0,AM94+Y94) -> 15891115 | AO94: =IF(Z94=0,0,AN94+Z94) -> 18332349 | AP94: =IF(AA94=0,0,AO94+AA94) -> 20838266 | ... AS94: =IF(AD94=0,0,AR94+AD94) -> 0
C95: PSSD (kWh) | R95: PSSD (kWh) | S95: 25796.952 | T95: 25897.104 | U95: 26006.26 | V95: 26064.07 | W95: 26129.592 | X95: 26187.624 | Y95: 26242.848 | Z95: 26366.904 | AA95: 26419.32 | AG95: PSSD (kWh) | AH95: =IF(S95=0,0,S95) -> 25796.952 | AI95: =IF(T95=0,0,AH95+T95) -> 51694.056 | AJ95: =IF(U95=0,0,AI95+U95) -> 77700.316 | AK95: =IF(V95=0,0,AJ95+V95) -> 103764.39 | AL95: =IF(W95=0,0,AK95+W95) -> 129893.98 | AM95: =IF(X95=0,0,AL95+X95) -> 156081.6 | AN95: =IF(Y95=0,0,AM95+Y95) -> 182324.45 | AO95: =IF(Z95=0,0,AN95+Z95) -> 208691.35 | AP95: =IF(AA95=0,0,AO95+AA95) -> 235110.67 | ... AS95: =IF(AD95=0,0,AR95+AD95) -> 0
C96: Jual Tanpa E-min (kWh) | R96: Jual Tanpa E-min (kWh) | S96: 3339865.6 | T96: 2785378.9 | U96: 2418373 | V96: 1351580.5 | W96: 1680582 | X96: 1944171.6 | Y96: 2016687.6 | Z96: 2144934.6 | AA96: 2217045.2 | AG96: Jual Tanpa E-min (kWh) | AH96: =IF(S96=0,0,S96) -> 3339865.6 | AI96: =IF(T96=0,0,AH96+T96) -> 6125244.5 | AJ96: =IF(U96=0,0,AI96+U96) -> 8543617.5 | AK96: =IF(V96=0,0,AJ96+V96) -> 9895198.1 | AL96: =IF(W96=0,0,AK96+W96) -> 11575780 | AM96: =IF(X96=0,0,AL96+X96) -> 13519952 | AN96: =IF(Y96=0,0,AM96+Y96) -> 15536639 | AO96: =IF(Z96=0,0,AN96+Z96) -> 17681574 | AP96: =IF(AA96=0,0,AO96+AA96) -> 19898619 | ... AS96: =IF(AD96=0,0,AR96+AD96) -> 0
C97: Susut Jaringan (%) | D97: 8.62 | E97: 8.62 | F97: 8.62 | G97: 8.47 | H97: 8.31 | I97: 8.15 | J97: 8.1 | K97: 8.04 | L97: 7.98 | M97: 7.92 | N97: 7.86 | O97: 7.8 | R97: Susut Jaringan (%) | S97: =IF(S94=0,0,(S94-S95-S96)/S94*100) -> -42.071974 | T97: =IF(T94=0,0,(T94-T95-T96)/T94*100) -> -28.103365 | U97: =IF(U94=0,0,(U94-U95-U96)/U94*100) -> -1.9737073 | V97: =IF(V94=0,0,(V94-V95-V96)/V94*100) -> 34.671642 | W97: =IF(W94=0,0,(W94-W95-W96)/W94*100) -> 23.076364 | X97: =IF(X94=0,0,(X94-X95-X96)/X94*100) -> 11.797042 | Y97: =IF(Y94=0,0,(Y94-Y95-Y96)/Y94*100) -> 13.768533 | Z97: =IF(Z94=0,0,(Z94-Z95-Z96)/Z94*100) -> 11.05719 | ... AD97: =IF(AD94=0,0,(AD94-AD95-AD96)/AD94*100) -> 0 | AG97: Susut Jaringan (%) | AH97: =IF(AH94=0,0,(AH94-AH95-AH96)/AH94*100) -> -42.071974 | AI97: =IF(AI94=0,0,(AI94-AI95-AI96)/AI94*100) -> -35.354654 | AJ97: =IF(AJ94=0,0,(AJ94-AJ95-AJ96)/AJ94*100) -> -23.859018 | AK97: =IF(AK94=0,0,(AK94-AK95-AK96)/AK94*100) -> -10.249561 | AL97: =IF(AL94=0,0,(AL94-AL95-AL96)/AL94*100) -> -3.6992523 | AM97: =IF(AM94=0,0,(AM94-AM95-AM96)/AM94*100) -> -1.1391963 | AN97: =IF(AN94=0,0,(AN94-AN95-AN96)/AN94*100) -> 1.0833198 | AO97: =IF(AO94=0,0,(AO94-AO95-AO96)/AO94*100) -> 2.4114935 | ... AS97: =IF(AS94=0,0,(AS94-AS95-AS96)/AS94*100) -> 0
B98: ULP Moutong | C98: kWh Siap Salur (kWh) | Q98: ULP Moutong | R98: kWh Siap Salur (kWh) | S98: 2895890.1 | T98: 2632389.8 | U98: 3190012.1 | V98: 3170447.9 | W98: 3353437.8 | X98: 3164248.8 | Y98: 3028316.9 | Z98: 2990318.2 | AA98: 3079895.1 | AF98: ULP Moutong | AG98: kWh Siap Salur (kWh) | AH98: =IF(S98=0,0,S98) -> 2895890.1 | AI98: =IF(T98=0,0,AH98+T98) -> 5528279.9 | AJ98: =IF(U98=0,0,AI98+U98) -> 8718292.1 | AK98: =IF(V98=0,0,AJ98+V98) -> 11888740 | AL98: =IF(W98=0,0,AK98+W98) -> 15242178 | AM98: =IF(X98=0,0,AL98+X98) -> 18406427 | AN98: =IF(Y98=0,0,AM98+Y98) -> 21434743 | AO98: =IF(Z98=0,0,AN98+Z98) -> 24425062 | AP98: =IF(AA98=0,0,AO98+AA98) -> 27504957 | ... AS98: =IF(AD98=0,0,AR98+AD98) -> 0
C99: PSSD (kWh) | R99: PSSD (kWh) | S99: 27447.192 | T99: 27547.344 | U99: 27650.3 | V99: 27754.2 | W99: 27774.792 | X99: 27801.936 | Y99: 27824.4 | Z99: 27986.04 | AA99: 28027.952 | AG99: PSSD (kWh) | AH99: =IF(S99=0,0,S99) -> 27447.192 | AI99: =IF(T99=0,0,AH99+T99) -> 54994.536 | AJ99: =IF(U99=0,0,AI99+U99) -> 82644.836 | AK99: =IF(V99=0,0,AJ99+V99) -> 110399.04 | AL99: =IF(W99=0,0,AK99+W99) -> 138173.83 | AM99: =IF(X99=0,0,AL99+X99) -> 165975.76 | AN99: =IF(Y99=0,0,AM99+Y99) -> 193800.16 | AO99: =IF(Z99=0,0,AN99+Z99) -> 221786.2 | AP99: =IF(AA99=0,0,AO99+AA99) -> 249814.16 | ... AS99: =IF(AD99=0,0,AR99+AD99) -> 0
C100: Jual Tanpa E-min (kWh) | R100: Jual Tanpa E-min (kWh) | S100: 3234246.2 | T100: 2506182.5 | U100: 2680131 | V100: 2480217.4 | W100: 2790015 | X100: 2806945.6 | Y100: 2707512.3 | Z100: 2609979.2 | AA100: 2715996.7 | AG100: Jual Tanpa E-min (kWh) | AH100: =IF(S100=0,0,S100) -> 3234246.2 | AI100: =IF(T100=0,0,AH100+T100) -> 5740428.7 | AJ100: =IF(U100=0,0,AI100+U100) -> 8420559.7 | AK100: =IF(V100=0,0,AJ100+V100) -> 10900777 | AL100: =IF(W100=0,0,AK100+W100) -> 13690792 | AM100: =IF(X100=0,0,AL100+X100) -> 16497738 | AN100: =IF(Y100=0,0,AM100+Y100) -> 19205250 | AO100: =IF(Z100=0,0,AN100+Z100) -> 21815229 | AP100: =IF(AA100=0,0,AO100+AA100) -> 24531226 | ... AS100: =IF(AD100=0,0,AR100+AD100) -> 0
C101: Susut Jaringan (%) | D101: 10.62 | E101: 10.62 | F101: 10.62 | G101: 10.42 | H101: 10.23 | I101: 10.04 | J101: 9.96 | K101: 9.89 | L101: 9.82 | M101: 9.75 | N101: 9.67 | O101: 9.6 | R101: Susut Jaringan (%) | S101: =IF(S98=0,0,(S98-S99-S100)/S98*100) -> -12.631807 | T101: =IF(T98=0,0,(T98-T99-T100)/T98*100) -> 3.7479221 | U101: =IF(U98=0,0,(U98-U99-U100)/U98*100) -> 15.116897 | V101: =IF(V98=0,0,(V98-V99-V100)/V98*100) -> 20.895355 | W101: =IF(W98=0,0,(W98-W99-W100)/W98*100) -> 15.973101 | X101: =IF(X98=0,0,(X98-X99-X100)/X98*100) -> 10.413254 | Y101: =IF(Y98=0,0,(Y98-Y99-Y100)/Y98*100) -> 9.6746875 | Z101: =IF(Z98=0,0,(Z98-Z99-Z100)/Z98*100) -> 11.783126 | ... AD101: =IF(AD98=0,0,(AD98-AD99-AD100)/AD98*100) -> 0 | AG101: Susut Jaringan (%) | AH101: =IF(AH98=0,0,(AH98-AH99-AH100)/AH98*100) -> -12.631807 | AI101: =IF(AI98=0,0,(AI98-AI99-AI100)/AI98*100) -> -4.8323047 | AJ101: =IF(AJ98=0,0,(AJ98-AJ99-AJ100)/AJ98*100) -> 2.4670831 | AK101: =IF(AK98=0,0,(AK98-AK99-AK100)/AK98*100) -> 7.3814708 | AL101: =IF(AL98=0,0,(AL98-AL99-AL100)/AL98*100) -> 9.2717189 | AM101: =IF(AM98=0,0,(AM98-AM99-AM100)/AM98*100) -> 9.4679602 | AN101: =IF(AN98=0,0,(AN98-AN99-AN100)/AN98*100) -> 9.4971668 | AO101: =IF(AO98=0,0,(AO98-AO99-AO100)/AO98*100) -> 9.7770328 | ... AS101: =IF(AS98=0,0,(AS98-AS99-AS100)/AS98*100) -> 0
B102: ULP Kotaraya | C102: kWh Siap Salur (kWh) | Q102: ULP Kotaraya | R102: kWh Siap Salur (kWh) | S102: 3227200.9 | T102: 2950915.4 | U102: 3446256 | V102: 3253528.3 | W102: 3311683.8 | X102: 3162196.9 | Y102: 3279861.2 | Z102: 3231677.1 | AA102: 3173585.3 | AF102: ULP Kotaraya | AG102: kWh Siap Salur (kWh) | AH102: =IF(S102=0,0,S102) -> 3227200.9 | AI102: =IF(T102=0,0,AH102+T102) -> 6178116.2 | AJ102: =IF(U102=0,0,AI102+U102) -> 9624372.3 | AK102: =IF(V102=0,0,AJ102+V102) -> 12877901 | AL102: =IF(W102=0,0,AK102+W102) -> 16189584 | AM102: =IF(X102=0,0,AL102+X102) -> 19351781 | AN102: =IF(Y102=0,0,AM102+Y102) -> 22631642 | AO102: =IF(Z102=0,0,AN102+Z102) -> 25863319 | AP102: =IF(AA102=0,0,AO102+AA102) -> 29036905 | ... AS102: =IF(AD102=0,0,AR102+AD102) -> 0
C103: PSSD (kWh) | R103: PSSD (kWh) | S103: 35385.912 | T103: 35478.576 | U103: 35584.06 | V103: 35657.78 | W103: 35817.624 | X103: 36030.312 | Y103: 36149.184 | Z103: 36339.552 | AA103: 36408.488 | AG103: PSSD (kWh) | AH103: =IF(S103=0,0,S103) -> 35385.912 | AI103: =IF(T103=0,0,AH103+T103) -> 70864.488 | AJ103: =IF(U103=0,0,AI103+U103) -> 106448.55 | AK103: =IF(V103=0,0,AJ103+V103) -> 142106.33 | AL103: =IF(W103=0,0,AK103+W103) -> 177923.95 | AM103: =IF(X103=0,0,AL103+Z98) -> 3168242.2 | AN103: =IF(Y103=0,0,AM103+Y103) -> 3204391.4 | AO103: =IF(Z103=0,0,AN103+Z103) -> 3240730.9 | AP103: =IF(AA103=0,0,AO103+AA103) -> 3277139.4 | AQ103: =IF(AB103=0,0,AP103+AB103) -> 0 | AR103: =IF(AC103=0,0,AQ103+AC103) -> 0 | AS103: =IF(AD103=0,0,AR103+AD103) -> 0
C104: Jual Tanpa E-min (kWh) | R104: Jual Tanpa E-min (kWh) | S104: 3822574.7 | T104: 3055884.6 | U104: 2991582 | V104: 2529214 | W104: 2774782.6 | X104: 2881688.7 | Y104: 3046430.1 | Z104: 2923099.5 | AA104: 2888353.8 | AG104: Jual Tanpa E-min (kWh) | AH104: =IF(S104=0,0,S104) -> 3822574.7 | AI104: =IF(T104=0,0,AH104+T104) -> 6878459.4 | AJ104: =IF(U104=0,0,AI104+U104) -> 9870041.4 | AK104: =IF(V104=0,0,AJ104+V104) -> 12399255 | AL104: =IF(W104=0,0,AK104+W104) -> 15174038 | AM104: =IF(X104=0,0,AL104+X104) -> 18055727 | AN104: =IF(Y104=0,0,AM104+Y104) -> 21102157 | AO104: =IF(Z104=0,0,AN104+Z104) -> 24025256 | AP104: =IF(AA104=0,0,AO104+AA104) -> 26913610 | ... AS104: =IF(AD104=0,0,AR104+AD104) -> 0
C105: Susut Jaringan (%) | D105: 6.91 | E105: 6.91 | F105: 6.91 | G105: 6.78 | H105: 6.66 | I105: 6.53 | J105: 6.49 | K105: 6.44 | L105: 6.39 | M105: 6.34 | N105: 6.3 | O105: 6.25 | R105: Susut Jaringan (%) | S105: =IF(S102=0,0,(S102-S103-S104)/S102*100) -> -19.545105 | T105: =IF(T102=0,0,(T102-T103-T104)/T102*100) -> -4.7594651 | U105: =IF(U102=0,0,(U102-U103-U104)/U102*100) -> 12.160732 | V105: =IF(V102=0,0,(V102-V103-V104)/V102*100) -> 21.166451 | W105: =IF(W102=0,0,(W102-W103-W104)/W102*100) -> 15.130779 | X105: =IF(X102=0,0,(X102-X103-X104)/X102*100) -> 7.7312671 | Y105: =IF(Y102=0,0,(Y102-Y103-Y104)/Y102*100) -> 6.0149472 | Z105: =IF(Z102=0,0,(Z102-Z103-Z104)/Z102*100) -> 8.4240487 | ... AD105: =IF(AD102=0,0,(AD102-AD103-AD104)/AD102*100) -> 0 | AG105: Susut Jaringan (%) | AH105: =IF(AH102=0,0,(AH102-AH103-AH104)/AH102*100) -> -19.545105 | AI105: =IF(AI102=0,0,(AI102-AI103-AI104)/AI102*100) -> -12.482892 | AJ105: =IF(AJ102=0,0,(AJ102-AJ103-AJ104)/AJ102*100) -> -3.6586035 | AK105: =IF(AK102=0,0,(AK102-AK103-AK104)/AK102*100) -> 2.6133053 | AL105: =IF(AL102=0,0,(AL102-AL103-AL104)/AL102*100) -> 5.1738351 | AM105: =IF(AM102=0,0,(AM102-AM103-AM104)/AM102*100) -> -9.6744978 | AN105: =IF(AN102=0,0,(AN102-AN103-AN104)/AN102*100) -> -7.4007255 | AO105: =IF(AO102=0,0,(AO102-AO103-AO104)/AO102*100) -> -5.4233861 | ... AS105: =IF(AS102=0,0,(AS102-AS103-AS104)/AS102*100) -> 0
B106: UP3 Tolitoli | C106: kWh Siap Salur (kWh) | Q106: UP3 Tolitoli | R106: kWh Siap Salur (kWh) | S106: =S86+S90+S94+S98+S102 -> 19958616 | T106: =T86+T90+T94+T98+T102 -> 18477722 | U106: =U86+U90+U94+U98+U102 -> 21017324 | V106: =V86+V90+V94+V98+V102 -> 20070207 | W106: =W86+W90+W94+W98+W102 -> 21247312 | X106: =X86+X90+X94+X98+X102 -> 19796439 | Y106: =Y86+Y90+Y94+Y98+Y102 -> 20612570 | Z106: =Z86+Z90+Z94+Z98+Z102 -> 20306031 | ... AD106: =AD86+AD90+AD94+AD98+AD102 -> 0 | AF106: UP3 Tolitoli | AG106: kWh Siap Salur (kWh) | AH106: =AH86+AH90+AH94+AH98+AH102 -> 19958616 | AI106: =AI86+AI90+AI94+AI98+AI102 -> 38436338 | AJ106: =IF(U106=0,0,AI106+U106) -> 59453662 | AK106: =IF(V106=0,0,AJ106+V106) -> 79523869 | AL106: =IF(W106=0,0,AK106+W106) -> 1.0077118e+08 | AM106: =IF(X106=0,0,AL106+X106) -> 1.2056762e+08 | AN106: =IF(Y106=0,0,AM106+Y106) -> 1.4118019e+08 | AO106: =IF(Z106=0,0,AN106+Z106) -> 1.6148622e+08 | AP106: =IF(AA106=0,0,AO106+AA106) -> 1.820024e+08 | AQ106: =IF(AB106=0,0,AP106+AB106) -> 0 | ... AS106: =IF(AD106=0,0,AR106+AD106) -> 0
C107: PSSD (kWh) | R107: PSSD (kWh) | S107: =S87+S91+S95+S99+S103 -> 195355.15 | T107: =T87+T91+T95+T99+T103 -> 196250.69 | U107: =U87+U91+U95+U99+U103 -> 196777.01 | V107: =V87+V91+V95+V99+V103 -> 197250.91 | W107: =W87+W91+W95+W99+W103 -> 197702.57 | X107: =X87+X91+X95+X99+X103 -> 198153 | Y107: =Y87+Y91+Y95+Y99+Y103 -> 198541.44 | Z107: =Z87+Z91+Z95+Z99+Z103 -> 199352.3 | ... AD107: =AD87+AD91+AD95+AD99+AD103 -> 0 | AG107: PSSD (kWh) | AH107: =AH87+AH91+AH95+AH99+AH103 -> 195355.15 | AI107: =AI87+AI91+AI95+AI99+AI103 -> 391605.84 | AJ107: =IF(U107=0,0,AI107+U107) -> 588382.85 | AK107: =IF(V107=0,0,AJ107+V107) -> 785633.76 | AL107: =IF(W107=0,0,AK107+W107) -> 983336.33 | AM107: =IF(X107=0,0,AL107+X107) -> 1181489.3 | AN107: =IF(Y107=0,0,AM107+Y107) -> 1380030.8 | AO107: =IF(Z107=0,0,AN107+Z107) -> 1579383.1 | AP107: =IF(AA107=0,0,AO107+AA107) -> 1779088.2 | AQ107: =IF(AB107=0,0,AP107+AB107) -> 0 | ... AS107: =IF(AD107=0,0,AR107+AD107) -> 0
...

Sheet SIMULASI
B1: KONTRAK MANAJEMEN 2022
B2: PT PLN (PERSERO) UIW SULUTTENGGO | M2: JUNI | N2: PILIH BULAN LAPORAN
B3: UP3 TOLITOLI
A4: NO | B4: KPI | D4: SATUAN | E4: BOBOT | F4: TARGET 2022 | G4: =VLOOKUP(M2,M7:N18,2,FALSE) -> S.D. JUNI
G5: TARGET | H5: REAL | I5: PENCAPAIAN | J5: NILAI
A6: 1 | B6: 2 | D6: 3 | E6: 4 | F6: 5 | G6: 6 | H6: 7 | I6: 8 | J6: 9
A7: =T.UP3!A7 -> I | B7: =T.UP3!B7 -> Key Performance Indikator | E7: =SUM(E8:E10) -> 28 | J7: =SUM(J8:J10) -> 29.4 | M7: JAN | N7: S.D. JANUARI
A8: =T.UP3!A8 -> 1 | B8: =T.UP3!B8 -> Penjualan Tenaga Listrik | C8: =T.UP3!C8 -> ñ | D8: =T.UP3!D8 -> GWh | E8: =IF(OR(H8="N/A",G8="N/A"),0,T.UP3!F8) -> 14 | F8: =T.UP3!H8 -> 231.47 | G8: =VLOOKUP(B8,T.UP3!$B$4:$T$70,MATCH(SIMULASI!$M$2,T.UP3!$B$5:$T$5,0),FALSE) -> 113.73 | H8: =VLOOKUP(B8,'R.UP3'!$B$4:$S$54,MATCH(SIMULASI!$M$2,'R.UP3'!$B$5:$S$5,0),FALSE) -> 111.65157 | I8: 100 | J8: =IF(I8="N/A",0,IF(I8>110,E8*110/100,E8*I8/100)) -> 14 | K8: OK | M8: FEB | N8: S.D. FEBRUARI
A9: =T.UP3!A9 -> 2 | B9: =T.UP3!B9 -> Keandalan Sistem | C9: =T.UP3!C9 -> 0 | D9: =T.UP3!D9 -> 0 | E9: =IF(OR(H9="N/A",G9="N/A"),0,T.UP3!F9) -> 14 | F9: =T.UP3!H9 -> 0 | G9: =VLOOKUP(B9,T.UP3!$B$4:$T$70,MATCH(SIMULASI!$M$2,T.UP3!$B$5:$T$5,0),FALSE) -> 0 | H9: =VLOOKUP(B9,'R.UP3'!$B$4:$S$54,MATCH(SIMULASI!$M$2,'R.UP3'!$B$5:$S$5,0),FALSE) -> 0 | I9: 110 | J9: =IF(I9="N/A",0,IF(I9>110,E9*110/100,E9*I9/100)) -> 15.4 | K9: OK | M9: MAR | N9: S.D. MARET
A10: =T.UP3!A10 -> 0 | B10: =T.UP3!B10 -> a. SAIDI Sesuai Kewenangannya | C10: =T.UP3!C10 -> ò | D10: =T.UP3!D10 -> Menit/Plg | E10: =IF(OR(H10="N/A",G10="N/A"),0,T.UP3!F10) -> 0 | F10: =T.UP3!H10 -> 280.67 | G10: =VLOOKUP(B10,T.UP3!$B$4:$T$70,MATCH(SIMULASI!$M$2,T.UP3!$B$5:$T$5,0),FALSE) -> 140.34 | H10: =VLOOKUP(B10,'R.UP3'!$B$4:$S$54,MATCH(SIMULASI!$M$2,'R.UP3'!$B$5:$S$5,0),FALSE) -> 122.5917 | I10: 105 | J10: =IF(I10="N/A",0,IF(I10>110,E10*110/100,E10*I10/100)) -> 0 | K10: OK | M10: APRIL | N10: S.D. APRIL
A11: =T.UP3!A17 -> II | B11: =T.UP3!B17 -> Perfomance Indicators | E11: =SUM(E12:E42) -> #REF! | J11: =SUM(J12:J42) -> #REF! | M11: MEI | N11: S.D. MEI
A12: =T.UP3!A18 -> 4 | B12: =T.UP3!B18 -> Keandalan Jaringan Distribusi | C12: =T.UP3!C18 -> 0 | D12: =T.UP3!D18 -> 0 | E12: =IF(OR(H12="N/A",G12="N/A"),0,T.UP3!F18) -> 6 | F12: =T.UP3!H18 -> 0 | G12: =VLOOKUP(B12,T.UP3!$B$4:$T$70,MATCH(SIMULASI!$M$2,T.UP3!$B$5:$T$5,0),FALSE) -> 0 | H12: =VLOOKUP(B12,'R.UP3'!$B$4:$S$54,MATCH(SIMULASI!$M$2,'R.UP3'!$B$5:$S$5,0),FALSE) -> 0 | I12: =IF(OR(G12="N/A",H12="N/A"),"N/A",IF(AND(G12=0,H12=0),0,(2-H12/G12)*100)) -> 0 | J12: =IF(I12="N/A",0,IF(I12>110,E12*110/100,E12*I12/100)) -> 0 | K12: OK | M12: JUNI | N12: S.D. JUNI
A13: =T.UP3!A19 -> 0 | B13: =T.UP3!B19 -> a. Gangguan TM > 5 Menit | C13: =T.UP3!C19 -> ò | D13: =T.UP3!D19 -> Kali | E13: =IF(OR(H13="N/A",G13="N/A"),0,T.UP3!F19) -> 0 | F13: =T.UP3!H19 -> 166 | G13: =VLOOKUP(B13,T.UP3!$B$4:$T$70,MATCH(SIMULASI!$M$2,T.UP3!$B$5:$T$5,0),FALSE) -> 88 | H13: =VLOOKUP(B13,'R.UP3'!$B$4:$S$54,MATCH(SIMULASI!$M$2,'R.UP3'!$B$5:$S$5,0),FALSE) -> 73 | I13: =IF(OR(G13="N/A",H13="N/A"),"N/A",IF(AND(G13=0,H13=0),0,(2-H13/G13)*100)) -> 117.04545 | J13: =IF(I13="N/A",0,IF(I13>110,E13*110/100,E13*I13/100)) -> 0 | K13: OK | M13: JULI | N13: S.D. JULI
A14: =T.UP3!A20 -> 0 | B14: =T.UP3!B20 -> b. Gangguan TM ≤ 5 Menit | C14: =T.UP3!C20 -> ò | D14: =T.UP3!D20 -> Kali | E14: =IF(OR(H14="N/A",G14="N/A"),0,T.UP3!F20) -> 0 | F14: =T.UP3!H20 -> 191 | G14: =VLOOKUP(B14,T.UP3!$B$4:$T$70,MATCH(SIMULASI!$M$2,T.UP3!$B$5:$T$5,0),FALSE) -> 96 | H14: =VLOOKUP(B14,'R.UP3'!$B$4:$S$54,MATCH(SIMULASI!$M$2,'R.UP3'!$B$5:$S$5,0),FALSE) -> 76 | I14: 98 | J14: =IF(I14="N/A",0,IF(I14>110,E14*110/100,E14*I14/100)) -> 0 | K14: OK | M14: AUG | N14: S.D. AGUSTUS
A15: =T.UP3!A21 -> 0 | B15: =T.UP3!B21 -> c. Kerusakan Peralatan Distribusi (PHB TM dan Trafo) Sesuai Kewenangan | M15: SEP | N15: S.D. SEPTEMBER
B16: =T.UP3!B22 -> Peningkatan Layanan | C16: =T.UP3!C22 -> 0 | D16: =T.UP3!D22 -> 0 | E16: =IF(OR(H16="N/A",G16="N/A"),0,T.UP3!F22) -> 6 | F16: =T.UP3!H22 -> 0 | G16: =VLOOKUP(B16,T.UP3!$B$4:$T$70,MATCH(SIMULASI!$M$2,T.UP3!$B$5:$T$5,0),FALSE) -> 0 | H16: =VLOOKUP(B16,'R.UP3'!$B$4:$S$54,MATCH(SIMULASI!$M$2,'R.UP3'!$B$5:$S$5,0),FALSE) -> 0 | I16: 110 | J16: =IF(I16="N/A",0,IF(I16>110,E16*110/100,E16*I16/100)) -> 6.6 | K16: OK | M16: OKT | N16: S.D. OKTOBER
B17: =T.UP3!B24 -> b. Pengaduan Gangguan Berulang pada PLN Mobile | C17: =T.UP3!C24 -> ò | D17: =T.UP3!D24 -> % | E17: =IF(OR(H17="N/A",G17="N/A"),0,T.UP3!F24) -> 0 | F17: =T.UP3!H24 -> 0.04 | G17: =VLOOKUP(B17,T.UP3!$B$4:$T$70,MATCH(SIMULASI!$M$2,T.UP3!$B$5:$T$5,0),FALSE) -> 0.04 | H17: =VLOOKUP(B17,'R.UP3'!$B$4:$S$54,MATCH(SIMULASI!$M$2,'R.UP3'!$B$5:$S$5,0),FALSE) -> 0 | I17: 110 | J17: =IF(I17="N/A",0,IF(I17>110,E17*110/100,E17*I17/100)) -> 0 | K17: OK | M17: NOV | N17: S.D. NOVEMBER
A18: =T.UP3!A25 -> 0 | B18: =T.UP3!B25 -> c. Rating PLN Mobile | C18: =T.UP3!C25 -> ñ | D18: =T.UP3!D25 -> Rating | E18: =IF(OR(H18="N/A",G18="N/A"),0,T.UP3!F25) -> 0 | F18: =T.UP3!H25 -> 4.9 | G18: =VLOOKUP(B18,T.UP3!$B$4:$T$70,MATCH(SIMULASI!$M$2,T.UP3!$B$5:$T$5,0),FALSE) -> 4.9 | H18: N/A | I18: =IF(OR(G18="N/A",H18="N/A"),"N/A",IF(AND(G18=0,H18=0),0,H18/G18*100)) -> N/A | J18: =IF(I18="N/A",0,IF(I18>110,E18*110/100,E18*I18/100)) -> 0 | K18: OK | M18: DES | N18: S.D. DESEMBER
A19: =T.UP3!#REF! -> #REF! | B19: =T.UP3!#REF! -> #REF!
B20: =T.UP3!B26 -> d. Jumlah Kali Transaksi Keuangan melalui PLN Mobile | C20: =T.UP3!C26 -> ñ | D20: =T.UP3!D26 -> Kali Transaksi | E20: =IF(OR(H20="N/A",G20="N/A"),0,T.UP3!F26) -> 0 | F20: =T.UP3!H26 -> 62908 | G20: =VLOOKUP(B20,T.UP3!$B$4:$T$70,MATCH(SIMULASI!$M$2,T.UP3!$B$5:$T$5,0),FALSE) -> 31455 | H20: =VLOOKUP(B20,'R.UP3'!$B$4:$S$54,MATCH(SIMULASI!$M$2,'R.UP3'!$B$5:$S$5,0),FALSE) -> 45061 | I20: 110 | J20: =IF(OR(I20="N/A",I20<0),0,IF(I20>110,E20*110/100,E20*I20/100)) -> 0 | K20: OK
B21: =T.UP3!#REF! -> #REF! | C21: =T.UP3!#REF! -> #REF! | D21: =T.UP3!#REF! -> #REF! | E21: =IF(OR(H21="N/A",G21="N/A"),0,T.UP3!#REF!) -> #REF! | F21: =T.UP3!#REF! -> #REF! | G21: =VLOOKUP(B21,T.UP3!$B$4:$T$70,MATCH(SIMULASI!$M$2,T.UP3!$B$5:$T$5,0),FALSE) -> #REF! | H21: =VLOOKUP(B21,'R.UP3'!$B$4:$S$54,MATCH(SIMULASI!$M$2,'R.UP3'!$B$5:$S$5,0),FALSE) -> #REF! | I21: 110 | J21: =IF(I21="N/A",0,IF(I21>110,E21*110/100,E21*I21/100)) -> #REF! | K21: OK
A22: =T.UP3!A38 -> 0 | B22: =T.UP3!B38 -> b. Penambahan Jumlah Pelanggan | C22: =T.UP3!C38 -> ñ | D22: =T.UP3!D38 -> Pelanggan | E22: =IF(OR(H22="N/A",G22="N/A"),0,T.UP3!F38) -> 2 | F22: =T.UP3!H38 -> 10632 | G22: =VLOOKUP(B22,T.UP3!$B$4:$T$70,MATCH(SIMULASI!$M$2,T.UP3!$B$5:$T$5,0),FALSE) -> 4619 | H22: 3.17 | I22: =IF(OR(G22="N/A",H22="N/A"),"N/A",IF(AND(G22=0,H22=0),0,H22/G22*100)) -> 0.068629574 | J22: =IF(I22="N/A",0,IF(I22>110,E22*110/100,E22*I22/100)) -> 0.0013725915 | K22: OK
A23: =T.UP3!A41 -> 0 | B23: =T.UP3!B41 -> e. Penambahan Jumlah Pelanggan Rumah Tangga Lisdes | C23: =T.UP3!C41 -> ñ | D23: =T.UP3!D41 -> Pelanggan | E23: =IF(OR(H23="N/A",G23="N/A"),0,T.UP3!F41) -> 1.5 | F23: =T.UP3!H41 -> 441 | G23: =VLOOKUP(B23,T.UP3!$B$4:$T$70,MATCH(SIMULASI!$M$2,T.UP3!$B$5:$T$5,0),FALSE) -> 14 | H23: 100 | I23: =IF(OR(G23="N/A",H23="N/A"),"N/A",IF(AND(G23=0,H23=0),0,H23/G23*100)) -> 714.28571 | J23: =IF(I23="N/A",0,IF(I23>110,E23*110/100,E23*I23/100)) -> 1.65 | K23: OK
A24: =T.UP3!A42 -> 0 | B24: =T.UP3!B42 -> f. Peningkatan kWh Penjualan dari Pelanggan Rumah Tangga Lisdes | C24: =T.UP3!C42 -> ñ | D24: =T.UP3!D42 -> KWh | E24: =IF(OR(H24="N/A",G24="N/A"),0,T.UP3!F42) -> 1.5 | F24: =T.UP3!H42 -> 58950.99 | G24: 100 | H24: 100 | I24: =IF(OR(G24="N/A",H24="N/A"),"N/A",IF(AND(G24=0,H24=0),0,H24/G24*100)) -> 100 | J24: =IF(I24="N/A",0,IF(I24>110,E24*110/100,E24*I24/100)) -> 1.5 | K24: OK
A25: =T.UP3!A43 -> 10 | B25: =T.UP3!B43 -> Pengelolaan Pembacaan Meter | C25: =T.UP3!C43 -> 0 | D25: =T.UP3!D43 -> 0 | E25: =IF(OR(H25="N/A",G25="N/A"),0,T.UP3!F43) -> 4 | F25: =T.UP3!H43 -> 0 | G25: =VLOOKUP(B25,T.UP3!$B$4:$T$70,MATCH(SIMULASI!$M$2,T.UP3!$B$5:$T$5,0),FALSE) -> 0 | H25: 80 | I25: =IF(OR(G25="N/A",H25="N/A"),"N/A",IF(AND(G25=0,H25=0),0,H25/G25*100)) -> #DIV/0! | J25: =IF(I25="N/A",0,IF(I25>110,E25*110/100,E25*I25/100)) -> #DIV/0! | K25: OK
A26: =T.UP3!A44 -> 0 | B26: =T.UP3!B44 -> a. Jumlah Pengguna Swa Cam
B27: =T.UP3!#REF! -> #REF! | C27: =T.UP3!#REF! -> #REF! | D27: =T.UP3!#REF! -> #REF! | E27: =IF(OR(H27="N/A",G27="N/A"),0,T.UP3!#REF!) -> #REF! | F27: =T.UP3!#REF! -> #REF! | G27: =VLOOKUP(B27,T.UP3!$B$4:$T$70,MATCH(SIMULASI!$M$2,T.UP3!$B$5:$T$5,0),FALSE) -> #REF! | H27: =VLOOKUP(B27,'R.UP3'!$B$4:$S$54,MATCH(SIMULASI!$M$2,'R.UP3'!$B$5:$S$5,0),FALSE) -> #REF! | I27: =IF(OR(G27="N/A",H27="N/A"),"N/A",IF(AND(G27=0,H27=0),0,H27/G27*100)) -> #REF! | J27: =IF(I27="N/A",0,IF(I27>110,E27*110/100,E27*I27/100)) -> #REF! | K27: OK
B28: =T.UP3!B47 -> a. Pencapaian Rata-Rata Saldo Tanggal 20 diluar Konsumen Instansi (Kementerian & Lembaga)
B29: =T.UP3!B51 -> a. Pengendalian Penggunaan Anggaran Investasi sesuai RKAP | C29: =T.UP3!C51 -> ó | D29: =T.UP3!D51 -> % | E29: =IF(OR(H29="N/A",G29="N/A"),0,T.UP3!F51) -> 0 | F29: =T.UP3!H51 -> 95-100 | G29: =VLOOKUP(B29,T.UP3!$B$4:$T$70,MATCH(SIMULASI!$M$2,T.UP3!$B$5:$T$5,0),FALSE) -> 95-100 | H29: =VLOOKUP(B29,'R.UP3'!$B$4:$S$54,MATCH(SIMULASI!$M$2,'R.UP3'!$B$5:$S$5,0),FALSE) -> 99.43 | I29: 110 | J29: =IF(I29="N/A",0,IF(I29>110,E29*110/100,E29*I29/100)) -> 0 | K29: OK
B30: =T.UP3!#REF! -> #REF! | C30: =T.UP3!#REF! -> #REF! | D30: =T.UP3!#REF! -> #REF! | E30: =IF(OR(H30="N/A",G30="N/A"),0,T.UP3!#REF!) -> #REF! | F30: =T.UP3!#REF! -> #REF! | G30: =VLOOKUP(B30,T.UP3!$B$4:$T$70,MATCH(SIMULASI!$M$2,T.UP3!$B$5:$T$5,0),FALSE) -> #REF! | H30: =VLOOKUP(B30,'R.UP3'!$B$4:$S$54,MATCH(SIMULASI!$M$2,'R.UP3'!$B$5:$S$5,0),FALSE) -> #REF! | I30: 110 | J30: =IF(I30="N/A",0,IF(I30>110,E30*110/100,E30*I30/100)) -> #REF! | K30: OK
B31: =T.UP3!#REF! -> #REF! | C31: =T.UP3!#REF! -> #REF! | D31: =T.UP3!#REF! -> #REF! | E31: =IF(OR(H31="N/A",G31="N/A"),0,T.UP3!#REF!) -> #REF! | F31: =T.UP3!#REF! -> #REF! | G31: =VLOOKUP(B31,T.UP3!$B$4:$T$70,MATCH(SIMULASI!$M$2,T.UP3!$B$5:$T$5,0),FALSE) -> #REF! | H31: =VLOOKUP(B31,'R.UP3'!$B$4:$S$54,MATCH(SIMULASI!$M$2,'R.UP3'!$B$5:$S$5,0),FALSE) -> #REF! | I31: 110 | J31: =IF(I31="N/A",0,IF(I31>110,E31*110/100,E31*I31/100)) -> #REF! | K31: OK
B32: =T.UP3!#REF! -> #REF! | C32: =T.UP3!#REF! -> #REF! | D32: =T.UP3!#REF! -> #REF! | E32: =IF(OR(H32="N/A",G32="N/A"),0,T.UP3!#REF!) -> #REF! | F32: =T.UP3!#REF! -> #REF! | G32: =VLOOKUP(B32,T.UP3!$B$4:$T$70,MATCH(SIMULASI!$M$2,T.UP3!$B$5:$T$5,0),FALSE) -> #REF! | H32: =VLOOKUP(B32,'R.UP3'!$B$4:$S$54,MATCH(SIMULASI!$M$2,'R.UP3'!$B$5:$S$5,0),FALSE) -> #REF! | I32: =IF(OR(G32="N/A",H32="N/A"),"N/A",IF(AND(G32=0,H32=0),0,H32/G32*100)) -> #REF! | J32: =IF(I32="N/A",0,IF(I32>110,E32*110/100,E32*I32/100)) -> #REF! | K32: OK
B33: =T.UP3!B52 -> b. Usulan Penghapusan ATTB | C33: =T.UP3!C52 -> ñ | D33: =T.UP3!D52 -> Rp. Milyar | E33: =IF(OR(H33="N/A",G33="N/A"),0,T.UP3!F52) -> 0 | F33: =T.UP3!H52 -> 3.16 | G33: =VLOOKUP(B33,T.UP3!$B$4:$T$70,MATCH(SIMULASI!$M$2,T.UP3!$B$5:$T$5,0),FALSE) -> 0 | H33: =VLOOKUP(B33,'R.UP3'!$B$4:$S$54,MATCH(SIMULASI!$M$2,'R.UP3'!$B$5:$S$5,0),FALSE) -> 0 | I33: 70 | J33: =IF(I33="N/A",0,IF(I33>110,E33*110/100,E33*I33/100)) -> 0 | K33: OK
B34: =T.UP3!#REF! -> #REF! | C34: =T.UP3!#REF! -> #REF! | D34: =T.UP3!#REF! -> #REF! | E34: =IF(OR(H34="N/A",G34="N/A"),0,T.UP3!#REF!) -> #REF! | F34: =T.UP3!#REF! -> #REF! | G34: =VLOOKUP(B34,T.UP3!$B$4:$T$70,MATCH(SIMULASI!$M$2,T.UP3!$B$5:$T$5,0),FALSE) -> #REF! | H34: 5 | I34: =IF(OR(G34="N/A",H34="N/A"),"N/A",IF(AND(G34=0,H34=0),0,H34/G34*100)) -> #REF! | J34: =IF(I34="N/A",0,IF(I34>110,E34*110/100,E34*I34/100)) -> #REF! | K34: OK
A35: =T.UP3!A53 -> 0 | B35: =T.UP3!B53 -> c. Usulan Penghapusan PRR
B36: =T.UP3!B55 -> a. HCR, OCR, dan Produktivitas Pegawai | C36: =T.UP3!C55 -> ñ | D36: =T.UP3!D55 -> % | E36: =IF(OR(H36="N/A",G36="N/A"),0,T.UP3!F55) -> 0 | F36: =T.UP3!H55 -> 100 | G36: =VLOOKUP(B36,T.UP3!$B$4:$T$70,MATCH(SIMULASI!$M$2,T.UP3!$B$5:$T$5,0),FALSE) -> 100 | H36: 80 | I36: =IF(OR(G36="N/A",H36="N/A"),"N/A",IF(AND(G36=0,H36=0),0,H36/G36*100)) -> 80 | J36: =IF(I36="N/A",0,IF(I36>110,E36*110/100,E36*I36/100)) -> 0 | K36: OK
B37: =T.UP3!B56 -> b. Produktivitas Unit | C37: =T.UP3!C56 -> ñ | D37: =T.UP3!D56 -> % | E37: =IF(OR(H37="N/A",G37="N/A"),0,T.UP3!F56) -> 0 | F37: =T.UP3!H56 -> 100 | G37: =VLOOKUP(B37,T.UP3!$B$4:$T$70,MATCH(SIMULASI!$M$2,T.UP3!$B$5:$T$5,0),FALSE) -> 100 | H37: 80 | I37: =IF(OR(G37="N/A",H37="N/A"),"N/A",IF(AND(G37=0,H37=0),0,H37/G37*100)) -> 80 | J37: =IF(I37="N/A",0,IF(I37>110,E37*110/100,E37*I37/100)) -> 0 | K37: OK
A38: =T.UP3!A61 -> 0 | B38: =T.UP3!B61 -> b. Maturity Level Gudang
B39: =T.UP3!B62 -> c. Maturity Level Sustainbility | E39: =IF(H39="N/A",0,T.UP3!F62) -> 0
B40: =T.UP3!B63 -> d. Implementasi Roadmap Perbaikan Penerapan Manajemen Risiko dan Pencapaian Perlakuan Risiko | E40: =IF(H40="N/A",0,T.UP3!F63) -> 0
B41: =T.UP3!B67 -> c. Ketepatan penyampaian pelaporan dan Akurasi Data Kinerja | E41: =IF(H41="N/A",0,T.UP3!F67) -> Max-10
B42: =T.UP3!B69 -> e. Pencapaian Beyond RKAP | E42: =IF(H42="N/A",0,T.UP3!F69) -> Max-2 Max+2
B43: TOTAL BOBOT | E43: =E7+E11 -> #REF! | J43: =J7+J11 -> #REF!
B44: TOTAL BOBOT PROPORSIONAL | E44: 100 | J44: =E44/E43*J43 -> #REF!
A46: TOLITOLI, 08 JUNI 2022

Sheet PI
B1: KONTRAK MANAJEMEN 2024
B2: PT PLN (PERSERO) UNIT INDUK DISTRIBUSI SULUTTENGGO
B3: UNIT PELAKSANA PELAYANAN PELANGGAN TOLITOLI
B5: GANGGUAN TM | Q5: =B5 -> GANGGUAN TM | AF5: =B5 -> GANGGUAN TM
B6: TARGET | Q6: REALISASI BULANAN | AF6: REALISASI KOMULATIF
B7: Unit | D7: Jan | E7: Feb | F7: Mar | G7: Apr | H7: May | I7: Jun | J7: Jul | K7: Aug | L7: Sep | M7: Oct | N7: Nov | O7: Dec | Q7: Unit | S7: Jan | T7: Feb | U7: Mar | V7: Apr | W7: May | X7: Jun | Y7: Jul | Z7: Aug | AA7: Sep | AB7: Oct | AC7: Nov | AD7: Dec | AF7: Unit | AH7: Jan | AI7: Feb | AJ7: Mar | AK7: Apr | AL7: May | AM7: Jun | AN7: Jul | AO7: Aug | AP7: Sep | AQ7: Oct | AR7: Nov | AS7: Dec
B8: ULP Tolitoli | C8: Gangguan TM > 5 Menit | D8: 6 | E8: 11 | F8: 17 | G8: 22 | H8: 28 | I8: 33 | J8: 39 | K8: 44 | L8: 50 | M8: 55 | N8: 61 | O8: 62 | Q8: ULP Tolitoli | R8: =C8 -> Gangguan TM > 5 Menit | S8: 2 | T8: 1 | U8: 5 | V8: 3 | W8: 18 | X8: 2 | Y8: 7 | Z8: 0 | AA8: 8 | AF8: ULP Tolitoli | AG8: =R8 -> Gangguan TM > 5 Menit | AH8: =S8 -> 2 | AI8: =SUM($S8:T8) -> 3 | AJ8: =SUM($S8:U8) -> 8 | AK8: =SUM($S8:V8) -> 11 | AL8: =SUM($S8:W8) -> 29 | AM8: =SUM($S8:X8) -> 31 | AN8: =SUM($S8:Y8) -> 38 | AO8: =SUM($S8:Z8) -> 38 | AP8: =SUM($S8:AA8) -> 46 | ... AS8: =SUM($S8:AD8) -> 46
C9: Gangguan TM ≤ 5 Menit | D9: 7 | E9: 14 | F9: 22 | G9: 29 | H9: 36 | I9: 43 | J9: 50 | K9: 57 | L9: 65 | M9: 72 | N9: 79 | O9: 86 | R9: =C9 -> Gangguan TM ≤ 5 Menit | S9: 0 | T9: 6 | U9: 2 | V9: 0 | W9: 15 | X9: 11 | Y9: 8 | Z9: 2 | AA9: 11 | AG9: =R9 -> Gangguan TM ≤ 5 Menit | AH9: =S9 -> 0 | AI9: =SUM($S9:T9) -> 6 | AJ9: =SUM($S9:U9) -> 8 | AK9: =SUM($S9:V9) -> 8 | AL9: =SUM($S9:W9) -> 23 | AM9: =SUM($S9:X9) -> 34 | AN9: =SUM($S9:Y9) -> 42 | AO9: =SUM($S9:Z9) -> 44 | AP9: =SUM($S9:AA9) -> 55 | ... AS9: =SUM($S9:AD9) -> 55
B11: ULP Leok | C11: Gangguan TM > 5 Menit | D11: 3 | E11: 5 | F11: 8 | G11: 11 | H11: 13 | I11: 16 | J11: 19 | K11: 21 | L11: 24 | M11: 27 | N11: 29 | O11: 30 | Q11: ULP Leok | R11: =C11 -> Gangguan TM > 5 Menit | S11: 2 | T11: 3 | U11: 3 | V11: 2 | W11: 3 | X11: 0 | Y11: 2 | Z11: 0 | AA11: 1 | AF11: ULP Leok | AG11: =R11 -> Gangguan TM > 5 Menit | AH11: =S11 -> 2 | AI11: =SUM($S11:T11) -> 5 | AJ11: =SUM($S11:U11) -> 8 | AK11: =SUM($S11:V11) -> 10 | AL11: =SUM($S11:W11) -> 13 | AM11: =SUM($S11:X11) -> 13 | AN11: =SUM($S11:Y11) -> 15 | AO11: =SUM($S11:Z11) -> 15 | AP11: =SUM($S11:AA11) -> 16 | ... AS11: =SUM($S11:AD11) -> 16
C12: Gangguan TM ≤ 5 Menit | D12: 4 | E12: 7 | F12: 11 | G12: 15 | H12: 18 | I12: 22 | J12: 26 | K12: 29 | L12: 33 | M12: 37 | N12: 40 | O12: 44 | R12: =C12 -> Gangguan TM ≤ 5 Menit | S12: 0 | T12: 2 | U12: 1 | V12: 1 | W12: 11 | X12: 4 | Y12: 1 | Z12: 0 | AA12: 1 | AG12: =R12 -> Gangguan TM ≤ 5 Menit | AH12: =S12 -> 0 | AI12: =SUM($S12:T12) -> 2 | AJ12: =SUM($S12:U12) -> 3 | AK12: =SUM($S12:V12) -> 4 | AL12: =SUM($S12:W12) -> 15 | AM12: =SUM($S12:X12) -> 19 | AN12: =SUM($S12:Y12) -> 20 | AO12: =SUM($S12:Z12) -> 20 | AP12: =SUM($S12:AA12) -> 21 | ... AS12: =SUM($S12:AD12) -> 21
B14: ULP Bangkir | C14: Gangguan TM > 5 Menit | D14: 3 | E14: 6 | F14: 10 | G14: 13 | H14: 16 | I14: 19 | J14: 22 | K14: 26 | L14: 29 | M14: 32 | N14: 35 | O14: 36 | Q14: ULP Bangkir | R14: =C14 -> Gangguan TM > 5 Menit | S14: 0 | T14: 0 | U14: 8 | V14: 1 | W14: 2 | X14: 2 | Y14: 3 | Z14: 0 | AA14: 2 | AF14: ULP Bangkir | AG14: =R14 -> Gangguan TM > 5 Menit | AH14: =S14 -> 0 | AI14: =SUM($S14:T14) -> 0 | AJ14: =SUM($S14:U14) -> 8 | AK14: =SUM($S14:V14) -> 9 | AL14: =SUM($S14:W14) -> 11 | AM14: =SUM($S14:X14) -> 13 | AN14: =SUM($S14:Y14) -> 16 | AO14: =SUM($S14:Z14) -> 16 | AP14: =SUM($S14:AA14) -> 18 | ... AS14: =SUM($S14:AD14) -> 18
C15: Gangguan TM ≤ 5 Menit | D15: 2 | E15: 4 | F15: 5 | G15: 7 | H15: 9 | I15: 11 | J15: 13 | K15: 14 | L15: 16 | M15: 18 | N15: 20 | O15: 21 | R15: =C15 -> Gangguan TM ≤ 5 Menit | S15: 0 | T15: 4 | U15: 0 | V15: 0 | W15: 3 | X15: 2 | Y15: 2 | Z15: 0 | AA15: 1 | AG15: =R15 -> Gangguan TM ≤ 5 Menit | AH15: =S15 -> 0 | AI15: =SUM($S15:T15) -> 4 | AJ15: =SUM($S15:U15) -> 4 | AK15: =SUM($S15:V15) -> 4 | AL15: =SUM($S15:W15) -> 7 | AM15: =SUM($S15:X15) -> 9 | AN15: =SUM($S15:Y15) -> 11 | AO15: =SUM($S15:Z15) -> 11 | AP15: =SUM($S15:AA15) -> 12 | ... AS15: =SUM($S15:AD15) -> 12
B17: ULP Moutong | C17: Gangguan TM > 5 Menit | D17: 1 | E17: 2 | F17: 3 | G17: 4 | H17: 5 | I17: 6 | J17: 7 | K17: 9 | L17: 10 | M17: 11 | N17: 12 | O17: 12 | Q17: ULP Moutong | R17: =C17 -> Gangguan TM > 5 Menit | S17: 0 | T17: 1 | U17: 1 | V17: 1 | W17: 1 | X17: 1 | Y17: 2 | Z17: 0 | AA17: 0 | AF17: ULP Moutong | AG17: =R17 -> Gangguan TM > 5 Menit | AH17: =S17 -> 0 | AI17: =SUM($S17:T17) -> 1 | AJ17: =SUM($S17:U17) -> 2 | AK17: =SUM($S17:V17) -> 3 | AL17: =SUM($S17:W17) -> 4 | AM17: =SUM($S17:X17) -> 5 | AN17: =SUM($S17:Y17) -> 7 | AO17: =SUM($S17:Z17) -> 7 | AP17: =SUM($S17:AA17) -> 7 | ... AS17: =SUM($S17:AD17) -> 7
C18: Gangguan TM ≤ 5 Menit | D18: 2 | E18: 3 | F18: 5 | G18: 7 | H18: 8 | I18: 10 | J18: 12 | K18: 14 | L18: 15 | M18: 17 | N18: 19 | O18: 20 | R18: =C18 -> Gangguan TM ≤ 5 Menit | S18: 0 | T18: 2 | U18: 0 | V18: 0 | W18: 4 | X18: 1 | Y18: 3 | Z18: 1 | AA18: 1 | AG18: =R18 -> Gangguan TM ≤ 5 Menit | AH18: =S18 -> 0 | AI18: =SUM($S18:T18) -> 2 | AJ18: =SUM($S18:U18) -> 2 | AK18: =SUM($S18:V18) -> 2 | AL18: =SUM($S18:W18) -> 6 | AM18: =SUM($S18:X18) -> 7 | AN18: =SUM($S18:Y18) -> 10 | AO18: =SUM($S18:Z18) -> 11 | AP18: =SUM($S18:AA18) -> 12 | ... AS18: =SUM($S18:AD18) -> 12
B20: ULP Kotaraya | C20: Gangguan TM > 5 Menit | D20: 2 | E20: 5 | F20: 7 | G20: 9 | H20: 12 | I20: 14 | J20: 16 | K20: 19 | L20: 21 | M20: 23 | N20: 26 | O20: 26 | Q20: ULP Kotaraya | R20: =C20 -> Gangguan TM > 5 Menit | S20: 1 | T20: 0 | U20: 5 | V20: 1 | W20: 2 | X20: 2 | Y20: 0 | Z20: 0 | AA20: 0 | AF20: ULP Kotaraya | AG20: =R20 -> Gangguan TM > 5 Menit | AH20: =S20 -> 1 | AI20: =SUM($S20:T20) -> 1 | AJ20: =SUM($S20:U20) -> 6 | AK20: =SUM($S20:V20) -> 7 | AL20: =SUM($S20:W20) -> 9 | AM20: =SUM($S20:X20) -> 11 | AN20: =SUM($S20:Y20) -> 11 | AO20: =SUM($S20:Z20) -> 11 | AP20: =SUM($S20:AA20) -> 11 | ... AS20: =SUM($S20:AD20) -> 11
C21: Gangguan TM ≤ 5 Menit | D21: 2 | E21: 3 | F21: 5 | G21: 7 | H21: 8 | I21: 10 | J21: 12 | K21: 14 | L21: 15 | M21: 17 | N21: 19 | O21: 20 | R21: =C21 -> Gangguan TM ≤ 5 Menit | S21: 1 | T21: 3 | U21: 0 | V21: 0 | W21: 2 | X21: 1 | Y21: 3 | Z21: 0 | AA21: 2 | AG21: =R21 -> Gangguan TM ≤ 5 Menit | AH21: =S21 -> 1 | AI21: =SUM($S21:T21) -> 4 | AJ21: =SUM($S21:U21) -> 4 | AK21: =SUM($S21:V21) -> 4 | AL21: =SUM($S21:W21) -> 6 | AM21: =SUM($S21:X21) -> 7 | AN21: =SUM($S21:Y21) -> 10 | AO21: =SUM($S21:Z21) -> 10 | AP21: =SUM($S21:AA21) -> 12 | ... AS21: =SUM($S21:AD21) -> 12
B23: UP3 Tolitoli | C23: Gangguan TM > 5 Menit | D23: 15 | E23: 29 | F23: 45 | G23: 59 | H23: 74 | I23: 88 | J23: 103 | K23: 119 | L23: 134 | M23: 148 | N23: 163 | O23: 166 | Q23: UP3 Tolitoli | R23: =C23 -> Gangguan TM > 5 Menit | S23: =S8+S11+S14+S17+S20 -> 5 | T23: =T8+T11+T14+T17+T20 -> 5 | U23: =U8+U11+U14+U17+U20 -> 22 | V23: =V8+V11+V14+V17+V20 -> 8 | W23: =W8+W11+W14+W17+W20 -> 26 | X23: =X8+X11+X14+X17+X20 -> 7 | Y23: =Y8+Y11+Y14+Y17+Y20 -> 14 | Z23: =Z8+Z11+Z14+Z17+Z20 -> 0 | ... AD23: =AD8+AD11+AD14+AD17+AD20 -> 0 | AF23: UP3 Tolitoli | AG23: =R23 -> Gangguan TM > 5 Menit | AH23: =AH8+AH11+AH14+AH17+AH20 -> 5 | AI23: =AI8+AI11+AI14+AI17+AI20 -> 10 | AJ23: =AJ8+AJ11+AJ14+AJ17+AJ20 -> 32 | AK23: =AK8+AK11+AK14+AK17+AK20 -> 40 | AL23: =AL8+AL11+AL14+AL17+AL20 -> 66 | AM23: =AM8+AM11+AM14+AM17+AM20 -> 73 | AN23: =AN8+AN11+AN14+AN17+AN20 -> 87 | AO23: =AO8+AO11+AO14+AO17+AO20 -> 87 | ... AS23: =AS8+AS11+AS14+AS17+AS20 -> 98
C24: Gangguan TM ≤ 5 Menit | D24: 17 | E24: 31 | F24: 48 | G24: 65 | H24: 79 | I24: 96 | J24: 113 | K24: 128 | L24: 144 | M24: 161 | N24: 177 | O24: 191 | R24: =C24 -> Gangguan TM ≤ 5 Menit | S24: =S9+S12+S15+S18+S21 -> 1 | T24: =T9+T12+T15+T18+T21 -> 17 | U24: =U9+U12+U15+U18+U21 -> 3 | V24: =V9+V12+V15+V18+V21 -> 1 | W24: =W9+W12+W15+W18+W21 -> 35 | X24: =X9+X12+X15+X18+X21 -> 19 | Y24: =Y9+Y12+Y15+Y18+Y21 -> 17 | Z24: =Z9+Z12+Z15+Z18+Z21 -> 3 | ... AD24: =AD9+AD12+AD15+AD18+AD21 -> 0 | AG24: =R24 -> Gangguan TM ≤ 5 Menit | AH24: =AH9+AH12+AH15+AH18+AH21 -> 1 | AI24: =AI9+AI12+AI15+AI18+AI21 -> 18 | AJ24: =AJ9+AJ12+AJ15+AJ18+AJ21 -> 21 | AK24: =AK9+AK12+AK15+AK18+AK21 -> 22 | AL24: =AL9+AL12+AL15+AL18+AL21 -> 57 | AM24: =AM9+AM12+AM15+AM18+AM21 -> 76 | AN24: =AN9+AN12+AN15+AN18+AN21 -> 93 | AO24: =AO9+AO12+AO15+AO18+AO21 -> 96 | ... AS24: =AS9+AS12+AS15+AS18+AS21 -> 112
B28: KERUSAKAN PERALATAN DISTRIBUSI | Q28: =B28 -> KERUSAKAN PERALATAN DISTRIBUSI | AF28: =Q28 -> KERUSAKAN PERALATAN DISTRIBUSI
B29: TARGET | Q29: REALISASI BULANAN | AF29: REALIASI KOMULATIF
B30: Unit | D30: Jan | E30: Feb | F30: Mar | G30: Apr | H30: May | I30: Jun | J30: Jul | K30: Aug | L30: Sep | M30: Oct | N30: Nov | O30: Dec | Q30: Unit | S30: Jan | T30: Feb | U30: Mar | V30: Apr | W30: May | X30: Jun | Y30: Jul | Z30: Aug | AA30: Sep | AB30: Oct | AC30: Nov | AD30: Dec | AF30: Unit | AH30: Jan | AI30: Feb | AJ30: Mar | AK30: Apr | AL30: May | AM30: Jun | AN30: Jul | AO30: Aug | AP30: Sep | AQ30: Oct | AR30: Nov | AS30: Dec
B31: ULP Tolitoli | C31: Kerusakan PHB - TM | Q31: ULP Tolitoli | R31: =C31 -> Kerusakan PHB - TM | S31: 0 | T31: 0 | U31: 0 | V31: 0 | W31: 0 | X31: 0 | Y31: 1 | Z31: 0 | AA31: 0 | AF31: ULP Tolitoli | AG31: =C31 -> Kerusakan PHB - TM | AH31: =S31 -> 0 | AI31: =SUM($S31:T31) -> 0 | AJ31: =SUM($S31:U31) -> 0 | AK31: =SUM($S31:V31) -> 0 | AL31: =SUM($S31:W31) -> 0 | AM31: =SUM($S31:X31) -> 0 | AN31: =SUM($S31:Y31) -> 1 | AO31: =SUM($S31:Z31) -> 1 | AP31: =SUM($S31:AA31) -> 1 | ... AS31: =SUM($S31:AD31) -> 1
C32: Kerusakan Trafo Distribusi | R32: =C32 -> Kerusakan Trafo Distribusi | S32: 0 | T32: 0 | U32: 0 | V32: 0 | W32: 1 | X32: 1 | Y32: 0 | Z32: 0 | AA32: 0 | AG32: =C32 -> Kerusakan Trafo Distribusi | AH32: =S32 -> 0 | AI32: =SUM($S32:T32) -> 0 | AJ32: =SUM($S32:U32) -> 0 | AK32: =SUM($S32:V32) -> 0 | AL32: =SUM($S32:W32) -> 1 | AM32: =SUM($S32:X32) -> 2 | AN32: =SUM($S32:Y32) -> 2 | AO32: =SUM($S32:Z32) -> 2 | AP32: =SUM($S32:AA32) -> 2 | ... AS32: =SUM($S32:AD32) -> 2
C33: Jumlah | D33: 0 | E33: 0 | F33: 1 | G33: 1 | H33: 1 | I33: 1 | J33: 1 | K33: 1 | L33: 1 | M33: 1 | N33: 1 | O33: 1 | R33: =C33 -> Jumlah | S33: =SUM(S31:S32) -> 0 | T33: =SUM(T31:T32) -> 0 | U33: =SUM(U31:U32) -> 0 | V33: =SUM(V31:V32) -> 0 | W33: =SUM(W31:W32) -> 1 | X33: =SUM(X31:X32) -> 1 | Y33: =SUM(Y31:Y32) -> 1 | Z33: =SUM(Z31:Z32) -> 0 | ... AD33: =SUM(AD31:AD32) -> 0 | AG33: =C33 -> Jumlah | AH33: =SUM(AH31:AH32) -> 0 | AI33: =SUM(AI31:AI32) -> 0 | AJ33: =SUM(AJ31:AJ32) -> 0 | AK33: =SUM(AK31:AK32) -> 0 | AL33: =SUM(AL31:AL32) -> 1 | AM33: =SUM(AM31:AM32) -> 2 | AN33: =SUM(AN31:AN32) -> 3 | AO33: =SUM(AO31:AO32) -> 3 | ... AS33: =SUM(AS31:AS32) -> 3
B34: ULP Leok | C34: Kerusakan PHB - TM | Q34: ULP Leok | R34: =C34 -> Kerusakan PHB - TM | S34: 0 | T34: 0 | U34: 0 | V34: 0 | W34: 0 | X34: 0 | Y34: 0 | Z34: 0 | AA34: 0 | AF34: ULP Leok | AG34: =C34 -> Kerusakan PHB - TM | AH34: =S34 -> 0 | AI34: =SUM($S34:T34) -> 0 | AJ34: =SUM($S34:U34) -> 0 | AK34: =SUM($S34:V34) -> 0 | AL34: =SUM($S34:W34) -> 0 | AM34: =SUM($S34:X34) -> 0 | AN34: =SUM($S34:Y34) -> 0 | AO34: =SUM($S34:Z34) -> 0 | AP34: =SUM($S34:AA34) -> 0 | ... AS34: =SUM($S34:AD34) -> 0
C35: Kerusakan Trafo Distribusi | R35: =C35 -> Kerusakan Trafo Distribusi | S35: 0 | T35: 0 | U35: 0 | V35: 0 | W35: 0 | X35: 0 | Y35: 0 | Z35: 0 | AA35: 0 | AG35: =C35 -> Kerusakan Trafo Distribusi | AH35: =S35 -> 0 | AI35: =SUM($S35:T35) -> 0 | AJ35: =SUM($S35:U35) -> 0 | AK35: =SUM($S35:V35) -> 0 | AL35: =SUM($S35:W35) -> 0 | AM35: =SUM($S35:X35) -> 0 | AN35: =SUM($S35:Y35) -> 0 | AO35: =SUM($S35:Z35) -> 0 | AP35: =SUM($S35:AA35) -> 0 | ... AS35: =SUM($S35:AD35) -> 0
C36: Jumlah | D36: 0 | E36: 0 | F36: 1 | G36: 1 | H36: 1 | I36: 1 | J36: 1 | K36: 1 | L36: 1 | M36: 1 | N36: 1 | O36: 1 | R36: =C36 -> Jumlah | S36: =SUM(S34:S35) -> 0 | T36: =SUM(T34:T35) -> 0 | U36: =SUM(U34:U35) -> 0 | V36: =SUM(V34:V35) -> 0 | W36: =SUM(W34:W35) -> 0 | X36: =SUM(X34:X35) -> 0 | Y36: =SUM(Y34:Y35) -> 0 | Z36: =SUM(Z34:Z35) -> 0 | ... AD36: =SUM(AD34:AD35) -> 0 | AG36: =C36 -> Jumlah | AH36: =SUM(AH34:AH35) -> 0 | AI36: =SUM(AI34:AI35) -> 0 | AJ36: =SUM(AJ34:AJ35) -> 0 | AK36: =SUM(AK34:AK35) -> 0 | AL36: =SUM(AL34:AL35) -> 0 | AM36: =SUM(AM34:AM35) -> 0 | AN36: =SUM(AN34:AN35) -> 0 | AO36: =SUM(AO34:AO35) -> 0 | ... AS36: =SUM(AS34:AS35) -> 0
B37: ULP Bangkir | C37: Kerusakan PHB - TM | Q37: ULP Bangkir | R37: =C37 -> Kerusakan PHB - TM | S37: 0 | T37: 0 | U37: 0 | V37: 0 | W37: 0 | X37: 0 | Y37: 0 | Z37: 0 | AA37: 0 | AF37: ULP Bangkir | AG37: =C37 -> Kerusakan PHB - TM | AH37: =S37 -> 0 | AI37: =SUM($S37:T37) -> 0 | AJ37: =SUM($S37:U37) -> 0 | AK37: =SUM($S37:V37) -> 0 | AL37: =SUM($S37:W37) -> 0 | AM37: =SUM($S37:X37) -> 0 | AN37: =SUM($S37:Y37) -> 0 | AO37: =SUM($S37:Z37) -> 0 | AP37: =SUM($S37:AA37) -> 0 | ... AS37: =SUM($S37:AD37) -> 0
C38: Kerusakan Trafo Distribusi | R38: =C38 -> Kerusakan Trafo Distribusi | S38: 0 | T38: 0 | U38: 0 | V38: 0 | W38: 0 | X38: 0 | Y38: 0 | Z38: 0 | AA38: 0 | AG38: =C38 -> Kerusakan Trafo Distribusi | AH38: =S38 -> 0 | AI38: =SUM($S38:T38) -> 0 | AJ38: =SUM($S38:U38) -> 0 | AK38: =SUM($S38:V38) -> 0 | AL38: =SUM($S38:W38) -> 0 | AM38: =SUM($S38:X38) -> 0 | AN38: =SUM($S38:Y38) -> 0 | AO38: =SUM($S38:Z38) -> 0 | AP38: =SUM($S38:AA38) -> 0 | ... AS38: =SUM($S38:AD38) -> 0
C39: Jumlah | D39: 0 | E39: 0 | F39: 1 | G39: 1 | H39: 1 | I39: 1 | J39: 1 | K39: 1 | L39: 1 | M39: 1 | N39: 1 | O39: 1 | R39: =C39 -> Jumlah | S39: =SUM(S37:S38) -> 0 | T39: =SUM(T37:T38) -> 0 | U39: =SUM(U37:U38) -> 0 | V39: =SUM(V37:V38) -> 0 | W39: =SUM(W37:W38) -> 0 | X39: =SUM(X37:X38) -> 0 | Y39: =SUM(Y37:Y38) -> 0 | Z39: =SUM(Z37:Z38) -> 0 | ... AD39: =SUM(AD37:AD38) -> 0 | AG39: =C39 -> Jumlah | AH39: =SUM(AH37:AH38) -> 0 | AI39: =SUM(AI37:AI38) -> 0 | AJ39: =SUM(AJ37:AJ38) -> 0 | AK39: =SUM(AK37:AK38) -> 0 | AL39: =SUM(AL37:AL38) -> 0 | AM39: =SUM(AM37:AM38) -> 0 | AN39: =SUM(AN37:AN38) -> 0 | AO39: =SUM(AO37:AO38) -> 0 | ... AS39: =SUM(AS37:AS38) -> 0
B40: ULP Moutong | C40: Kerusakan PHB - TM | Q40: ULP Moutong | R40: =C40 -> Kerusakan PHB - TM | S40: 0 | T40: 0 | U40: 0 | V40: 0 | W40: 0 | X40: 0 | Y40: 0 | Z40: 0 | AA40: 0 | AF40: ULP Moutong | AG40: =C40 -> Kerusakan PHB - TM | AH40: =S40 -> 0 | AI40: =SUM($S40:T40) -> 0 | AJ40: =SUM($S40:U40) -> 0 | AK40: =SUM($S40:V40) -> 0 | AL40: =SUM($S40:W40) -> 0 | AM40: =SUM($S40:X40) -> 0 | AN40: =SUM($S40:Y40) -> 0 | AO40: =SUM($S40:Z40) -> 0 | AP40: =SUM($S40:AA40) -> 0 | ... AS40: =SUM($S40:AD40) -> 0
C41: Kerusakan Trafo Distribusi | R41: =C41 -> Kerusakan Trafo Distribusi | S41: 0 | T41: 0 | U41: 0 | V41: 0 | W41: 0 | X41: 0 | Y41: 0 | Z41: 0 | AA41: 0 | AG41: =C41 -> Kerusakan Trafo Distribusi | AH41: =S41 -> 0 | AI41: =SUM($S41:T41) -> 0 | AJ41: =SUM($S41:U41) -> 0 | AK41: =SUM($S41:V41) -> 0 | AL41: =SUM($S41:W41) -> 0 | AM41: =SUM($S41:X41) -> 0 | AN41: =SUM($S41:Y41) -> 0 | AO41: =SUM($S41:Z41) -> 0 | AP41: =SUM($S41:AA41) -> 0 | ... AS41: =SUM($S41:AD41) -> 0
C42: Jumlah | D42: 0 | E42: 0 | F42: 0 | G42: 0 | H42: 0 | I42: 1 | J42: 1 | K42: 1 | L42: 1 | M42: 1 | N42: 1 | O42: 1 | R42: =C42 -> Jumlah | S42: =SUM(S40:S41) -> 0 | T42: =SUM(T40:T41) -> 0 | U42: =SUM(U40:U41) -> 0 | V42: =SUM(V40:V41) -> 0 | W42: =SUM(W40:W41) -> 0 | X42: =SUM(X40:X41) -> 0 | Y42: =SUM(Y40:Y41) -> 0 | Z42: =SUM(Z40:Z41) -> 0 | ... AD42: =SUM(AD40:AD41) -> 0 | AG42: =C42 -> Jumlah | AH42: =SUM(AH40:AH41) -> 0 | AI42: =SUM(AI40:AI41) -> 0 | AJ42: =SUM(AJ40:AJ41) -> 0 | AK42: =SUM(AK40:AK41) -> 0 | AL42: =SUM(AL40:AL41) -> 0 | AM42: =SUM(AM40:AM41) -> 0 | AN42: =SUM(AN40:AN41) -> 0 | AO42: =SUM(AO40:AO41) -> 0 | ... AS42: =SUM(AS40:AS41) -> 0
B43: ULP Kotaraya | C43: Kerusakan PHB - TM | Q43: ULP Kotaraya | R43: =C43 -> Kerusakan PHB - TM | S43: 0 | T43: 0 | U43: 0 | V43: 0 | W43: 0 | X43: 0 | Y43: 0 | Z43: 0 | AA43: 0 | AF43: ULP Kotaraya | AG43: =C43 -> Kerusakan PHB - TM | AH43: =S43 -> 0 | AI43: =SUM($S43:T43) -> 0 | AJ43: =SUM($S43:U43) -> 0 | AK43: =SUM($S43:V43) -> 0 | AL43: =SUM($S43:W43) -> 0 | AM43: =SUM($S43:X43) -> 0 | AN43: =SUM($S43:Y43) -> 0 | AO43: =SUM($S43:Z43) -> 0 | AP43: =SUM($S43:AA43) -> 0 | ... AS43: =SUM($S43:AD43) -> 0
C44: Kerusakan Trafo Distribusi | R44: =C44 -> Kerusakan Trafo Distribusi | S44: 0 | T44: 0 | U44: 0 | V44: 0 | W44: 0 | X44: 0 | Y44: 0 | Z44: 0 | AA44: 0 | AG44: =C44 -> Kerusakan Trafo Distribusi | AH44: =S44 -> 0 | AI44: =SUM($S44:T44) -> 0 | AJ44: =SUM($S44:U44) -> 0 | AK44: =SUM($S44:V44) -> 0 | AL44: =SUM($S44:W44) -> 0 | AM44: =SUM($S44:X44) -> 0 | AN44: =SUM($S44:Y44) -> 0 | AO44: =SUM($S44:Z44) -> 0 | AP44: =SUM($S44:AA44) -> 0 | ... AS44: =SUM($S44:AD44) -> 0
C45: Jumlah | D45: 0 | E45: 0 | F45: 1 | G45: 1 | H45: 1 | I45: 1 | J45: 1 | K45: 1 | L45: 1 | M45: 1 | N45: 1 | O45: 1 | R45: =C45 -> Jumlah | S45: =SUM(S43:S44) -> 0 | T45: =SUM(T43:T44) -> 0 | U45: =SUM(U43:U44) -> 0 | V45: =SUM(V43:V44) -> 0 | W45: =SUM(W43:W44) -> 0 | X45: =SUM(X43:X44) -> 0 | Y45: =SUM(Y43:Y44) -> 0 | Z45: =SUM(Z43:Z44) -> 0 | ... AD45: =SUM(AD43:AD44) -> 0 | AG45: =C45 -> Jumlah | AH45: =SUM(AH43:AH44) -> 0 | AI45: =SUM(AI43:AI44) -> 0 | AJ45: =SUM(AJ43:AJ44) -> 0 | AK45: =SUM(AK43:AK44) -> 0 | AL45: =SUM(AL43:AL44) -> 0 | AM45: =SUM(AM43:AM44) -> 0 | AN45: =SUM(AN43:AN44) -> 0 | AO45: =SUM(AO43:AO44) -> 0 | ... AS45: =SUM(AS43:AS44) -> 0
B46: UP3 Tolitoli | C46: Kerusakan PHB - TM | Q46: ULP Kotaraya | R46: =C46 -> Kerusakan PHB - TM | S46: =S31+S34+S37+S40+S43 -> 0 | T46: =T31+T34+T37+T40+T43 -> 0 | U46: =U31+U34+U37+U40+U43 -> 0 | V46: =V31+V34+V37+V40+V43 -> 0 | W46: =W31+W34+W37+W40+W43 -> 0 | X46: =X31+X34+X37+X40+X43 -> 0 | Y46: =Y31+Y34+Y37+Y40+Y43 -> 1 | Z46: 0 | AA46: 0 | AF46: ULP Kotaraya | AG46: =C46 -> Kerusakan PHB - TM | AH46: =S46 -> 0 | AI46: =SUM($S46:T46) -> 0 | AJ46: =SUM($S46:U46) -> 0 | AK46: =SUM($S46:V46) -> 0 | AL46: =SUM($S46:W46) -> 0 | AM46: =SUM($S46:X46) -> 0 | AN46: =SUM($S46:Y46) -> 1 | AO46: =SUM($S46:Z46) -> 1 | AP46: =SUM($S46:AA46) -> 1 | ... AS46: =SUM($S46:AD46) -> 1
C47: Kerusakan Trafo Distribusi | R47: =C47 -> Kerusakan Trafo Distribusi | S47: =S32+S35+S38+S41+S44 -> 0 | T47: =T32+T35+T38+T41+T44 -> 0 | U47: =U32+U35+U38+U41+U44 -> 0 | V47: =V32+V35+V38+V41+V44 -> 0 | W47: =W32+W35+W38+W41+W44 -> 1 | X47: =X32+X35+X38+X41+X44 -> 1 | Y47: =Y32+Y35+Y38+Y41+Y44 -> 0 | Z47: 0 | AA47: 0 | AG47: =C47 -> Kerusakan Trafo Distribusi | AH47: =S47 -> 0 | AI47: =SUM($S47:T47) -> 0 | AJ47: =SUM($S47:U47) -> 0 | AK47: =SUM($S47:V47) -> 0 | AL47: =SUM($S47:W47) -> 1 | AM47: =SUM($S47:X47) -> 2 | AN47: =SUM($S47:Y47) -> 2 | AO47: =SUM($S47:Z47) -> 2 | AP47: =SUM($S47:AA47) -> 2 | ... AS47: =SUM($S47:AD47) -> 2
C48: Jumlah | D48: 0 | E48: 0 | F48: 5 | G48: 5 | H48: 5 | I48: 5 | J48: 5 | K48: 5 | L48: 5 | M48: 5 | N48: 5 | O48: 5 | R48: =C48 -> Jumlah | S48: =SUM(S46:S47) -> 0 | T48: =SUM(T46:T47) -> 0 | U48: =SUM(U46:U47) -> 0 | V48: =SUM(V46:V47) -> 0 | W48: =SUM(W46:W47) -> 1 | X48: =SUM(X46:X47) -> 1 | Y48: =SUM(Y46:Y47) -> 1 | Z48: =SUM(Z46:Z47) -> 0 | ... AD48: =SUM(AD46:AD47) -> 0 | AG48: =C48 -> Jumlah | AH48: =SUM(AH46:AH47) -> 0 | AI48: =SUM(AI46:AI47) -> 0 | AJ48: =SUM(AJ46:AJ47) -> 0 | AK48: =SUM(AK46:AK47) -> 0 | AL48: =SUM(AL46:AL47) -> 1 | AM48: =SUM(AM46:AM47) -> 2 | AN48: =SUM(AN46:AN47) -> 3 | AO48: =SUM(AO46:AO47) -> 3 | ... AS48: =SUM(AS46:AS47) -> 3
A50: 4 | B50: PENURUNAN FEEDBACK RATING NEGATIF PADA PLN MOBILE - GANGGUAN | Q50: =$B$50 -> PENURUNAN FEEDBACK RATING NEGATIF PADA PLN MOBILE - GANGGUAN | AF50: =$B$50 -> PENURUNAN FEEDBACK RATING NEGATIF PADA PLN MOBILE - GANGGUAN
B51: TARGET | Q51: REALISASI BULANAN | AF51: REALISASI KOMULATIF
B52: Unit | D52: Jan | E52: Feb | F52: Mar | G52: Apr | H52: May | I52: Jun | J52: Jul | K52: Aug | L52: Sep | M52: Oct | N52: Nov | O52: Dec | Q52: Unit | S52: Jan | T52: Feb | U52: Mar | V52: Apr | W52: May | X52: Jun | Y52: Jul | Z52: Aug | AA52: Sep | AB52: Oct | AC52: Nov | AD52: Dec | AF52: Unit | AH52: Jan | AI52: Feb | AJ52: Mar | AK52: Apr | AL52: May | AM52: Jun | AN52: Jul | AO52: Aug | AP52: Sep | AQ52: Oct | AR52: Nov | AS52: Dec
B53: ULP Tolitoli | C53: Total WO Gangguan | Q53: ULP Tolitoli | R53: Total WO Gangguan | S53: 341 | T53: 292 | U53: 397 | V53: 339 | W53: 317 | X53: 299 | Y53: 390 | Z53: 320 | AA53: 300 | AF53: ULP Tolitoli | AG53: Total WO Gangguan | AH53: =S53 -> 341 | AI53: =SUM($S53:T$53) -> 633 | AJ53: =SUM($S53:U$53) -> 1030 | AK53: =SUM($S53:V$53) -> 1369 | AL53: =SUM($S53:W$53) -> 1686 | AM53: =SUM($S53:X$53) -> 1985 | AN53: =SUM($S53:Y$53) -> 2375 | AO53: =SUM($S53:Z$53) -> 2695 | AP53: =SUM($S53:AA$53) -> 2995 | ... AS53: =SUM($S53:AD$53) -> 2995
C54: Rating Negatif Gangguan | R54: Rating Negatif Gangguan | S54: 0 | T54: 0 | U54: 0 | V54: 0 | W54: 0 | X54: 0 | Y54: 0 | Z54: 0 | AA54: 0 | AG54: Rating Negatif Gangguan | AH54: =S54 -> 0 | AI54: =SUM($S54:T$54) -> 0 | AJ54: =SUM($S54:U$54) -> 0 | AK54: =SUM($S54:V$54) -> 0 | AL54: =SUM($S54:W$54) -> 0 | AM54: =SUM($S54:X$54) -> 0 | AN54: =SUM($S54:Y$54) -> 0 | AO54: =SUM($S54:Z$54) -> 0 | AP54: =SUM($S54:AA$54) -> 0 | ... AS54: =SUM($S54:AD$54) -> 0
C55: Feedback Rating Negatif | D55: 0.09 | E55: 0.09 | F55: 0.09 | G55: 0.09 | H55: 0.09 | I55: 0.09 | J55: 0.09 | K55: 0.09 | L55: 0.09 | M55: 0.09 | N55: 0.09 | O55: 0.09 | R55: Feedback Rating Negatif | S55: =S54/S53*100 -> 0 | T55: =T54/T53*100 -> 0 | U55: =U54/U53*100 -> 0 | V55: =V54/V53*100 -> 0 | W55: =W54/W53*100 -> 0 | X55: =X54/X53*100 -> 0 | Y55: =Y54/Y53*100 -> 0 | Z55: =Z54/Z53*100 -> 0 | ... AD55: =AD54/AD53*100 -> #DIV/0! | AG55: Feedback Rating Negatif | AH55: =AH54/AH53*100 -> 0 | AI55: =AI54/AI53*100 -> 0 | AJ55: =AJ54/AJ53*100 -> 0 | AK55: =AK54/AK53*100 -> 0 | AL55: =AL54/AL53*100 -> 0 | AM55: =AM54/AM53*100 -> 0 | AN55: =AN54/AN53*100 -> 0 | AO55: =AO54/AO53*100 -> 0 | ... AS55: =AS54/AS53*100 -> 0
B56: ULP Leok | C56: Total WO Gangguan | Q56: ULP Leok | R56: Total WO Gangguan | S56: 466 | T56: 413 | U56: 389 | V56: 322 | W56: 319 | X56: 261 | Y56: 351 | Z56: 422 | AA56: 489 | AF56: ULP Leok | AG56: Total WO Gangguan | AH56: =S56 -> 466 | AI56: =SUM($S$56:T56) -> 879 | AJ56: =SUM($S$56:U56) -> 1268 | AK56: =SUM($S$56:V56) -> 1590 | AL56: =SUM($S$56:W56) -> 1909 | AM56: =SUM($S$56:X56) -> 2170 | AN56: =SUM($S$56:Y56) -> 2521 | AO56: =SUM($S$56:Z56) -> 2943 | AP56: =SUM($S$56:AA56) -> 3432 | ... AS56: =SUM($S$56:AD56) -> 3432
C57: Rating Negatif Gangguan | R57: Rating Negatif Gangguan | S57: 0 | T57: 0 | U57: 0 | V57: 0 | W57: 0 | X57: 0 | Y57: 0 | Z57: 0 | AA57: 0 | AG57: Rating Negatif Gangguan | AH57: =S57 -> 0 | AI57: =SUM($S$57:T57) -> 0 | AJ57: =SUM($S$57:U57) -> 0 | AK57: =SUM($S$57:V57) -> 0 | AL57: =SUM($S$57:W57) -> 0 | AM57: =SUM($S$57:X57) -> 0 | AN57: =SUM($S$57:Y57) -> 0 | AO57: =SUM($S$57:Z57) -> 0 | AP57: =SUM($S$57:AA57) -> 0 | ... AS57: =SUM($S$57:AD57) -> 0
C58: Feedback Rating Negatif | D58: 0.09 | E58: 0.09 | F58: 0.09 | G58: 0.09 | H58: 0.09 | I58: 0.09 | J58: 0.09 | K58: 0.09 | L58: 0.09 | M58: 0.09 | N58: 0.09 | O58: 0.09 | R58: Feedback Rating Negatif | S58: =S57/S56*100 -> 0 | T58: =T57/T56*100 -> 0 | U58: =U57/U56*100 -> 0 | V58: =V57/V56*100 -> 0 | W58: =W57/W56*100 -> 0 | X58: =X57/X56*100 -> 0 | Y58: =Y57/Y56*100 -> 0 | Z58: =Z57/Z56*100 -> 0 | ... AD58: =AD57/AD56*100 -> #DIV/0! | AG58: Feedback Rating Negatif | AH58: =AH57/AH56*100 -> 0 | AI58: =AI57/AI56*100 -> 0 | AJ58: =AJ57/AJ56*100 -> 0 | AK58: =AK57/AK56*100 -> 0 | AL58: =AL57/AL56*100 -> 0 | AM58: =AM57/AM56*100 -> 0 | AN58: =AN57/AN56*100 -> 0 | AO58: =AO57/AO56*100 -> 0 | ... AS58: =AS57/AS56*100 -> 0
B59: ULP Bangkir | C59: Total WO Gangguan | Q59: ULP Bangkir | R59: Total WO Gangguan | S59: 351 | T59: 334 | U59: 431 | V59: 335 | W59: 299 | X59: 269 | Y59: 308 | Z59: 322 | AA59: 290 | AF59: ULP Bangkir | AG59: Total WO Gangguan | AH59: =S59 -> 351 | AI59: =SUM($S$59:T59) -> 685 | AJ59: =SUM($S$59:U59) -> 1116 | AK59: =SUM($S$59:V59) -> 1451 | AL59: =SUM($S$59:W59) -> 1750 | AM59: =SUM($S$59:X59) -> 2019 | AN59: =SUM($S$59:Y59) -> 2327 | AO59: =SUM($S$59:Z59) -> 2649 | AP59: =SUM($S$59:AA59) -> 2939 | ... AS59: =SUM($S$59:AD59) -> 2939
C60: Rating Negatif Gangguan | R60: Rating Negatif Gangguan | S60: 0 | T60: 0 | U60: 0 | V60: 0 | W60: 0 | X60: 0 | Y60: 0 | Z60: 0 | AA60: 0 | AG60: Rating Negatif Gangguan | AH60: =S60 -> 0 | AI60: =SUM($S$60:T60) -> 0 | AJ60: =SUM($S$60:U60) -> 0 | AK60: =SUM($S$60:V60) -> 0 | AL60: =SUM($S$60:W60) -> 0 | AM60: =SUM($S$60:X60) -> 0 | AN60: =SUM($S$60:Y60) -> 0 | AO60: =SUM($S$60:Z60) -> 0 | AP60: =SUM($S$60:AA60) -> 0 | ... AS60: =SUM($S$60:AD60) -> 0
C61: Feedback Rating Negatif | D61: 0.09 | E61: 0.09 | F61: 0.09 | G61: 0.09 | H61: 0.09 | I61: 0.09 | J61: 0.09 | K61: 0.09 | L61: 0.09 | M61: 0.09 | N61: 0.09 | O61: 0.09 | R61: Feedback Rating Negatif | S61: =S60/S59*100 -> 0 | T61: =T60/T59*100 -> 0 | U61: =U60/U59*100 -> 0 | V61: =V60/V59*100 -> 0 | W61: =W60/W59*100 -> 0 | X61: =X60/X59*100 -> 0 | Y61: =Y60/Y59*100 -> 0 | Z61: =Z60/Z59*100 -> 0 | ... AD61: =AD60/AD59*100 -> #DIV/0! | AG61: Feedback Rating Negatif | AH61: =AH60/AH59*100 -> 0 | AI61: =AI60/AI59*100 -> 0 | AJ61: =AJ60/AJ59*100 -> 0 | AK61: =AK60/AK59*100 -> 0 | AL61: =AL60/AL59*100 -> 0 | AM61: =AM60/AM59*100 -> 0 | AN61: =AN60/AN59*100 -> 0 | AO61: =AO60/AO59*100 -> 0 | ... AS61: =AS60/AS59*100 -> 0
B62: ULP Moutong | C62: Total WO Gangguan | Q62: ULP Moutong | R62: Total WO Gangguan | S62: 209 | T62: 341 | U62: 351 | V62: 249 | W62: 213 | X62: 224 | Y62: 220 | Z62: 218 | AA62: 200 | AF62: ULP Moutong | AG62: Total WO Gangguan | AH62: =S62 -> 209 | AI62: =SUM($S$62:T62) -> 550 | AJ62: =SUM($S$62:U62) -> 901 | AK62: =SUM($S$62:V62) -> 1150 | AL62: =SUM($S$62:W62) -> 1363 | AM62: =SUM($S$62:X62) -> 1587 | AN62: =SUM($S$62:Y62) -> 1807 | AO62: =SUM($S$62:Z62) -> 2025 | AP62: =SUM($S$62:AA62) -> 2225 | ... AS62: =SUM($S$62:AD62) -> 2225
C63: Rating Negatif Gangguan | R63: Rating Negatif Gangguan | S63: 0 | T63: 0 | U63: 0 | V63: 0 | W63: 0 | X63: 0 | Y63: 0 | Z63: 0 | AA63: 0 | AG63: Rating Negatif Gangguan | AH63: =S63 -> 0 | AI63: =SUM($S$63:T63) -> 0 | AJ63: =SUM($S$63:U63) -> 0 | AK63: =SUM($S$63:V63) -> 0 | AL63: =SUM($S$63:W63) -> 0 | AM63: =SUM($S$63:X63) -> 0 | AN63: =SUM($S$63:Y63) -> 0 | AO63: =SUM($S$63:Z63) -> 0 | AP63: =SUM($S$63:AA63) -> 0 | ... AS63: =SUM($S$63:AD63) -> 0
C64: Feedback Rating Negatif | D64: 0.09 | E64: 0.09 | F64: 0.09 | G64: 0.09 | H64: 0.09 | I64: 0.09 | J64: 0.09 | K64: 0.09 | L64: 0.09 | M64: 0.09 | N64: 0.09 | O64: 0.09 | R64: Feedback Rating Negatif | S64: =S63/S62*100 -> 0 | T64: =T63/T62*100 -> 0 | U64: =U63/U62*100 -> 0 | V64: =V63/V62*100 -> 0 | W64: =W63/W62*100 -> 0 | X64: =X63/X62*100 -> 0 | Y64: =Y63/Y62*100 -> 0 | Z64: =Z63/Z62*100 -> 0 | ... AD64: =AD63/AD62*100 -> #DIV/0! | AG64: Feedback Rating Negatif | AH64: =AH63/AH62*100 -> 0 | AI64: =AI63/AI62*100 -> 0 | AJ64: =AJ63/AJ62*100 -> 0 | AK64: =AK63/AK62*100 -> 0 | AL64: =AL63/AL62*100 -> 0 | AM64: =AM63/AM62*100 -> 0 | AN64: =AN63/AN62*100 -> 0 | AO64: =AO63/AO62*100 -> 0 | ... AS64: =AS63/AS62*100 -> 0
B65: ULP Kotaraya | C65: Total WO Gangguan | Q65: ULP Kotaraya | R65: Total WO Gangguan | S65: 947 | T65: 887 | U65: 975 | V65: 975 | W65: 892 | X65: 874 | Y65: 832 | Z65: 874 | AA65: 123 | AF65: ULP Kotaraya | AG65: Total WO Gangguan | AH65: =S65 -> 947 | AI65: =SUM($S$65:T65) -> 1834 | AJ65: =SUM($S$65:U65) -> 2809 | AK65: =SUM($S$65:V65) -> 3784 | AL65: =SUM($S$65:W65) -> 4676 | AM65: =SUM($S$65:X65) -> 5550 | AN65: =SUM($S$65:Y65) -> 6382 | AO65: =SUM($S$65:Z65) -> 7256 | AP65: =SUM($S$65:AA65) -> 7379 | ... AS65: =SUM($S$65:AD65) -> 7379
C66: Rating Negatif Gangguan | R66: Rating Negatif Gangguan | S66: 0 | T66: 0 | U66: 0 | V66: 0 | W66: 0 | X66: 0 | Y66: 0 | Z66: 0 | AA66: 0 | AG66: Rating Negatif Gangguan | AH66: =S66 -> 0 | AI66: =SUM($S$66:T66) -> 0 | AJ66: =SUM($S$66:U66) -> 0 | AK66: =SUM($S$66:V66) -> 0 | AL66: =SUM($S$66:W66) -> 0 | AM66: =SUM($S$66:X66) -> 0 | AN66: =SUM($S$66:Y66) -> 0 | AO66: =SUM($S$66:Z66) -> 0 | AP66: =SUM($S$66:AA66) -> 0 | ... AS66: =SUM($S$66:AD66) -> 0
C67: Feedback Rating Negatif | D67: 0.09 | E67: 0.09 | F67: 0.09 | G67: 0.09 | H67: 0.09 | I67: 0.09 | J67: 0.09 | K67: 0.09 | L67: 0.09 | M67: 0.09 | N67: 0.09 | O67: 0.09 | R67: Feedback Rating Negatif | S67: =S66/S65*100 -> 0 | T67: =T66/T65*100 -> 0 | U67: =U66/U65*100 -> 0 | V67: =V66/V65*100 -> 0 | W67: =W66/W65*100 -> 0 | X67: =X66/X65*100 -> 0 | Y67: =Y66/Y65*100 -> 0 | Z67: =Z66/Z65*100 -> 0 | ... AD67: =AD66/AD65*100 -> #DIV/0! | AG67: Feedback Rating Negatif | AH67: =AH66/AH65*100 -> 0 | AI67: =AI66/AI65*100 -> 0 | AJ67: =AJ66/AJ65*100 -> 0 | AK67: =AK66/AK65*100 -> 0 | AL67: =AL66/AL65*100 -> 0 | AM67: =AM66/AM65*100 -> 0 | AN67: =AN66/AN65*100 -> 0 | AO67: =AO66/AO65*100 -> 0 | ... AS67: =AS66/AS65*100 -> 0
B68: UP3 Tolitoli | C68: Total WO Gangguan | Q68: UP3 Tolitoli | R68: Total WO Gangguan | S68: =S65+S62+S59+S56+S53 -> 2314 | T68: =T65+T62+T59+T56+T53 -> 2267 | U68: =U65+U62+U59+U56+U53 -> 2543 | V68: =V65+V62+V59+V56+V53 -> 2220 | W68: =W65+W62+W59+W56+W53 -> 2040 | X68: =X65+X62+X59+X56+X53 -> 1927 | Y68: =Y65+Y62+Y59+Y56+Y53 -> 2101 | Z68: =Z65+Z62+Z59+Z56+Z53 -> 2156 | ... AD68: =AD65+AD62+AD59+AD56+AD53 -> 0 | AF68: UP3 Tolitoli | AG68: Total WO Gangguan | AH68: =S68 -> 2314 | AI68: =SUM($S$68:T68) -> 4581 | AJ68: =SUM($S$68:U68) -> 7124 | AK68: =SUM($S$68:V68) -> 9344 | AL68: =SUM($S$68:W68) -> 11384 | AM68: =SUM($S$68:X68) -> 13311 | AN68: =SUM($S$68:Y68) -> 15412 | AO68: =SUM($S$68:Z68) -> 17568 | AP68: =SUM($S$68:AA68) -> 18970 | ... AS68: =SUM($S$68:AD68) -> 18970
C69: Rating Negatif Gangguan | R69: Rating Negatif Gangguan | S69: =S66+S63+S60+S57+S54 -> 0 | T69: =T66+T63+T60+T57+T54 -> 0 | U69: =U66+U63+U60+U57+U54 -> 0 | V69: =V66+V63+V60+V57+V54 -> 0 | W69: =W66+W63+W60+W57+W54 -> 0 | X69: =X66+X63+X60+X57+X54 -> 0 | Y69: =Y66+Y63+Y60+Y57+Y54 -> 0 | Z69: =Z66+Z63+Z60+Z57+Z54 -> 0 | ... AD69: =AD66+AD63+AD60+AD57+AD54 -> 0 | AG69: Rating Negatif Gangguan | AH69: =S69 -> 0 | AI69: =SUM($S$69:T69) -> 0 | AJ69: =SUM($S$69:U69) -> 0 | AK69: =SUM($S$69:V69) -> 0 | AL69: =SUM($S$69:W69) -> 0 | AM69: =SUM($S$69:X69) -> 0 | AN69: =SUM($S$69:Y69) -> 0 | AO69: =SUM($S$69:Z69) -> 0 | AP69: =SUM($S$69:AA69) -> 0 | ... AS69: =SUM($S$69:AD69) -> 0
C70: Feedback Rating Negatif | D70: 0.09 | E70: 0.09 | F70: 0.09 | G70: 0.09 | H70: 0.09 | I70: 0.09 | J70: 0.09 | K70: 0.09 | L70: 0.09 | M70: 0.09 | N70: 0.09 | O70: 0.09 | R70: Feedback Rating Negatif | S70: =S69/S68*100 -> 0 | T70: =T69/T68*100 -> 0 | U70: =U69/U68*100 -> 0 | V70: =V69/V68*100 -> 0 | W70: =W69/W68*100 -> 0 | X70: =X69/X68*100 -> 0 | Y70: =Y69/Y68*100 -> 0 | Z70: =Z69/Z68*100 -> 0 | ... AD70: =AD69/AD68*100 -> #DIV/0! | AG70: Feedback Rating Negatif | AH70: =AH69/AH68*100 -> 0 | AI70: =AI69/AI68*100 -> 0 | AJ70: =AJ69/AJ68*100 -> 0 | AK70: =AK69/AK68*100 -> 0 | AL70: =AL69/AL68*100 -> 0 | AM70: =AM69/AM68*100 -> 0 | AN70: =AN69/AN68*100 -> 0 | AO70: =AO69/AO68*100 -> 0 | ... AS70: =AS69/AS68*100 -> 0
B72: PENURUNAN PENGADUAN GANGGUAN BERULANG PADA PLN MOBILE | Q72: =$B$72 -> PENURUNAN PENGADUAN GANGGUAN BERULANG PADA PLN MOBILE | AF72: =Q72 -> PENURUNAN PENGADUAN GANGGUAN BERULANG PADA PLN MOBILE | AJ72: =IF(B2="", "", SUM($B$2:B2)) -> 0
B73: TARGET | Q73: REALISASI BULANAN | AF73: REALIASI KOMULATIF
B74: Unit | D74: Jan | E74: Feb | F74: Mar | G74: Apr | H74: May | I74: Jun | J74: Jul | K74: Aug | L74: Sep | M74: Oct | N74: Nov | O74: Dec | Q74: Unit | S74: Jan | T74: Feb | U74: Mar | V74: Apr | W74: May | X74: Jun | Y74: Jul | Z74: Aug | AA74: Sep | AB74: Oct | AC74: Nov | AD74: Dec | AF74: Unit | AH74: Jan | AI74: Feb | AJ74: Mar | AK74: Apr | AL74: May | AM74: Jun | AN74: Jul | AO74: Aug | AP74: Sep | AQ74: Oct | AR74: Nov | AS74: Dec
B75: ULP Tolitoli | C75: Total WO Gangguan | Q75: ULP Tolitoli | R75: Total WO Gangguan | S75: =S53 -> 341 | T75: =T53 -> 292 | U75: =U53 -> 397 | V75: =V53 -> 339 | W75: =W53 -> 317 | X75: =X53 -> 299 | Y75: =Y53 -> 390 | Z75: =Z53 -> 320 | ... AD75: =AD53 -> 0 | AF75: ULP Tolitoli | AG75: Total WO Gangguan | AH75: =S75 -> 341 | AI75: =SUM($S$75:T75) -> 633 | AJ75: =SUM($S$75:U75) -> 1030 | AK75: =SUM($S$75:V75) -> 1369 | AL75: =SUM($S$75:W75) -> 1686 | AM75: =SUM($S$75:X75) -> 1985 | AN75: =SUM($S$75:Y75) -> 2375 | AO75: =SUM($S$75:Z75) -> 2695 | AP75: =SUM($S$75:AA75) -> 2995 | ... AS75: =SUM($S$75:AD75) -> 2995
C76: Laporan Berulang | R76: Laporan Berulang | S76: 0 | T76: 0 | U76: 0 | V76: 0 | W76: 0 | X76: 0 | Y76: 0 | Z76: 0 | AA76: 0 | AB76: 0 | AC76: 1 | AD76: 0 | AG76: Laporan Berulang | AH76: =S76 -> 0 | AI76: =SUM($S$76:T76) -> 0 | AJ76: =SUM($S$76:U76) -> 0 | AK76: =SUM($S$76:V76) -> 0 | AL76: =SUM($S$76:W76) -> 0 | AM76: =SUM($S$76:X76) -> 0 | AN76: =SUM($S$76:Y76) -> 0 | AO76: =SUM($S$76:Z76) -> 0 | AP76: =SUM($S$76:AA76) -> 0 | ... AS76: =SUM($S$76:AD76) -> 1
C77: Laporan Berulang | D77: 0.04 | E77: 0.04 | F77: 0.04 | G77: 0.04 | H77: 0.04 | I77: 0.04 | J77: 0.04 | K77: 0.04 | L77: 0.04 | M77: 0.04 | N77: 0.04 | O77: 0.04 | R77: Laporan Berulang | S77: =S76/S75*100 -> 0 | T77: =T76/T75*100 -> 0 | U77: =U76/U75*100 -> 0 | V77: =V76/V75*100 -> 0 | W77: =W76/W75*100 -> 0 | X77: =X76/X75*100 -> 0 | Y77: =Y76/Y75*100 -> 0 | Z77: =Z76/Z75*100 -> 0 | ... AD77: =AD76/AD75*100 -> #DIV/0! | AG77: Laporan Berulang | AH77: =AH76/AH75*100 -> 0 | AI77: =AI76/AI75*100 -> 0 | AJ77: =AJ76/AJ75*100 -> 0 | AK77: =AK76/AK75*100 -> 0 | AL77: =AL76/AL75*100 -> 0 | AM77: =AM76/AM75*100 -> 0 | AN77: =AN76/AN75*100 -> 0 | AO77: =AO76/AO75*100 -> 0 | ... AS77: =AS76/AS75*100 -> 0.033388982
B78: ULP Leok | C78: Total WO Gangguan | Q78: ULP Leok | R78: Total WO Gangguan | S78: =S56 -> 466 | T78: =T56 -> 413 | U78: =U56 -> 389 | V78: =V56 -> 322 | W78: =W56 -> 319 | X78: =X56 -> 261 | Y78: =Y56 -> 351 | Z78: =Z56 -> 422 | ... AD78: =AD56 -> 0 | AF78: ULP Leok | AG78: Total WO Gangguan | AH78: =S78 -> 466 | AI78: =SUM($S$78:T78) -> 879 | AJ78: =SUM($S$78:U78) -> 1268 | AK78: =SUM($S$78:V78) -> 1590 | AL78: =SUM($S$78:W78) -> 1909 | AM78: =SUM($S$78:X78) -> 2170 | AN78: =SUM($S$78:Y78) -> 2521 | AO78: =SUM($S$78:Z78) -> 2943 | AP78: =SUM($S$78:AA78) -> 3432 | ... AS78: =SUM($S$78:AD78) -> 3432
C79: Laporan Berulang | R79: Laporan Berulang | S79: 0 | T79: 0 | U79: 0 | V79: 0 | W79: 0 | X79: 0 | Y79: 0 | Z79: 0 | AA79: 0 | AB79: 0 | AC79: 0 | AD79: 1 | AG79: Laporan Berulang | AH79: =S79 -> 0 | AI79: =SUM($S$79:T79) -> 0 | AJ79: =SUM($S$79:U79) -> 0 | AK79: =SUM($S$79:V79) -> 0 | AL79: =SUM($S$79:W79) -> 0 | AM79: =SUM($S$79:X79) -> 0 | AN79: =SUM($S$79:Y79) -> 0 | AO79: =SUM($S$79:Z79) -> 0 | AP79: =SUM($S$79:AA79) -> 0 | ... AS79: =SUM($S$79:AD79) -> 1
C80: Laporan Berulang | D80: 0.04 | E80: 0.04 | F80: 0.04 | G80: 0.04 | H80: 0.04 | I80: 0.04 | J80: 0.04 | K80: 0.04 | L80: 0.04 | M80: 0.04 | N80: 0.04 | O80: 0.04 | R80: Laporan Berulang | S80: =S79/S78*100 -> 0 | T80: =T79/T78*100 -> 0 | U80: =U79/U78*100 -> 0 | V80: =V79/V78*100 -> 0 | W80: =W79/W78*100 -> 0 | X80: =X79/X78*100 -> 0 | Y80: =Y79/Y78*100 -> 0 | Z80: =Z79/Z78*100 -> 0 | ... AD80: =AD79/AD78*100 -> #DIV/0! | AG80: Laporan Berulang | AH80: =AH79/AH78*100 -> 0 | AI80: =AI79/AI78*100 -> 0 | AJ80: =AJ79/AJ78*100 -> 0 | AK80: =AK79/AK78*100 -> 0 | AL80: =AL79/AL78*100 -> 0 | AM80: =AM79/AM78*100 -> 0 | AN80: =AN79/AN78*100 -> 0 | AO80: =AO79/AO78*100 -> 0 | ... AS80: =AS79/AS78*100 -> 0.029137529
B81: ULP Bangkir | C81: Total WO Gangguan | Q81: ULP Bangkir | R81: Total WO Gangguan | S81: =S59 -> 351 | T81: =T59 -> 334 | U81: =U59 -> 431 | V81: =V59 -> 335 | W81: =W59 -> 299 | X81: =X59 -> 269 | Y81: =Y59 -> 308 | Z81: =Z59 -> 322 | ... AD81: =AD59 -> 0 | AF81: ULP Bangkir | AG81: Total WO Gangguan | AH81: =S81 -> 351 | AI81: =SUM($S$81:T81) -> 685 | AJ81: =SUM($S$81:U81) -> 1116 | AK81: =SUM($S$81:V81) -> 1451 | AL81: =SUM($S$81:W81) -> 1750 | AM81: =SUM($S$81:X81) -> 2019 | AN81: =SUM($S$81:Y81) -> 2327 | AO81: =SUM($S$81:Z81) -> 2649 | AP81: =SUM($S$81:AA81) -> 2939 | ... AS81: =SUM($S$81:AD81) -> 2939
C82: Laporan Berulang | R82: Laporan Berulang | S82: 0 | T82: 0 | U82: 0 | V82: 0 | W82: 0 | X82: 0 | Y82: 0 | Z82: 0 | AA82: 0 | AB82: 0 | AC82: 1 | AD82: 0 | AG82: Laporan Berulang | AH82: =S82 -> 0 | AI82: =SUM($S$82:T82) -> 0 | AJ82: =SUM($S$82:U82) -> 0 | AK82: =SUM($S$82:V82) -> 0 | AL82: =SUM($S$82:W82) -> 0 | AM82: =SUM($S$82:X82) -> 0 | AN82: =SUM($S$82:Y82) -> 0 | AO82: =SUM($S$82:Z82) -> 0 | AP82: =SUM($S$82:AA82) -> 0 | ... AS82: =SUM($S$82:AD82) -> 1
C83: Laporan Berulang | D83: 0.04 | E83: 0.04 | F83: 0.04 | G83: 0.04 | H83: 0.04 | I83: 0.04 | J83: 0.04 | K83: 0.04 | L83: 0.04 | M83: 0.04 | N83: 0.04 | O83: 0.04 | R83: Laporan Berulang | S83: =S82/S81*100 -> 0 | T83: =T82/T81*100 -> 0 | U83: =U82/U81*100 -> 0 | V83: =V82/V81*100 -> 0 | W83: =W82/W81*100 -> 0 | X83: =X82/X81*100 -> 0 | Y83: =Y82/Y81*100 -> 0 | Z83: =Z82/Z81*100 -> 0 | ... AD83: =AD82/AD81*100 -> #DIV/0! | AG83: Laporan Berulang | AH83: =AH82/AH81*100 -> 0 | AI83: =AI82/AI81*100 -> 0 | AJ83: =AJ82/AJ81*100 -> 0 | AK83: =AK82/AK81*100 -> 0 | AL83: =AL82/AL81*100 -> 0 | AM83: =AM82/AM81*100 -> 0 | AN83: =AN82/AN81*100 -> 0 | AO83: =AO82/AO81*100 -> 0 | ... AS83: =AS82/AS81*100 -> 0.034025179
B84: ULP Moutong | C84: Total WO Gangguan | Q84: ULP Moutong | R84: Total WO Gangguan | S84: =S62 -> 209 | T84: =T62 -> 341 | U84: =U62 -> 351 | V84: =V62 -> 249 | W84: =W62 -> 213 | X84: =X62 -> 224 | Y84: =Y62 -> 220 | Z84: =Z62 -> 218 | ... AD84: =AD62 -> 0 | AF84: ULP Moutong | AG84: Total WO Gangguan | AH84: =S84 -> 209 | AI84: =SUM($S$84:T84) -> 550 | AJ84: =SUM($S$84:U84) -> 901 | AK84: =SUM($S$84:V84) -> 1150 | AL84: =SUM($S$84:W84) -> 1363 | AM84: =SUM($S$84:X84) -> 1587 | AN84: =SUM($S$84:Y84) -> 1807 | AO84: =SUM($S$84:Z84) -> 2025 | AP84: =SUM($S$84:AA84) -> 2225 | ... AS84: =SUM($S$84:AD84) -> 2225
C85: Laporan Berulang | R85: Laporan Berulang | S85: 0 | T85: 0 | U85: 0 | V85: 0 | W85: 0 | X85: 0 | Y85: 0 | Z85: 0 | AA85: 0 | AB85: 0 | AC85: 0 | AD85: 0 | AG85: Laporan Berulang | AH85: =S85 -> 0 | AI85: =SUM($S$85:T85) -> 0 | AJ85: =SUM($S$85:U85) -> 0 | AK85: =SUM($S$85:V85) -> 0 | AL85: =SUM($S$85:W85) -> 0 | AM85: =SUM($S$85:X85) -> 0 | AN85: =SUM($S$85:Y85) -> 0 | AO85: =SUM($S$85:Z85) -> 0 | AP85: =SUM($S$85:AA85) -> 0 | ... AS85: =SUM($S$85:AD85) -> 0
C86: Laporan Berulang | D86: 0.04 | E86: 0.04 | F86: 0.04 | G86: 0.04 | H86: 0.04 | I86: 0.04 | J86: 0.04 | K86: 0.04 | L86: 0.04 | M86: 0.04 | N86: 0.04 | O86: 0.04 | R86: Laporan Berulang | S86: =S85/S84*100% -> 0 | T86: =T85/T84*100 -> 0 | U86: =U85/U84*100 -> 0 | V86: =V85/V84*100 -> 0 | W86: =W85/W84*100 -> 0 | X86: =X85/X84*100 -> 0 | Y86: =Y85/Y84*100 -> 0 | Z86: =Z85/Z84*100 -> 0 | AA86: =AA85/AA84*100 -> 0 | ... AD86: =AD85/AD84*100 -> #DIV/0! | AG86: Laporan Berulang | AH86: =AH85/AH84*100 -> 0 | AI86: =AI85/AI84*100 -> 0 | AJ86: =AJ85/AJ84*100 -> 0 | AK86: =AK85/AK84*100 -> 0 | AL86: =AL85/AL84*100 -> 0 | AM86: =AM85/AM84*100 -> 0 | AN86: =AN85/AN84*100 -> 0 | AO86: =AO85/AO84*100 -> 0 | ... AS86: =AS85/AS84*100 -> 0
B87: ULP Kotaraya | C87: Total WO Gangguan | Q87: ULP Kotaraya | R87: Total WO Gangguan | S87: =S65 -> 947 | T87: =T65 -> 887 | U87: =U65 -> 975 | V87: =V65 -> 975 | W87: =W65 -> 892 | X87: =X65 -> 874 | Y87: =Y65 -> 832 | Z87: =Z65 -> 874 | ... AD87: =AD65 -> 0 | AF87: ULP Kotaraya | AG87: Total WO Gangguan | AH87: =S87 -> 947 | AI87: =SUM($S$87:T87) -> 1834 | AJ87: =SUM($S$87:U87) -> 2809 | AK87: =SUM($S$87:V87) -> 3784 | AL87: =SUM($S$87:W87) -> 4676 | AM87: =SUM($S$87:X87) -> 5550 | AN87: =SUM($S$87:Y87) -> 6382 | AO87: =SUM($S$87:Z87) -> 7256 | AP87: =SUM($S$87:AA87) -> 7379 | ... AS87: =SUM($S$87:AD87) -> 7379
C88: Laporan Berulang | R88: Laporan Berulang | S88: 0 | T88: 0 | U88: 0 | V88: 0 | W88: 0 | X88: 0 | Y88: 0 | Z88: 0 | AA88: 0 | AB88: 0 | AC88: 0 | AD88: 0 | AG88: Laporan Berulang | AH88: =S88 -> 0 | AI88: =SUM($S$88:T88) -> 0 | AJ88: =SUM($S$88:U88) -> 0 | AK88: =SUM($S$88:V88) -> 0 | AL88: =SUM($S$88:W88) -> 0 | AM88: =SUM($S$88:X88) -> 0 | AN88: =SUM($S$88:Y88) -> 0 | AO88: =SUM($S$88:Z88) -> 0 | AP88: =SUM($S$88:AA88) -> 0 | ... AS88: =SUM($S$88:AD88) -> 0
C89: Laporan Berulang | D89: 0.04 | E89: 0.04 | F89: 0.04 | G89: 0.04 | H89: 0.04 | I89: 0.04 | J89: 0.04 | K89: 0.04 | L89: 0.04 | M89: 0.04 | N89: 0.04 | O89: 0.04 | R89: Laporan Berulang | S89: =S88/S87*100 -> 0 | T89: =T88/T87*100 -> 0 | U89: =U88/U87*100 -> 0 | V89: =V88/V87*100 -> 0 | W89: =W88/W87*100 -> 0 | X89: =X88/X87*100 -> 0 | Y89: =Y88/Y87*100 -> 0 | Z89: =Z88/Z87*100 -> 0 | ... AD89: =AD88/AD87*100 -> #DIV/0! | AG89: Laporan Berulang | AH89: =AH88/AH87*100 -> 0 | AI89: =AI88/AI87*100 -> 0 | AJ89: =AJ88/AJ87*100 -> 0 | AK89: =AK88/AK87*100 -> 0 | AL89: =AL88/AL87*100 -> 0 | AM89: =AM88/AM87*100 -> 0 | AN89: =AN88/AN87*100 -> 0 | AO89: =AO88/AO87*100 -> 0 | ... AS89: =AS88/AS87*100 -> 0
B90: UP3 Tolitoli | C90: Total WO Gangguan | Q90: UP3 Tolitoli | R90: Total WO Gangguan | S90: =S68 -> 2314 | T90: =T68 -> 2267 | U90: =U68 -> 2543 | V90: =V68 -> 2220 | W90: =W68 -> 2040 | X90: =X68 -> 1927 | Y90: =Y68 -> 2101 | Z90: =Z68 -> 2156 | ... AD90: =AD68 -> 0 | AF90: UP3 Tolitoli | AG90: Total WO Gangguan | AH90: =S90 -> 2314 | AI90: =SUM($S$90:T90) -> 4581 | AJ90: =SUM($S$90:U90) -> 7124 | AK90: =SUM($S$90:V90) -> 9344 | AL90: =SUM($S$90:W90) -> 11384 | AM90: =SUM($S$90:X90) -> 13311 | AN90: =SUM($S$90:Y90) -> 15412 | AO90: =SUM($S$90:Z90) -> 17568 | AP90: =SUM($S$90:AA90) -> 18970 | ... AS90: =SUM($S$90:AD90) -> 18970
C91: Laporan Berulang | R91: Laporan Berulang | S91: =S76+S79+S82+S85+S88 -> 0 | T91: =T76+T79+T82+T85+T88 -> 0 | U91: =U76+U79+U82+U85+U88 -> 0 | V91: =V76+V79+V82+V85+V88 -> 0 | W91: =W76+W79+W82+W85+W88 -> 0 | X91: =X76+X79+X82+X85+X88 -> 0 | Y91: =Y76+Y79+Y82+Y85+Y88 -> 0 | Z91: =Z76+Z79+Z82+Z85+Z88 -> 0 | AA91: 0 | AB91: 0 | AC91: 0 | AD91: 1 | AG91: Laporan Berulang | AH91: =S91 -> 0 | AI91: =SUM($S$91:T91) -> 0 | AJ91: =SUM($S$91:U91) -> 0 | AK91: =SUM($S$91:V91) -> 0 | AL91: =SUM($S$91:W91) -> 0 | AM91: =SUM($S$91:X91) -> 0 | AN91: =SUM($S$91:Y91) -> 0 | AO91: =SUM($S$91:Z91) -> 0 | AP91: =SUM($S$91:AA91) -> 0 | ... AS91: =SUM($S$91:AD91) -> 1
C92: Laporan Berulang | D92: 0.04 | E92: 0.04 | F92: 0.04 | G92: 0.04 | H92: 0.04 | I92: 0.04 | J92: 0.04 | K92: 0.04 | L92: 0.04 | M92: 0.04 | N92: 0.04 | O92: 0.04 | R92: Laporan Berulang | S92: =S91/S90*100 -> 0 | T92: =T91/T90*100 -> 0 | U92: =U91/U90*100 -> 0 | V92: =V91/V90*100 -> 0 | W92: =W91/W90*100 -> 0 | X92: =X91/X90*100 -> 0 | Y92: =Y91/Y90*100 -> 0 | Z92: =Z91/Z90*100 -> 0 | ... AD92: =AD91/AD90*100 -> #DIV/0! | AG92: Laporan Berulang | AH92: =AH91/AH90*100 -> 0 | AI92: =AI91/AI90*100 -> 0 | AJ92: =AJ91/AJ90*100 -> 0 | AK92: =AK91/AK90*100 -> 0 | AL92: =AL91/AL90*100 -> 0 | AM92: =AM91/AM90*100 -> 0 | AN92: =AN91/AN90*100 -> 0 | AO92: =AO91/AO90*100 -> 0 | ... AS92: =AS91/AS90*100 -> 0.0052714813
B94: RATING PLN MOBILE | Q94: =B94 -> RATING PLN MOBILE | AF94: =B94 -> RATING PLN MOBILE
B95: TARGET | Q95: REALISASI BULANAN | AF95: REALIASI KOMULATIF
B96: Unit | D96: Jan | E96: Feb | F96: Mar | G96: Apr | H96: May | I96: Jun | J96: Jul | K96: Aug | L96: Sep | M96: Oct | N96: Nov | O96: Dec | Q96: Unit | S96: Jan | T96: Feb | U96: Mar | V96: Apr | W96: May | X96: Jun | Y96: Jul | Z96: Aug | AA96: Sep | AB96: Oct | AC96: Nov | AD96: Dec | AF96: Unit | AH96: Jan | AI96: Feb | AJ96: Mar | AK96: Apr | AL96: May | AM96: Jun | AN96: Jul | AO96: Aug | AP96: Sep | AQ96: Oct | AR96: Nov | AS96: Dec
B97: Semua Unit | C97: Rating | D97: 4.9 | E97: 4.9 | F97: 4.9 | G97: 4.9 | H97: 4.9 | I97: 4.9 | J97: 4.9 | K97: 4.9 | L97: 4.9 | M97: 4.9 | N97: 4.9 | O97: 4.9 | Q97: =B97 -> Semua Unit | R97: =C97 -> Rating | S97: 4.91 | T97: 4.91 | U97: 4.91 | V97: 4.91 | W97: 4.9 | X97: 4.9 | Y97: 4.9 | Z97: 4.9 | AA97: 4.9 | AB97: 4.9 | AC97: 4.9 | AD97: 4.9 | AF97: =Q97 -> Semua Unit | AG97: =R97 -> Rating | AH97: =S97 -> 4.91 | AI97: =T97 -> 4.91 | AJ97: =U97 -> 4.91 | AK97: =V97 -> 4.91 | AL97: =W97 -> 4.9 | AM97: =X97 -> 4.9 | ... AS97: =AD97 -> 4.9
AF98: =B231 -> JUMLAH PENGGUNA SWACAM
B99: JUMLAH KALI TRANSAKSI KEUANGAN PLN MOBILE - TOTAL | Q99: =B99 -> JUMLAH KALI TRANSAKSI KEUANGAN PLN MOBILE - TOTAL | AF99: =B99 -> JUMLAH KALI TRANSAKSI KEUANGAN PLN MOBILE - TOTAL
B100: TARGET | Q100: REALISASI BULANAN | AF100: REALIASI KOMULATIF
B101: Unit | D101: Jan | E101: Feb | F101: Mar | G101: Apr | H101: May | I101: Jun | J101: Jul | K101: Aug | L101: Sep | M101: Oct | N101: Nov | O101: Dec | Q101: Unit | S101: Jan | T101: Feb | U101: Mar | V101: Apr | W101: May | X101: Jun | Y101: Jul | Z101: Aug | AA101: Sep | AB101: Oct | AC101: Nov | AD101: Dec | AF101: Unit | AH101: Jan | AI101: Feb | AJ101: Mar | AK101: Apr | AL101: May | AM101: Jun | AN101: Jul | AO101: Aug | AP101: Sep | AQ101: Oct | AR101: Nov | AS101: Dec
B102: ULP Tolitoli | C102: Jumlah Kali Transaksi | D102: 1598 | E102: 3042 | F102: 4641 | G102: 6188 | H102: 7786 | I102: 9333 | J102: 10381 | K102: 11430 | L102: 12444 | M102: 13492 | N102: 14507 | O102: 15555 | Q102: =B102 -> ULP Tolitoli | R102: Jumlah Kali Transaksi | S102: 859 | T102: 1155 | U102: 1832 | V102: 2510 | W102: 2246 | X102: 1704 | Y102: 1965 | Z102: 1940 | AA102: 1898 | AF102: =Q102 -> ULP Tolitoli | AG102: Jumlah Kali Transaksi | AH102: =S102 -> 859 | AI102: =IF(T102=0,0,AH102+T102) -> 2014 | AJ102: =IF(U102=0,0,AI102+U102) -> 3846 | AK102: =IF(V102=0,0,AJ102+V102) -> 6356 | AL102: =IF(W102=0,0,AK102+W102) -> 8602 | AM102: =IF(X102=0,0,AL102+X102) -> 10306 | AN102: =IF(Y102=0,0,AM102+Y102) -> 12271 | AO102: =IF(Z102=0,0,AN102+Z102) -> 14211 | AP102: =IF(AA102=0,0,AO102+AA102) -> 16109 | ... AS102: =IF(AD102=0,0,AR102+AD102) -> 0
B103: ULP Leok | C103: Jumlah Kali Transaksi | D103: 1826 | E103: 3476 | F103: 5303 | G103: 7070 | H103: 8896 | I103: 10664 | J103: 11862 | K103: 13060 | L103: 14219 | M103: 15417 | N103: 16576 | O103: 17774 | Q103: =B103 -> ULP Leok | R103: Jumlah Kali Transaksi | S103: 1054 | T103: 1117 | U103: 3018 | V103: 2434 | W103: 2576 | X103: 2432 | Y103: 2646 | Z103: 1661 | AA103: 1615 | AF103: =Q103 -> ULP Leok | AG103: Jumlah Kali Transaksi | AH103: =S103 -> 1054 | AI103: =IF(T103=0,0,AH103+T103) -> 2171 | AJ103: =IF(U103=0,0,AI103+U103) -> 5189 | AK103: =IF(V103=0,0,AJ103+V103) -> 7623 | AL103: =IF(W103=0,0,AK103+W103) -> 10199 | AM103: =IF(X103=0,0,AL103+X103) -> 12631 | AN103: =IF(Y103=0,0,AM103+Y103) -> 15277 | AO103: =IF(Z103=0,0,AN103+Z103) -> 16938 | AP103: =IF(AA103=0,0,AO103+AA103) -> 18553 | ... AS103: =IF(AD103=0,0,AR103+AD103) -> 0
B104: ULP Bangkir | C104: Jumlah Kali Transaksi | D104: 841 | E104: 1601 | F104: 2442 | G104: 3257 | H104: 4098 | I104: 4912 | J104: 5740 | K104: 6567 | L104: 7368 | M104: 8196 | N104: 8996 | O104: 9824 | Q104: =B104 -> ULP Bangkir | R104: Jumlah Kali Transaksi | S104: 293 | T104: 222 | U104: 1609 | V104: 1844 | W104: 1467 | X104: 830 | Y104: 976 | Z104: 873 | AA104: 1374 | AF104: =Q104 -> ULP Bangkir | AG104: Jumlah Kali Transaksi | AH104: =S104 -> 293 | AI104: =IF(T104=0,0,AH104+T104) -> 515 | AJ104: =IF(U104=0,0,AI104+U104) -> 2124 | AK104: =IF(V104=0,0,AJ104+V104) -> 3968 | AL104: =IF(W104=0,0,AK104+W104) -> 5435 | AM104: =IF(X104=0,0,AL104+X104) -> 6265 | AN104: =IF(Y104=0,0,AM104+Y104) -> 7241 | AO104: =IF(Z104=0,0,AN104+Z104) -> 8114 | AP104: =IF(AA104=0,0,AO104+AA104) -> 9488 | ... AS104: =IF(AD104=0,0,AR104+AD104) -> 0
B105: ULP Moutong | C105: Jumlah Kali Transaksi | D105: 987 | E105: 1878 | F105: 2865 | G105: 3820 | H105: 4807 | I105: 5762 | J105: 6409 | K105: 7056 | L105: 7683 | M105: 8330 | N105: 8956 | O105: 9603 | Q105: =B105 -> ULP Moutong | R105: Jumlah Kali Transaksi | S105: 239 | T105: 388 | U105: 1743 | V105: 1778 | W105: 2124 | X105: 2399 | Y105: 2001 | Z105: 1572 | AA105: 1058 | AF105: =Q105 -> ULP Moutong | AG105: Jumlah Kali Transaksi | AH105: =S105 -> 239 | AI105: =IF(T105=0,0,AH105+T105) -> 627 | AJ105: =IF(U105=0,0,AI105+U105) -> 2370 | AK105: =IF(V105=0,0,AJ105+V105) -> 4148 | AL105: =IF(W105=0,0,AK105+W105) -> 6272 | AM105: =IF(X105=0,0,AL105+X105) -> 8671 | AN105: =IF(Y105=0,0,AM105+Y105) -> 10672 | AO105: =IF(Z105=0,0,AN105+Z105) -> 12244 | AP105: =IF(AA105=0,0,AO105+AA105) -> 13302 | ... AS105: =IF(AD105=0,0,AR105+AD105) -> 0
B106: ULP Kotaraya | C106: Jumlah Kali Transaksi | D106: 1043 | E106: 1985 | F106: 3029 | G106: 4038 | H106: 5081 | I106: 6091 | J106: 6775 | K106: 7459 | L106: 8122 | M106: 8806 | N106: 9468 | O106: 10152 | Q106: =B106 -> ULP Kotaraya | R106: Jumlah Kali Transaksi | S106: 336 | T106: 500 | U106: 1984 | V106: 1752 | W106: 1469 | X106: 1147 | Y106: 917 | Z106: 1060 | AA106: 1473 | AF106: =Q106 -> ULP Kotaraya | AG106: Jumlah Kali Transaksi | AH106: =S106 -> 336 | AI106: =IF(T106=0,0,AH106+T106) -> 836 | AJ106: =IF(U106=0,0,AI106+U106) -> 2820 | AK106: =IF(V106=0,0,AJ106+V106) -> 4572 | AL106: =IF(W106=0,0,AK106+W106) -> 6041 | AM106: =IF(X106=0,0,AL106+X106) -> 7188 | AN106: =IF(Y106=0,0,AM106+Y106) -> 8105 | AO106: =IF(Z106=0,0,AN106+Z106) -> 9165 | AP106: =IF(AA106=0,0,AO106+AA106) -> 10638 | ... AS106: =IF(AD106=0,0,AR106+AD106) -> 0
B107: UP3 Tolitoli | C107: Jumlah Kali Transaksi | D107: 5386 | E107: 10253 | F107: 15641 | G107: 20855 | H107: 26242 | I107: 31455 | J107: 36754 | K107: 42054 | L107: 47183 | M107: 52481 | N107: 57609 | O107: 62908 | Q107: =B107 -> UP3 Tolitoli | R107: Jumlah Kali Transaksi | S107: =SUM(S102:S106) -> 2781 | T107: =SUM(T102:T106) -> 3382 | U107: =SUM(U102:U106) -> 10186 | V107: =SUM(V102:V106) -> 10318 | W107: =SUM(W102:W106) -> 9882 | X107: =SUM(X102:X106) -> 8512 | Y107: =SUM(Y102:Y106) -> 8505 | Z107: =SUM(Z102:Z106) -> 7106 | ... AD107: =SUM(AD102:AD106) -> 0 | AF107: =Q107 -> UP3 Tolitoli | AG107: Jumlah Kali Transaksi | AH107: =S107 -> 2781 | AI107: =IF(T107=0,0,AH107+T107) -> 6163 | AJ107: =IF(U107=0,0,AI107+U107) -> 16349 | AK107: =IF(V107=0,0,AJ107+V107) -> 26667 | AL107: =IF(W107=0,0,AK107+W107) -> 36549 | AM107: =IF(X107=0,0,AL107+X107) -> 45061 | AN107: =IF(Y107=0,0,AM107+Y107) -> 53566 | AO107: =IF(Z107=0,0,AN107+Z107) -> 60672 | AP107: =IF(AA107=0,0,AO107+AA107) -> 68090 | ... AS107: =IF(AD107=0,0,AR107+AD107) -> 0
A110: 5 | B110: RCT DAN RPT GANGGUAN (MENIT) | Q110: =B110 -> RCT DAN RPT GANGGUAN (MENIT) | AF110: =B110 -> RCT DAN RPT GANGGUAN (MENIT)
B111: TARGET | Q111: REALISASI BULANAN | AF111: REALISASI KOMULATIF
B112: Unit | D112: Jan | E112: Feb | F112: Mar | G112: Apr | H112: May | I112: Jun | J112: Jul | K112: Aug | L112: Sep | M112: Oct | N112: Nov | O112: Dec | Q112: Unit | S112: Jan | T112: Feb | U112: Mar | V112: Apr | W112: May | X112: Jun | Y112: Jul | Z112: Aug | AA112: Sep | AB112: Oct | AC112: Nov | AD112: Dec | AF112: Unit | AH112: Jan | AI112: Feb | AJ112: Mar | AK112: Apr | AL112: May | AM112: Jun | AN112: Jul | AO112: Aug | AP112: Sep | AQ112: Oct | AR112: Nov | AS112: Dec
B113: ULP Tolitoli | C113: Respond Time (RPT) | D113: 30 | E113: 30 | F113: 30 | G113: 30 | H113: 30 | I113: 30 | J113: 30 | K113: 30 | L113: 30 | M113: 30 | N113: 30 | O113: 30 | Q113: ULP Tolitoli | R113: Respond Time (RPT) | S113: 11.47716 | T113: 11.275 | U113: 11.162054 | V113: 11.401995 | W113: 14.48 | X113: 13.31789 | Y113: 13.31789 | Z113: 14.690741 | AA113: 14.942134 | AF113: ULP Tolitoli | AG113: Respond Time (RPT) | AH113: =S113 -> 11.47716 | AI113: =AVERAGE($S$113:T113) -> 11.37608 | AJ113: =AVERAGE($S$113:U113) -> 11.304738 | AK113: =AVERAGE($S$113:V113) -> 11.329052 | AL113: =AVERAGE($S$113:W113) -> 11.959242 | AM113: =AVERAGE($S$113:X113) -> 12.185683 | AN113: =AVERAGE($S$113:Y113) -> 12.347427 | AO113: =AVERAGE($S$113:Z113) -> 12.640341 | AP113: =AVERAGE($S$113:AA113) -> 12.896096 | ... AS113: =AVERAGE($S$113:AD113) -> 12.896096
C114: Recovery Time (RCT) | R114: Recovery Time (RCT) | AG114: Recovery Time (RCT)
...

Sheet UP3
B1: KONTRAK MANAJEMEN 2025
B2: PT PLN (PERSERO) UID SULUTTENGGO | M2: SEP | N2: PILIH BULAN LAPORAN
B3: UP3 TOLITOLI
A4: NO | B4: KPI | D4: SATUAN | E4: BOBOT | F4: TARGET 2025 | G4: =VLOOKUP(M2,M7:N18,2,FALSE) -> S.D. SEPTEMBER
G5: TARGET | H5: REALISASI | I5: PENCAPAIAN | J5: NILAI
A6: 1 | B6: 2 | D6: 3 | E6: 4 | F6: 5 | G6: 6 | H6: 7 | I6: 8 | J6: 9
A7: =T.UP3!A7 -> I | B7: =T.UP3!B7 -> Key Performance Indikator | E7: =SUM(E8:E16) -> 40 | J7: =SUM(J8:J16) -> 41.67 | M7: JAN | N7: S.D. JANUARI | R7: =R8+R9+R10 -> 40.96 | S7: =S8+S9+S10 -> 41.25
A8: =T.UP3!A8 -> 1 | B8: =T.UP3!B8 -> Penjualan Tenaga Listrik | C8: =T.UP3!C8 -> ñ | D8: =T.UP3!D8 -> GWh | E8: =IF(OR(H8="N/A",G8="N/A"),0,T.UP3!F8) -> 14 | F8: =T.UP3!H8 -> 231.47 | G8: =VLOOKUP(B8,T.UP3!$B$4:$T$70,MATCH('UP3'!$M$2,T.UP3!$B$5:$T$5,0),FALSE) -> 171.15 | H8: =VLOOKUP(B8,'R.UP3'!$B$4:$T$67,MATCH('UP3'!$M$2,'R.UP3'!$B$5:$T$5,0),FALSE) -> 166.35581 | I8: =IF(OR(G8="N/A",H8="N/A"),"N/A",IF((H8/G8*100)>=110,110,(H8/G8*100))) -> 97.198835 | J8: =ROUNDDOWN(IF(I8="N/A",0,IF(I8>110,E8*110/100,E8*I8/100)),2) -> 13.6 | M8: FEB | N8: S.D. FEBRUARI | R8: 13.56 | S8: 13.53 | T8: =R8-S8 -> 0.03
A9: =T.UP3!A9 -> 2 | B9: =T.UP3!B9 -> Keandalan Sistem | E9: =IF(OR(H9="N/A",G9="N/A"),0,T.UP3!F9) -> 14 | I9: =AVERAGE(I10:I12) -> 110 | J9: =ROUNDDOWN(IF(I9="N/A",0,IF(I9>110,E9*110/100,E9*I9/100)),2) -> 15.4 | M9: MAR | N9: S.D. MARET | R9: 15.4 | S9: 15.4 | T9: =R9-S9 -> 0
B10: =T.UP3!B10 -> a. SAIDI Sesuai Kewenangannya | C10: =T.UP3!C10 -> ò | D10: =T.UP3!D10 -> Menit/Plg | F10: =T.UP3!H10 -> 280.67 | G10: =VLOOKUP(B10,T.UP3!$B$4:$T$70,MATCH('UP3'!$M$2,T.UP3!$B$5:$T$5,0),FALSE) -> 210.5 | H10: =VLOOKUP(B10,'R.UP3'!$B$4:$T$67,MATCH('UP3'!$M$2,'R.UP3'!$B$5:$T$5,0),FALSE) -> 159.21376 | I10: =IF(OR(G10="N/A",H10="N/A"),"N/A",IF((2-(H10/G10))*100>=110,110,(2-(H10/G10))*100)) -> 110 | M10: APRIL | N10: S.D. APRIL | R10: 12 | S10: 12.32 | T10: =R10-S10 -> -0.32
B11: =T.UP3!B11 -> b. SAIFI Sesuai Kewenangannya | C11: =T.UP3!C11 -> ò | D11: =T.UP3!D11 -> Kali/Plg | F11: =T.UP3!H11 -> 2.97 | G11: =VLOOKUP(B11,T.UP3!$B$4:$T$70,MATCH('UP3'!$M$2,T.UP3!$B$5:$T$5,0),FALSE) -> 2.22 | H11: =VLOOKUP(B11,'R.UP3'!$B$4:$T$67,MATCH('UP3'!$M$2,'R.UP3'!$B$5:$T$5,0),FALSE) -> 1.7486104 | I11: =IF(OR(G11="N/A",H11="N/A"),"N/A",IF((2-(H11/G11))*100>=110,110,(2-(H11/G11))*100)) -> 110 | M11: MEI | N11: S.D. MEI
B12: =T.UP3!B12 -> c. ENS | C12: =T.UP3!C12 -> ò | D12: =T.UP3!D12 -> MWh | F12: =T.UP3!H12 -> 107.87 | G12: =VLOOKUP(B12,T.UP3!$B$4:$T$70,MATCH('UP3'!$M$2,T.UP3!$B$5:$T$5,0),FALSE) -> 80.9 | H12: =VLOOKUP(B12,'R.UP3'!$B$4:$T$67,MATCH('UP3'!$M$2,'R.UP3'!$B$5:$T$5,0),FALSE) -> 50.782 | I12: =IF(G12=0,0,IF(((G12-(H12-G12))/G12)*100<=0,0,IF(((G12-(H12-G12))/G12)*100>=110,110,((G12-(H12-G12))/G12)*100))) -> 110 | M12: JUNI | N12: S.D. JUNI
A13: =T.UP3!A13 -> 3 | B13: =T.UP3!B13 -> Efisiensi Jaringan Distribusi | E13: =IF(OR(H13="N/A",G13="N/A"),0,T.UP3!F13) -> 12 | I13: =AVERAGE(I14:I16) -> 105.60639 | J13: =ROUNDDOWN(IF(I13="N/A",0,IF(I13>110,E13*110/100,E13*I13/100)),2) -> 12.67 | M13: JULI | N13: S.D. JULI
B14: =T.UP3!B14 -> a. Susut Distribusi Tanpa E-min (sesuai kewenangan) | C14: =T.UP3!C14 -> ò | D14: =T.UP3!D14 -> % | F14: =T.UP3!H14 -> 9 | G14: =VLOOKUP(B14,T.UP3!$B$4:$T$70,MATCH('UP3'!$M$2,T.UP3!$B$5:$T$5,0),FALSE) -> 9.2 | H14: =VLOOKUP(B14,'R.UP3'!$B$4:$T$67,MATCH('UP3'!$M$2,'R.UP3'!$B$5:$T$5,0),FALSE) -> 8.2084941 | I14: =IF(OR(G14="N/A",H14="N/A"),"N/A",IF((2-(H14/G14))*100>=110,110,(2-(H14/G14))*100)) -> 110 | M14: AUG | N14: S.D. AGUSTUS
B15: =T.UP3!B15 -> b. Penyelesaian Temuan P2TL | C15: =T.UP3!C15 -> ñ | D15: =T.UP3!D15 -> % | F15: =T.UP3!H15 -> 100 | G15: =VLOOKUP(B15,T.UP3!$B$4:$T$70,MATCH('UP3'!$M$2,T.UP3!$B$5:$T$5,0),FALSE) -> 70 | H15: =VLOOKUP(B15,'R.UP3'!$B$4:$T$67,MATCH('UP3'!$M$2,'R.UP3'!$B$5:$T$5,0),FALSE) -> 91.575633 | I15: =IF(OR(G15="N/A",H15="N/A"),"N/A",IF((H15/G15*100)>=110,110,(H15/G15*100))) -> 110 | M15: SEP | N15: S.D. SEPTEMBER
