Workbook
Name \0: #REF!
Name \0: #REF!
Name \0: #REF!
Name \0: #REF!
Name \0: #REF!
Name \0: #REF!
Name \0: #REF!
Name \0: #REF!
Name \1: #REF!
Name \1: #REF!
Name \1: #REF!
Name \1: #REF!
Name \1: #REF!
Name \1: #REF!
Name \1: #REF!
Name \1: #REF!
Name \a: #REF!
Name \a: #REF!
Name \a: #REF!
Name \a: #REF!
Name \a: #REF!
Name \a: #REF!
Name \a: #REF!
Name \a: #REF!
Name \a: #REF!
Name \a: #REF!
Name \b: #REF!
Name \b: #REF!
Name \b: #REF!
Name \b: #REF!
Name \b: #REF!
Name \b: #REF!
Name \b: #REF!
Name \b: #REF!
Name \b: #REF!
Name \b: #REF!
Name \b11_567891011: #REF!
Name \b11_567891011: #REF!
Name \b11_567891011: #REF!
Name \b11_567891011: #REF!
Name \b11_567891011: #REF!
Name \b11_567891011: #REF!
Name \b11_567891011: #REF!
Name \b12_567891011: #REF!
Name \b12_567891011: #REF!
Name \b12_567891011: #REF!
Name \b12_567891011: #REF!
Name \b12_567891011: #REF!
Name \b12_567891011: #REF!
Name \b12_567891011: #REF!
Name \b13_567891011: #REF!
Name \b13_567891011: #REF!
Name \b13_567891011: #REF!
Name \b13_567891011: #REF!
Name \b13_567891011: #REF!
Name \b13_567891011: #REF!
Name \b13_567891011: #REF!
Name \b14_567891011: #REF!
Name \b14_567891011: #REF!
Name \b14_567891011: #REF!

Sheet RANK
B2: ="NILAI KINERJA UP3 TOLITOLI S.D "&[0]!A&" 2023" -> #REF!
B4: RANK | C4: UNIT | D4: ="NKO S.D "&[0]!A -> #REF!
B5: 1 | C5: =VLOOKUP(B5,$G$5:$I$9,2,FALSE) -> ULP BANGKIR | D5: =VLOOKUP(B5,$G$5:$I$9,3,FALSE) -> 105.5 | G5: =RANK(I5,$I$5:$I$9) -> 5 | H5: ULP TOLITOLI | I5: =ULP!L58 -> 98.94
B6: 2 | C6: =VLOOKUP(B6,$G$5:$I$9,2,FALSE) -> ULP KOTARAYA | D6: =VLOOKUP(B6,$G$5:$I$9,3,FALSE) -> 103.42 | G6: =RANK(I6,$I$5:$I$9) -> 4 | H6: ULP LEOK | I6: =ULP!W58 -> 99.73
B7: 3 | C7: =VLOOKUP(B7,$G$5:$I$9,2,FALSE) -> ULP MOUTONG | D7: =VLOOKUP(B7,$G$5:$I$9,3,FALSE) -> 99.85 | G7: =RANK(I7,$I$5:$I$9) -> 1 | H7: ULP BANGKIR | I7: =ULP!AH58 -> 105.5
B8: 4 | C8: =VLOOKUP(B8,$G$5:$I$9,2,FALSE) -> ULP LEOK | D8: =VLOOKUP(B8,$G$5:$I$9,3,FALSE) -> 99.73 | G8: =RANK(I8,$I$5:$I$9) -> 3 | H8: ULP MOUTONG | I8: =ULP!AS58 -> 99.85
B9: 5 | C9: =VLOOKUP(B9,$G$5:$I$9,2,FALSE) -> ULP TOLITOLI | D9: =VLOOKUP(B9,$G$5:$I$9,3,FALSE) -> 98.94 | G9: =RANK(I9,$I$5:$I$9) -> 2 | H9: ULP KOTARAYA | I9: =ULP!BD58 -> 103.42
C10: UP3 TOLITOLI | D10: ='UP3'!J70 -> 102.84

Sheet CHECKLIST
B3: NO | C3: KPI | D3: ULP TOLITOLI | E3: ULP LEOK | F3: ULP BANGKIR | G3: ULP MOUTONG | H3: ULP KOTARAYA
C4: Key Performance Indicators
B5: 1 | C5: Penjualan dan Pendapatan Tenaga Listrik
C6: a. Penjualan Tenaga listrik | D6: =ULP!K11 -> 110 | E6: =ULP!V11 -> 110 | F6: =ULP!AG11 -> 110 | G6: =ULP!AR11 -> 110 | H6: =ULP!BC11 -> 110
C7: b. Pendapatan Penjualan Tenaga Listrik | D7: =ULP!K12 -> 110 | E7: =ULP!V12 -> 110 | F7: =ULP!AG12 -> 110 | G7: =ULP!AR12 -> 110 | H7: =ULP!BC12 -> 110
B8: 2 | C8: Pengendalian Piutang Rata-Rata Tunggakan | D8: =ULP!#REF! -> #REF! | E8: =ULP!#REF! -> #REF! | F8: =ULP!#REF! -> #REF! | G8: =ULP!#REF! -> #REF! | H8: =ULP!#REF! -> #REF!
B9: 3 | C9: Susut Jaringan (Tanpa E-Min) | D9: =ULP!#REF! -> #REF! | E9: =ULP!#REF! -> #REF! | F9: =ULP!#REF! -> #REF! | G9: =ULP!#REF! -> #REF! | H9: =ULP!#REF! -> #REF!
C10: Performance Indikator
B11: 4 | C11: Peningkatan Pelayanan
C12: a. Response Time Atas Keluhan | D12: =ULP!K21 -> 110 | E12: =ULP!V21 -> 110 | F12: =ULP!AG21 -> 110 | G12: =ULP!AR21 -> 110 | H12: =ULP!BC21 -> 110
C13: b. Recovery Time Atas Keluhan | D13: =ULP!K22 -> 110 | E13: =ULP!V22 -> 110 | F13: =ULP!AG22 -> 110 | G13: =ULP!AR22 -> 110 | H13: =ULP!BC22 -> 110
C14: c. Response Time Atas Gangguan | D14: =ULP!K23 -> 50 | E14: =ULP!V23 -> 110 | F14: =ULP!AG23 -> 110 | G14: =ULP!AR23 -> 110 | H14: =ULP!BC23 -> 110
C15: d. Recovery Time Atas Gangguan | D15: =ULP!K24 -> 107.5 | E15: =ULP!V24 -> 107.5 | F15: =ULP!AG24 -> 107.5 | G15: =ULP!AR24 -> 107.5 | H15: =ULP!BC24 -> 107.5
B16: 5 | C16: Jumlah Pengguna Aktif Aplikasi "PLN Mobile" | D16: =ULP!K26 -> 110 | E16: =ULP!V26 -> 110 | F16: =ULP!AG26 -> 110 | G16: =ULP!AR26 -> 110 | H16: =ULP!BC26 -> 110
B17: 6 | C17: Peningkatan Keandalan Jaringan
C18: a. SAIDI sesuai kewenangannya | D18: =ULP!K28 -> 110 | E18: =ULP!V28 -> 110 | F18: =ULP!AG28 -> 110 | G18: =ULP!AR28 -> 110 | H18: =ULP!BC28 -> 110
C19: b. SAIFI sesuai kewenangannya | D19: =ULP!K32 -> 110 | E19: =ULP!V32 -> 110 | F19: =ULP!AG32 -> 110 | G19: =ULP!AR32 -> 110 | H19: =ULP!BC32 -> 110
B20: 7 | C20: Percepatan Penyambungan Pelanggan
C21: - PB/PD Paskem TR Tanpa Perluasan Jaringan | D21: =ULP!K46 -> 100 | E21: =ULP!V46 -> 100 | F21: =ULP!AG46 -> 100 | G21: =ULP!AR46 -> 100 | H21: =ULP!BC46 -> 100
B22: 8 | C22: Organization Capital Readiness (OCR) | D22: =ULP!K48 -> 110 | E22: =ULP!V48 -> 110 | F22: =ULP!AG48 -> 110 | G22: =ULP!AR48 -> 78.485472 | H22: =ULP!BC48 -> 84.527461
B23: 9 | C23: Maturity Level Kepatuhan | D23: =ULP!#REF! -> #REF! | E23: =ULP!#REF! -> #REF! | F23: =ULP!#REF! -> #REF! | G23: =ULP!#REF! -> #REF! | H23: =ULP!#REF! -> #REF!
B24: 10 | C24: Pengelolaan Revenue Assurence
C25: a. Update Data Pelanggan | D25: =ULP!#REF! -> #REF! | E25: =ULP!#REF! -> #REF! | F25: =ULP!#REF! -> #REF! | G25: =ULP!#REF! -> #REF! | H25: =ULP!#REF! -> #REF!
C26: b. Migrasi VKRN 41 dan VKRN 42 | D26: =ULP!K49 -> 93.472631 | E26: =ULP!V49 -> 110 | F26: =ULP!AG49 -> 110 | G26: =ULP!AR49 -> 76.647386 | H26: =ULP!BC49 -> 68.506645
B27: 11 | C27: Migrasi LPB | D27: =ULP!K53 -> 0 | E27: =ULP!V53 -> 0 | F27: =ULP!AG53 -> 0 | G27: =ULP!AR53 -> 0 | H27: =ULP!BC53 -> 0
B28: 12 | C28: Eksekusi Program Peningkatan Keandalan dan Efisiensi Distribusi (NNC)
C29: a. Eksekusi Program Keandalan Distribusi | D29: =ULP!K56 -> 0 | E29: =ULP!V56 -> 0 | F29: =ULP!AG56 -> 0 | G29: =ULP!AR56 -> 0 | H29: =ULP!BC56 -> 0
C30: b. Eksekusi P2TL | D30: =ULP!#REF! -> #REF! | E30: =ULP!#REF! -> #REF! | F30: =ULP!#REF! -> #REF! | G30: =ULP!#REF! -> #REF! | H30: =ULP!#REF! -> #REF!
B31: 13 | C31: Kepatuhan
C32: a. Keselamatan Ketenagalistrikan
C33: b. Pengelolaan Lingkungan Hidup
C34: c. Ketepatan Penyampaian Laporan dan Akurasi Data Kinerja
C35: d.Pemenuhan TMP
B36: TOTAL PENILAIAN | D36: =ULP!L58 -> 98.94 | E36: =RANK!D6 -> 103.42 | F36: =ULP!AH58 -> 105.5 | G36: =ULP!AS58 -> 99.85 | H36: =ULP!BD58 -> 103.42

Sheet scoreboard
B2: KPI | C2: Target | D2: Real
A3: Key Performance Indicators
B4: Pertumbuhan Penjualan Tenaga Listrik | C4: ='UP3'!G9 -> 0 | D4: ='UP3'!H9 -> 0 | E4: =D4/C4 -> #DIV/0! | F4: =IF(E4>1,1,E4) -> #DIV/0! | G4: =1-F4 -> #DIV/0!
B5: Delta Daya Tersambung | C5: ='UP3'!G10 -> 233.89 | D5: ='UP3'!H10 -> 196.05712 | E5: =D5/C5 -> 0.83824498 | F5: =IF(E5>1,1,E5) -> 0.83824498 | G5: =1-F5 -> 0.16175502
B6: kWh Jual Multiguna Non Backfeeding | C6: ='UP3'!G17 -> 0 | D6: ='UP3'!H17 -> 0 | E6: =D6/C6 -> #DIV/0! | F6: =IF(E6>1,1,E6) -> #DIV/0! | G6: =1-F6 -> #DIV/0!
B7: Pertumbuhan Penjualan Layanan Khusus | C7: ='UP3'!#REF! -> #REF! | D7: ='UP3'!#REF! -> #REF! | E7: =D7/C7 -> #REF! | F7: =IF(E7>1,1,E7) -> #REF! | G7: =1-F7 -> #REF!
B8: Penambahan Pelanggan Premium | C8: ='UP3'!G18 -> 0 | D8: ='UP3'!H18 -> 0 | E8: =D8/C8 -> #DIV/0! | F8: =IF(E8>1,1,E8) -> #DIV/0! | G8: =1-F8 -> #DIV/0!
B9: Susut Jaringan (Tanpa E-Min) | C9: ='UP3'!G19 -> 148 | D9: ='UP3'!H19 -> 115 | E9: =2-(D9/C9) -> 1.222973 | F9: =IF(E9>1,1,E9) -> 1 | G9: =1-F9 -> 0
B10: SAIDI sesuai kewenangannya | C10: ='UP3'!G21 -> 5 | D10: ='UP3'!H21 -> 3 | E10: =2-(D10/C10) -> 1.4 | F10: =IF(E10>1,1,E10) -> 1 | G10: =1-F10 -> 0
B11: SAIFI sesuai kewenangannya | C11: ='UP3'!G22 -> 0 | D11: ='UP3'!H22 -> 0 | E11: =2-(D11/C11) -> #DIV/0! | F11: =IF(E11>1,1,E11) -> #DIV/0! | G11: =1-F11 -> #DIV/0!
B12: Energy Not Served | C12: ='UP3'!G24 -> 0.04 | D12: ='UP3'!H24 -> 0 | E12: =2-(D12/C12) -> 2 | F12: =IF(E12>1,1,E12) -> 1 | G12: =1-F12 -> 0
B13: Implementasi PLN Mobile | C13: ='UP3'!G25 -> 4.9 | D13: 100 | E13: =D13/C13 -> 20.408163 | F13: =IF(E13>1,1,E13) -> 1 | G13: =1-F13 -> 0
B14: Jumlah Komplain Pelanggan | C14: ='UP3'!#REF! -> #REF! | D14: ='UP3'!#REF! -> #REF! | E14: =D14/C14 -> #REF! | F14: 0 | G14: =1-F14 -> 1
B15: Aging Complaint | C15: ='UP3'!G33 -> 0 | D15: ='UP3'!H33 -> 0 | E15: =2-(D15/C15) -> #DIV/0! | F15: =IF(E15>1,1,E15) -> #DIV/0! | G15: =1-F15 -> #DIV/0!
B16: Rata-Rata Rasio Tunggakan | C16: ='UP3'!G38 -> 864 | D16: ='UP3'!H38 -> 939 | E16: =2-(D16/C16) -> 0.91319444 | F16: =IF(E16>1,1,E16) -> 0.91319444 | G16: =1-F16 -> 0.086805556
B17: Jumlah ULP NIHIL | C17: ='UP3'!G41 -> 21521.791 | D17: ='UP3'!H41 -> 74417.7 | E17: =D17/C17 -> 3.4577838 | F17: =IF(E17>1,1,E17) -> 1 | G17: =1-F17 -> 0
B18: Migrasi LPB pelanggan menunggak berulang | C18: ='UP3'!G42 -> 0 | D18: ='UP3'!H42 -> 0 | E18: =D18/C18 -> #DIV/0! | F18: =IF(E18>1,1,E18) -> #DIV/0! | G18: =1-F18 -> #DIV/0!
B19: BPP - Opex Non Fuel | C19: ='UP3'!G46 -> 1175 | D19: ='UP3'!H46 -> 1001.412 | E19: =2-(D19/C19) -> 1.1477345 | F19: =IF(E19>1,1,E19) -> 1 | G19: =1-F19 -> 0
B20: CF Pembangkit Non BBM | C20: ='UP3'!G50 -> 95-100 | D20: ='UP3'!H50 -> 90.3 | E20: =D20/C20 -> #VALUE! | F20: =IF(E20>1,1,E20) -> #VALUE! | G20: =1-F20 -> #VALUE!
B21: SFC PLTD PLN | C21: ='UP3'!G51 -> 0 | D21: ='UP3'!H51 -> 0 | E21: =2-(D21/C21) -> #DIV/0! | F21: =IF(E21>1,1,E21) -> #DIV/0! | G21: =1-F21 -> #DIV/0!
B22: ='UP3'!B53 -> Manajemen SDM, Komunikasi, dan TJSL | C22: ='UP3'!G53 -> 0 | D22: ='UP3'!H53 -> 0 | E22: =D22/C22 -> #DIV/0! | F22: =E22 -> #DIV/0! | G22: =1-F22 -> #DIV/0! | AO22: 264116
B23: ='UP3'!B55 -> b. Produktivitas Unit | C23: ='UP3'!G55 -> 100 | D23: ='UP3'!H55 -> 90 | E23: =D23/C23 -> 0.9 | F23: =IF(E23>1,1,E23) -> 0.9 | G23: =1-F23 -> 0.1 | AO23: =AO22-39 -> 264077
B24: ='UP3'!B56 -> c. Pengelolaan Komunikasi dan TJSL | C24: ='UP3'!G56 -> 100 | D24: ='UP3'!H56 -> 110 | E24: 100 | F24: =IF(E24>1,1,E24) -> 1 | G24: =1-F24 -> 0
B25: ='UP3'!B60 -> b. Maturity Level Gudang | C25: ='UP3'!G60 -> 3.65 | D25: ='UP3'!H60 -> 3.65 | E25: 100 | F25: =IF(E25>1,1,E25) -> 1 | G25: =1-F25 -> 0
B26: ='UP3'!B61 -> c. Maturity Level Sustainbility | C26: ='UP3'!G61 -> 100 | D26: ='UP3'!H61 -> 110 | E26: =D26/C26 -> 1.1 | F26: =IF(E26>1,1,E26) -> 1 | G26: =1-F26 -> 0
B27: ='UP3'!B62 -> d. Implementasi Roadmap Perbaikan Penerapan Manajemen Risiko dan Pencapaian Perlakuan Risiko | C27: ='UP3'!G62 -> 100 | D27: ='UP3'!H62 -> 100 | E27: =D27/C27 -> 1 | F27: =IF(E27>1,1,E27) -> 1 | G27: =1-F27 -> 0
B28: ='UP3'!B63 -> Kepatuhan : | C28: ='UP3'!G63 -> 0 | D28: ='UP3'!H63 -> 0 | E28: =D28/C28 -> #DIV/0! | F28: =IF(E28>1,1,E28) -> #DIV/0! | G28: =1-F28 -> #DIV/0!
B29: ='UP3'!B64 -> a. Pengelolaan K3, Keamanan dan Lingkungan Hidup | C29: ='UP3'!G64 -> 0 | D29: ='UP3'!H64 -> 0 | E29: 100 | F29: =IF(E29>1,1,E29) -> 1 | G29: =1-F29 -> 0
B30: ='UP3'!B66 -> c. Ketepatan penyampaian pelaporan dan Akurasi Data Kinerja | C30: ='UP3'!G66 -> 0 | D30: ='UP3'!H66 -> 0 | E30: 100 | F30: =IF(E30>1,1,E30) -> 1 | G30: =1-F30 -> 0
B39: SAIDI | C39: ='UP3'!G21 -> 5 | D39: ='UP3'!H21 -> 3 | E39: =2-(D39/C39) -> 1.4 | F39: =IF(E39>1,1,E39) -> 1 | G39: =1-F39 -> 0
B40: Rasio Tunggakan | C40: ='UP3'!G38 -> 864 | D40: ='UP3'!H38 -> 939 | E40: =2-(D40/C40) -> 0.91319444 | F40: =IF(E40>1,1,E40) -> 0.91319444 | G40: =1-F40 -> 0.086805556
B41: Multiguna | C41: ='UP3'!G17 -> 0 | D41: ='UP3'!H17 -> 0 | E41: =D41/C41 -> #DIV/0! | F41: =IF(E41>1,1,E41) -> #DIV/0! | G41: =1-F41 -> #DIV/0!
B42: RE 99 % | C42: ='UP3'!G55 -> 100 | D42: ='UP3'!H55 -> 90 | E42: =D42/C42 -> 0.9 | F42: =IF(E42>1,1,E42) -> 0.9 | G42: =1-F42 -> 0.1
B43: Komplain Pelanggan | C43: ='UP3'!#REF! -> #REF! | D43: ='UP3'!#REF! -> #REF! | E43: =D43/C43 -> #REF! | F43: 0 | G43: =1-F43 -> 1

Sheet TRACK
B2: Unit | C2: Nilai Kinerja Organisasi (NKO)
C3: Jan | D3: Feb | E3: Mar | F3: Apr | G3: May | H3: Jun | I3: Jul | J3: Aug | K3: Sep | L3: Oct | M3: Nov | N3: Dec
B4: ULP Tolitoli Khusus
B5: ULP Leok
B6: ULP Bangkir
B7: ULP Kotaraya
B8: UP3 Tolitoli | C8: =DETAIL!J43 -> #REF! | D8: =DETAIL!P43 -> #REF! | E8: =DETAIL!V43 -> #REF! | F8: =DETAIL!AB43 -> #N/A

Sheet DETAIL
B1: KONTRAK MANAJEMEN 2022
B2: PT PLN (PERSERO) UIW SULUTTENGGO
B3: UP3 TOLITOLI
A4: NO | B4: KPI | D4: SATUAN | F4: JAN | L4: FEB | R4: MAR | X4: APRIL | AD4: MEI
F5: BOBOT | G5: TARGET | H5: REAL | I5: PENCAPAIAN | J5: NILAI | L5: BOBOT | M5: TARGET | N5: REAL | O5: PENCAPAIAN | P5: NILAI | R5: BOBOT | S5: TARGET | T5: REAL | U5: PENCAPAIAN | V5: NILAI | X5: BOBOT | Y5: TARGET | Z5: REAL | AA5: PENCAPAIAN | AB5: NILAI | AD5: BOBOT | AE5: TARGET | AF5: REAL | AG5: PENCAPAIAN | AH5: NILAI
A6: 1 | B6: 2 | D6: 3 | F6: 4 | G6: 6 | H6: 7 | I6: 8 | J6: 9 | L6: 4 | M6: 6 | N6: 7 | O6: 8 | P6: 9 | R6: 4 | S6: 6 | T6: 7 | U6: 8 | V6: 9 | X6: 4 | Y6: 6 | Z6: 7 | AA6: 8 | AB6: 9 | AD6: 4 | AE6: 6 | AF6: 7 | AG6: 8 | AH6: 9
A7: =T.UP3!A7 -> I | B7: =T.UP3!B7 -> Key Performance Indikator | F7: =SUM(F8:F10) -> 28 | J7: =SUM(J8:J10) -> 15.4 | L7: =SUM(L8:L10) -> 28 | P7: =SUM(P8:P10) -> 15.4 | R7: =SUM(R8:R10) -> 28 | V7: =SUM(V8:V10) -> 15.126234 | X7: =SUM(X8:X10) -> #N/A | AB7: =SUM(AB8:AB10) -> #N/A | AD7: =SUM(AD8:AD10) -> #N/A | AH7: =SUM(AH8:AH10) -> #N/A
A8: =T.UP3!A8 -> 1 | B8: =T.UP3!B8 -> Penjualan Tenaga Listrik | C8: =T.UP3!C8 -> ñ | D8: =T.UP3!D8 -> GWh | F8: =IF(H8="N/A",0,T.UP3!$F$8) -> 14 | G8: =VLOOKUP($B$8,T.UP3!$B$4:$T$69,MATCH(DETAIL!$F$4,T.UP3!$B$5:$T$5,0),FALSE) -> 18.74 | H8: =VLOOKUP($B$8,'R.UP3'!$B$4:$S$54,MATCH(DETAIL!$F$4,'R.UP3'!$B$5:$S$5,0),FALSE) -> 22.980831 | I8: =IF(OR(G8="N/A",H8="N/A"),"N/A",IF(AND(G8=0,H8=0),0,H8/G8*100)) -> 122.62983 | J8: =IF(OR(I8="N/A",I8<0),0,IF(I8>110,F8*110/100,F8*I8/100)) -> 15.4 | L8: =IF(N8="N/A",0,T.UP3!$F$8) -> 14 | M8: =VLOOKUP($B$8,T.UP3!$B$4:$T$69,MATCH(DETAIL!$L$4,T.UP3!$B$5:$T$5,0),FALSE) -> 36.55 | N8: =VLOOKUP($B$8,'R.UP3'!$B$4:$S$54,MATCH(DETAIL!$L$4,'R.UP3'!$B$5:$S$5,0),FALSE) -> 42.202826 | O8: =IF(OR(M8="N/A",N8="N/A"),"N/A",IF(AND(M8=0,N8=0),0,N8/M8*100)) -> 115.46601 | P8: =IF(OR(O8="N/A",O8<0),0,IF(O8>110,L8*110/100,L8*O8/100)) -> 15.4 | R8: =IF(T8="N/A",0,T.UP3!$F$8) -> 14 | S8: =VLOOKUP($B$8,T.UP3!$B$4:$T$69,MATCH(DETAIL!$R$4,T.UP3!$B$5:$T$5,0),FALSE) -> 56.39 | T8: =VLOOKUP($B$8,'R.UP3'!$B$4:$S$54,MATCH(DETAIL!$R$4,'R.UP3'!$B$5:$S$5,0),FALSE) -> 60.926308 | U8: =IF(OR(S8="N/A",T8="N/A"),"N/A",IF(AND(S8=0,T8=0),0,T8/S8*100)) -> 108.04453 | V8: =IF(OR(U8="N/A",U8<0),0,IF(U8>110,R8*110/100,R8*U8/100)) -> 15.126234 | X8: =IF(Z8="N/A",0,T.UP3!$F$8) -> #N/A | Y8: =VLOOKUP($B$8,T.UP3!$B$4:$T$69,MATCH(DETAIL!$X$4,T.UP3!$B$5:$T$5,0),FALSE) -> #N/A | Z8: =VLOOKUP($B$8,'R.UP3'!$B$4:$S$54,MATCH(DETAIL!$X$4,'R.UP3'!$B$5:$S$5,0),FALSE) -> #N/A | AA8: =IF(OR(Y8="N/A",Z8="N/A"),"N/A",IF(AND(Y8=0,Z8=0),0,Z8/Y8*100)) -> #N/A | AB8: =IF(OR(AA8="N/A",AA8<0),0,IF(AA8>110,X8*110/100,X8*AA8/100)) -> #N/A | AD8: =IF(AF8="N/A",0,T.UP3!$F$8) -> #N/A | AE8: =VLOOKUP($B$8,T.UP3!$B$4:$T$69,MATCH(DETAIL!$AD$4,T.UP3!$B$5:$T$5,0),FALSE) -> #N/A | AF8: =VLOOKUP($B$8,'R.UP3'!$B$4:$S$54,MATCH(DETAIL!$AD$4,'R.UP3'!$B$5:$S$5,0),FALSE) -> #N/A | AG8: =IF(OR(AE8="N/A",AF8="N/A"),"N/A",IF(AND(AE8=0,AF8=0),0,AF8/AE8*100)) -> #N/A | AH8: =IF(OR(AG8="N/A",AG8<0),0,IF(AG8>110,AD8*110/100,AD8*AG8/100)) -> #N/A
A9: =T.UP3!A9 -> 2 | B9: =T.UP3!B9 -> Keandalan Sistem | C9: =T.UP3!C9 -> 0 | D9: =T.UP3!D9 -> 0 | F9: =IF(H9="N/A",0,T.UP3!$F$9) -> 14 | G9: =VLOOKUP($B$9,T.UP3!$B$4:$T$69,MATCH(DETAIL!$F$4,T.UP3!$B$5:$T$5,0),FALSE) -> 0 | H9: =VLOOKUP($B$9,'R.UP3'!$B$4:$S$54,MATCH(DETAIL!$F$4,'R.UP3'!$B$5:$S$5,0),FALSE) -> 0 | I9: =IF(OR(G9="N/A",H9="N/A"),"N/A",IF(AND(G9=0,H9=0),0,(2-H9/G9)*100)) -> 0 | J9: =IF(OR(I9="N/A",I9<0),0,IF(I9>110,F9*110/100,F9*I9/100)) -> 0 | L9: =IF(N9="N/A",0,T.UP3!$F$9) -> 14 | M9: =VLOOKUP($B$9,T.UP3!$B$4:$T$69,MATCH(DETAIL!$L$4,T.UP3!$B$5:$T$5,0),FALSE) -> 0 | N9: =VLOOKUP($B$9,'R.UP3'!$B$4:$S$54,MATCH(DETAIL!$L$4,'R.UP3'!$B$5:$S$5,0),FALSE) -> 0 | O9: =IF(OR(M9="N/A",N9="N/A"),"N/A",IF(AND(M9=0,N9=0),0,(2-N9/M9)*100)) -> 0 | P9: =IF(OR(O9="N/A",O9<0),0,IF(O9>110,L9*110/100,L9*O9/100)) -> 0 | R9: =IF(T9="N/A",0,T.UP3!$F$9) -> 14 | S9: =VLOOKUP($B$9,T.UP3!$B$4:$T$69,MATCH(DETAIL!$R$4,T.UP3!$B$5:$T$5,0),FALSE) -> 0 | T9: =VLOOKUP($B$9,'R.UP3'!$B$4:$S$54,MATCH(DETAIL!$R$4,'R.UP3'!$B$5:$S$5,0),FALSE) -> 0 | U9: =IF(OR(S9="N/A",T9="N/A"),"N/A",IF(AND(S9=0,T9=0),0,(2-T9/S9)*100)) -> 0 | V9: =IF(OR(U9="N/A",U9<0),0,IF(U9>110,R9*110/100,R9*U9/100)) -> 0 | X9: =IF(Z9="N/A",0,T.UP3!$F$9) -> #N/A | Y9: =VLOOKUP($B$9,T.UP3!$B$4:$T$69,MATCH(DETAIL!$X$4,T.UP3!$B$5:$T$5,0),FALSE) -> #N/A | Z9: =VLOOKUP($B$9,'R.UP3'!$B$4:$S$54,MATCH(DETAIL!$X$4,'R.UP3'!$B$5:$S$5,0),FALSE) -> #N/A | AA9: =IF(OR(Y9="N/A",Z9="N/A"),"N/A",IF(AND(Y9=0,Z9=0),0,(2-Z9/Y9)*100)) -> #N/A | AB9: =IF(OR(AA9="N/A",AA9<0),0,IF(AA9>110,X9*110/100,X9*AA9/100)) -> #N/A | AD9: =IF(AF9="N/A",0,T.UP3!$F$9) -> #N/A | AE9: =VLOOKUP($B$9,T.UP3!$B$4:$T$69,MATCH(DETAIL!$AD$4,T.UP3!$B$5:$T$5,0),FALSE) -> #N/A | AF9: =VLOOKUP($B$9,'R.UP3'!$B$4:$S$54,MATCH(DETAIL!$AD$4,'R.UP3'!$B$5:$S$5,0),FALSE) -> #N/A | AG9: =IF(OR(AE9="N/A",AF9="N/A"),"N/A",IF(AND(AE9=0,AF9=0),0,(2-AF9/AE9)*100)) -> #N/A | AH9: =IF(OR(AG9="N/A",AG9<0),0,IF(AG9>110,AD9*110/100,AD9*AG9/100)) -> #N/A
A10: =T.UP3!A10 -> 0 | B10: =T.UP3!B10 -> a. SAIDI Sesuai Kewenangannya | C10: =T.UP3!C10 -> ò | D10: =T.UP3!D10 -> Menit/Plg | F10: =IF(H10="N/A",0,T.UP3!$F$10) -> 0 | G10: =VLOOKUP($B$10,T.UP3!$B$4:$T$69,MATCH(DETAIL!$F$4,T.UP3!$B$5:$T$5,0),FALSE) -> 23.39 | H10: =VLOOKUP($B$10,'R.UP3'!$B$4:$S$54,MATCH(DETAIL!$F$4,'R.UP3'!$B$5:$S$5,0),FALSE) -> 12.366709 | I10: =IF(OR(G10="N/A",H10="N/A"),"N/A",IF(AND(G10=0,H10=0),0,H10/G10*100)) -> 52.871777 | J10: =IF(OR(I10="N/A",I10<0),0,IF(I10>110,F10*110/100,F10*I10/100)) -> 0 | L10: =IF(N10="N/A",0,T.UP3!$F$10) -> 0 | M10: =VLOOKUP($B$10,T.UP3!$B$4:$T$69,MATCH(DETAIL!$L$4,T.UP3!$B$5:$T$5,0),FALSE) -> 46.78 | N10: =VLOOKUP($B$10,'R.UP3'!$B$4:$S$54,MATCH(DETAIL!$L$4,'R.UP3'!$B$5:$S$5,0),FALSE) -> 14.217818 | O10: =IF(OR(M10="N/A",N10="N/A"),"N/A",IF(AND(M10=0,N10=0),0,N10/M10*100)) -> 30.392942 | P10: =IF(OR(O10="N/A",O10<0),0,IF(O10>110,L10*110/100,L10*O10/100)) -> 0 | R10: =IF(T10="N/A",0,T.UP3!$F$10) -> 0 | S10: =VLOOKUP($B$10,T.UP3!$B$4:$T$69,MATCH(DETAIL!$R$4,T.UP3!$B$5:$T$5,0),FALSE) -> 70.17 | T10: =VLOOKUP($B$10,'R.UP3'!$B$4:$S$54,MATCH(DETAIL!$R$4,'R.UP3'!$B$5:$S$5,0),FALSE) -> 15.90799 | U10: =IF(OR(S10="N/A",T10="N/A"),"N/A",IF(AND(S10=0,T10=0),0,T10/S10*100)) -> 22.670642 | V10: =IF(OR(U10="N/A",U10<0),0,IF(U10>110,R10*110/100,R10*U10/100)) -> 0 | X10: =IF(Z10="N/A",0,T.UP3!$F$10) -> #N/A | Y10: =VLOOKUP($B$10,T.UP3!$B$4:$T$69,MATCH(DETAIL!$X$4,T.UP3!$B$5:$T$5,0),FALSE) -> #N/A | Z10: =VLOOKUP($B$10,'R.UP3'!$B$4:$S$54,MATCH(DETAIL!$X$4,'R.UP3'!$B$5:$S$5,0),FALSE) -> #N/A | AA10: =IF(OR(Y10="N/A",Z10="N/A"),"N/A",IF(AND(Y10=0,Z10=0),0,Z10/Y10*100)) -> #N/A | AB10: =IF(OR(AA10="N/A",AA10<0),0,IF(AA10>110,X10*110/100,X10*AA10/100)) -> #N/A | AD10: =IF(AF10="N/A",0,T.UP3!$F$10) -> #N/A | AE10: =VLOOKUP($B$10,T.UP3!$B$4:$T$69,MATCH(DETAIL!$AD$4,T.UP3!$B$5:$T$5,0),FALSE) -> #N/A | AF10: =VLOOKUP($B$10,'R.UP3'!$B$4:$S$54,MATCH(DETAIL!$AD$4,'R.UP3'!$B$5:$S$5,0),FALSE) -> #N/A | AG10: =IF(OR(AE10="N/A",AF10="N/A"),"N/A",IF(AND(AE10=0,AF10=0),0,AF10/AE10*100)) -> #N/A | AH10: =IF(OR(AG10="N/A",AG10<0),0,IF(AG10>110,AD10*110/100,AD10*AG10/100)) -> #N/A
A11: =T.UP3!A17 -> II | B11: =T.UP3!B17 -> Perfomance Indicators | F11: =SUM(F12:F41) -> #REF! | J11: =SUM(J12:J41) -> #REF! | L11: =SUM(L12:L41) -> #REF! | P11: =SUM(P12:P41) -> #REF! | R11: =SUM(R12:R41) -> #REF! | V11: =SUM(V12:V41) -> #REF! | X11: =SUM(X12:X41) -> #N/A | AB11: =SUM(AB12:AB41) -> #N/A | AD11: =SUM(AD12:AD41) -> #N/A | AH11: =SUM(AH12:AH41) -> #N/A
A12: =T.UP3!A18 -> 4 | B12: =T.UP3!B18 -> Keandalan Jaringan Distribusi | C12: =T.UP3!C18 -> 0 | D12: =T.UP3!D18 -> 0 | F12: =IF(H12="N/A",0,T.UP3!$F$18) -> 6 | G12: =VLOOKUP($B$12,T.UP3!$B$4:$T$69,MATCH(DETAIL!$F$4,T.UP3!$B$5:$T$5,0),FALSE) -> 0 | H12: =VLOOKUP($B$12,'R.UP3'!$B$4:$S$54,MATCH(DETAIL!$F$4,'R.UP3'!$B$5:$S$5,0),FALSE) -> 0 | I12: =IF(OR(G12="N/A",H12="N/A"),"N/A",IF(AND(G12=0,H12=0),0,(2-H12/G12)*100)) -> 0 | J12: =IF(I12="N/A",0,IF(I12>110,F12*110/100,F12*I12/100)) -> 0 | L12: =IF(N12="N/A",0,T.UP3!$F$18) -> 6 | M12: =VLOOKUP($B$12,T.UP3!$B$4:$T$69,MATCH(DETAIL!$L$4,T.UP3!$B$5:$T$5,0),FALSE) -> 0 | N12: =VLOOKUP($B$12,'R.UP3'!$B$4:$S$54,MATCH(DETAIL!$L$4,'R.UP3'!$B$5:$S$5,0),FALSE) -> 0 | O12: =IF(OR(M12="N/A",N12="N/A"),"N/A",IF(AND(M12=0,N12=0),0,(2-N12/M12)*100)) -> 0 | P12: =IF(O12="N/A",0,IF(O12>110,L12*110/100,L12*O12/100)) -> 0 | R12: =IF(T12="N/A",0,T.UP3!$F$18) -> 6 | S12: =VLOOKUP($B$12,T.UP3!$B$4:$T$69,MATCH(DETAIL!$R$4,T.UP3!$B$5:$T$5,0),FALSE) -> 0 | T12: =VLOOKUP($B$12,'R.UP3'!$B$4:$S$54,MATCH(DETAIL!$R$4,'R.UP3'!$B$5:$S$5,0),FALSE) -> 0 | U12: =IF(OR(S12="N/A",T12="N/A"),"N/A",IF(AND(S12=0,T12=0),0,(2-T12/S12)*100)) -> 0 | V12: =IF(U12="N/A",0,IF(U12>110,R12*110/100,R12*U12/100)) -> 0 | X12: =IF(Z12="N/A",0,T.UP3!$F$18) -> #N/A | Y12: =VLOOKUP($B$12,T.UP3!$B$4:$T$69,MATCH(DETAIL!$X$4,T.UP3!$B$5:$T$5,0),FALSE) -> #N/A | Z12: =VLOOKUP($B$12,'R.UP3'!$B$4:$S$54,MATCH(DETAIL!$X$4,'R.UP3'!$B$5:$S$5,0),FALSE) -> #N/A | AA12: =IF(OR(Y12="N/A",Z12="N/A"),"N/A",IF(AND(Y12=0,Z12=0),0,(2-Z12/Y12)*100)) -> #N/A | AB12: =IF(AA12="N/A",0,IF(AA12>110,X12*110/100,X12*AA12/100)) -> #N/A | AD12: =IF(AF12="N/A",0,T.UP3!$F$18) -> #N/A | AE12: =VLOOKUP($B$12,T.UP3!$B$4:$T$69,MATCH(DETAIL!$AD$4,T.UP3!$B$5:$T$5,0),FALSE) -> #N/A | AF12: =VLOOKUP($B$12,'R.UP3'!$B$4:$S$54,MATCH(DETAIL!$AD$4,'R.UP3'!$B$5:$S$5,0),FALSE) -> #N/A | AG12: =IF(OR(AE12="N/A",AF12="N/A"),"N/A",IF(AND(AE12=0,AF12=0),0,(2-AF12/AE12)*100)) -> #N/A | AH12: =IF(AG12="N/A",0,IF(AG12>110,AD12*110/100,AD12*AG12/100)) -> #N/A
A13: =T.UP3!A19 -> 0 | B13: =T.UP3!B19 -> a. Gangguan TM > 5 Menit | C13: =T.UP3!C19 -> ò | D13: =T.UP3!D19 -> Kali | F13: =IF(H13="N/A",0,T.UP3!$F$19) -> 0 | G13: =VLOOKUP($B$13,T.UP3!$B$4:$T$69,MATCH(DETAIL!$F$4,T.UP3!$B$5:$T$5,0),FALSE) -> 15 | H13: =VLOOKUP($B$13,'R.UP3'!$B$4:$S$54,MATCH(DETAIL!$F$4,'R.UP3'!$B$5:$S$5,0),FALSE) -> 5 | I13: =IF(OR(G13="N/A",H13="N/A"),"N/A",IF(AND(G13=0,H13=0),0,(2-H13/G13)*100)) -> 166.66667 | J13: =IF(I13="N/A",0,IF(I13>110,F13*110/100,F13*I13/100)) -> 0 | L13: =IF(N13="N/A",0,T.UP3!$F$19) -> 0 | M13: =VLOOKUP($B$13,T.UP3!$B$4:$T$69,MATCH(DETAIL!$L$4,T.UP3!$B$5:$T$5,0),FALSE) -> 29 | N13: =VLOOKUP($B$13,'R.UP3'!$B$4:$S$54,MATCH(DETAIL!$L$4,'R.UP3'!$B$5:$S$5,0),FALSE) -> 10 | O13: =IF(OR(M13="N/A",N13="N/A"),"N/A",IF(AND(M13=0,N13=0),0,(2-N13/M13)*100)) -> 165.51724 | P13: =IF(O13="N/A",0,IF(O13>110,L13*110/100,L13*O13/100)) -> 0 | R13: =IF(T13="N/A",0,T.UP3!$F$19) -> 0 | S13: =VLOOKUP($B$13,T.UP3!$B$4:$T$69,MATCH(DETAIL!$R$4,T.UP3!$B$5:$T$5,0),FALSE) -> 45 | T13: =VLOOKUP($B$13,'R.UP3'!$B$4:$S$54,MATCH(DETAIL!$R$4,'R.UP3'!$B$5:$S$5,0),FALSE) -> 32 | U13: =IF(OR(S13="N/A",T13="N/A"),"N/A",IF(AND(S13=0,T13=0),0,(2-T13/S13)*100)) -> 128.88889 | V13: =IF(U13="N/A",0,IF(U13>110,R13*110/100,R13*U13/100)) -> 0 | X13: =IF(Z13="N/A",0,T.UP3!$F$19) -> #N/A | Y13: =VLOOKUP($B$13,T.UP3!$B$4:$T$69,MATCH(DETAIL!$X$4,T.UP3!$B$5:$T$5,0),FALSE) -> #N/A | Z13: =VLOOKUP($B$13,'R.UP3'!$B$4:$S$54,MATCH(DETAIL!$X$4,'R.UP3'!$B$5:$S$5,0),FALSE) -> #N/A | AA13: =IF(OR(Y13="N/A",Z13="N/A"),"N/A",IF(AND(Y13=0,Z13=0),0,(2-Z13/Y13)*100)) -> #N/A | AB13: =IF(AA13="N/A",0,IF(AA13>110,X13*110/100,X13*AA13/100)) -> #N/A | AD13: =IF(AF13="N/A",0,T.UP3!$F$19) -> #N/A | AE13: =VLOOKUP($B$13,T.UP3!$B$4:$T$69,MATCH(DETAIL!$AD$4,T.UP3!$B$5:$T$5,0),FALSE) -> #N/A | AF13: =VLOOKUP($B$13,'R.UP3'!$B$4:$S$54,MATCH(DETAIL!$AD$4,'R.UP3'!$B$5:$S$5,0),FALSE) -> #N/A | AG13: =IF(OR(AE13="N/A",AF13="N/A"),"N/A",IF(AND(AE13=0,AF13=0),0,(2-AF13/AE13)*100)) -> #N/A | AH13: =IF(AG13="N/A",0,IF(AG13>110,AD13*110/100,AD13*AG13/100)) -> #N/A
A14: =T.UP3!A20 -> 0 | B14: =T.UP3!B20 -> b. Gangguan TM ≤ 5 Menit | C14: =T.UP3!C20 -> ò | D14: =T.UP3!D20 -> Kali | F14: =IF(H14="N/A",0,T.UP3!$F$20) -> 0 | G14: =VLOOKUP($B$14,T.UP3!$B$4:$T$69,MATCH(DETAIL!$F$4,T.UP3!$B$5:$T$5,0),FALSE) -> 17 | H14: =VLOOKUP($B$14,'R.UP3'!$B$4:$S$54,MATCH(DETAIL!$F$4,'R.UP3'!$B$5:$S$5,0),FALSE) -> 1 | I14: =IF(OR(G14="N/A",H14="N/A"),"N/A",IF(AND(G14=0,H14=0),0,(2-H14/G14)*100)) -> 194.11765 | J14: =IF(I14="N/A",0,IF(I14>110,F14*110/100,F14*I14/100)) -> 0 | L14: =IF(N14="N/A",0,T.UP3!$F$20) -> 0 | M14: =VLOOKUP($B$14,T.UP3!$B$4:$T$69,MATCH(DETAIL!$L$4,T.UP3!$B$5:$T$5,0),FALSE) -> 31 | N14: =VLOOKUP($B$14,'R.UP3'!$B$4:$S$54,MATCH(DETAIL!$L$4,'R.UP3'!$B$5:$S$5,0),FALSE) -> 18 | O14: =IF(OR(M14="N/A",N14="N/A"),"N/A",IF(AND(M14=0,N14=0),0,(2-N14/M14)*100)) -> 141.93548 | P14: =IF(O14="N/A",0,IF(O14>110,L14*110/100,L14*O14/100)) -> 0 | R14: =IF(T14="N/A",0,T.UP3!$F$20) -> 0 | S14: =VLOOKUP($B$14,T.UP3!$B$4:$T$69,MATCH(DETAIL!$R$4,T.UP3!$B$5:$T$5,0),FALSE) -> 48 | T14: =VLOOKUP($B$14,'R.UP3'!$B$4:$S$54,MATCH(DETAIL!$R$4,'R.UP3'!$B$5:$S$5,0),FALSE) -> 21 | U14: =IF(OR(S14="N/A",T14="N/A"),"N/A",IF(AND(S14=0,T14=0),0,(2-T14/S14)*100)) -> 156.25 | V14: =IF(U14="N/A",0,IF(U14>110,R14*110/100,R14*U14/100)) -> 0 | X14: =IF(Z14="N/A",0,T.UP3!$F$20) -> #N/A | Y14: =VLOOKUP($B$14,T.UP3!$B$4:$T$69,MATCH(DETAIL!$X$4,T.UP3!$B$5:$T$5,0),FALSE) -> #N/A | Z14: =VLOOKUP($B$14,'R.UP3'!$B$4:$S$54,MATCH(DETAIL!$X$4,'R.UP3'!$B$5:$S$5,0),FALSE) -> #N/A | AA14: =IF(OR(Y14="N/A",Z14="N/A"),"N/A",IF(AND(Y14=0,Z14=0),0,(2-Z14/Y14)*100)) -> #N/A | AB14: =IF(AA14="N/A",0,IF(AA14>110,X14*110/100,X14*AA14/100)) -> #N/A | AD14: =IF(AF14="N/A",0,T.UP3!$F$20) -> #N/A | AE14: =VLOOKUP($B$14,T.UP3!$B$4:$T$69,MATCH(DETAIL!$AD$4,T.UP3!$B$5:$T$5,0),FALSE) -> #N/A | AF14: =VLOOKUP($B$14,'R.UP3'!$B$4:$S$54,MATCH(DETAIL!$AD$4,'R.UP3'!$B$5:$S$5,0),FALSE) -> #N/A | AG14: =IF(OR(AE14="N/A",AF14="N/A"),"N/A",IF(AND(AE14=0,AF14=0),0,(2-AF14/AE14)*100)) -> #N/A | AH14: =IF(AG14="N/A",0,IF(AG14>110,AD14*110/100,AD14*AG14/100)) -> #N/A
A15: =T.UP3!A21 -> 0 | B15: =T.UP3!B21 -> c. Kerusakan Peralatan Distribusi (PHB TM dan Trafo) Sesuai Kewenangan
B16: =T.UP3!B22 -> Peningkatan Layanan | C16: =T.UP3!C22 -> 0 | D16: =T.UP3!D22 -> 0 | F16: =IF(H16="N/A",0,T.UP3!$F$22) -> 6 | G16: =VLOOKUP($B$16,T.UP3!$B$4:$T$69,MATCH(DETAIL!$F$4,T.UP3!$B$5:$T$5,0),FALSE) -> 0 | H16: =VLOOKUP($B$16,'R.UP3'!$B$4:$S$54,MATCH(DETAIL!$F$4,'R.UP3'!$B$5:$S$5,0),FALSE) -> 0 | I16: =IF(OR(G16="N/A",H16="N/A"),"N/A",IF(AND(G16=0,H16=0),0,(2-H16/G16)*100)) -> 0 | J16: =IF(I16="N/A",0,IF(I16>110,F16*110/100,F16*I16/100)) -> 0 | L16: =IF(N16="N/A",0,T.UP3!$F$22) -> 6 | M16: =VLOOKUP($B$16,T.UP3!$B$4:$T$69,MATCH(DETAIL!$L$4,T.UP3!$B$5:$T$5,0),FALSE) -> 0 | N16: =VLOOKUP($B$16,'R.UP3'!$B$4:$S$54,MATCH(DETAIL!$L$4,'R.UP3'!$B$5:$S$5,0),FALSE) -> 0 | O16: =IF(OR(M16="N/A",N16="N/A"),"N/A",IF(AND(M16=0,N16=0),0,(2-N16/M16)*100)) -> 0 | P16: =IF(O16="N/A",0,IF(O16>110,L16*110/100,L16*O16/100)) -> 0 | R16: =IF(T16="N/A",0,T.UP3!$F$22) -> 6 | S16: =VLOOKUP($B$16,T.UP3!$B$4:$T$69,MATCH(DETAIL!$R$4,T.UP3!$B$5:$T$5,0),FALSE) -> 0 | T16: =VLOOKUP($B$16,'R.UP3'!$B$4:$S$54,MATCH(DETAIL!$R$4,'R.UP3'!$B$5:$S$5,0),FALSE) -> 0 | U16: =IF(OR(S16="N/A",T16="N/A"),"N/A",IF(AND(S16=0,T16=0),0,(2-T16/S16)*100)) -> 0 | V16: =IF(U16="N/A",0,IF(U16>110,R16*110/100,R16*U16/100)) -> 0 | X16: =IF(Z16="N/A",0,T.UP3!$F$22) -> #N/A | Y16: =VLOOKUP($B$16,T.UP3!$B$4:$T$69,MATCH(DETAIL!$X$4,T.UP3!$B$5:$T$5,0),FALSE) -> #N/A | Z16: =VLOOKUP($B$16,'R.UP3'!$B$4:$S$54,MATCH(DETAIL!$X$4,'R.UP3'!$B$5:$S$5,0),FALSE) -> #N/A | AA16: =IF(OR(Y16="N/A",Z16="N/A"),"N/A",IF(AND(Y16=0,Z16=0),0,(2-Z16/Y16)*100)) -> #N/A | AB16: =IF(AA16="N/A",0,IF(AA16>110,X16*110/100,X16*AA16/100)) -> #N/A | AD16: =IF(AF16="N/A",0,T.UP3!$F$22) -> #N/A | AE16: =VLOOKUP($B$16,T.UP3!$B$4:$T$69,MATCH(DETAIL!$AD$4,T.UP3!$B$5:$T$5,0),FALSE) -> #N/A | AF16: =VLOOKUP($B$16,'R.UP3'!$B$4:$S$54,MATCH(DETAIL!$AD$4,'R.UP3'!$B$5:$S$5,0),FALSE) -> #N/A | AG16: =IF(OR(AE16="N/A",AF16="N/A"),"N/A",IF(AND(AE16=0,AF16=0),0,(2-AF16/AE16)*100)) -> #N/A | AH16: =IF(AG16="N/A",0,IF(AG16>110,AD16*110/100,AD16*AG16/100)) -> #N/A
B17: =T.UP3!B24 -> b. Pengaduan Gangguan Berulang pada PLN Mobile | C17: =T.UP3!C24 -> ò | D17: =T.UP3!D24 -> % | F17: =IF(H17="N/A",0,T.UP3!$F$24) -> 0 | G17: =VLOOKUP($B$17,T.UP3!$B$4:$T$69,MATCH(DETAIL!$F$4,T.UP3!$B$5:$T$5,0),FALSE) -> 0.04 | H17: =VLOOKUP($B$17,'R.UP3'!$B$4:$S$54,MATCH(DETAIL!$F$4,'R.UP3'!$B$5:$S$5,0),FALSE) -> 0 | I17: =IF(OR(G17="N/A",H17="N/A"),"N/A",IF(AND(G17=0,H17=0),0,(2-H17/G17)*100)) -> 200 | J17: =IF(I17="N/A",0,IF(I17>110,F17*110/100,F17*I17/100)) -> 0 | L17: =IF(N17="N/A",0,T.UP3!$F$24) -> 0 | M17: =VLOOKUP($B$17,T.UP3!$B$4:$T$69,MATCH(DETAIL!$L$4,T.UP3!$B$5:$T$5,0),FALSE) -> 0.04 | N17: =VLOOKUP($B$17,'R.UP3'!$B$4:$S$54,MATCH(DETAIL!$L$4,'R.UP3'!$B$5:$S$5,0),FALSE) -> 0 | O17: =IF(OR(M17="N/A",N17="N/A"),"N/A",IF(AND(M17=0,N17=0),0,(2-N17/M17)*100)) -> 200 | P17: =IF(O17="N/A",0,IF(O17>110,L17*110/100,L17*O17/100)) -> 0 | R17: =IF(T17="N/A",0,T.UP3!$F$24) -> 0 | S17: =VLOOKUP($B$17,T.UP3!$B$4:$T$69,MATCH(DETAIL!$R$4,T.UP3!$B$5:$T$5,0),FALSE) -> 0.04 | T17: =VLOOKUP($B$17,'R.UP3'!$B$4:$S$54,MATCH(DETAIL!$R$4,'R.UP3'!$B$5:$S$5,0),FALSE) -> 0 | U17: =IF(OR(S17="N/A",T17="N/A"),"N/A",IF(AND(S17=0,T17=0),0,(2-T17/S17)*100)) -> 200 | V17: =IF(U17="N/A",0,IF(U17>110,R17*110/100,R17*U17/100)) -> 0 | X17: =IF(Z17="N/A",0,T.UP3!$F$24) -> #N/A | Y17: =VLOOKUP($B$17,T.UP3!$B$4:$T$69,MATCH(DETAIL!$X$4,T.UP3!$B$5:$T$5,0),FALSE) -> #N/A | Z17: =VLOOKUP($B$17,'R.UP3'!$B$4:$S$54,MATCH(DETAIL!$X$4,'R.UP3'!$B$5:$S$5,0),FALSE) -> #N/A | AA17: =IF(OR(Y17="N/A",Z17="N/A"),"N/A",IF(AND(Y17=0,Z17=0),0,(2-Z17/Y17)*100)) -> #N/A | AB17: =IF(AA17="N/A",0,IF(AA17>110,X17*110/100,X17*AA17/100)) -> #N/A | AD17: =IF(AF17="N/A",0,T.UP3!$F$24) -> #N/A | AE17: =VLOOKUP($B$17,T.UP3!$B$4:$T$69,MATCH(DETAIL!$AD$4,T.UP3!$B$5:$T$5,0),FALSE) -> #N/A | AF17: =VLOOKUP($B$17,'R.UP3'!$B$4:$S$54,MATCH(DETAIL!$AD$4,'R.UP3'!$B$5:$S$5,0),FALSE) -> #N/A | AG17: =IF(OR(AE17="N/A",AF17="N/A"),"N/A",IF(AND(AE17=0,AF17=0),0,(2-AF17/AE17)*100)) -> #N/A | AH17: =IF(AG17="N/A",0,IF(AG17>110,AD17*110/100,AD17*AG17/100)) -> #N/A
A18: =T.UP3!A25 -> 0 | B18: =T.UP3!B25 -> c. Rating PLN Mobile | C18: =T.UP3!C25 -> ñ | D18: =T.UP3!D25 -> Rating | F18: =IF(H18="N/A",0,T.UP3!$F$25) -> 0 | G18: =VLOOKUP($B$18,T.UP3!$B$4:$T$69,MATCH(DETAIL!$F$4,T.UP3!$B$5:$T$5,0),FALSE) -> 4.9 | H18: =VLOOKUP($B$18,'R.UP3'!$B$4:$S$54,MATCH(DETAIL!$F$4,'R.UP3'!$B$5:$S$5,0),FALSE) -> 4.91 | I18: =IF(OR(G18="N/A",H18="N/A"),"N/A",IF(AND(G18=0,H18=0),0,H18/G18*100)) -> 100.20408 | J18: =IF(I18="N/A",0,IF(I18>110,F18*110/100,F18*I18/100)) -> 0 | L18: =IF(N18="N/A",0,T.UP3!$F$25) -> 0 | M18: =VLOOKUP($B$18,T.UP3!$B$4:$T$69,MATCH(DETAIL!$L$4,T.UP3!$B$5:$T$5,0),FALSE) -> 4.9 | N18: =VLOOKUP($B$18,'R.UP3'!$B$4:$S$54,MATCH(DETAIL!$L$4,'R.UP3'!$B$5:$S$5,0),FALSE) -> 4.91 | O18: =IF(OR(M18="N/A",N18="N/A"),"N/A",IF(AND(M18=0,N18=0),0,N18/M18*100)) -> 100.20408 | P18: =IF(O18="N/A",0,IF(O18>110,L18*110/100,L18*O18/100)) -> 0 | R18: =IF(T18="N/A",0,T.UP3!$F$25) -> 0 | S18: =VLOOKUP($B$18,T.UP3!$B$4:$T$69,MATCH(DETAIL!$R$4,T.UP3!$B$5:$T$5,0),FALSE) -> 4.9 | T18: =VLOOKUP($B$18,'R.UP3'!$B$4:$S$54,MATCH(DETAIL!$R$4,'R.UP3'!$B$5:$S$5,0),FALSE) -> 4.91 | U18: =IF(OR(S18="N/A",T18="N/A"),"N/A",IF(AND(S18=0,T18=0),0,T18/S18*100)) -> 100.20408 | V18: =IF(U18="N/A",0,IF(U18>110,R18*110/100,R18*U18/100)) -> 0 | X18: =IF(Z18="N/A",0,T.UP3!$F$25) -> #N/A | Y18: =VLOOKUP($B$18,T.UP3!$B$4:$T$69,MATCH(DETAIL!$X$4,T.UP3!$B$5:$T$5,0),FALSE) -> #N/A | Z18: =VLOOKUP($B$18,'R.UP3'!$B$4:$S$54,MATCH(DETAIL!$X$4,'R.UP3'!$B$5:$S$5,0),FALSE) -> #N/A | AA18: =IF(OR(Y18="N/A",Z18="N/A"),"N/A",IF(AND(Y18=0,Z18=0),0,Z18/Y18*100)) -> #N/A | AB18: =IF(AA18="N/A",0,IF(AA18>110,X18*110/100,X18*AA18/100)) -> #N/A | AD18: =IF(AF18="N/A",0,T.UP3!$F$25) -> #N/A | AE18: =VLOOKUP($B$18,T.UP3!$B$4:$T$69,MATCH(DETAIL!$AD$4,T.UP3!$B$5:$T$5,0),FALSE) -> #N/A | AF18: =VLOOKUP($B$18,'R.UP3'!$B$4:$S$54,MATCH(DETAIL!$AD$4,'R.UP3'!$B$5:$S$5,0),FALSE) -> #N/A | AG18: =IF(OR(AE18="N/A",AF18="N/A"),"N/A",IF(AND(AE18=0,AF18=0),0,AF18/AE18*100)) -> #N/A | AH18: =IF(AG18="N/A",0,IF(AG18>110,AD18*110/100,AD18*AG18/100)) -> #N/A
A19: =T.UP3!#REF! -> #REF! | B19: =T.UP3!#REF! -> #REF!
B20: =T.UP3!B26 -> d. Jumlah Kali Transaksi Keuangan melalui PLN Mobile | C20: =T.UP3!C26 -> ñ | D20: =T.UP3!D26 -> Kali Transaksi | F20: =IF(H20="N/A",0,T.UP3!$F$26) -> 0 | G20: =VLOOKUP($B$20,T.UP3!$B$4:$T$69,MATCH(DETAIL!$F$4,T.UP3!$B$5:$T$5,0),FALSE) -> 5386 | H20: =VLOOKUP($B$20,'R.UP3'!$B$4:$S$54,MATCH(DETAIL!$F$4,'R.UP3'!$B$5:$S$5,0),FALSE) -> 2781 | I20: =IF(OR(G20="N/A",H20="N/A"),"N/A",IF(AND(G20=0,H20=0),0,IF(H20<0,0,(2-H20/G20)*100))) -> 148.36613 | J20: =IF(OR(I20="N/A",I20<0),0,IF(I20>110,F20*110/100,F20*I20/100)) -> 0 | L20: =IF(N20="N/A",0,T.UP3!$F$26) -> 0 | M20: =VLOOKUP($B$20,T.UP3!$B$4:$T$69,MATCH(DETAIL!$L$4,T.UP3!$B$5:$T$5,0),FALSE) -> 10253 | N20: =VLOOKUP($B$20,'R.UP3'!$B$4:$S$54,MATCH(DETAIL!$L$4,'R.UP3'!$B$5:$S$5,0),FALSE) -> 6163 | O20: =IF(OR(M20="N/A",N20="N/A"),"N/A",IF(AND(M20=0,N20=0),0,IF(N20<0,0,(2-N20/M20)*100))) -> 139.89076 | P20: =IF(OR(O20="N/A",O20<0),0,IF(O20>110,L20*110/100,L20*O20/100)) -> 0 | R20: =IF(T20="N/A",0,T.UP3!$F$26) -> 0 | S20: =VLOOKUP($B$20,T.UP3!$B$4:$T$69,MATCH(DETAIL!$R$4,T.UP3!$B$5:$T$5,0),FALSE) -> 15641 | T20: =VLOOKUP($B$20,'R.UP3'!$B$4:$S$54,MATCH(DETAIL!$R$4,'R.UP3'!$B$5:$S$5,0),FALSE) -> 16349 | U20: =IF(OR(S20="N/A",T20="N/A"),"N/A",IF(AND(S20=0,T20=0),0,IF(T20<0,0,(2-T20/S20)*100))) -> 95.473435 | V20: =IF(OR(U20="N/A",U20<0),0,IF(U20>110,R20*110/100,R20*U20/100)) -> 0 | X20: =IF(Z20="N/A",0,T.UP3!$F$26) -> #N/A | Y20: =VLOOKUP($B$20,T.UP3!$B$4:$T$69,MATCH(DETAIL!$X$4,T.UP3!$B$5:$T$5,0),FALSE) -> #N/A | Z20: =VLOOKUP($B$20,'R.UP3'!$B$4:$S$54,MATCH(DETAIL!$X$4,'R.UP3'!$B$5:$S$5,0),FALSE) -> #N/A | AA20: =IF(OR(Y20="N/A",Z20="N/A"),"N/A",IF(AND(Y20=0,Z20=0),0,IF(Z20<0,0,(2-Z20/Y20)*100))) -> #N/A | AB20: =IF(OR(AA20="N/A",AA20<0),0,IF(AA20>110,X20*110/100,X20*AA20/100)) -> #N/A | AD20: =IF(AF20="N/A",0,T.UP3!$F$26) -> #N/A | AE20: =VLOOKUP($B$20,T.UP3!$B$4:$T$69,MATCH(DETAIL!$AD$4,T.UP3!$B$5:$T$5,0),FALSE) -> #N/A | AF20: =VLOOKUP($B$20,'R.UP3'!$B$4:$S$54,MATCH(DETAIL!$AD$4,'R.UP3'!$B$5:$S$5,0),FALSE) -> #N/A | AG20: =IF(OR(AE20="N/A",AF20="N/A"),"N/A",IF(AND(AE20=0,AF20=0),0,IF(AF20<0,0,(2-AF20/AE20)*100))) -> #N/A | AH20: =IF(OR(AG20="N/A",AG20<0),0,IF(AG20>110,AD20*110/100,AD20*AG20/100)) -> #N/A
B21: =T.UP3!#REF! -> #REF! | C21: =T.UP3!#REF! -> #REF! | D21: =T.UP3!#REF! -> #REF! | F21: =IF(H21="N/A",0,T.UP3!#REF!) -> #REF! | G21: =VLOOKUP($B$21,T.UP3!$B$4:$T$69,MATCH(DETAIL!$F$4,T.UP3!$B$5:$T$5,0),FALSE) -> #REF! | H21: =VLOOKUP($B$21,'R.UP3'!$B$4:$S$54,MATCH(DETAIL!$F$4,'R.UP3'!$B$5:$S$5,0),FALSE) -> #REF! | I21: =IF(OR(G21="N/A",H21="N/A"),"N/A",IF(AND(G21=0,H21=0),0,(2-H21/G21)*100)) -> #REF! | J21: =IF(OR(I21="N/A",I21<0),0,IF(I21>110,F21*110/100,F21*I21/100)) -> #REF! | L21: =IF(N21="N/A",0,T.UP3!#REF!) -> #REF! | M21: =VLOOKUP($B$21,T.UP3!$B$4:$T$69,MATCH(DETAIL!$L$4,T.UP3!$B$5:$T$5,0),FALSE) -> #REF! | N21: =VLOOKUP($B$21,'R.UP3'!$B$4:$S$54,MATCH(DETAIL!$L$4,'R.UP3'!$B$5:$S$5,0),FALSE) -> #REF! | O21: =IF(OR(M21="N/A",N21="N/A"),"N/A",IF(AND(M21=0,N21=0),0,(2-N21/M21)*100)) -> #REF! | P21: =IF(OR(O21="N/A",O21<0),0,IF(O21>110,L21*110/100,L21*O21/100)) -> #REF! | R21: =IF(T21="N/A",0,T.UP3!#REF!) -> #REF! | S21: =VLOOKUP($B$21,T.UP3!$B$4:$T$69,MATCH(DETAIL!$R$4,T.UP3!$B$5:$T$5,0),FALSE) -> #REF! | T21: =VLOOKUP($B$21,'R.UP3'!$B$4:$S$54,MATCH(DETAIL!$R$4,'R.UP3'!$B$5:$S$5,0),FALSE) -> #REF! | U21: =IF(OR(S21="N/A",T21="N/A"),"N/A",IF(AND(S21=0,T21=0),0,(2-T21/S21)*100)) -> #REF! | V21: =IF(OR(U21="N/A",U21<0),0,IF(U21>110,R21*110/100,R21*U21/100)) -> #REF! | X21: =IF(Z21="N/A",0,T.UP3!#REF!) -> #REF! | Y21: =VLOOKUP($B$21,T.UP3!$B$4:$T$69,MATCH(DETAIL!$X$4,T.UP3!$B$5:$T$5,0),FALSE) -> #REF! | Z21: =VLOOKUP($B$21,'R.UP3'!$B$4:$S$54,MATCH(DETAIL!$X$4,'R.UP3'!$B$5:$S$5,0),FALSE) -> #REF! | AA21: =IF(OR(Y21="N/A",Z21="N/A"),"N/A",IF(AND(Y21=0,Z21=0),0,(2-Z21/Y21)*100)) -> #REF! | AB21: =IF(OR(AA21="N/A",AA21<0),0,IF(AA21>110,X21*110/100,X21*AA21/100)) -> #REF! | AD21: =IF(AF21="N/A",0,T.UP3!#REF!) -> #REF! | AE21: =VLOOKUP($B$21,T.UP3!$B$4:$T$69,MATCH(DETAIL!$AD$4,T.UP3!$B$5:$T$5,0),FALSE) -> #REF! | AF21: =VLOOKUP($B$21,'R.UP3'!$B$4:$S$54,MATCH(DETAIL!$AD$4,'R.UP3'!$B$5:$S$5,0),FALSE) -> #REF! | AG21: =IF(OR(AE21="N/A",AF21="N/A"),"N/A",IF(AND(AE21=0,AF21=0),0,(2-AF21/AE21)*100)) -> #REF! | AH21: =IF(OR(AG21="N/A",AG21<0),0,IF(AG21>110,AD21*110/100,AD21*AG21/100)) -> #REF!
A22: =T.UP3!A37 -> 0 | B22: =T.UP3!B37 -> b. Penambahan Jumlah Pelanggan | C22: =T.UP3!C37 -> ñ | D22: =T.UP3!D37 -> Pelanggan | F22: =IF(H22="N/A",0,T.UP3!$F$37) -> 2 | G22: =VLOOKUP($B$22,T.UP3!$B$4:$T$69,MATCH(DETAIL!$F$4,T.UP3!$B$5:$T$5,0),FALSE) -> 631 | H22: =VLOOKUP($B$22,'R.UP3'!$B$4:$S$54,MATCH(DETAIL!$F$4,'R.UP3'!$B$5:$S$5,0),FALSE) -> 498 | I22: =IF(OR(G22="N/A",H22="N/A"),"N/A",IF(AND(G22=0,H22=0),0,H22/G22*100)) -> 78.922345 | J22: =IF(OR(I22="N/A",I22<0),0,IF(I22>110,F22*110/100,F22*I22/100)) -> 1.5784469 | L22: =IF(N22="N/A",0,T.UP3!$F$37) -> 2 | M22: =VLOOKUP($B$22,T.UP3!$B$4:$T$69,MATCH(DETAIL!$L$4,T.UP3!$B$5:$T$5,0),FALSE) -> 1283 | N22: =VLOOKUP($B$22,'R.UP3'!$B$4:$S$54,MATCH(DETAIL!$L$4,'R.UP3'!$B$5:$S$5,0),FALSE) -> 965 | O22: =IF(OR(M22="N/A",N22="N/A"),"N/A",IF(AND(M22=0,N22=0),0,N22/M22*100)) -> 75.214341 | P22: =IF(OR(O22="N/A",O22<0),0,IF(O22>110,L22*110/100,L22*O22/100)) -> 1.5042868 | R22: =IF(T22="N/A",0,T.UP3!$F$37) -> 2 | S22: =VLOOKUP($B$22,T.UP3!$B$4:$T$69,MATCH(DETAIL!$R$4,T.UP3!$B$5:$T$5,0),FALSE) -> 1968 | T22: =VLOOKUP($B$22,'R.UP3'!$B$4:$S$54,MATCH(DETAIL!$R$4,'R.UP3'!$B$5:$S$5,0),FALSE) -> 1364 | U22: =IF(OR(S22="N/A",T22="N/A"),"N/A",IF(AND(S22=0,T22=0),0,T22/S22*100)) -> 69.308943 | V22: =IF(OR(U22="N/A",U22<0),0,IF(U22>110,R22*110/100,R22*U22/100)) -> 1.3861789 | X22: =IF(Z22="N/A",0,T.UP3!$F$37) -> #N/A | Y22: =VLOOKUP($B$22,T.UP3!$B$4:$T$69,MATCH(DETAIL!$X$4,T.UP3!$B$5:$T$5,0),FALSE) -> #N/A | Z22: =VLOOKUP($B$22,'R.UP3'!$B$4:$S$54,MATCH(DETAIL!$X$4,'R.UP3'!$B$5:$S$5,0),FALSE) -> #N/A | AA22: =IF(OR(Y22="N/A",Z22="N/A"),"N/A",IF(AND(Y22=0,Z22=0),0,Z22/Y22*100)) -> #N/A | AB22: =IF(OR(AA22="N/A",AA22<0),0,IF(AA22>110,X22*110/100,X22*AA22/100)) -> #N/A | AD22: =IF(AF22="N/A",0,T.UP3!$F$37) -> #N/A | AE22: =VLOOKUP($B$22,T.UP3!$B$4:$T$69,MATCH(DETAIL!$AD$4,T.UP3!$B$5:$T$5,0),FALSE) -> #N/A | AF22: =VLOOKUP($B$22,'R.UP3'!$B$4:$S$54,MATCH(DETAIL!$AD$4,'R.UP3'!$B$5:$S$5,0),FALSE) -> #N/A | AG22: =IF(OR(AE22="N/A",AF22="N/A"),"N/A",IF(AND(AE22=0,AF22=0),0,AF22/AE22*100)) -> #N/A | AH22: =IF(OR(AG22="N/A",AG22<0),0,IF(AG22>110,AD22*110/100,AD22*AG22/100)) -> #N/A
A23: =T.UP3!A40 -> 0 | B23: =T.UP3!B40 -> e. Penambahan Jumlah Pelanggan Rumah Tangga Lisdes | C23: =T.UP3!C40 -> ñ | D23: =T.UP3!D40 -> Pelanggan | F23: =IF(H23="N/A",0,T.UP3!$F$40) -> 1.5 | G23: =VLOOKUP($B$23,T.UP3!$B$4:$T$69,MATCH(DETAIL!$F$4,T.UP3!$B$5:$T$5,0),FALSE) -> 3 | H23: =VLOOKUP($B$23,'R.UP3'!$B$4:$S$54,MATCH(DETAIL!$F$4,'R.UP3'!$B$5:$S$5,0),FALSE) -> 50 | I23: =IF(OR(G23="N/A",H23="N/A"),"N/A",IF(AND(G23=0,H23=0),0,H23/G23*100)) -> 1666.6667 | J23: =IF(OR(I23="N/A",I23<0),0,IF(I23>110,F23*110/100,F23*I23/100)) -> 1.65 | L23: =IF(N23="N/A",0,T.UP3!$F$40) -> 1.5 | M23: =VLOOKUP($B$23,T.UP3!$B$4:$T$69,MATCH(DETAIL!$L$4,T.UP3!$B$5:$T$5,0),FALSE) -> 4 | N23: =VLOOKUP($B$23,'R.UP3'!$B$4:$S$54,MATCH(DETAIL!$L$4,'R.UP3'!$B$5:$S$5,0),FALSE) -> 71 | O23: =IF(OR(M23="N/A",N23="N/A"),"N/A",IF(AND(M23=0,N23=0),0,N23/M23*100)) -> 1775 | P23: =IF(OR(O23="N/A",O23<0),0,IF(O23>110,L23*110/100,L23*O23/100)) -> 1.65 | R23: =IF(T23="N/A",0,T.UP3!$F$40) -> 1.5 | S23: =VLOOKUP($B$23,T.UP3!$B$4:$T$69,MATCH(DETAIL!$R$4,T.UP3!$B$5:$T$5,0),FALSE) -> 4 | T23: =VLOOKUP($B$23,'R.UP3'!$B$4:$S$54,MATCH(DETAIL!$R$4,'R.UP3'!$B$5:$S$5,0),FALSE) -> 87 | U23: =IF(OR(S23="N/A",T23="N/A"),"N/A",IF(AND(S23=0,T23=0),0,T23/S23*100)) -> 2175 | V23: =IF(OR(U23="N/A",U23<0),0,IF(U23>110,R23*110/100,R23*U23/100)) -> 1.65 | X23: =IF(Z23="N/A",0,T.UP3!$F$40) -> #N/A | Y23: =VLOOKUP($B$23,T.UP3!$B$4:$T$69,MATCH(DETAIL!$X$4,T.UP3!$B$5:$T$5,0),FALSE) -> #N/A | Z23: =VLOOKUP($B$23,'R.UP3'!$B$4:$S$54,MATCH(DETAIL!$X$4,'R.UP3'!$B$5:$S$5,0),FALSE) -> #N/A | AA23: =IF(OR(Y23="N/A",Z23="N/A"),"N/A",IF(AND(Y23=0,Z23=0),0,Z23/Y23*100)) -> #N/A | AB23: =IF(OR(AA23="N/A",AA23<0),0,IF(AA23>110,X23*110/100,X23*AA23/100)) -> #N/A | AD23: =IF(AF23="N/A",0,T.UP3!$F$40) -> #N/A | AE23: =VLOOKUP($B$23,T.UP3!$B$4:$T$69,MATCH(DETAIL!$AD$4,T.UP3!$B$5:$T$5,0),FALSE) -> #N/A | AF23: =VLOOKUP($B$23,'R.UP3'!$B$4:$S$54,MATCH(DETAIL!$AD$4,'R.UP3'!$B$5:$S$5,0),FALSE) -> #N/A | AG23: =IF(OR(AE23="N/A",AF23="N/A"),"N/A",IF(AND(AE23=0,AF23=0),0,AF23/AE23*100)) -> #N/A | AH23: =IF(OR(AG23="N/A",AG23<0),0,IF(AG23>110,AD23*110/100,AD23*AG23/100)) -> #N/A
A24: =T.UP3!A42 -> 10 | B24: =T.UP3!B42 -> Pengelolaan Pembacaan Meter | C24: =T.UP3!C42 -> 0 | D24: =T.UP3!D42 -> 0 | F24: =IF(H24="N/A",0,T.UP3!$F$42) -> 4 | G24: =VLOOKUP($B$24,T.UP3!$B$4:$T$69,MATCH(DETAIL!$F$4,T.UP3!$B$5:$T$5,0),FALSE) -> 0 | H24: =VLOOKUP($B$24,'R.UP3'!$B$4:$S$54,MATCH(DETAIL!$F$4,'R.UP3'!$B$5:$S$5,0),FALSE) -> 0 | I24: =IF(OR(G24="N/A",H24="N/A"),"N/A",IF(AND(G24=0,H24=0),0,H24/G24*100)) -> 0 | J24: =IF(OR(I24="N/A",I24<0),0,IF(I24>110,F24*110/100,F24*I24/100)) -> 0 | L24: =IF(N24="N/A",0,T.UP3!$F$42) -> 4 | M24: =VLOOKUP($B$24,T.UP3!$B$4:$T$69,MATCH(DETAIL!$L$4,T.UP3!$B$5:$T$5,0),FALSE) -> 0 | N24: =VLOOKUP($B$24,'R.UP3'!$B$4:$S$54,MATCH(DETAIL!$L$4,'R.UP3'!$B$5:$S$5,0),FALSE) -> 0 | O24: =IF(OR(M24="N/A",N24="N/A"),"N/A",IF(AND(M24=0,N24=0),0,N24/M24*100)) -> 0 | P24: =IF(OR(O24="N/A",O24<0),0,IF(O24>110,L24*110/100,L24*O24/100)) -> 0 | R24: =IF(T24="N/A",0,T.UP3!$F$42) -> 4 | S24: =VLOOKUP($B$24,T.UP3!$B$4:$T$69,MATCH(DETAIL!$R$4,T.UP3!$B$5:$T$5,0),FALSE) -> 0 | T24: =VLOOKUP($B$24,'R.UP3'!$B$4:$S$54,MATCH(DETAIL!$R$4,'R.UP3'!$B$5:$S$5,0),FALSE) -> 0 | U24: =IF(OR(S24="N/A",T24="N/A"),"N/A",IF(AND(S24=0,T24=0),0,T24/S24*100)) -> 0 | V24: =IF(OR(U24="N/A",U24<0),0,IF(U24>110,R24*110/100,R24*U24/100)) -> 0 | X24: =IF(Z24="N/A",0,T.UP3!$F$42) -> #N/A | Y24: =VLOOKUP($B$24,T.UP3!$B$4:$T$69,MATCH(DETAIL!$X$4,T.UP3!$B$5:$T$5,0),FALSE) -> #N/A | Z24: =VLOOKUP($B$24,'R.UP3'!$B$4:$S$54,MATCH(DETAIL!$X$4,'R.UP3'!$B$5:$S$5,0),FALSE) -> #N/A | AA24: =IF(OR(Y24="N/A",Z24="N/A"),"N/A",IF(AND(Y24=0,Z24=0),0,Z24/Y24*100)) -> #N/A | AB24: =IF(OR(AA24="N/A",AA24<0),0,IF(AA24>110,X24*110/100,X24*AA24/100)) -> #N/A | AD24: =IF(AF24="N/A",0,T.UP3!$F$42) -> #N/A | AE24: =VLOOKUP($B$24,T.UP3!$B$4:$T$69,MATCH(DETAIL!$AD$4,T.UP3!$B$5:$T$5,0),FALSE) -> #N/A | AF24: =VLOOKUP($B$24,'R.UP3'!$B$4:$S$54,MATCH(DETAIL!$AD$4,'R.UP3'!$B$5:$S$5,0),FALSE) -> #N/A | AG24: =IF(OR(AE24="N/A",AF24="N/A"),"N/A",IF(AND(AE24=0,AF24=0),0,AF24/AE24*100)) -> #N/A | AH24: =IF(OR(AG24="N/A",AG24<0),0,IF(AG24>110,AD24*110/100,AD24*AG24/100)) -> #N/A
A25: =T.UP3!A43 -> 0 | B25: =T.UP3!B43 -> a. Jumlah Pengguna Swa Cam
B26: =T.UP3!#REF! -> #REF! | C26: =T.UP3!#REF! -> #REF! | D26: =T.UP3!#REF! -> #REF! | F26: =IF(H26="N/A",0,T.UP3!#REF!) -> #REF! | G26: =VLOOKUP($B$26,T.UP3!$B$4:$T$69,MATCH(DETAIL!$F$4,T.UP3!$B$5:$T$5,0),FALSE) -> #REF! | H26: =VLOOKUP($B$26,'R.UP3'!$B$4:$S$54,MATCH(DETAIL!$F$4,'R.UP3'!$B$5:$S$5,0),FALSE) -> #REF! | I26: =IF(OR(G26="N/A",H26="N/A"),"N/A",IF(AND(G26=0,H26=0),0,H26/G26*100)) -> #REF! | J26: =IF(OR(I26="N/A",I26<0),0,IF(I26>110,F26*110/100,F26*I26/100)) -> #REF! | L26: =IF(N26="N/A",0,T.UP3!#REF!) -> #REF! | M26: =VLOOKUP($B$26,T.UP3!$B$4:$T$69,MATCH(DETAIL!$L$4,T.UP3!$B$5:$T$5,0),FALSE) -> #REF! | N26: =VLOOKUP($B$26,'R.UP3'!$B$4:$S$54,MATCH(DETAIL!$L$4,'R.UP3'!$B$5:$S$5,0),FALSE) -> #REF! | O26: =IF(OR(M26="N/A",N26="N/A"),"N/A",IF(AND(M26=0,N26=0),0,N26/M26*100)) -> #REF! | P26: =IF(OR(O26="N/A",O26<0),0,IF(O26>110,L26*110/100,L26*O26/100)) -> #REF! | R26: =IF(T26="N/A",0,T.UP3!#REF!) -> #REF! | S26: =VLOOKUP($B$26,T.UP3!$B$4:$T$69,MATCH(DETAIL!$R$4,T.UP3!$B$5:$T$5,0),FALSE) -> #REF! | T26: =VLOOKUP($B$26,'R.UP3'!$B$4:$S$54,MATCH(DETAIL!$R$4,'R.UP3'!$B$5:$S$5,0),FALSE) -> #REF! | U26: =IF(OR(S26="N/A",T26="N/A"),"N/A",IF(AND(S26=0,T26=0),0,T26/S26*100)) -> #REF! | V26: =IF(OR(U26="N/A",U26<0),0,IF(U26>110,R26*110/100,R26*U26/100)) -> #REF! | X26: =IF(Z26="N/A",0,T.UP3!#REF!) -> #REF! | Y26: =VLOOKUP($B$26,T.UP3!$B$4:$T$69,MATCH(DETAIL!$X$4,T.UP3!$B$5:$T$5,0),FALSE) -> #REF! | Z26: =VLOOKUP($B$26,'R.UP3'!$B$4:$S$54,MATCH(DETAIL!$X$4,'R.UP3'!$B$5:$S$5,0),FALSE) -> #REF! | AA26: =IF(OR(Y26="N/A",Z26="N/A"),"N/A",IF(AND(Y26=0,Z26=0),0,Z26/Y26*100)) -> #REF! | AB26: =IF(OR(AA26="N/A",AA26<0),0,IF(AA26>110,X26*110/100,X26*AA26/100)) -> #REF! | AD26: =IF(AF26="N/A",0,T.UP3!#REF!) -> #REF! | AE26: =VLOOKUP($B$26,T.UP3!$B$4:$T$69,MATCH(DETAIL!$AD$4,T.UP3!$B$5:$T$5,0),FALSE) -> #REF! | AF26: =VLOOKUP($B$26,'R.UP3'!$B$4:$S$54,MATCH(DETAIL!$AD$4,'R.UP3'!$B$5:$S$5,0),FALSE) -> #REF! | AG26: =IF(OR(AE26="N/A",AF26="N/A"),"N/A",IF(AND(AE26=0,AF26=0),0,AF26/AE26*100)) -> #REF! | AH26: =IF(OR(AG26="N/A",AG26<0),0,IF(AG26>110,AD26*110/100,AD26*AG26/100)) -> #REF!
B27: =T.UP3!B46 -> a. Pencapaian Rata-Rata Saldo Tanggal 20 diluar Konsumen Instansi (Kementerian & Lembaga)
B28: =T.UP3!B50 -> a. Pengendalian Penggunaan Anggaran Investasi sesuai RKAP | C28: =T.UP3!C50 -> ó | D28: =T.UP3!D50 -> % | F28: =IF(H28="N/A",0,T.UP3!$F$50) -> 0 | G28: =VLOOKUP($B$28,T.UP3!$B$4:$T$69,MATCH(DETAIL!$F$4,T.UP3!$B$5:$T$5,0),FALSE) -> 95-100 | H28: =VLOOKUP($B$28,'R.UP3'!$B$4:$S$54,MATCH(DETAIL!$F$4,'R.UP3'!$B$5:$S$5,0),FALSE) -> 100 | I28: =IF(OR(G28="N/A",H28="N/A"),"N/A",IF(AND(G28=0,H28=0),0,(2-H28/G28)*100)) -> #VALUE! | J28: =IF(OR(I28="N/A",I28<0),0,IF(I28>110,F28*110/100,F28*I28/100)) -> #VALUE! | L28: =IF(N28="N/A",0,T.UP3!$F$50) -> 0 | M28: =VLOOKUP($B$28,T.UP3!$B$4:$T$69,MATCH(DETAIL!$L$4,T.UP3!$B$5:$T$5,0),FALSE) -> 95-100 | N28: =VLOOKUP($B$28,'R.UP3'!$B$4:$S$54,MATCH(DETAIL!$L$4,'R.UP3'!$B$5:$S$5,0),FALSE) -> 100 | O28: =IF(OR(M28="N/A",N28="N/A"),"N/A",IF(AND(M28=0,N28=0),0,(2-N28/M28)*100)) -> #VALUE! | P28: =IF(OR(O28="N/A",O28<0),0,IF(O28>110,L28*110/100,L28*O28/100)) -> #VALUE! | R28: =IF(T28="N/A",0,T.UP3!$F$50) -> 0 | S28: =VLOOKUP($B$28,T.UP3!$B$4:$T$69,MATCH(DETAIL!$R$4,T.UP3!$B$5:$T$5,0),FALSE) -> 95-100 | T28: =VLOOKUP($B$28,'R.UP3'!$B$4:$S$54,MATCH(DETAIL!$R$4,'R.UP3'!$B$5:$S$5,0),FALSE) -> 39.55 | U28: =IF(OR(S28="N/A",T28="N/A"),"N/A",IF(AND(S28=0,T28=0),0,(2-T28/S28)*100)) -> #VALUE! | V28: =IF(OR(U28="N/A",U28<0),0,IF(U28>110,R28*110/100,R28*U28/100)) -> #VALUE! | X28: =IF(Z28="N/A",0,T.UP3!$F$50) -> #N/A | Y28: =VLOOKUP($B$28,T.UP3!$B$4:$T$69,MATCH(DETAIL!$X$4,T.UP3!$B$5:$T$5,0),FALSE) -> #N/A | Z28: =VLOOKUP($B$28,'R.UP3'!$B$4:$S$54,MATCH(DETAIL!$X$4,'R.UP3'!$B$5:$S$5,0),FALSE) -> #N/A | AA28: =IF(OR(Y28="N/A",Z28="N/A"),"N/A",IF(AND(Y28=0,Z28=0),0,(2-Z28/Y28)*100)) -> #N/A | AB28: =IF(OR(AA28="N/A",AA28<0),0,IF(AA28>110,X28*110/100,X28*AA28/100)) -> #N/A | AD28: =IF(AF28="N/A",0,T.UP3!$F$50) -> #N/A | AE28: =VLOOKUP($B$28,T.UP3!$B$4:$T$69,MATCH(DETAIL!$AD$4,T.UP3!$B$5:$T$5,0),FALSE) -> #N/A | AF28: =VLOOKUP($B$28,'R.UP3'!$B$4:$S$54,MATCH(DETAIL!$AD$4,'R.UP3'!$B$5:$S$5,0),FALSE) -> #N/A | AG28: =IF(OR(AE28="N/A",AF28="N/A"),"N/A",IF(AND(AE28=0,AF28=0),0,(2-AF28/AE28)*100)) -> #N/A | AH28: =IF(OR(AG28="N/A",AG28<0),0,IF(AG28>110,AD28*110/100,AD28*AG28/100)) -> #N/A
B29: =T.UP3!#REF! -> #REF! | C29: =T.UP3!#REF! -> #REF! | D29: =T.UP3!#REF! -> #REF! | F29: =IF(H29="N/A",0,T.UP3!#REF!) -> #REF! | G29: =VLOOKUP($B$29,T.UP3!$B$4:$T$69,MATCH(DETAIL!$F$4,T.UP3!$B$5:$T$5,0),FALSE) -> #REF! | H29: =VLOOKUP($B$29,'R.UP3'!$B$4:$S$54,MATCH(DETAIL!$F$4,'R.UP3'!$B$5:$S$5,0),FALSE) -> #REF! | I29: =IF(OR(G29="N/A",H29="N/A"),"N/A",IF(AND(G29=0,H29=0),0,(2-H29/G29)*100)) -> #REF! | J29: =IF(OR(I29="N/A",I29<0),0,IF(I29>110,F29*110/100,F29*I29/100)) -> #REF! | L29: =IF(N29="N/A",0,T.UP3!#REF!) -> #REF! | M29: =VLOOKUP($B$29,T.UP3!$B$4:$T$69,MATCH(DETAIL!$L$4,T.UP3!$B$5:$T$5,0),FALSE) -> #REF! | N29: =VLOOKUP($B$29,'R.UP3'!$B$4:$S$54,MATCH(DETAIL!$L$4,'R.UP3'!$B$5:$S$5,0),FALSE) -> #REF! | O29: =IF(OR(M29="N/A",N29="N/A"),"N/A",IF(AND(M29=0,N29=0),0,(2-N29/M29)*100)) -> #REF! | P29: =IF(OR(O29="N/A",O29<0),0,IF(O29>110,L29*110/100,L29*O29/100)) -> #REF! | R29: =IF(T29="N/A",0,T.UP3!#REF!) -> #REF! | S29: =VLOOKUP($B$29,T.UP3!$B$4:$T$69,MATCH(DETAIL!$R$4,T.UP3!$B$5:$T$5,0),FALSE) -> #REF! | T29: =VLOOKUP($B$29,'R.UP3'!$B$4:$S$54,MATCH(DETAIL!$R$4,'R.UP3'!$B$5:$S$5,0),FALSE) -> #REF! | U29: =IF(OR(S29="N/A",T29="N/A"),"N/A",IF(AND(S29=0,T29=0),0,(2-T29/S29)*100)) -> #REF! | V29: =IF(OR(U29="N/A",U29<0),0,IF(U29>110,R29*110/100,R29*U29/100)) -> #REF! | X29: =IF(Z29="N/A",0,T.UP3!#REF!) -> #REF! | Y29: =VLOOKUP($B$29,T.UP3!$B$4:$T$69,MATCH(DETAIL!$X$4,T.UP3!$B$5:$T$5,0),FALSE) -> #REF! | Z29: =VLOOKUP($B$29,'R.UP3'!$B$4:$S$54,MATCH(DETAIL!$X$4,'R.UP3'!$B$5:$S$5,0),FALSE) -> #REF! | AA29: =IF(OR(Y29="N/A",Z29="N/A"),"N/A",IF(AND(Y29=0,Z29=0),0,(2-Z29/Y29)*100)) -> #REF! | AB29: =IF(OR(AA29="N/A",AA29<0),0,IF(AA29>110,X29*110/100,X29*AA29/100)) -> #REF! | AD29: =IF(AF29="N/A",0,T.UP3!#REF!) -> #REF! | AE29: =VLOOKUP($B$29,T.UP3!$B$4:$T$69,MATCH(DETAIL!$AD$4,T.UP3!$B$5:$T$5,0),FALSE) -> #REF! | AF29: =VLOOKUP($B$29,'R.UP3'!$B$4:$S$54,MATCH(DETAIL!$AD$4,'R.UP3'!$B$5:$S$5,0),FALSE) -> #REF! | AG29: =IF(OR(AE29="N/A",AF29="N/A"),"N/A",IF(AND(AE29=0,AF29=0),0,(2-AF29/AE29)*100)) -> #REF! | AH29: =IF(OR(AG29="N/A",AG29<0),0,IF(AG29>110,AD29*110/100,AD29*AG29/100)) -> #REF!
B30: =T.UP3!#REF! -> #REF! | C30: =T.UP3!#REF! -> #REF! | D30: =T.UP3!#REF! -> #REF! | F30: =IF(H30="N/A",0,T.UP3!#REF!) -> #REF! | G30: =VLOOKUP($B$30,T.UP3!$B$4:$T$69,MATCH(DETAIL!$F$4,T.UP3!$B$5:$T$5,0),FALSE) -> #REF! | H30: =VLOOKUP($B$30,'R.UP3'!$B$4:$S$54,MATCH(DETAIL!$F$4,'R.UP3'!$B$5:$S$5,0),FALSE) -> #REF! | I30: =IF(OR(G30="N/A",H30="N/A"),"N/A",IF(AND(G30=0,H30=0),0,(2-H30/G30)*100)) -> #REF! | J30: =IF(OR(I30="N/A",I30<0),0,IF(I30>110,F30*110/100,F30*I30/100)) -> #REF! | L30: =IF(N30="N/A",0,T.UP3!#REF!) -> #REF! | M30: =VLOOKUP($B$30,T.UP3!$B$4:$T$69,MATCH(DETAIL!$L$4,T.UP3!$B$5:$T$5,0),FALSE) -> #REF! | N30: =VLOOKUP($B$30,'R.UP3'!$B$4:$S$54,MATCH(DETAIL!$L$4,'R.UP3'!$B$5:$S$5,0),FALSE) -> #REF! | O30: =IF(OR(M30="N/A",N30="N/A"),"N/A",IF(AND(M30=0,N30=0),0,(2-N30/M30)*100)) -> #REF! | P30: =IF(OR(O30="N/A",O30<0),0,IF(O30>110,L30*110/100,L30*O30/100)) -> #REF! | R30: =IF(T30="N/A",0,T.UP3!#REF!) -> #REF! | S30: =VLOOKUP($B$30,T.UP3!$B$4:$T$69,MATCH(DETAIL!$R$4,T.UP3!$B$5:$T$5,0),FALSE) -> #REF! | T30: =VLOOKUP($B$30,'R.UP3'!$B$4:$S$54,MATCH(DETAIL!$R$4,'R.UP3'!$B$5:$S$5,0),FALSE) -> #REF! | U30: =IF(OR(S30="N/A",T30="N/A"),"N/A",IF(AND(S30=0,T30=0),0,(2-T30/S30)*100)) -> #REF! | V30: =IF(OR(U30="N/A",U30<0),0,IF(U30>110,R30*110/100,R30*U30/100)) -> #REF! | X30: =IF(Z30="N/A",0,T.UP3!#REF!) -> #REF! | Y30: =VLOOKUP($B$30,T.UP3!$B$4:$T$69,MATCH(DETAIL!$X$4,T.UP3!$B$5:$T$5,0),FALSE) -> #REF! | Z30: =VLOOKUP($B$30,'R.UP3'!$B$4:$S$54,MATCH(DETAIL!$X$4,'R.UP3'!$B$5:$S$5,0),FALSE) -> #REF! | AA30: =IF(OR(Y30="N/A",Z30="N/A"),"N/A",IF(AND(Y30=0,Z30=0),0,(2-Z30/Y30)*100)) -> #REF! | AB30: =IF(OR(AA30="N/A",AA30<0),0,IF(AA30>110,X30*110/100,X30*AA30/100)) -> #REF! | AD30: =IF(AF30="N/A",0,T.UP3!#REF!) -> #REF! | AE30: =VLOOKUP($B$30,T.UP3!$B$4:$T$69,MATCH(DETAIL!$AD$4,T.UP3!$B$5:$T$5,0),FALSE) -> #REF! | AF30: =VLOOKUP($B$30,'R.UP3'!$B$4:$S$54,MATCH(DETAIL!$AD$4,'R.UP3'!$B$5:$S$5,0),FALSE) -> #REF! | AG30: =IF(OR(AE30="N/A",AF30="N/A"),"N/A",IF(AND(AE30=0,AF30=0),0,(2-AF30/AE30)*100)) -> #REF! | AH30: =IF(OR(AG30="N/A",AG30<0),0,IF(AG30>110,AD30*110/100,AD30*AG30/100)) -> #REF!
B31: =T.UP3!#REF! -> #REF! | C31: =T.UP3!#REF! -> #REF! | D31: =T.UP3!#REF! -> #REF! | F31: =IF(H31="N/A",0,T.UP3!#REF!) -> #REF! | G31: =VLOOKUP($B$31,T.UP3!$B$4:$T$69,MATCH(DETAIL!$F$4,T.UP3!$B$5:$T$5,0),FALSE) -> #REF! | H31: =VLOOKUP($B$31,'R.UP3'!$B$4:$S$54,MATCH(DETAIL!$F$4,'R.UP3'!$B$5:$S$5,0),FALSE) -> #REF! | I31: =IF(OR(G31="N/A",H31="N/A"),"N/A",IF(AND(G31=0,H31=0),0,H31/G31*100)) -> #REF! | J31: =IF(OR(I31="N/A",I31<0),0,IF(I31>110,F31*110/100,F31*I31/100)) -> #REF! | L31: =IF(N31="N/A",0,T.UP3!#REF!) -> #REF! | M31: =VLOOKUP($B$31,T.UP3!$B$4:$T$69,MATCH(DETAIL!$L$4,T.UP3!$B$5:$T$5,0),FALSE) -> #REF! | N31: =VLOOKUP($B$31,'R.UP3'!$B$4:$S$54,MATCH(DETAIL!$L$4,'R.UP3'!$B$5:$S$5,0),FALSE) -> #REF! | O31: =IF(OR(M31="N/A",N31="N/A"),"N/A",IF(AND(M31=0,N31=0),0,N31/M31*100)) -> #REF! | P31: =IF(OR(O31="N/A",O31<0),0,IF(O31>110,L31*110/100,L31*O31/100)) -> #REF! | R31: =IF(T31="N/A",0,T.UP3!#REF!) -> #REF! | S31: =VLOOKUP($B$31,T.UP3!$B$4:$T$69,MATCH(DETAIL!$R$4,T.UP3!$B$5:$T$5,0),FALSE) -> #REF! | T31: =VLOOKUP($B$31,'R.UP3'!$B$4:$S$54,MATCH(DETAIL!$R$4,'R.UP3'!$B$5:$S$5,0),FALSE) -> #REF! | U31: =IF(OR(S31="N/A",T31="N/A"),"N/A",IF(AND(S31=0,T31=0),0,T31/S31*100)) -> #REF! | V31: =IF(OR(U31="N/A",U31<0),0,IF(U31>110,R31*110/100,R31*U31/100)) -> #REF! | X31: =IF(Z31="N/A",0,T.UP3!#REF!) -> #REF! | Y31: =VLOOKUP($B$31,T.UP3!$B$4:$T$69,MATCH(DETAIL!$X$4,T.UP3!$B$5:$T$5,0),FALSE) -> #REF! | Z31: =VLOOKUP($B$31,'R.UP3'!$B$4:$S$54,MATCH(DETAIL!$X$4,'R.UP3'!$B$5:$S$5,0),FALSE) -> #REF! | AA31: =IF(OR(Y31="N/A",Z31="N/A"),"N/A",IF(AND(Y31=0,Z31=0),0,Z31/Y31*100)) -> #REF! | AB31: =IF(OR(AA31="N/A",AA31<0),0,IF(AA31>110,X31*110/100,X31*AA31/100)) -> #REF! | AD31: =IF(AF31="N/A",0,T.UP3!#REF!) -> #REF! | AE31: =VLOOKUP($B$31,T.UP3!$B$4:$T$69,MATCH(DETAIL!$AD$4,T.UP3!$B$5:$T$5,0),FALSE) -> #REF! | AF31: =VLOOKUP($B$31,'R.UP3'!$B$4:$S$54,MATCH(DETAIL!$AD$4,'R.UP3'!$B$5:$S$5,0),FALSE) -> #REF! | AG31: =IF(OR(AE31="N/A",AF31="N/A"),"N/A",IF(AND(AE31=0,AF31=0),0,AF31/AE31*100)) -> #REF! | AH31: =IF(OR(AG31="N/A",AG31<0),0,IF(AG31>110,AD31*110/100,AD31*AG31/100)) -> #REF!
B32: =T.UP3!B51 -> b. Usulan Penghapusan ATTB | C32: =T.UP3!C51 -> ñ | D32: =T.UP3!D51 -> Rp. Milyar | F32: =IF(H32="N/A",0,T.UP3!$F$51) -> 0 | G32: =VLOOKUP($B$32,T.UP3!$B$4:$T$69,MATCH(DETAIL!$F$4,T.UP3!$B$5:$T$5,0),FALSE) -> 0 | H32: =VLOOKUP($B$32,'R.UP3'!$B$4:$S$54,MATCH(DETAIL!$F$4,'R.UP3'!$B$5:$S$5,0),FALSE) -> 0 | I32: =IF(OR(G32="N/A",H32="N/A"),"N/A",IF(AND(G32=0,H32=0),0,H32/G32*100)) -> 0 | J32: =IF(OR(I32="N/A",I32<0),0,IF(I32>110,F32*110/100,F32*I32/100)) -> 0 | L32: =IF(N32="N/A",0,T.UP3!$F$51) -> 0 | M32: =VLOOKUP($B$32,T.UP3!$B$4:$T$69,MATCH(DETAIL!$L$4,T.UP3!$B$5:$T$5,0),FALSE) -> 0 | N32: =VLOOKUP($B$32,'R.UP3'!$B$4:$S$54,MATCH(DETAIL!$L$4,'R.UP3'!$B$5:$S$5,0),FALSE) -> 0 | O32: =IF(OR(M32="N/A",N32="N/A"),"N/A",IF(AND(M32=0,N32=0),0,N32/M32*100)) -> 0 | P32: =IF(OR(O32="N/A",O32<0),0,IF(O32>110,L32*110/100,L32*O32/100)) -> 0 | R32: =IF(T32="N/A",0,T.UP3!$F$51) -> 0 | S32: =VLOOKUP($B$32,T.UP3!$B$4:$T$69,MATCH(DETAIL!$R$4,T.UP3!$B$5:$T$5,0),FALSE) -> 0 | T32: =VLOOKUP($B$32,'R.UP3'!$B$4:$S$54,MATCH(DETAIL!$R$4,'R.UP3'!$B$5:$S$5,0),FALSE) -> 0 | U32: =IF(OR(S32="N/A",T32="N/A"),"N/A",IF(AND(S32=0,T32=0),0,T32/S32*100)) -> 0 | V32: =IF(OR(U32="N/A",U32<0),0,IF(U32>110,R32*110/100,R32*U32/100)) -> 0 | X32: =IF(Z32="N/A",0,T.UP3!$F$51) -> #N/A | Y32: =VLOOKUP($B$32,T.UP3!$B$4:$T$69,MATCH(DETAIL!$X$4,T.UP3!$B$5:$T$5,0),FALSE) -> #N/A | Z32: =VLOOKUP($B$32,'R.UP3'!$B$4:$S$54,MATCH(DETAIL!$X$4,'R.UP3'!$B$5:$S$5,0),FALSE) -> #N/A | AA32: =IF(OR(Y32="N/A",Z32="N/A"),"N/A",IF(AND(Y32=0,Z32=0),0,Z32/Y32*100)) -> #N/A | AB32: =IF(OR(AA32="N/A",AA32<0),0,IF(AA32>110,X32*110/100,X32*AA32/100)) -> #N/A | AD32: =IF(AF32="N/A",0,T.UP3!$F$51) -> #N/A | AE32: =VLOOKUP($B$32,T.UP3!$B$4:$T$69,MATCH(DETAIL!$AD$4,T.UP3!$B$5:$T$5,0),FALSE) -> #N/A | AF32: =VLOOKUP($B$32,'R.UP3'!$B$4:$S$54,MATCH(DETAIL!$AD$4,'R.UP3'!$B$5:$S$5,0),FALSE) -> #N/A | AG32: =IF(OR(AE32="N/A",AF32="N/A"),"N/A",IF(AND(AE32=0,AF32=0),0,AF32/AE32*100)) -> #N/A | AH32: =IF(OR(AG32="N/A",AG32<0),0,IF(AG32>110,AD32*110/100,AD32*AG32/100)) -> #N/A
B33: =T.UP3!#REF! -> #REF! | C33: =T.UP3!#REF! -> #REF! | D33: =T.UP3!#REF! -> #REF! | F33: =IF(H33="N/A",0,T.UP3!#REF!) -> #REF! | G33: =VLOOKUP($B$33,T.UP3!$B$4:$T$69,MATCH(DETAIL!$F$4,T.UP3!$B$5:$T$5,0),FALSE) -> #REF! | H33: =VLOOKUP($B$33,'R.UP3'!$B$4:$S$54,MATCH(DETAIL!$F$4,'R.UP3'!$B$5:$S$5,0),FALSE) -> #REF! | I33: =IF(OR(G33="N/A",H33="N/A"),"N/A",IF(AND(G33=0,H33=0),0,H33/G33*100)) -> #REF! | J33: =IF(OR(I33="N/A",I33<0),0,IF(I33>110,F33*110/100,F33*I33/100)) -> #REF! | L33: =IF(N33="N/A",0,T.UP3!#REF!) -> #REF! | M33: =VLOOKUP($B$33,T.UP3!$B$4:$T$69,MATCH(DETAIL!$L$4,T.UP3!$B$5:$T$5,0),FALSE) -> #REF! | N33: =VLOOKUP($B$33,'R.UP3'!$B$4:$S$54,MATCH(DETAIL!$L$4,'R.UP3'!$B$5:$S$5,0),FALSE) -> #REF! | O33: =IF(OR(M33="N/A",N33="N/A"),"N/A",IF(AND(M33=0,N33=0),0,N33/M33*100)) -> #REF! | P33: =IF(OR(O33="N/A",O33<0),0,IF(O33>110,L33*110/100,L33*O33/100)) -> #REF! | R33: =IF(T33="N/A",0,T.UP3!#REF!) -> #REF! | S33: =VLOOKUP($B$33,T.UP3!$B$4:$T$69,MATCH(DETAIL!$R$4,T.UP3!$B$5:$T$5,0),FALSE) -> #REF! | T33: =VLOOKUP($B$33,'R.UP3'!$B$4:$S$54,MATCH(DETAIL!$R$4,'R.UP3'!$B$5:$S$5,0),FALSE) -> #REF! | U33: =IF(OR(S33="N/A",T33="N/A"),"N/A",IF(AND(S33=0,T33=0),0,T33/S33*100)) -> #REF! | V33: =IF(OR(U33="N/A",U33<0),0,IF(U33>110,R33*110/100,R33*U33/100)) -> #REF! | X33: =IF(Z33="N/A",0,T.UP3!#REF!) -> #REF! | Y33: =VLOOKUP($B$33,T.UP3!$B$4:$T$69,MATCH(DETAIL!$X$4,T.UP3!$B$5:$T$5,0),FALSE) -> #REF! | Z33: =VLOOKUP($B$33,'R.UP3'!$B$4:$S$54,MATCH(DETAIL!$X$4,'R.UP3'!$B$5:$S$5,0),FALSE) -> #REF! | AA33: =IF(OR(Y33="N/A",Z33="N/A"),"N/A",IF(AND(Y33=0,Z33=0),0,Z33/Y33*100)) -> #REF! | AB33: =IF(OR(AA33="N/A",AA33<0),0,IF(AA33>110,X33*110/100,X33*AA33/100)) -> #REF! | AD33: =IF(AF33="N/A",0,T.UP3!#REF!) -> #REF! | AE33: =VLOOKUP($B$33,T.UP3!$B$4:$T$69,MATCH(DETAIL!$AD$4,T.UP3!$B$5:$T$5,0),FALSE) -> #REF! | AF33: =VLOOKUP($B$33,'R.UP3'!$B$4:$S$54,MATCH(DETAIL!$AD$4,'R.UP3'!$B$5:$S$5,0),FALSE) -> #REF! | AG33: =IF(OR(AE33="N/A",AF33="N/A"),"N/A",IF(AND(AE33=0,AF33=0),0,AF33/AE33*100)) -> #REF! | AH33: =IF(OR(AG33="N/A",AG33<0),0,IF(AG33>110,AD33*110/100,AD33*AG33/100)) -> #REF!
A34: =T.UP3!A52 -> 0 | B34: =T.UP3!B52 -> c. Usulan Penghapusan PRR
B35: =T.UP3!B54 -> a. HCR, OCR, dan Produktivitas Pegawai | C35: =T.UP3!C54 -> ñ | D35: =T.UP3!D54 -> % | F35: =IF(H35="N/A",0,T.UP3!$F$54) -> 0 | G35: =VLOOKUP($B$35,T.UP3!$B$4:$T$69,MATCH(DETAIL!$F$4,T.UP3!$B$5:$T$5,0),FALSE) -> 0 | H35: =VLOOKUP($B$35,'R.UP3'!$B$4:$S$54,MATCH(DETAIL!$F$4,'R.UP3'!$B$5:$S$5,0),FALSE) -> 100 | I35: =IF(OR(G35="N/A",H35="N/A"),"N/A",IF(AND(G35=0,H35=0),0,H35/G35*100)) -> #DIV/0! | J35: =IF(OR(I35="N/A",I35<0),0,IF(I35>110,F35*110/100,F35*I35/100)) -> #DIV/0! | L35: =IF(N35="N/A",0,T.UP3!$F$54) -> 0 | M35: =VLOOKUP($B$35,T.UP3!$B$4:$T$69,MATCH(DETAIL!$L$4,T.UP3!$B$5:$T$5,0),FALSE) -> 0 | N35: =VLOOKUP($B$35,'R.UP3'!$B$4:$S$54,MATCH(DETAIL!$L$4,'R.UP3'!$B$5:$S$5,0),FALSE) -> 100 | O35: =IF(OR(M35="N/A",N35="N/A"),"N/A",IF(AND(M35=0,N35=0),0,N35/M35*100)) -> #DIV/0! | P35: =IF(OR(O35="N/A",O35<0),0,IF(O35>110,L35*110/100,L35*O35/100)) -> #DIV/0! | R35: =IF(T35="N/A",0,T.UP3!$F$54) -> 0 | S35: =VLOOKUP($B$35,T.UP3!$B$4:$T$69,MATCH(DETAIL!$R$4,T.UP3!$B$5:$T$5,0),FALSE) -> 0 | T35: =VLOOKUP($B$35,'R.UP3'!$B$4:$S$54,MATCH(DETAIL!$R$4,'R.UP3'!$B$5:$S$5,0),FALSE) -> 100 | U35: =IF(OR(S35="N/A",T35="N/A"),"N/A",IF(AND(S35=0,T35=0),0,T35/S35*100)) -> #DIV/0! | V35: =IF(OR(U35="N/A",U35<0),0,IF(U35>110,R35*110/100,R35*U35/100)) -> #DIV/0! | X35: =IF(Z35="N/A",0,T.UP3!$F$54) -> #N/A | Y35: =VLOOKUP($B$35,T.UP3!$B$4:$T$69,MATCH(DETAIL!$X$4,T.UP3!$B$5:$T$5,0),FALSE) -> #N/A | Z35: =VLOOKUP($B$35,'R.UP3'!$B$4:$S$54,MATCH(DETAIL!$X$4,'R.UP3'!$B$5:$S$5,0),FALSE) -> #N/A | AA35: =IF(OR(Y35="N/A",Z35="N/A"),"N/A",IF(AND(Y35=0,Z35=0),0,Z35/Y35*100)) -> #N/A | AB35: =IF(OR(AA35="N/A",AA35<0),0,IF(AA35>110,X35*110/100,X35*AA35/100)) -> #N/A | AD35: =IF(AF35="N/A",0,T.UP3!$F$54) -> #N/A | AE35: =VLOOKUP($B$35,T.UP3!$B$4:$T$69,MATCH(DETAIL!$AD$4,T.UP3!$B$5:$T$5,0),FALSE) -> #N/A | AF35: =VLOOKUP($B$35,'R.UP3'!$B$4:$S$54,MATCH(DETAIL!$AD$4,'R.UP3'!$B$5:$S$5,0),FALSE) -> #N/A | AG35: =IF(OR(AE35="N/A",AF35="N/A"),"N/A",IF(AND(AE35=0,AF35=0),0,AF35/AE35*100)) -> #N/A | AH35: =IF(OR(AG35="N/A",AG35<0),0,IF(AG35>110,AD35*110/100,AD35*AG35/100)) -> #N/A
B36: =T.UP3!B55 -> b. Produktivitas Unit | C36: =T.UP3!C55 -> ñ | D36: =T.UP3!D55 -> % | F36: =IF(H36="N/A",0,T.UP3!$F$55) -> #N/A | G36: =VLOOKUP($B$36,T.UP3!$B$4:$T$69,MATCH(DETAIL!$F$4,T.UP3!$B$5:$T$5,0),FALSE) -> 0 | H36: =VLOOKUP($B$36,'R.UP3'!$B$4:$S$54,MATCH(DETAIL!$F$4,'R.UP3'!$B$5:$S$5,0),FALSE) -> #N/A | I36: =IF(OR(G36="N/A",H36="N/A"),"N/A",IF(AND(G36=0,H36=0),0,H36/G36*100)) -> #N/A | J36: =IF(OR(I36="N/A",I36<0),0,IF(I36>110,F36*110/100,F36*I36/100)) -> #N/A | L36: =IF(N36="N/A",0,T.UP3!$F$55) -> #N/A | M36: =VLOOKUP($B$36,T.UP3!$B$4:$T$69,MATCH(DETAIL!$L$4,T.UP3!$B$5:$T$5,0),FALSE) -> 0 | N36: =VLOOKUP($B$36,'R.UP3'!$B$4:$S$54,MATCH(DETAIL!$L$4,'R.UP3'!$B$5:$S$5,0),FALSE) -> #N/A | O36: =IF(OR(M36="N/A",N36="N/A"),"N/A",IF(AND(M36=0,N36=0),0,N36/M36*100)) -> #N/A | P36: =IF(OR(O36="N/A",O36<0),0,IF(O36>110,L36*110/100,L36*O36/100)) -> #N/A | R36: =IF(T36="N/A",0,T.UP3!$F$55) -> #N/A | S36: =VLOOKUP($B$36,T.UP3!$B$4:$T$69,MATCH(DETAIL!$R$4,T.UP3!$B$5:$T$5,0),FALSE) -> 0 | T36: =VLOOKUP($B$36,'R.UP3'!$B$4:$S$54,MATCH(DETAIL!$R$4,'R.UP3'!$B$5:$S$5,0),FALSE) -> #N/A | U36: =IF(OR(S36="N/A",T36="N/A"),"N/A",IF(AND(S36=0,T36=0),0,T36/S36*100)) -> #N/A | V36: =IF(OR(U36="N/A",U36<0),0,IF(U36>110,R36*110/100,R36*U36/100)) -> #N/A | X36: =IF(Z36="N/A",0,T.UP3!$F$55) -> #N/A | Y36: =VLOOKUP($B$36,T.UP3!$B$4:$T$69,MATCH(DETAIL!$X$4,T.UP3!$B$5:$T$5,0),FALSE) -> #N/A | Z36: =VLOOKUP($B$36,'R.UP3'!$B$4:$S$54,MATCH(DETAIL!$X$4,'R.UP3'!$B$5:$S$5,0),FALSE) -> #N/A | AA36: =IF(OR(Y36="N/A",Z36="N/A"),"N/A",IF(AND(Y36=0,Z36=0),0,Z36/Y36*100)) -> #N/A | AB36: =IF(OR(AA36="N/A",AA36<0),0,IF(AA36>110,X36*110/100,X36*AA36/100)) -> #N/A | AD36: =IF(AF36="N/A",0,T.UP3!$F$55) -> #N/A | AE36: =VLOOKUP($B$36,T.UP3!$B$4:$T$69,MATCH(DETAIL!$AD$4,T.UP3!$B$5:$T$5,0),FALSE) -> #N/A | AF36: =VLOOKUP($B$36,'R.UP3'!$B$4:$S$54,MATCH(DETAIL!$AD$4,'R.UP3'!$B$5:$S$5,0),FALSE) -> #N/A | AG36: =IF(OR(AE36="N/A",AF36="N/A"),"N/A",IF(AND(AE36=0,AF36=0),0,AF36/AE36*100)) -> #N/A | AH36: =IF(OR(AG36="N/A",AG36<0),0,IF(AG36>110,AD36*110/100,AD36*AG36/100)) -> #N/A
A37: =T.UP3!A60 -> 0 | B37: =T.UP3!B60 -> b. Maturity Level Gudang
B38: =T.UP3!B61 -> c. Maturity Level Sustainbility | F38: =IF(H38="N/A",0,T.UP3!$F$61) -> 0 | L38: =IF(N38="N/A",0,T.UP3!$F$61) -> 0 | R38: =IF(T38="N/A",0,T.UP3!$F$61) -> 0 | X38: =IF(Z38="N/A",0,T.UP3!$F$61) -> 0 | AD38: =IF(AF38="N/A",0,T.UP3!$F$61) -> 0
B39: =T.UP3!B62 -> d. Implementasi Roadmap Perbaikan Penerapan Manajemen Risiko dan Pencapaian Perlakuan Risiko | F39: =IF(H39="N/A",0,T.UP3!$F$62) -> 0 | L39: =IF(N39="N/A",0,T.UP3!$F$62) -> 0 | R39: =IF(T39="N/A",0,T.UP3!$F$62) -> 0 | X39: =IF(Z39="N/A",0,T.UP3!$F$62) -> 0 | AD39: =IF(AF39="N/A",0,T.UP3!$F$62) -> 0
B40: =T.UP3!B66 -> c. Ketepatan penyampaian pelaporan dan Akurasi Data Kinerja | F40: =IF(H40="N/A",0,T.UP3!$F$66) -> Max-10 | L40: =IF(N40="N/A",0,T.UP3!$F$66) -> Max-10 | R40: =IF(T40="N/A",0,T.UP3!$F$66) -> Max-10 | X40: =IF(Z40="N/A",0,T.UP3!$F$66) -> Max-10 | AD40: =IF(AF40="N/A",0,T.UP3!$F$66) -> Max-10
B41: =T.UP3!B68 -> e. Pencapaian Beyond RKAP | F41: =IF(H41="N/A",0,T.UP3!$F$68) -> Max-2 Max+2 | L41: =IF(N41="N/A",0,T.UP3!$F$68) -> Max-2 Max+2 | R41: =IF(T41="N/A",0,T.UP3!$F$68) -> Max-2 Max+2 | X41: =IF(Z41="N/A",0,T.UP3!$F$68) -> Max-2 Max+2 | AD41: =IF(AF41="N/A",0,T.UP3!$F$68) -> Max-2 Max+2
B42: TOTAL BOBOT | F42: =F7+F11 -> #REF! | J42: =J7+J11 -> #REF! | L42: =L7+L11 -> #REF! | P42: =P7+P11 -> #REF! | R42: =R7+R11 -> #REF! | V42: =V7+V11 -> #REF! | X42: =X7+X11 -> #N/A | AB42: =AB7+AB11 -> #N/A | AD42: =AD7+AD11 -> #N/A | AH42: =AH7+AH11 -> #N/A
B43: TOTAL BOBOT PROPORSIONAL | F43: 100 | J43: =F43/F42*J42 -> #REF! | L43: 100 | P43: =L43/L42*P42 -> #REF! | R43: 100 | V43: =R43/R42*V42 -> #REF! | X43: 100 | AB43: =X43/X42*AB42 -> #N/A | AD43: 100 | AH43: =AD43/AD42*AH42 -> #N/A

Sheet TREN
B2: UNIT | C2: NKO
C3: Januari | D3: Februari | E3: Maret | F3: April | G3: Mei | H3: Juni | I3: Juli | J3: Agustus | K3: September | L3: Oktober | M3: November | N3: Desember
B4: UP3 Tolitoli | C4: 80.4 | D4: 87.04 | E4: 93.39
B5: ULP Tolitoli Kota | C5: 75.72 | D5: 87.05 | E5: 93.36
B6: ULP Leok | C6: 66.71 | D6: 77.27 | E6: 90.08
B7: ULP Bangkir | C7: 74.87 | D7: 75.95 | E7: 87.94
B8: ULP Moutong | C8: 88.26 | D8: 86.77 | E8: 86.59
B9: ULP Kotaraya | C9: 65.25 | D9: 74.42 | E9: 79.99

Sheet KPI
B1: KONTRAK MANAJEMEN 2024
B2: PT PLN (PERSERO) UNIT INDUK DISTRIBUSI SULUTTENGGO
B3: UNIT PELAKSANA PELAYANAN PELANGGAN TOLITOLI
A5: 1 | B5: PENJUALAN DAN PENDAPATAN TENAGA LISTRIK
B6: TARGET | Q6: REALISASI BULANAN | AF6: REALISASI KOMULATIF
B7: Unit | D7: Jan | E7: Feb | F7: Mar | G7: Apr | H7: May | I7: Jun | J7: Jul | K7: Aug | L7: Sep | M7: Oct | N7: Nov | O7: Dec | Q7: Unit | S7: Jan | T7: Feb | U7: Mar | V7: Apr | W7: May | X7: Jun | Y7: Jul | Z7: Aug | AA7: Sep | AB7: Oct | AC7: Nov | AD7: Dec | AF7: Unit | AH7: Jan | AI7: Feb | AJ7: Mar | AK7: Apr | AL7: May | AM7: Jun | AN7: Jul | AO7: Aug | AP7: Sep | AQ7: Oct | AR7: Nov | AS7: Dec
B8: ULP Tolitoli | C8: Penjualan TL (GWh) | D8: 6.54 | E8: 12.76 | F8: 19.68 | G8: 26.37 | H8: 33.24 | I8: 39.7 | J8: 46.24 | K8: 52.96 | L8: 59.74 | M8: 66.82 | N8: 73.76 | O8: 80.8 | Q8: ULP Tolitoli | R8: Penjualan TL (GWh) | S8: 7.513838 | T8: 6.6075826 | U8: 6.2866504 | V8: 5.3273309 | W8: 6.0775352 | X8: 5.8227203 | Y8: 6.0798251 | Z8: 6.0595866 | AA8: 6.0901056 | AB8: 6.5045151 | AF8: ULP Tolitoli | AG8: Penjualan TL (GWh) | AH8: 7.513838 | AI8: 14.121421 | AJ8: 20.408071 | AK8: 25.735402 | AL8: 31.812937 | AM8: 37.635657 | AN8: 43.715482 | AO8: 49.775069 | AP8: 55.865175 | AQ8: 62.36969 | AR8: 0 | AS8: 0
C9: Pendapatan TL (Rp) | R9: Pendapatan TL (Rp) | S9: 5758.6689 | T9: 4805.807 | U9: 5685.7965 | V9: 5644.9557 | W9: 6466.5394 | X9: 6206.7761 | Y9: 6472.3053 | Z9: 6395.7097 | AA9: 6431.5954 | AB9: 6901.6412 | AG9: Pendapatan TL (Rp) | AH9: 5758.6689 | AI9: 10564.476 | AJ9: 16250.272 | AK9: 21895.228 | AL9: 28361.767 | AM9: 34568.544 | AN9: 41040.849 | AO9: 47436.559 | AP9: 53868.154 | AQ9: 60769.795 | AR9: 0 | AS9: 0
C10: Harga Jual (Rp/kWh) | R10: Harga Jual (Rp/kWh) | S10: 766.40844 | T10: 727.31698 | U10: 904.42383 | V10: 1059.6218 | W10: 1064.0069 | X10: 1065.9582 | Y10: 1064.5545 | Z10: 1055.4696 | AA10: 1056.0729 | AB10: 1061.0539 | AC10: 0 | AD10: 0 | AG10: Harga Jual (Rp/kWh) | AH10: 766.40844 | AI10: 748.11708 | AJ10: 796.26695 | AK10: 850.78244 | AL10: 891.51679 | AM10: 918.50511 | AN10: 938.81725 | AO10: 953.01844 | AP10: 964.25285 | AQ10: 974.3482 | AR10: 0 | AS10: 0
B11: ULP Leok | C11: Penjualan TL (GWh) | D11: 4.27 | E11: 8.33 | F11: 12.85 | G11: 17.22 | H11: 21.7 | I11: 25.92 | J11: 30.2 | K11: 34.58 | L11: 39.01 | M11: 43.63 | N11: 48.16 | O11: 52.76 | Q11: ULP Leok | R11: Penjualan TL (GWh) | S11: 5.0476842 | T11: 4.2129476 | U11: 4.296454 | V11: 3.7453335 | W11: 4.1215169 | X11: 4.263192 | Y11: 4.3133183 | Z11: 4.4597583 | AA11: 4.3609504 | AB11: 4.5066069 | AF11: ULP Leok | AG11: Penjualan TL (GWh) | AH11: 5.0476842 | AI11: 9.2606318 | AJ11: 13.557086 | AK11: 17.302419 | AL11: 21.423936 | AM11: 25.687128 | AN11: 30.000447 | AO11: 34.460205 | AP11: 38.821155 | AQ11: 43.327762 | AR11: 0 | AS11: 0
C12: Pendapatan TL (Rp) | R12: Pendapatan TL (Rp) | S12: 3590.437 | T12: 2787.8467 | U12: 3850.8055 | V12: 3929.3757 | W12: 4350.1471 | X12: 4541.8532 | Y12: 4551.0917 | Z12: 4715.1307 | AA12: 4593.0558 | AB12: 4708.9169 | AG12: Pendapatan TL (Rp) | AH12: 3590.437 | AI12: 6378.2837 | AJ12: 10229.089 | AK12: 14158.465 | AL12: 18508.612 | AM12: 23050.465 | AN12: 27601.557 | AO12: 32316.687 | AP12: 36909.743 | AQ12: 41618.66 | AR12: 0 | AS12: 0
C13: Harga Jual (Rp/kWh) | R13: Harga Jual (Rp/kWh) | S13: 711.30382 | T13: 661.73304 | U13: 896.27528 | V13: 1049.139 | W13: 1055.4724 | X13: 1065.3644 | Y13: 1055.1254 | Z13: 1057.2615 | AA13: 1053.2236 | AB13: 1044.8919 | AC13: 0 | AD13: 0 | AG13: Harga Jual (Rp/kWh) | AH13: 711.30382 | AI13: 688.75254 | AJ13: 754.51976 | AK13: 818.29394 | AL13: 863.9221 | AM13: 897.35469 | AN13: 920.0382 | AO13: 937.79731 | AP13: 950.76365 | AQ13: 960.55411 | AR13: 0 | AS13: 0
B14: ULP Bangkir | C14: Penjualan TL (GWh) | D14: 2.19 | E14: 4.28 | F14: 6.6 | G14: 8.84 | H14: 11.15 | I14: 13.31 | J14: 15.51 | K14: 17.76 | L14: 20.04 | M14: 22.41 | N14: 24.74 | O14: 27.1 | Q14: ULP Bangkir | R14: Penjualan TL (GWh) | S14: 3.3499516 | T14: 2.7952299 | U14: 2.4283223 | V14: 1.3904715 | W14: 1.718491 | X14: 1.9566386 | Y14: 2.0255426 | Z14: 2.1538006 | AA14: 2.2264042 | AB14: 2.2760171 | AF14: ULP Bangkir | AG14: Penjualan TL (GWh) | AH14: 3.3499516 | AI14: 6.1451815 | AJ14: 8.5735038 | AK14: 9.9639754 | AL14: 11.682466 | AM14: 13.639105 | AN14: 15.664648 | AO14: 17.818448 | AP14: 20.044852 | AQ14: 22.320869 | AR14: 0 | AS14: 0
C15: Pendapatan TL (Rp) | R15: Pendapatan TL (Rp) | S15: 2094.2917 | T15: 1685.6909 | U15: 1628.1596 | V15: 1396.8175 | W15: 1668.0895 | X15: 1935.3136 | Y15: 1935.1123 | Z15: 2062.2802 | AA15: 2148.6193 | AB15: 2175.3659 | AG15: Pendapatan TL (Rp) | AH15: 2094.2917 | AI15: 3779.9825 | AJ15: 5408.1422 | AK15: 6804.9597 | AL15: 8473.0492 | AM15: 10408.363 | AN15: 12343.475 | AO15: 14405.755 | AP15: 16554.375 | AQ15: 18729.741 | AR15: 0 | AS15: 0
C16: Harga Jual (Rp/kWh) | R16: Harga Jual (Rp/kWh) | S16: 625.17072 | T16: 603.05983 | U16: 670.48745 | V16: 1004.5639 | W16: 970.67107 | X16: 989.10122 | Y16: 955.35501 | Z16: 957.50749 | AA16: 965.06253 | AB16: 955.77752 | AC16: 0 | AD16: 0 | AG16: Harga Jual (Rp/kWh) | AH16: 625.17072 | AI16: 615.11324 | AJ16: 630.79719 | AK16: 682.95629 | AL16: 725.27914 | AM16: 763.12653 | AN16: 787.98294 | AO16: 808.47418 | AP16: 825.86663 | AQ16: 839.11339 | AR16: 0 | AS16: 0
B17: ULP Moutong | C17: Penjualan TL (GWh) | D17: 2.82 | E17: 5.5 | F17: 8.49 | G17: 11.37 | H17: 14.33 | I17: 17.11 | J17: 19.94 | K17: 22.83 | L17: 25.75 | M17: 28.8 | N17: 31.8 | O17: 34.83 | Q17: ULP Moutong | R17: Penjualan TL (GWh) | S17: 3.2428242 | T17: 2.5461385 | U17: 2.7160148 | V17: 2.4894414 | W17: 2.798196 | X17: 2.8152356 | Y17: 2.7164543 | Z17: 2.6185962 | AA17: 2.7242467 | AB17: 2.7727625 | AF17: ULP Moutong | AG17: Penjualan TL (GWh) | AH17: 3.2428242 | AI17: 5.7889627 | AJ17: 8.5049775 | AK17: 10.994419 | AL17: 13.792615 | AM17: 16.60785 | AN17: 19.324305 | AO17: 21.942901 | AP17: 24.667148 | AQ17: 27.43991 | AR17: 0 | AS17: 0
C18: Pendapatan TL (Rp) | R18: Pendapatan TL (Rp) | S18: 1776.4605 | T18: 1336.4275 | U18: 1865.9663 | V18: 2166.6713 | W18: 2408.7867 | X18: 2391.1408 | Y18: 2329.8405 | Z18: 2143.2016 | AA18: 2273.9831 | AB18: 2295.6883 | AG18: Pendapatan TL (Rp) | AH18: 1776.4605 | AI18: 3112.8881 | AJ18: 4978.8544 | AK18: 7145.5257 | AL18: 9554.3123 | AM18: 11945.453 | AN18: 14275.294 | AO18: 16418.495 | AP18: 18692.478 | AQ18: 20988.167 | AR18: 0 | AS18: 0
C19: Harga Jual (Rp/kWh) | R19: Harga Jual (Rp/kWh) | S19: 547.81278 | T19: 524.88406 | U19: 687.02363 | V19: 870.34436 | W19: 860.83559 | X19: 849.35726 | Y19: 857.67707 | Z19: 818.45438 | AA19: 834.71997 | AB19: 827.94261 | AC19: 0 | AD19: 0 | AG19: Harga Jual (Rp/kWh) | AH19: 547.81278 | AI19: 537.72813 | AJ19: 585.40477 | AK19: 649.923 | AL19: 692.71218 | AM19: 719.26546 | AN19: 738.72224 | AO19: 748.23722 | AP19: 757.7884 | AQ19: 764.87738 | AR19: 0 | AS19: 0
B20: ULP Kotaraya | C20: Penjualan TL (GWh) | D20: 2.91 | E20: 5.68 | F20: 8.77 | G20: 11.75 | H20: 14.81 | I20: 17.68 | J20: 20.6 | K20: 23.59 | L20: 26.61 | M20: 29.76 | N20: 32.86 | O20: 35.99 | Q20: ULP Kotaraya | R20: Penjualan TL (GWh) | S20: 3.8265327 | T20: 3.0600966 | U20: 2.9960408 | V20: 2.533233 | W20: 2.7785356 | X20: 2.8873877 | Y20: 3.0526141 | Z20: 2.9289135 | AA20: 2.8941228 | AB20: 3.12119 | AF20: ULP Kotaraya | AG20: Penjualan TL (GWh) | AH20: 3.8265327 | AI20: 6.8866294 | AJ20: 9.8826701 | AK20: 12.415903 | AL20: 15.194439 | AM20: 18.081826 | AN20: 21.13444 | AO20: 24.063354 | AP20: 26.957477 | AQ20: 30.078667 | AR20: 0 | AS20: 0
C21: Pendapatan TL (Rp) | R21: Pendapatan TL (Rp) | S21: 2338.0716 | T21: 1779.9429 | U21: 2315.2552 | V21: 2456.7947 | W21: 2671.1729 | X21: 2741.3748 | Y21: 3020.9704 | Z21: 2782.4471 | AA21: 2752.9711 | AB21: 2981.2819 | AG21: Pendapatan TL (Rp) | AH21: 2338.0716 | AI21: 4118.0145 | AJ21: 6433.2698 | AK21: 8890.0645 | AL21: 11561.237 | AM21: 14302.612 | AN21: 17323.583 | AO21: 20106.03 | AP21: 22859.001 | AQ21: 25840.283 | AR21: 0 | AS21: 0
C22: Harga Jual (Rp/kWh) | R22: Harga Jual (Rp/kWh) | S22: 611.0157 | T22: 581.66233 | U22: 772.77161 | V22: 969.8258 | W22: 961.35998 | X22: 949.43082 | Y22: 989.63389 | Z22: 949.99292 | AA22: 951.22815 | AB22: 955.17476 | AC22: 0 | AD22: 0 | AG22: Harga Jual (Rp/kWh) | AH22: 611.0157 | AI22: 597.97244 | AJ22: 650.96474 | AK22: 716.02238 | AL22: 760.88611 | AM22: 790.99378 | AN22: 819.68494 | AO22: 835.54561 | AP22: 847.96515 | AQ22: 859.09003 | AR22: 0 | AS22: 0
B23: UP3 Tolitoli | C23: Penjualan TL (GWh) | D23: 18.74 | E23: 36.55 | F23: 56.39 | G23: 75.55 | H23: 95.22 | I23: 113.73 | J23: 132.49 | K23: 151.71 | L23: 171.15 | M23: 191.42 | N23: 211.32 | O23: 231.47 | Q23: UP3 Tolitoli | R23: Penjualan TL (GWh) | S23: 22.980831 | T23: 19.221995 | U23: 18.723482 | V23: 15.48581 | W23: 17.494275 | X23: 17.745174 | Y23: 18.187754 | Z23: 18.220655 | AA23: 18.29583 | AB23: 19.181092 | AC23: 0 | AD23: 0 | AF23: UP3 Tolitoli | AG23: Penjualan TL (GWh) | AH23: 22.980831 | AI23: 42.202826 | AJ23: 60.926308 | AK23: 76.412119 | AL23: 93.906393 | AM23: 111.65157 | AN23: 129.83932 | AO23: 148.05998 | AP23: 166.35581 | AQ23: 185.5369 | AR23: 185.5369 | AS23: 185.5369
C24: Pendapatan TL (Rp) | R24: Pendapatan TL (Rp) | S24: 15557.93 | T24: 12395.715 | U24: 15345.983 | V24: 15594.615 | W24: 17564.736 | X24: 17816.459 | Y24: 18309.32 | Z24: 18098.769 | AA24: 18200.225 | AB24: 19062.894 | AC24: 0 | AD24: 0 | AG24: Pendapatan TL (Rp) | AH24: 15557.93 | AI24: 27953.645 | AJ24: 43299.628 | AK24: 58894.243 | AL24: 76458.978 | AM24: 94275.437 | AN24: 112584.76 | AO24: 130683.53 | AP24: 148883.75 | AQ24: 167946.65 | AR24: 0 | AS24: 0
C25: Harga Jual (Rp/kWh) | R25: Harga Jual (Rp/kWh) | S25: 676.99597 | T25: 644.8714 | U25: 819.6116 | V25: 1007.0261 | W25: 1004.0277 | X25: 1004.0171 | Y25: 1006.6839 | Z25: 993.31056 | AA25: 994.7745 | AB25: 993.83781 | AC25: 0 | AD25: 0 | AG25: Harga Jual (Rp/kWh) | AH25: 676.99597 | AI25: 662.36429 | AJ25: 710.68852 | AK25: 770.7448 | AL25: 814.20418 | AM25: 844.37182 | AN25: 867.10833 | AO25: 882.63911 | AP25: 894.97177 | AQ25: 905.1927 | AR25: 0 | AS25: 0
A27: 2 | B27: SAIDI | Q27: SAIDI | AF27: SAIDI
B28: TARGET | Q28: REALISASI BULANAN | AF28: REALISASI KOMULATIF
B29: Unit | D29: Jan | E29: Feb | F29: Mar | G29: Apr | H29: May | I29: Jun | J29: Jul | K29: Aug | L29: Sep | M29: Oct | N29: Nov | O29: Dec | Q29: Unit | S29: Jan | T29: Feb | U29: Mar | V29: Apr | W29: May | X29: Jun | Y29: Jul | Z29: Aug | AA29: Sep | AB29: Oct | AC29: Nov | AD29: Dec | AF29: Unit | AH29: Jan | AI29: Feb | AJ29: Mar | AK29: Apr | AL29: May | AM29: Jun | AN29: Jul | AO29: Aug | AP29: Sep | AQ29: Oct | AR29: Nov | AS29: Dec
B30: ULP Tolitoli | C30: Menit | Q30: ULP Tolitoli | R30: Menit | S30: 601323 | T30: 124702.2 | U30: 87940.2 | V30: 1229737.2 | W30: 4141732.2 | X30: 3751348.8 | Y30: 639718.8 | Z30: 279409.2 | AA30: 739663.2 | AB30: 4153693.8 | AF30: ULP Tolitoli | AG30: Menit | AH30: 601323 | AI30: 726025.2 | AJ30: 813965.4 | AK30: 2043702.6 | AL30: 6185434.8 | AM30: 9936783.6 | AN30: 10576502 | AO30: 10855912 | AP30: 11595575 | AQ30: 15749269 | AR30: 0 | AS30: 0
C31: Pelanggan | R31: Pelanggan | S31: 46737 | T31: 46863 | U31: 46970 | V31: 47063 | W31: 47155 | X31: 47250 | Y31: 47346 | Z31: 47446 | AA31: 47552 | AB31: 47718 | AG31: Pelanggan | AH31: 46737 | AI31: 46863 | AJ31: 46970 | AK31: 47063 | AL31: 47155 | AM31: 47250 | AN31: 47346 | AO31: 47446 | AP31: 47552 | AQ31: 47718 | AR31: 0 | AS31: 0
C32: SAIDI (Menit/Plg) | D32: 32.44 | E32: 64.87 | F32: 97.31 | G32: 129.75 | H32: 162.18 | I32: 194.62 | J32: 227.06 | K32: 259.49 | L32: 291.93 | M32: 324.37 | N32: 356.8 | O32: 389.24 | R32: SAIDI (Menit/Plg) | S32: 12.866102 | T32: 2.6609948 | U32: 1.8722631 | V32: 26.129596 | W32: 87.832302 | X32: 79.393625 | Y32: 13.51157 | Z32: 5.8889938 | AA32: 15.554828 | AB32: 87.046687 | AC32: 0 | AD32: 0 | AG32: SAIDI (Menit/Plg) | AH32: 12.866102 | AI32: 15.492504 | AJ32: 17.329474 | AK32: 43.424826 | AL32: 131.17241 | AM32: 210.3023 | AN32: 223.38745 | AO32: 228.80562 | AP32: 243.85041 | AQ32: 330.0488 | AR32: 0 | AS32: 0
B33: ULP Leok | C33: Menit | Q33: ULP Leok | R33: Menit | S33: 944224.8 | T33: 146822.4 | U33: 29361.6 | V33: 461679 | W33: 1637719.2 | X33: 1542110.4 | Y33: 905589.6 | Z33: 11126.4 | AA33: 469104 | AB33: 778915.2 | AF33: ULP Leok | AG33: Menit | AH33: 944224.8 | AI33: 1091047.2 | AJ33: 1120408.8 | AK33: 1582087.8 | AL33: 3219807 | AM33: 4761917.4 | AN33: 5667507 | AO33: 5678633.4 | AP33: 6147737.4 | AQ33: 6926652.6 | AR33: 0 | AS33: 0
C34: Pelanggan | R34: Pelanggan | S34: 35785 | T34: 35893 | U34: 35986 | V34: 36089 | W34: 36170 | X34: 36277 | Y34: 36362 | Z34: 36498 | AA34: 36621 | AB34: 36783 | AG34: Pelanggan | AH34: 35785 | AI34: 35893 | AJ34: 35986 | AK34: 36089 | AL34: 36170 | AM34: 36277 | AN34: 36362 | AO34: 36498 | AP34: 36621 | AQ34: 36783 | AR34: 0 | AS34: 0
C35: SAIDI (Menit/Plg) | D35: 25.22 | E35: 50.45 | F35: 75.67 | G35: 100.89 | H35: 126.12 | I35: 151.34 | J35: 176.56 | K35: 201.78 | L35: 227.01 | M35: 252.23 | N35: 277.45 | O35: 302.68 | R35: SAIDI (Menit/Plg) | S35: 26.38605 | T35: 4.090558 | U35: 0.8159173 | V35: 12.79279 | W35: 45.278385 | X35: 42.509314 | Y35: 24.904835 | Z35: 0.30484958 | AA35: 12.809699 | AB35: 21.175956 | AC35: 0 | AD35: 0 | AG35: SAIDI (Menit/Plg) | AH35: 26.38605 | AI35: 30.397214 | AJ35: 31.134575 | AK35: 43.838505 | AL35: 89.018717 | AM35: 131.26547 | AN35: 155.86346 | AO35: 155.58752 | AP35: 167.87465 | AQ35: 188.31125 | AR35: 0 | AS35: 0
B36: ULP Bangkir | C36: Menit | Q36: ULP Bangkir | R36: Menit | S36: 329472.6 | T36: 2916 | U36: 76846.8 | V36: 319051.2 | W36: 383077.2 | X36: 342031.8 | Y36: 455848.2 | Z36: 6705.6 | AA36: 261202.2 | AB36: 591444.6 | AF36: ULP Bangkir | AG36: Menit | AH36: 329472.6 | AI36: 332388.6 | AJ36: 409235.4 | AK36: 728286.6 | AL36: 1111363.8 | AM36: 1453395.6 | AN36: 1909243.8 | AO36: 1915949.4 | AP36: 2177151.6 | AQ36: 2768596.2 | AR36: 0 | AS36: 0
C37: Pelanggan | R37: Pelanggan | S37: 21705 | T37: 21751 | U37: 21798 | V37: 21849 | W37: 21902 | X37: 21961 | Y37: 21999 | Z37: 22037 | AA37: 22094 | AB37: 22155 | AG37: Pelanggan | AH37: 21705 | AI37: 21751 | AJ37: 21798 | AK37: 21849 | AL37: 21902 | AM37: 21961 | AN37: 21999 | AO37: 22037 | AP37: 22094 | AQ37: 22155 | AR37: 0 | AS37: 0
C38: SAIDI (Menit/Plg) | D38: 14.65 | E38: 29.3 | F38: 43.94 | G38: 58.59 | H38: 73.24 | I38: 87.89 | J38: 102.54 | K38: 117.18 | L38: 131.83 | M38: 146.48 | N38: 161.13 | O38: 175.78 | R38: SAIDI (Menit/Plg) | S38: 15.179572 | T38: 0.1340628 | U38: 3.525406 | V38: 14.602554 | W38: 17.490512 | X38: 15.574509 | Y38: 20.721315 | Z38: 0.30428824 | AA38: 11.822314 | AB38: 26.695762 | AC38: 0 | AD38: 0 | AG38: SAIDI (Menit/Plg) | AH38: 15.179572 | AI38: 15.281532 | AJ38: 18.773988 | AK38: 33.33272 | AL38: 50.742571 | AM38: 66.180757 | AN38: 86.787754 | AO38: 86.942388 | AP38: 98.5404 | AQ38: 124.96485 | AR38: 0 | AS38: 0
B39: ULP Moutong | C39: Menit | Q39: ULP Moutong | R39: Menit | S39: 21018.6 | T39: 9666 | U39: 24330 | V39: 305365.8 | W39: 921459.6 | X39: 409921.2 | Y39: 388913.4 | Z39: 4813.8 | AA39: 90725.4 | AB39: 274821 | AF39: ULP Moutong | AG39: Menit | AH39: 21018.6 | AI39: 30684.6 | AJ39: 55014.6 | AK39: 360380.4 | AL39: 1281840 | AM39: 1691761.2 | AN39: 2080674.6 | AO39: 2085488.4 | AP39: 2176213.8 | AQ39: 2451034.8 | AR39: 0 | AS39: 0
C40: Pelanggan | R40: Pelanggan | S40: 22738 | T40: 22826 | U40: 22869 | V40: 22908 | W40: 22948 | X40: 23000 | Y40: 23047 | Z40: 23067 | AA40: 23111 | AB40: 23195 | AG40: Pelanggan | AH40: 22738 | AI40: 22826 | AJ40: 22869 | AK40: 22908 | AL40: 22948 | AM40: 23000 | AN40: 23047 | AO40: 23067 | AP40: 23111 | AQ40: 23195 | AR40: 0 | AS40: 0
C41: SAIDI (Menit/Plg) | D41: 17.31 | E41: 34.62 | F41: 51.92 | G41: 69.23 | H41: 86.54 | I41: 103.85 | J41: 121.16 | K41: 138.47 | L41: 155.77 | M41: 173.08 | N41: 190.39 | O41: 207.7 | R41: SAIDI (Menit/Plg) | S41: 0.92438209 | T41: 0.42346447 | U41: 1.0638856 | V41: 13.330094 | W41: 40.154244 | X41: 17.822661 | Y41: 16.874795 | Z41: 0.20868774 | AA41: 3.9256371 | AB41: 11.848286 | AC41: 0 | AD41: 0 | AG41: SAIDI (Menit/Plg) | AH41: 0.92438209 | AI41: 1.3442828 | AJ41: 2.4056408 | AK41: 15.73164 | AL41: 55.858463 | AM41: 73.554835 | AN41: 90.279629 | AO41: 90.41004 | AP41: 94.16355 | AQ41: 105.67083 | AR41: 0 | AS41: 0
B42: ULP Kotaraya | C42: Menit | Q42: ULP Kotaraya | R42: Menit | S42: 39313.8 | T42: 12226.2 | U42: 53164.8 | V42: 53568.6 | W42: 1122787.8 | X42: 313221.6 | Y42: 1299536.4 | Z42: 440695.2 | AA42: 4797.6 | AB42: 209952.6 | AF42: ULP Kotaraya | AG42: Menit | AH42: 39313.8 | AI42: 51540 | AJ42: 104704.8 | AK42: 158273.4 | AL42: 1281061.2 | AM42: 1594282.8 | AN42: 2893819.2 | AO42: 3334514.4 | AP42: 3339312 | AQ42: 3549264.6 | AR42: 0 | AS42: 0
C43: Pelanggan | R43: Pelanggan | S43: 29532 | T43: 29631 | U43: 29740 | V43: 29882 | W43: 29977 | X43: 30072 | Y43: 30175 | Z43: 30244 | AA43: 30382 | AB43: 30535 | AG43: Pelanggan | AH43: 29532 | AI43: 29631 | AJ43: 29740 | AK43: 29882 | AL43: 29977 | AM43: 30072 | AN43: 30175 | AO43: 30244 | AP43: 30382 | AQ43: 30535 | AR43: 0 | AS43: 0
C44: SAIDI (Menit/Plg) | D44: 17.89 | E44: 35.78 | F44: 53.68 | G44: 71.57 | H44: 89.46 | I44: 107.35 | J44: 125.25 | K44: 143.14 | L44: 161.03 | M44: 178.92 | N44: 196.81 | O44: 214.71 | R44: SAIDI (Menit/Plg) | S44: 1.3312271 | T44: 0.41261517 | U44: 1.787653 | V44: 1.7926712 | W44: 37.454975 | X44: 10.415722 | Y44: 43.066658 | Z44: 14.571327 | AA44: 0.15790929 | AB44: 6.8758015 | AC44: 0 | AD44: 0 | AG44: SAIDI (Menit/Plg) | AH44: 1.3312271 | AI44: 1.7393946 | AJ44: 3.5206725 | AK44: 5.2966133 | AL44: 42.734803 | AM44: 53.015523 | AN44: 95.901216 | AO44: 110.25375 | AP44: 109.91087 | AQ44: 116.23595 | AR44: 0 | AS44: 0
B45: UP3 Tolitoli | C45: Menit | Q45: UP3 Tolitoli | R45: Menit | S45: 1935352.8 | T45: 296332.8 | U45: 271643.4 | V45: 2369401.8 | W45: 8206776 | X45: 6358633.8 | Y45: 3689606.4 | Z45: 742750.2 | AA45: 1565492.4 | AB45: 6008827.2 | AC45: 0 | AD45: 0 | AF45: UP3 Tolitoli | AG45: Menit | AH45: 1935352.8 | AI45: 2231685.6 | AJ45: 2503329 | AK45: 4872730.8 | AL45: 13079507 | AM45: 19438141 | AN45: 23127747 | AO45: 23870497 | AP45: 25435990 | AQ45: 31444817 | AR45: 0 | AS45: 0
C46: Pelanggan | R46: Pelanggan | S46: 156497 | T46: 156964 | U46: 157363 | V46: 157791 | W46: 158152 | X46: 158560 | Y46: 158929 | Z46: 159292 | AA46: 159760 | AB46: 160386 | AC46: 0 | AD46: 0 | AG46: Pelanggan | AH46: 156497 | AI46: 156964 | AJ46: 157363 | AK46: 157791 | AL46: 158152 | AM46: 158560 | AN46: 158929 | AO46: 159292 | AP46: 159760 | AQ46: 160386 | AR46: 0 | AS46: 0
C47: SAIDI (Menit/Plg) | D47: 23.39 | E47: 46.78 | F47: 70.17 | G47: 93.56 | H47: 116.95 | I47: 140.34 | J47: 163.72 | K47: 187.11 | L47: 210.5 | M47: 233.89 | N47: 257.28 | O47: 280.67 | R47: SAIDI (Menit/Plg) | S47: 12.366709 | T47: 1.887903 | U47: 1.7262215 | V47: 15.016077 | W47: 51.891699 | X47: 40.102383 | Y47: 23.215438 | Z47: 4.6628217 | AA47: 9.799026 | AB47: 37.464786 | AC47: 0 | AD47: 0 | AG47: SAIDI (Menit/Plg) | AH47: 12.366709 | AI47: 14.217818 | AJ47: 15.90799 | AK47: 30.880917 | AL47: 82.702127 | AM47: 122.5917 | AN47: 145.52251 | AO47: 149.85371 | AP47: 159.21376 | AQ47: 196.05712 | AR47: 0 | AS47: 0
B49: SAIFI | Q49: SAIFI | AF49: SAIFI
B50: TARGET | Q50: REALISASI BULANAN | AF50: REALISASI KOMULATIF
B51: Unit | D51: Jan | E51: Feb | F51: Mar | G51: Apr | H51: May | I51: Jun | J51: Jul | K51: Aug | L51: Sep | M51: Oct | N51: Nov | O51: Dec | Q51: Unit | S51: Jan | T51: Feb | U51: Mar | V51: Apr | W51: May | X51: Jun | Y51: Jul | Z51: Aug | AA51: Sep | AB51: Oct | AC51: Nov | AD51: Dec | AF51: Unit | AH51: Jan | AI51: Feb | AJ51: Mar | AK51: Apr | AL51: May | AM51: Jun | AN51: Jul | AO51: Aug | AP51: Sep | AQ51: Oct | AR51: Nov | AS51: Dec
B52: ULP Tolitoli | C52: Kali | Q52: ULP Tolitoli | R52: Kali | S52: 5656 | T52: 588 | U52: 4394 | V52: 16438 | W52: 30518 | X52: 22601 | Y52: 12961 | Z52: 1463 | AA52: 15802 | AB52: 36996 | AF52: ULP Tolitoli | AG52: Kali | AH52: 5656 | AI52: 6244 | AJ52: 10638 | AK52: 27076 | AL52: 57594 | AM52: 80195 | AN52: 93156 | AO52: 94619 | AP52: 110421 | AQ52: 147417 | AR52: 0 | AS52: 0
C53: Pelanggan | R53: Pelanggan | S53: 46737 | T53: 46863 | U53: 46970 | V53: 47063 | W53: 47155 | X53: 47250 | Y53: 47346 | Z53: 47446 | AA53: 47552 | AB53: 47718 | AC53: 0 | AD53: 0 | AG53: Pelanggan | AH53: 46737 | AI53: 46863 | AJ53: 46970 | AK53: 47063 | AL53: 47155 | AM53: 47250 | AN53: 47346 | AO53: 47446 | AP53: 47552 | AQ53: 47718 | AR53: 0 | AS53: 0
C54: SAIFI (Kali/Plg) | D54: 0.29 | E54: 0.59 | F54: 0.88 | G54: 1.18 | H54: 1.47 | I54: 1.76 | J54: 2.06 | K54: 2.35 | L54: 2.65 | M54: 2.94 | N54: 3.23 | O54: 3.53 | R54: SAIFI (Kali/Plg) | S54: 0.12101761 | T54: 0.012547212 | U54: 0.093549074 | V54: 0.3492765 | W54: 0.64718482 | X54: 0.47832804 | Y54: 0.27375069 | Z54: 0.030835055 | AA54: 0.33230989 | AB54: 0.77530492 | AC54: 0 | AD54: 0 | AG54: SAIFI (Menit/Plg) | AH54: 0.12101761 | AI54: 0.13323944 | AJ54: 0.22648499 | AK54: 0.57531394 | AL54: 1.2213763 | AM54: 1.6972487 | AN54: 1.967558 | AO54: 1.9942461 | AP54: 2.3221105 | AQ54: 3.0893374 | AR54: 0 | AS54: 0
B55: ULP Leok | C55: Kali | Q55: ULP Leok | R55: Kali | S55: 11743 | T55: 1524 | U55: 3191 | V55: 5084 | W55: 15127 | X55: 12709 | Y55: 10326 | Z55: 416 | AA55: 4445 | AB55: 13523 | AF55: ULP Leok | AG55: Kali | AH55: 11743 | AI55: 13267 | AJ55: 16458 | AK55: 21542 | AL55: 36669 | AM55: 49378 | AN55: 59704 | AO55: 60120 | AP55: 64565 | AQ55: 78088 | AR55: 0 | AS55: 0
C56: Pelanggan | R56: Pelanggan | S56: 35785 | T56: 35893 | U56: 35986 | V56: 36089 | W56: 36170 | X56: 36277 | Y56: 36362 | Z56: 36498 | AA56: 36621 | AB56: 36783 | AC56: 0 | AD56: 0 | AG56: Pelanggan | AH56: 35785 | AI56: 35893 | AJ56: 35986 | AK56: 36089 | AL56: 36170 | AM56: 36277 | AN56: 36362 | AO56: 36498 | AP56: 36621 | AQ56: 36783 | AR56: 0 | AS56: 0
C57: SAIFI (Kali/Plg) | D57: 0.27 | E57: 0.53 | F57: 0.8 | G57: 1.07 | H57: 1.33 | I57: 1.6 | J57: 1.86 | K57: 2.13 | L57: 2.4 | M57: 2.66 | N57: 2.93 | O57: 3.2 | R57: SAIFI (Kali/Plg) | S57: 0.32815425 | T57: 0.042459532 | U57: 0.088673373 | V57: 0.14087395 | W57: 0.41821952 | X57: 0.35033217 | Y57: 0.28397778 | Z57: 0.011397885 | AA57: 0.12137844 | AB57: 0.36764266 | AC57: 0 | AD57: 0 | AG57: SAIFI (Menit/Plg) | AH57: 0.32815425 | AI57: 0.36962639 | AJ57: 0.45734452 | AK57: 0.59691319 | AL57: 1.013796 | AM57: 1.3611379 | AN57: 1.6419339 | AO57: 1.6472135 | AP57: 1.7630594 | AQ57: 2.1229372 | AR57: 0 | AS57: 0
B58: ULP Bangkir | C58: Kali | Q58: ULP Bangkir | R58: Kali | S58: 3224 | T58: 242 | U58: 3124 | V58: 2117 | W58: 9271 | X58: 7125 | Y58: 5974 | Z58: 252 | AA58: 4077 | AB58: 10920 | AF58: ULP Bangkir | AG58: Kali | AH58: 3224 | AI58: 3466 | AJ58: 6590 | AK58: 8707 | AL58: 17978 | AM58: 25103 | AN58: 31077 | AO58: 31329 | AP58: 35406 | AQ58: 46326 | AR58: 0 | AS58: 0
C59: Pelanggan | R59: Pelanggan | S59: 21705 | T59: 21751 | U59: 21798 | V59: 21849 | W59: 21902 | X59: 21961 | Y59: 21999 | Z59: 22037 | AA59: 22094 | AB59: 22155 | AC59: 0 | AD59: 0 | AG59: Pelanggan | AH59: 21705 | AI59: 21751 | AJ59: 21798 | AK59: 21849 | AL59: 21902 | AM59: 21961 | AN59: 21999 | AO59: 22037 | AP59: 22094 | AQ59: 22155 | AR59: 0 | AS59: 0
C60: SAIFI (Kali/Plg) | D60: 0.23 | E60: 0.47 | F60: 0.7 | G60: 0.94 | H60: 1.17 | I60: 1.4 | J60: 1.64 | K60: 1.87 | L60: 2.1 | M60: 2.34 | N60: 2.57 | O60: 2.81 | R60: SAIFI (Kali/Plg) | S60: 0.1485372 | T60: 0.011125925 | U60: 0.1433159 | V60: 0.096892306 | W60: 0.42329468 | X60: 0.32443878 | Y60: 0.2715578 | Z60: 0.011435313 | AA60: 0.18452974 | AB60: 0.492891 | AC60: 0 | AD60: 0 | AG60: SAIFI (Menit/Plg) | AH60: 0.1485372 | AI60: 0.159349 | AJ60: 0.30232131 | AK60: 0.39850794 | AL60: 0.82083828 | AM60: 1.1430718 | AN60: 1.4126551 | AO60: 1.4216545 | AP60: 1.6025165 | AQ60: 2.0909953 | AR60: 0 | AS60: 0
B61: ULP Moutong | C61: Kali | Q61: ULP Moutong | R61: Kali | S61: 424 | T61: 939 | U61: 2405 | V61: 3369 | W61: 6494 | X61: 4710 | Y61: 4748 | Z61: 171 | AA61: 1578 | AB61: 6401 | AF61: ULP Moutong | AG61: Kali | AH61: 424 | AI61: 1363 | AJ61: 3768 | AK61: 7137 | AL61: 13631 | AM61: 18341 | AN61: 23089 | AO61: 23260 | AP61: 24838 | AQ61: 31239 | AR61: 0 | AS61: 0
C62: Pelanggan | R62: Pelanggan | S62: 22738 | T62: 22826 | U62: 22869 | V62: 22908 | W62: 22948 | X62: 23000 | Y62: 23047 | Z62: 23067 | AA62: 23111 | AB62: 23195 | AC62: 0 | AD62: 0 | AG62: Pelanggan | AH62: 22738 | AI62: 22826 | AJ62: 22869 | AK62: 22908 | AL62: 22948 | AM62: 23000 | AN62: 23047 | AO62: 23067 | AP62: 23111 | AQ62: 23195 | AR62: 0 | AS62: 0
C63: SAIFI (Kali/Plg) | D63: 0.17 | E63: 0.34 | F63: 0.51 | G63: 0.68 | H63: 0.85 | I63: 1.02 | J63: 1.19 | K63: 1.37 | L63: 1.54 | M63: 1.71 | N63: 1.88 | O63: 2.05 | R63: SAIFI (Kali/Plg) | S63: 0.018647199 | T63: 0.0411373 | U63: 0.1051642 | V63: 0.14706653 | W63: 0.28298762 | X63: 0.20478261 | Y63: 0.2060138 | Z63: 0.0074131877 | AA63: 0.068279174 | AB63: 0.27596465 | AC63: 0 | AD63: 0 | AG63: SAIFI (Menit/Plg) | AH63: 0.018647199 | AI63: 0.059712608 | AJ63: 0.16476453 | AK63: 0.31155055 | AL63: 0.59399512 | AM63: 0.79743478 | AN63: 1.0018224 | AO63: 1.0083669 | AP63: 1.0747263 | AQ63: 1.3467989 | AR63: 0 | AS63: 0
B64: ULP Kotaraya | C64: Kali | Q64: ULP Kotaraya | R64: Kali | S64: 1884 | T64: 548 | U64: 4685 | V64: 4588 | W64: 13583 | X64: 7160 | Y64: 8587 | Z64: 2924 | AA64: 169 | AB64: 1795 | AF64: ULP Kotaraya | AG64: Kali | AH64: 1884 | AI64: 2432 | AJ64: 7117 | AK64: 11705 | AL64: 25288 | AM64: 32448 | AN64: 41035 | AO64: 43959 | AP64: 44128 | AQ64: 45923 | AR64: 0 | AS64: 0
C65: Pelanggan | R65: Pelanggan | S65: 29532 | T65: 29631 | U65: 29740 | V65: 29882 | W65: 29977 | X65: 30072 | Y65: 30175 | Z65: 30244 | AA65: 30382 | AB65: 30535 | AC65: 0 | AD65: 0 | AG65: Pelanggan | AH65: 29532 | AI65: 29631 | AJ65: 29740 | AK65: 29882 | AL65: 29977 | AM65: 30072 | AN65: 30175 | AO65: 30244 | AP65: 30382 | AQ65: 30535 | AR65: 0 | AS65: 0
C66: SAIFI (Kali/Plg) | D66: 0.22 | E66: 0.44 | F66: 0.65 | G66: 0.87 | H66: 1.09 | I66: 1.31 | J66: 1.53 | K66: 1.75 | L66: 1.96 | M66: 2.18 | N66: 2.4 | O66: 2.62 | R66: SAIFI (Kali/Plg) | S66: 0.063795205 | T66: 0.018494145 | U66: 0.15753194 | V66: 0.15353725 | W66: 0.45311405 | X66: 0.23809524 | Y66: 0.28457332 | Z66: 0.096680333 | AA66: 0.0055625041 | AB66: 0.058785001 | AC66: 0 | AD66: 0 | AG66: SAIFI (Menit/Plg) | AH66: 0.063795205 | AI66: 0.082076204 | AJ66: 0.23930733 | AK66: 0.39170738 | AL66: 0.84358008 | AM66: 1.0790104 | AN66: 1.3599006 | AO66: 1.4534784 | AP66: 1.4524389 | AQ66: 1.5039463 | AR66: 0 | AS66: 0
B67: UP3 Tolitoli | C67: Kali | Q67: UP3 Tolitoli | R67: Kali | S67: 22931 | T67: 3841 | U67: 17799 | V67: 31596 | W67: 74993 | X67: 54305 | Y67: 42596 | Z67: 5226 | AA67: 26071 | AB67: 69635 | AC67: 0 | AD67: 0 | AF67: UP3 Tolitoli | AG67: Kali | AH67: 22931 | AI67: 26772 | AJ67: 44571 | AK67: 76167 | AL67: 151160 | AM67: 205465 | AN67: 248061 | AO67: 253287 | AP67: 279358 | AQ67: 348993 | AR67: 0 | AS67: 0
C68: Pelanggan | R68: Pelanggan | S68: 156497 | T68: 156964 | U68: 157363 | V68: 157791 | W68: 158152 | X68: 158560 | Y68: 158929 | Z68: 159292 | AA68: 159760 | AB68: 160386 | AC68: 0 | AD68: 0 | AG68: Pelanggan | AH68: 156497 | AI68: 156964 | AJ68: 157363 | AK68: 157791 | AL68: 158152 | AM68: 158560 | AN68: 158929 | AO68: 159292 | AP68: 159760 | AQ68: 160386 | AR68: 0 | AS68: 0
C69: SAIFI (Kali/Plg) | D69: 0.25 | E69: 0.49 | F69: 0.74 | G69: 0.99 | H69: 1.24 | I69: 1.48 | J69: 1.73 | K69: 1.98 | L69: 2.22 | M69: 2.47 | N69: 2.72 | O69: 2.97 | R69: SAIFI (Kali/Plg) | S69: 0.14652677 | T69: 0.024470579 | U69: 0.11310791 | V69: 0.20023956 | W69: 0.47418306 | X69: 0.34248865 | Y69: 0.26801905 | Z69: 0.032807674 | AA69: 0.16318853 | AB69: 0.43417131 | AC69: 0 | AD69: 0 | AG69: SAIFI (Menit/Plg) | AH69: 0.14652677 | AI69: 0.1705614 | AJ69: 0.28323685 | AK69: 0.48270814 | AL69: 0.95578937 | AM69: 1.2958186 | AN69: 1.560829 | AO69: 1.5900799 | AP69: 1.7486104 | AQ69: 2.1759568 | AR69: 0 | AS69: 0
B71: ENS DISTRIBUSI | Q71: ENS DISTRIBUSI | AF71: ENS DISTRIBUSI
B72: TARGET | Q72: REALISASI BULANAN | AF72: REALISASI KOMULATIF
B73: Unit | D73: Jan | E73: Feb | F73: Mar | G73: Apr | H73: May | I73: Jun | J73: Jul | K73: Aug | L73: Sep | M73: Oct | N73: Nov | O73: Dec | Q73: Unit | S73: Jan | T73: Feb | U73: Mar | V73: Apr | W73: May | X73: Jun | Y73: Jul | Z73: Aug | AA73: Sep | AB73: Oct | AC73: Nov | AD73: Dec | AF73: Unit | AH73: Jan | AI73: Feb | AJ73: Mar | AK73: Apr | AL73: May | AM73: Jun | AN73: Jul | AO73: Aug | AP73: Sep | AQ73: Oct | AR73: Nov | AS73: Dec
B74: ULP Tolitoli | C74: MWh | D74: 4.04 | E74: 8.08 | F74: 12.12 | G74: 16.16 | H74: 20.19 | I74: 24.23 | J74: 28.27 | K74: 32.31 | L74: 36.35 | M74: 40.39 | N74: 44.43 | O74: 48.47 | Q74: ULP Tolitoli | R74: MWh | S74: 1.709 | T74: 0.482 | U74: 0.228 | V74: 2.826 | W74: 6.701 | X74: 5.705 | Y74: 1.224 | Z74: 1.378 | AA74: 2.29 | AB74: 6.44 | AF74: ULP Tolitoli | AG74: MWh | AH74: 1.709 | AI74: 2.191 | AJ74: 2.419 | AK74: 5.245 | AL74: 11.946 | AM74: 17.651 | AN74: 18.875 | AO74: 20.253 | AP74: 22.543 | AQ74: 28.983 | AR74: 0 | AS74: 0
B75: ULP Leok | C75: MWh | D75: 2.45 | E75: 4.9 | F75: 7.35 | G75: 9.8 | H75: 12.25 | I75: 14.69 | J75: 17.14 | K75: 19.59 | L75: 22.04 | M75: 24.49 | N75: 26.94 | O75: 29.39 | Q75: ULP Leok | R75: MWh | S75: 2.703 | T75: 0.652 | U75: 0.07 | V75: 1.277 | W75: 3.142 | X75: 2.836 | Y75: 1.826 | Z75: 0.022 | AA75: 1.483 | AB75: 1.914 | AF75: ULP Leok | AG75: MWh | AH75: 2.703 | AI75: 3.355 | AJ75: 3.583 | AK75: 4.86 | AL75: 8.002 | AM75: 10.838 | AN75: 12.664 | AO75: 12.686 | AP75: 14.169 | AQ75: 16.083 | AR75: 0 | AS75: 0
B76: ULP Bangkir | C76: MWh | D76: 0.59 | E76: 1.18 | F76: 1.77 | G76: 2.36 | H76: 2.95 | I76: 3.54 | J76: 4.13 | K76: 4.72 | L76: 5.31 | M76: 5.9 | N76: 6.49 | O76: 7.08 | Q76: ULP Bangkir | R76: MWh | S76: 0.796 | T76: 0.006 | U76: 0.253 | V76: 0.839 | W76: 0.648 | X76: 0.496 | Y76: 0.615 | Z76: 0.013 | AA76: 0.495 | AB76: 0.904 | AF76: ULP Bangkir | AG76: MWh | AH76: 0.796 | AI76: 0.802 | AJ76: 1.055 | AK76: 1.894 | AL76: 2.542 | AM76: 3.038 | AN76: 3.653 | AO76: 3.666 | AP76: 4.161 | AQ76: 5.065 | AR76: 0 | AS76: 0
B77: ULP Moutong | C77: MWh | D77: 0.86 | E77: 1.72 | F77: 2.58 | G77: 3.45 | H77: 4.31 | I77: 5.17 | J77: 6.03 | K77: 6.89 | L77: 7.75 | M77: 8.61 | N77: 9.47 | O77: 10.34 | Q77: ULP Moutong | R77: MWh | S77: 0.154 | T77: 0.021 | U77: 0.067 | V77: 0.645 | W77: 2.211 | X77: 1.03 | Y77: 0.865 | Z77: 0.009 | AA77: 0.262 | AB77: 0.623 | AF77: ULP Moutong | AG77: MWh | AH77: 0.154 | AI77: 0.175 | AJ77: 0.242 | AK77: 0.887 | AL77: 3.098 | AM77: 4.128 | AN77: 4.993 | AO77: 5.002 | AP77: 5.264 | AQ77: 5.887 | AR77: 0 | AS77: 0
B78: ULP Kotaraya | C78: MWh | D78: 1.05 | E78: 2.1 | F78: 3.15 | G78: 4.2 | H78: 5.25 | I78: 6.3 | J78: 7.35 | K78: 8.4 | L78: 9.45 | M78: 10.5 | N78: 11.55 | O78: 12.6 | Q78: ULP Kotaraya | R78: MWh | S78: 0.082 | T78: 0.024 | U78: 0.113 | V78: 0.087 | W78: 1.656 | X78: 0.462 | Y78: 1.789 | Z78: 0.586 | AA78: 0.004 | AB78: 0.309 | AF78: ULP Kotaraya | AG78: MWh | AH78: 0.082 | AI78: 0.106 | AJ78: 0.219 | AK78: 0.306 | AL78: 1.962 | AM78: 2.424 | AN78: 4.213 | AO78: 4.799 | AP78: 4.803 | AQ78: 5.112 | AR78: 0 | AS78: 0
B79: UP3 Tolitoli | C79: MWh | D79: 8.99 | E79: 17.98 | F79: 26.97 | G79: 35.96 | H79: 44.94 | I79: 53.93 | J79: 62.92 | K79: 71.91 | L79: 80.9 | M79: 89.89 | N79: 98.88 | O79: 107.87 | Q79: UP3 Tolitoli | R79: MWh | S79: 5.444 | T79: 1.185 | U79: 0.731 | V79: 5.674 | W79: 14.358 | X79: 10.529 | Y79: 6.319 | Z79: 2.008 | AA79: 4.534 | AB79: 10.19 | AC79: 0 | AD79: 0 | AF79: UP3 Tolitoli | AG79: MWh | AH79: 5.444 | AI79: 6.629 | AJ79: 7.36 | AK79: 13.034 | AL79: 27.392 | AM79: 37.921 | AN79: 44.24 | AO79: 46.248 | AP79: 50.782 | AQ79: 60.972 | AR79: 0 | AS79: 0
A83: 3 | B83: SUSUT JARINGAN TANPA E-MIN (%) | Q83: SUSUT JARINGAN TANPA E-MIN (%) | AF83: SUSUT JARINGAN TANPA E-MIN (%)
B84: TARGET | Q84: REALISASI BULANAN | AF84: REALISASI KOMULATIF
B85: Unit | D85: Jan | E85: Feb | F85: Mar | G85: Apr | H85: May | I85: Jun | J85: Jul | K85: Aug | L85: Sep | M85: Oct | N85: Nov | O85: Dec | Q85: Unit | S85: Jan | T85: Feb | U85: Mar | V85: Apr | W85: May | X85: Jun | Y85: Jul | Z85: Aug | AA85: Sep | AB85: Oct | AC85: Nov | AD85: Dec | AF85: Unit | AH85: Jan | AI85: Feb | AJ85: Mar | AK85: Apr | AL85: May | AM85: Jun | AN85: Jul | AO85: Aug | AP85: Sep | AQ85: Oct | AR85: Nov | AS85: Dec
B86: ULP Tolitoli | C86: kWh Siap Salur (kWh) | Q86: ULP Tolitoli | R86: kWh Siap Salur (kWh) | S86: 7016666.3 | T86: 6257261.5 | U86: 6881436.7 | V86: 6762863.8 | W86: 7317520.2 | X86: 6412591 | Y86: 6791574.7 | Z86: 6576037.2 | AA86: 6699247 | AB86: 7024875.3 | AF86: ULP Tolitoli | AG86: kWh Siap Salur (kWh) | AH86: 7016666.3 | AI86: 13273928 | AJ86: 20155364 | AK86: 26918228 | AL86: 34235748 | AM86: 40648339 | AN86: 47439914 | AO86: 54015951 | AP86: 60715198 | AQ86: 67740074 | AR86: 0 | AS86: 0
C87: PSSD (kWh) | R87: PSSD (kWh) | S87: 60661.656 | T87: 60760.872 | U87: 60866.35 | V87: 60969.1 | W87: 61078.608 | X87: 61167.528 | Y87: 61281.72 | Z87: 61392.744 | AA87: 61476.448 | AB87: 61604.28 | AG87: PSSD (kWh) | AH87: 60661.656 | AI87: 121422.53 | AJ87: 182288.88 | AK87: 243257.98 | AL87: 304336.59 | AM87: 365504.11 | AN87: 426785.83 | AO87: 488178.58 | AP87: 549655.03 | AQ87: 611259.31 | AR87: 0 | AS87: 0
C88: Jual Tanpa E-min (kWh) | R88: Jual Tanpa E-min (kWh) | S88: 7471811 | T88: 6546925.6 | U88: 6242950 | V88: 5286155.9 | W88: 6041871.2 | X88: 5733166.3 | Y88: 5976394.1 | Z88: 5999696.6 | AA88: 6021804.6 | AB88: 6504515.1 | AG88: Jual Tanpa E-min (kWh) | AH88: 7471811 | AI88: 14018737 | AJ88: 20261687 | AK88: 25547842 | AL88: 31589714 | AM88: 37322880 | AN88: 43299274 | AO88: 49298971 | AP88: 55320775 | AQ88: 61825290 | AR88: 0 | AS88: 0
C89: Susut Jaringan (%) | D89: 10.36 | E89: 10.36 | F89: 10.36 | G89: 10.17 | H89: 9.98 | I89: 9.79 | J89: 9.72 | K89: 9.65 | L89: 9.58 | M89: 9.51 | N89: 9.44 | O89: 9.37 | R89: Susut Jaringan (%) | S89: -7.3511602 | T89: -5.6002929 | U89: 8.3938914 | V89: 20.934013 | W89: 16.598116 | X89: 9.6413014 | Y89: 11.100501 | Z89: 7.8306719 | AA89: 9.1945556 | AB89: 6.5304492 | AC89: 0 | AD89: 0 | AG89: Susut Jaringan (%) | AH89: -7.3511602 | AI89: -6.5258103 | AJ89: -1.4319316 | AK89: 4.1872287 | AL89: 6.8399213 | AM89: 7.2818608 | AN89: 7.8285435 | AO89: 7.8288026 | AP89: 7.9794983 | AQ89: 7.829227 | AR89: 0 | AS89: 0
B90: ULP Leok | C90: kWh Siap Salur (kWh) | Q90: ULP Leok | R90: kWh Siap Salur (kWh) | S90: 4449874.2 | T90: 4442618.1 | U90: 5102551.2 | V90: 4774566.5 | W90: 5045961.4 | X90: 4823509.5 | Y90: 5143693.7 | Z90: 5066765 | AA90: 5057536 | AB90: 5063452.4 | AF90: ULP Leok | AG90: kWh Siap Salur (kWh) | AH90: 4449874.2 | AI90: 8892492.3 | AJ90: 13995044 | AK90: 18769610 | AL90: 23815572 | AM90: 28639081 | AN90: 33782775 | AO90: 38849540 | AP90: 43907076 | AQ90: 48970528 | AR90: 0 | AS90: 0
C91: PSSD (kWh) | R91: PSSD (kWh) | S91: 46063.44 | T91: 46566.792 | U91: 46670.04 | V91: 46805.76 | W91: 46901.952 | X91: 46965.6 | Y91: 47043.288 | Z91: 47267.064 | AA91: 47372.968 | AB91: 47457.208 | AG91: PSSD (kWh) | AH91: 46063.44 | AI91: 92630.232 | AJ91: 139300.27 | AK91: 186106.03 | AL91: 233007.98 | AM91: 279973.58 | AN91: 327016.87 | AO91: 374283.94 | AP91: 421656.9 | AQ91: 469114.11 | AR91: 0 | AS91: 0
C92: Jual Tanpa E-min (kWh) | R92: Jual Tanpa E-min (kWh) | S92: 5024820.2 | T92: 4188626.6 | U92: 4270932 | V92: 3722369.5 | W92: 4101468.9 | X92: 4242295 | Y92: 4293714.3 | Z92: 4437258.3 | AA92: 4337942.4 | AB92: 4483417.9 | AG92: Jual Tanpa E-min (kWh) | AH92: 5024820.2 | AI92: 9213446.8 | AJ92: 13484379 | AK92: 17206748 | AL92: 21308217 | AM92: 25550512 | AN92: 29844227 | AO92: 34281485 | AP92: 38619427 | AQ92: 43102845 | AR92: 0 | AS92: 0
C93: Susut Jaringan (%) | D93: 11.44 | E93: 11.44 | F93: 11.44 | G93: 11.23 | H93: 11.03 | I93: 10.82 | J93: 10.74 | K93: 10.66 | L93: 10.58 | M93: 10.51 | N93: 10.43 | O93: 10.35 | R93: Susut Jaringan (%) | S93: -13.955662 | T93: 4.6689738 | U93: 15.383465 | V93: 21.057226 | W93: 17.788297 | X93: 11.075937 | Y93: 15.610107 | Z93: 11.491349 | AA93: 13.291464 | AB93: 10.518066 | AC93: 0 | AD93: 0 | AG93: Susut Jaringan (%) | AH93: -13.955662 | AI93: -4.6509426 | AJ93: 2.6535427 | AK93: 7.3350256 | AL93: 9.5498289 | AM93: 9.8068621 | AN93: 10.690452 | AO93: 10.794905 | AP93: 11.082477 | AQ93: 11.024118 | AR93: 0 | AS93: 0
B94: ULP Bangkir | C94: kWh Siap Salur (kWh) | Q94: ULP Bangkir | R94: kWh Siap Salur (kWh) | S94: 2368984.2 | T94: 2194537.2 | U94: 2397068.1 | V94: 2108800.3 | W94: 2218709 | X94: 2233892.4 | Y94: 2369124 | Z94: 2441233.3 | AA94: 2505917.9 | AB94: 2511511.2 | AF94: ULP Bangkir | AG94: kWh Siap Salur (kWh) | AH94: 2368984.2 | AI94: 4563521.4 | AJ94: 6960589.5 | AK94: 9069389.8 | AL94: 11288099 | AM94: 13521991 | AN94: 15891115 | AO94: 18332349 | AP94: 20838266 | AQ94: 23349778 | AR94: 0 | AS94: 0
C95: PSSD (kWh) | R95: PSSD (kWh) | S95: 25796.952 | T95: 25897.104 | U95: 26006.26 | V95: 26064.07 | W95: 26129.592 | X95: 26187.624 | Y95: 26242.848 | Z95: 26366.904 | AA95: 26419.32 | AB95: 26576.352 | AG95: PSSD (kWh) | AH95: 25796.952 | AI95: 51694.056 | AJ95: 77700.316 | AK95: 103764.39 | AL95: 129893.98 | AM95: 156081.6 | AN95: 182324.45 | AO95: 208691.35 | AP95: 235110.67 | AQ95: 261687.03 | AR95: 0 | AS95: 0
C96: Jual Tanpa E-min (kWh) | R96: Jual Tanpa E-min (kWh) | S96: 3339865.6 | T96: 2785378.9 | U96: 2418373 | V96: 1351580.5 | W96: 1680582 | X96: 1944171.6 | Y96: 2016687.6 | Z96: 2144934.6 | AA96: 2217045.2 | AB96: 2266660.1 | AG96: Jual Tanpa E-min (kWh) | AH96: 3339865.6 | AI96: 6125244.5 | AJ96: 8543617.5 | AK96: 9895198.1 | AL96: 11575780 | AM96: 13519952 | AN96: 15536639 | AO96: 17681574 | AP96: 19898619 | AQ96: 22165279 | AR96: 0 | AS96: 0
C97: Susut Jaringan (%) | D97: 8.62 | E97: 8.62 | F97: 8.62 | G97: 8.47 | H97: 8.31 | I97: 8.15 | J97: 8.1 | K97: 8.04 | L97: 7.98 | M97: 7.92 | N97: 7.86 | O97: 7.8 | R97: Susut Jaringan (%) | S97: -42.071974 | T97: -28.103365 | U97: -1.9737073 | V97: 34.671642 | W97: 23.076364 | X97: 11.797042 | Y97: 13.768533 | Z97: 11.05719 | AA97: 10.473341 | AB97: 8.6909758 | AC97: 0 | AD97: 0 | AG97: Susut Jaringan (%) | AH97: -42.071974 | AI97: -35.354654 | AJ97: -23.859018 | AK97: -10.249561 | AL97: -3.6992523 | AM97: -1.1391963 | AN97: 1.0833198 | AO97: 2.4114935 | AP97: 3.3809758 | AQ97: 3.9521214 | AR97: 0 | AS97: 0
B98: ULP Moutong | C98: kWh Siap Salur (kWh) | Q98: ULP Moutong | R98: kWh Siap Salur (kWh) | S98: 2895890.1 | T98: 2632389.8 | U98: 3190012.1 | V98: 3170447.9 | W98: 3353437.8 | X98: 3164248.8 | Y98: 3028316.9 | Z98: 2990318.2 | AA98: 3079895.1 | AB98: 3159407.1 | AF98: ULP Moutong | AG98: kWh Siap Salur (kWh) | AH98: 2895890.1 | AI98: 5528279.9 | AJ98: 8718292.1 | AK98: 11888740 | AL98: 15242178 | AM98: 18406427 | AN98: 21434743 | AO98: 24425062 | AP98: 27504957 | AQ98: 30664364 | AR98: 0 | AS98: 0
C99: PSSD (kWh) | R99: PSSD (kWh) | S99: 27447.192 | T99: 27547.344 | U99: 27650.3 | V99: 27754.2 | W99: 27774.792 | X99: 27801.936 | Y99: 27824.4 | Z99: 27986.04 | AA99: 28027.952 | AB99: 28076.528 | AG99: PSSD (kWh) | AH99: 27447.192 | AI99: 54994.536 | AJ99: 82644.836 | AK99: 110399.04 | AL99: 138173.83 | AM99: 165975.76 | AN99: 193800.16 | AO99: 221786.2 | AP99: 249814.16 | AQ99: 277890.68 | AR99: 0 | AS99: 0
C100: Jual Tanpa E-min (kWh) | R100: Jual Tanpa E-min (kWh) | S100: 3234246.2 | T100: 2506182.5 | U100: 2680131 | V100: 2480217.4 | W100: 2790015 | X100: 2806945.6 | Y100: 2707512.3 | Z100: 2609979.2 | AA100: 2715996.7 | AB100: 2759705.5 | AG100: Jual Tanpa E-min (kWh) | AH100: 3234246.2 | AI100: 5740428.7 | AJ100: 8420559.7 | AK100: 10900777 | AL100: 13690792 | AM100: 16497738 | AN100: 19205250 | AO100: 21815229 | AP100: 24531226 | AQ100: 27290931 | AR100: 0 | AS100: 0
C101: Susut Jaringan (%) | D101: 10.62 | E101: 10.62 | F101: 10.62 | G101: 10.42 | H101: 10.23 | I101: 10.04 | J101: 9.96 | K101: 9.89 | L101: 9.82 | M101: 9.75 | N101: 9.67 | O101: 9.6 | R101: Susut Jaringan (%) | S101: -12.631807 | T101: 3.7479221 | U101: 15.116897 | V101: 20.895355 | W101: 15.973101 | X101: 10.413254 | Y101: 9.6746875 | Z101: 11.783126 | AA101: 10.905257 | AB101: 11.762494 | AC101: 0 | AD101: 0 | AG101: Susut Jaringan (%) | AH101: -12.631807 | AI101: -4.8323047 | AJ101: 2.4670831 | AK101: 7.3814708 | AL101: 9.2717189 | AM101: 9.4679602 | AN101: 9.4971668 | AO101: 9.7770328 | AP101: 9.9033668 | AQ101: 10.094916 | AR101: 0 | AS101: 0
B102: ULP Kotaraya | C102: kWh Siap Salur (kWh) | Q102: ULP Kotaraya | R102: kWh Siap Salur (kWh) | S102: 3227200.9 | T102: 2950915.4 | U102: 3446256 | V102: 3253528.3 | W102: 3311683.8 | X102: 3162196.9 | Y102: 3279861.2 | Z102: 3231677.1 | AA102: 3173585.3 | AB102: 3370841 | AF102: ULP Kotaraya | AG102: kWh Siap Salur (kWh) | AH102: 3227200.9 | AI102: 6178116.2 | AJ102: 9624372.3 | AK102: 12877901 | AL102: 16189584 | AM102: 19351781 | AN102: 22631642 | AO102: 25863319 | AP102: 29036905 | AQ102: 32407746 | AR102: 0 | AS102: 0
C103: PSSD (kWh) | R103: PSSD (kWh) | S103: 35385.912 | T103: 35478.576 | U103: 35584.06 | V103: 35657.78 | W103: 35817.624 | X103: 36030.312 | Y103: 36149.184 | Z103: 36339.552 | AA103: 36408.488 | AB103: 36549.672 | AG103: PSSD (kWh) | AH103: 35385.912 | AI103: 70864.488 | AJ103: 106448.55 | AK103: 142106.33 | AL103: 177923.95 | AM103: 3168242.2 | AN103: 3204391.4 | AO103: 3240730.9 | AP103: 3277139.4 | AQ103: 3313689.1 | AR103: 0 | AS103: 0
C104: Jual Tanpa E-min (kWh) | R104: Jual Tanpa E-min (kWh) | S104: 3822574.7 | T104: 3055884.6 | U104: 2991582 | V104: 2529214 | W104: 2774782.6 | X104: 2881688.7 | Y104: 3046430.1 | Z104: 2923099.5 | AA104: 2888353.8 | AB104: 3115289 | AG104: Jual Tanpa E-min (kWh) | AH104: 3822574.7 | AI104: 6878459.4 | AJ104: 9870041.4 | AK104: 12399255 | AL104: 15174038 | AM104: 18055727 | AN104: 21102157 | AO104: 24025256 | AP104: 26913610 | AQ104: 30028899 | AR104: 0 | AS104: 0
C105: Susut Jaringan (%) | D105: 6.91 | E105: 6.91 | F105: 6.91 | G105: 6.78 | H105: 6.66 | I105: 6.53 | J105: 6.49 | K105: 6.44 | L105: 6.39 | M105: 6.34 | N105: 6.3 | O105: 6.25 | R105: Susut Jaringan (%) | S105: -19.545105 | T105: -4.7594651 | U105: 12.160732 | V105: 21.166451 | W105: 15.130779 | X105: 7.7312671 | Y105: 6.0149472 | Z105: 8.4240487 | AA105: 7.8404394 | AB105: 6.4969646 | AC105: 0 | AD105: 0 | AG105: Susut Jaringan (%) | AH105: -19.545105 | AI105: -12.482892 | AJ105: -3.6586035 | AK105: 2.6133053 | AL105: 5.1738351 | AM105: -9.6744978 | AN105: -7.4007255 | AO105: -5.4233861 | AP105: -3.9737178 | AQ105: -2.8846261 | AR105: 0 | AS105: 0
B106: UP3 Tolitoli | C106: kWh Siap Salur (kWh) | Q106: UP3 Tolitoli | R106: kWh Siap Salur (kWh) | S106: 19958616 | T106: 18477722 | U106: 21017324 | V106: 20070207 | W106: 21247312 | X106: 19796439 | Y106: 20612570 | Z106: 20306031 | AA106: 20516181 | AB106: 21130087 | AC106: 0 | AD106: 0 | AF106: UP3 Tolitoli | AG106: kWh Siap Salur (kWh) | AH106: 19958616 | AI106: 38436338 | AJ106: 59453662 | AK106: 79523869 | AL106: 1.0077118e+08 | AM106: 1.2056762e+08 | AN106: 1.4118019e+08 | AO106: 1.6148622e+08 | AP106: 1.820024e+08 | AQ106: 2.0313249e+08 | AR106: 0 | AS106: 0
C107: PSSD (kWh) | R107: PSSD (kWh) | S107: 195355.15 | T107: 196250.69 | U107: 196777.01 | V107: 197250.91 | W107: 197702.57 | X107: 198153 | Y107: 198541.44 | Z107: 199352.3 | AA107: 199705.18 | AB107: 200264.04 | AC107: 0 | AD107: 0 | AG107: PSSD (kWh) | AH107: 195355.15 | AI107: 391605.84 | AJ107: 588382.85 | AK107: 785633.76 | AL107: 983336.33 | AM107: 1181489.3 | AN107: 1380030.8 | AO107: 1579383.1 | AP107: 1779088.2 | AQ107: 1979352.3 | AR107: 0 | AS107: 0
...

Sheet SIMULASI
B1: KONTRAK MANAJEMEN 2022
B2: PT PLN (PERSERO) UIW SULUTTENGGO | M2: JUNI | N2: PILIH BULAN LAPORAN
B3: UP3 TOLITOLI
A4: NO | B4: KPI | D4: SATUAN | E4: BOBOT | F4: TARGET 2022 | G4: =VLOOKUP(M2,M7:N18,2,FALSE) -> S.D. JUNI
G5: TARGET | H5: REAL | I5: PENCAPAIAN | J5: NILAI
A6: 1 | B6: 2 | D6: 3 | E6: 4 | F6: 5 | G6: 6 | H6: 7 | I6: 8 | J6: 9
A7: =T.UP3!A7 -> I | B7: =T.UP3!B7 -> Key Performance Indikator | E7: =SUM(E8:E10) -> #N/A | J7: =SUM(J8:J10) -> #N/A | M7: JAN | N7: S.D. JANUARI
A8: =T.UP3!A8 -> 1 | B8: =T.UP3!B8 -> Penjualan Tenaga Listrik | C8: =T.UP3!C8 -> ñ | D8: =T.UP3!D8 -> GWh | E8: =IF(OR(H8="N/A",G8="N/A"),0,T.UP3!F8) -> #N/A | F8: =T.UP3!H8 -> 231.47 | G8: =VLOOKUP(B8,T.UP3!$B$4:$T$69,MATCH(SIMULASI!$M$2,T.UP3!$B$5:$T$5,0),FALSE) -> #N/A | H8: =VLOOKUP(B8,'R.UP3'!$B$4:$S$54,MATCH(SIMULASI!$M$2,'R.UP3'!$B$5:$S$5,0),FALSE) -> #N/A | I8: 100 | J8: =IF(I8="N/A",0,IF(I8>110,E8*110/100,E8*I8/100)) -> #N/A | K8: OK | M8: FEB | N8: S.D. FEBRUARI
A9: =T.UP3!A9 -> 2 | B9: =T.UP3!B9 -> Keandalan Sistem | C9: =T.UP3!C9 -> 0 | D9: =T.UP3!D9 -> 0 | E9: =IF(OR(H9="N/A",G9="N/A"),0,T.UP3!F9) -> #N/A | F9: =T.UP3!H9 -> 0 | G9: =VLOOKUP(B9,T.UP3!$B$4:$T$69,MATCH(SIMULASI!$M$2,T.UP3!$B$5:$T$5,0),FALSE) -> #N/A | H9: =VLOOKUP(B9,'R.UP3'!$B$4:$S$54,MATCH(SIMULASI!$M$2,'R.UP3'!$B$5:$S$5,0),FALSE) -> #N/A | I9: 110 | J9: =IF(I9="N/A",0,IF(I9>110,E9*110/100,E9*I9/100)) -> #N/A | K9: OK | M9: MAR | N9: S.D. MARET
A10: =T.UP3!A10 -> 0 | B10: =T.UP3!B10 -> a. SAIDI Sesuai Kewenangannya | C10: =T.UP3!C10 -> ò | D10: =T.UP3!D10 -> Menit/Plg | E10: =IF(OR(H10="N/A",G10="N/A"),0,T.UP3!F10) -> #N/A | F10: =T.UP3!H10 -> 280.67 | G10: =VLOOKUP(B10,T.UP3!$B$4:$T$69,MATCH(SIMULASI!$M$2,T.UP3!$B$5:$T$5,0),FALSE) -> #N/A | H10: =VLOOKUP(B10,'R.UP3'!$B$4:$S$54,MATCH(SIMULASI!$M$2,'R.UP3'!$B$5:$S$5,0),FALSE) -> #N/A | I10: 105 | J10: =IF(I10="N/A",0,IF(I10>110,E10*110/100,E10*I10/100)) -> #N/A | K10: OK | M10: APRIL | N10: S.D. APRIL
A11: =T.UP3!A17 -> II | B11: =T.UP3!B17 -> Perfomance Indicators | E11: =SUM(E12:E42) -> #N/A | J11: =SUM(J12:J42) -> #N/A | M11: MEI | N11: S.D. MEI
A12: =T.UP3!A18 -> 4 | B12: =T.UP3!B18 -> Keandalan Jaringan Distribusi | C12: =T.UP3!C18 -> 0 | D12: =T.UP3!D18 -> 0 | E12: =IF(OR(H12="N/A",G12="N/A"),0,T.UP3!F18) -> #N/A | F12: =T.UP3!H18 -> 0 | G12: =VLOOKUP(B12,T.UP3!$B$4:$T$69,MATCH(SIMULASI!$M$2,T.UP3!$B$5:$T$5,0),FALSE) -> #N/A | H12: =VLOOKUP(B12,'R.UP3'!$B$4:$S$54,MATCH(SIMULASI!$M$2,'R.UP3'!$B$5:$S$5,0),FALSE) -> #N/A | I12: =IF(OR(G12="N/A",H12="N/A"),"N/A",IF(AND(G12=0,H12=0),0,(2-H12/G12)*100)) -> #N/A | J12: =IF(I12="N/A",0,IF(I12>110,E12*110/100,E12*I12/100)) -> #N/A | K12: OK | M12: JUNI | N12: S.D. JUNI
A13: =T.UP3!A19 -> 0 | B13: =T.UP3!B19 -> a. Gangguan TM > 5 Menit | C13: =T.UP3!C19 -> ò | D13: =T.UP3!D19 -> Kali | E13: =IF(OR(H13="N/A",G13="N/A"),0,T.UP3!F19) -> #N/A | F13: =T.UP3!H19 -> 166 | G13: =VLOOKUP(B13,T.UP3!$B$4:$T$69,MATCH(SIMULASI!$M$2,T.UP3!$B$5:$T$5,0),FALSE) -> #N/A | H13: =VLOOKUP(B13,'R.UP3'!$B$4:$S$54,MATCH(SIMULASI!$M$2,'R.UP3'!$B$5:$S$5,0),FALSE) -> #N/A | I13: =IF(OR(G13="N/A",H13="N/A"),"N/A",IF(AND(G13=0,H13=0),0,(2-H13/G13)*100)) -> #N/A | J13: =IF(I13="N/A",0,IF(I13>110,E13*110/100,E13*I13/100)) -> #N/A | K13: OK | M13: JULI | N13: S.D. JULI
A14: =T.UP3!A20 -> 0 | B14: =T.UP3!B20 -> b. Gangguan TM ≤ 5 Menit | C14: =T.UP3!C20 -> ò | D14: =T.UP3!D20 -> Kali | E14: =IF(OR(H14="N/A",G14="N/A"),0,T.UP3!F20) -> #N/A | F14: =T.UP3!H20 -> 191 | G14: =VLOOKUP(B14,T.UP3!$B$4:$T$69,MATCH(SIMULASI!$M$2,T.UP3!$B$5:$T$5,0),FALSE) -> #N/A | H14: =VLOOKUP(B14,'R.UP3'!$B$4:$S$54,MATCH(SIMULASI!$M$2,'R.UP3'!$B$5:$S$5,0),FALSE) -> #N/A | I14: 98 | J14: =IF(I14="N/A",0,IF(I14>110,E14*110/100,E14*I14/100)) -> #N/A | K14: OK | M14: AUG | N14: S.D. AGUSTUS
A15: =T.UP3!A21 -> 0 | B15: =T.UP3!B21 -> c. Kerusakan Peralatan Distribusi (PHB TM dan Trafo) Sesuai Kewenangan | M15: SEP | N15: S.D. SEPTEMBER
B16: =T.UP3!B22 -> Peningkatan Layanan | C16: =T.UP3!C22 -> 0 | D16: =T.UP3!D22 -> 0 | E16: =IF(OR(H16="N/A",G16="N/A"),0,T.UP3!F22) -> #N/A | F16: =T.UP3!H22 -> 0 | G16: =VLOOKUP(B16,T.UP3!$B$4:$T$69,MATCH(SIMULASI!$M$2,T.UP3!$B$5:$T$5,0),FALSE) -> #N/A | H16: =VLOOKUP(B16,'R.UP3'!$B$4:$S$54,MATCH(SIMULASI!$M$2,'R.UP3'!$B$5:$S$5,0),FALSE) -> #N/A | I16: 110 | J16: =IF(I16="N/A",0,IF(I16>110,E16*110/100,E16*I16/100)) -> #N/A | K16: OK | M16: OKT | N16: S.D. OKTOBER
B17: =T.UP3!B24 -> b. Pengaduan Gangguan Berulang pada PLN Mobile | C17: =T.UP3!C24 -> ò | D17: =T.UP3!D24 -> % | E17: =IF(OR(H17="N/A",G17="N/A"),0,T.UP3!F24) -> #N/A | F17: =T.UP3!H24 -> 0.04 | G17: =VLOOKUP(B17,T.UP3!$B$4:$T$69,MATCH(SIMULASI!$M$2,T.UP3!$B$5:$T$5,0),FALSE) -> #N/A | H17: =VLOOKUP(B17,'R.UP3'!$B$4:$S$54,MATCH(SIMULASI!$M$2,'R.UP3'!$B$5:$S$5,0),FALSE) -> #N/A | I17: 110 | J17: =IF(I17="N/A",0,IF(I17>110,E17*110/100,E17*I17/100)) -> #N/A | K17: OK | M17: NOV | N17: S.D. NOVEMBER
A18: =T.UP3!A25 -> 0 | B18: =T.UP3!B25 -> c. Rating PLN Mobile | C18: =T.UP3!C25 -> ñ | D18: =T.UP3!D25 -> Rating | E18: =IF(OR(H18="N/A",G18="N/A"),0,T.UP3!F25) -> #N/A | F18: =T.UP3!H25 -> 4.9 | G18: =VLOOKUP(B18,T.UP3!$B$4:$T$69,MATCH(SIMULASI!$M$2,T.UP3!$B$5:$T$5,0),FALSE) -> #N/A | H18: N/A | I18: =IF(OR(G18="N/A",H18="N/A"),"N/A",IF(AND(G18=0,H18=0),0,H18/G18*100)) -> #N/A | J18: =IF(I18="N/A",0,IF(I18>110,E18*110/100,E18*I18/100)) -> #N/A | K18: OK | M18: DES | N18: S.D. DESEMBER
A19: =T.UP3!#REF! -> #REF! | B19: =T.UP3!#REF! -> #REF!
B20: =T.UP3!B26 -> d. Jumlah Kali Transaksi Keuangan melalui PLN Mobile | C20: =T.UP3!C26 -> ñ | D20: =T.UP3!D26 -> Kali Transaksi | E20: =IF(OR(H20="N/A",G20="N/A"),0,T.UP3!F26) -> #N/A | F20: =T.UP3!H26 -> 62908 | G20: =VLOOKUP(B20,T.UP3!$B$4:$T$69,MATCH(SIMULASI!$M$2,T.UP3!$B$5:$T$5,0),FALSE) -> #N/A | H20: =VLOOKUP(B20,'R.UP3'!$B$4:$S$54,MATCH(SIMULASI!$M$2,'R.UP3'!$B$5:$S$5,0),FALSE) -> #N/A | I20: 110 | J20: =IF(OR(I20="N/A",I20<0),0,IF(I20>110,E20*110/100,E20*I20/100)) -> #N/A | K20: OK
B21: =T.UP3!#REF! -> #REF! | C21: =T.UP3!#REF! -> #REF! | D21: =T.UP3!#REF! -> #REF! | E21: =IF(OR(H21="N/A",G21="N/A"),0,T.UP3!#REF!) -> #REF! | F21: =T.UP3!#REF! -> #REF! | G21: =VLOOKUP(B21,T.UP3!$B$4:$T$69,MATCH(SIMULASI!$M$2,T.UP3!$B$5:$T$5,0),FALSE) -> #REF! | H21: =VLOOKUP(B21,'R.UP3'!$B$4:$S$54,MATCH(SIMULASI!$M$2,'R.UP3'!$B$5:$S$5,0),FALSE) -> #REF! | I21: 110 | J21: =IF(I21="N/A",0,IF(I21>110,E21*110/100,E21*I21/100)) -> #REF! | K21: OK
A22: =T.UP3!A37 -> 0 | B22: =T.UP3!B37 -> b. Penambahan Jumlah Pelanggan | C22: =T.UP3!C37 -> ñ | D22: =T.UP3!D37 -> Pelanggan | E22: =IF(OR(H22="N/A",G22="N/A"),0,T.UP3!F37) -> #N/A | F22: =T.UP3!H37 -> 10632 | G22: =VLOOKUP(B22,T.UP3!$B$4:$T$69,MATCH(SIMULASI!$M$2,T.UP3!$B$5:$T$5,0),FALSE) -> #N/A | H22: 3.17 | I22: =IF(OR(G22="N/A",H22="N/A"),"N/A",IF(AND(G22=0,H22=0),0,H22/G22*100)) -> #N/A | J22: =IF(I22="N/A",0,IF(I22>110,E22*110/100,E22*I22/100)) -> #N/A | K22: OK
A23: =T.UP3!A40 -> 0 | B23: =T.UP3!B40 -> e. Penambahan Jumlah Pelanggan Rumah Tangga Lisdes | C23: =T.UP3!C40 -> ñ | D23: =T.UP3!D40 -> Pelanggan | E23: =IF(OR(H23="N/A",G23="N/A"),0,T.UP3!F40) -> #N/A | F23: =T.UP3!H40 -> 441 | G23: =VLOOKUP(B23,T.UP3!$B$4:$T$69,MATCH(SIMULASI!$M$2,T.UP3!$B$5:$T$5,0),FALSE) -> #N/A | H23: 100 | I23: =IF(OR(G23="N/A",H23="N/A"),"N/A",IF(AND(G23=0,H23=0),0,H23/G23*100)) -> #N/A | J23: =IF(I23="N/A",0,IF(I23>110,E23*110/100,E23*I23/100)) -> #N/A | K23: OK
A24: =T.UP3!A41 -> 0 | B24: =T.UP3!B41 -> f. Peningkatan kWh Penjualan dari Pelanggan Rumah Tangga Lisdes | C24: =T.UP3!C41 -> ñ | D24: =T.UP3!D41 -> KWh | E24: =IF(OR(H24="N/A",G24="N/A"),0,T.UP3!F41) -> 1.5 | F24: =T.UP3!H41 -> 58950.99 | G24: 100 | H24: 100 | I24: =IF(OR(G24="N/A",H24="N/A"),"N/A",IF(AND(G24=0,H24=0),0,H24/G24*100)) -> 100 | J24: =IF(I24="N/A",0,IF(I24>110,E24*110/100,E24*I24/100)) -> 1.5 | K24: OK
A25: =T.UP3!A42 -> 10 | B25: =T.UP3!B42 -> Pengelolaan Pembacaan Meter | C25: =T.UP3!C42 -> 0 | D25: =T.UP3!D42 -> 0 | E25: =IF(OR(H25="N/A",G25="N/A"),0,T.UP3!F42) -> #N/A | F25: =T.UP3!H42 -> 0 | G25: =VLOOKUP(B25,T.UP3!$B$4:$T$69,MATCH(SIMULASI!$M$2,T.UP3!$B$5:$T$5,0),FALSE) -> #N/A | H25: 80 | I25: =IF(OR(G25="N/A",H25="N/A"),"N/A",IF(AND(G25=0,H25=0),0,H25/G25*100)) -> #N/A | J25: =IF(I25="N/A",0,IF(I25>110,E25*110/100,E25*I25/100)) -> #N/A | K25: OK
A26: =T.UP3!A43 -> 0 | B26: =T.UP3!B43 -> a. Jumlah Pengguna Swa Cam
B27: =T.UP3!#REF! -> #REF! | C27: =T.UP3!#REF! -> #REF! | D27: =T.UP3!#REF! -> #REF! | E27: =IF(OR(H27="N/A",G27="N/A"),0,T.UP3!#REF!) -> #REF! | F27: =T.UP3!#REF! -> #REF! | G27: =VLOOKUP(B27,T.UP3!$B$4:$T$69,MATCH(SIMULASI!$M$2,T.UP3!$B$5:$T$5,0),FALSE) -> #REF! | H27: =VLOOKUP(B27,'R.UP3'!$B$4:$S$54,MATCH(SIMULASI!$M$2,'R.UP3'!$B$5:$S$5,0),FALSE) -> #REF! | I27: =IF(OR(G27="N/A",H27="N/A"),"N/A",IF(AND(G27=0,H27=0),0,H27/G27*100)) -> #REF! | J27: =IF(I27="N/A",0,IF(I27>110,E27*110/100,E27*I27/100)) -> #REF! | K27: OK
B28: =T.UP3!B46 -> a. Pencapaian Rata-Rata Saldo Tanggal 20 diluar Konsumen Instansi (Kementerian & Lembaga)
B29: =T.UP3!B50 -> a. Pengendalian Penggunaan Anggaran Investasi sesuai RKAP | C29: =T.UP3!C50 -> ó | D29: =T.UP3!D50 -> % | E29: =IF(OR(H29="N/A",G29="N/A"),0,T.UP3!F50) -> #N/A | F29: =T.UP3!H50 -> 95-100 | G29: =VLOOKUP(B29,T.UP3!$B$4:$T$69,MATCH(SIMULASI!$M$2,T.UP3!$B$5:$T$5,0),FALSE) -> #N/A | H29: =VLOOKUP(B29,'R.UP3'!$B$4:$S$54,MATCH(SIMULASI!$M$2,'R.UP3'!$B$5:$S$5,0),FALSE) -> #N/A | I29: 110 | J29: =IF(I29="N/A",0,IF(I29>110,E29*110/100,E29*I29/100)) -> #N/A | K29: OK
B30: =T.UP3!#REF! -> #REF! | C30: =T.UP3!#REF! -> #REF! | D30: =T.UP3!#REF! -> #REF! | E30: =IF(OR(H30="N/A",G30="N/A"),0,T.UP3!#REF!) -> #REF! | F30: =T.UP3!#REF! -> #REF! | G30: =VLOOKUP(B30,T.UP3!$B$4:$T$69,MATCH(SIMULASI!$M$2,T.UP3!$B$5:$T$5,0),FALSE) -> #REF! | H30: =VLOOKUP(B30,'R.UP3'!$B$4:$S$54,MATCH(SIMULASI!$M$2,'R.UP3'!$B$5:$S$5,0),FALSE) -> #REF! | I30: 110 | J30: =IF(I30="N/A",0,IF(I30>110,E30*110/100,E30*I30/100)) -> #REF! | K30: OK
B31: =T.UP3!#REF! -> #REF! | C31: =T.UP3!#REF! -> #REF! | D31: =T.UP3!#REF! -> #REF! | E31: =IF(OR(H31="N/A",G31="N/A"),0,T.UP3!#REF!) -> #REF! | F31: =T.UP3!#REF! -> #REF! | G31: =VLOOKUP(B31,T.UP3!$B$4:$T$69,MATCH(SIMULASI!$M$2,T.UP3!$B$5:$T$5,0),FALSE) -> #REF! | H31: =VLOOKUP(B31,'R.UP3'!$B$4:$S$54,MATCH(SIMULASI!$M$2,'R.UP3'!$B$5:$S$5,0),FALSE) -> #REF! | I31: 110 | J31: =IF(I31="N/A",0,IF(I31>110,E31*110/100,E31*I31/100)) -> #REF! | K31: OK
B32: =T.UP3!#REF! -> #REF! | C32: =T.UP3!#REF! -> #REF! | D32: =T.UP3!#REF! -> #REF! | E32: =IF(OR(H32="N/A",G32="N/A"),0,T.UP3!#REF!) -> #REF! | F32: =T.UP3!#REF! -> #REF! | G32: =VLOOKUP(B32,T.UP3!$B$4:$T$69,MATCH(SIMULASI!$M$2,T.UP3!$B$5:$T$5,0),FALSE) -> #REF! | H32: =VLOOKUP(B32,'R.UP3'!$B$4:$S$54,MATCH(SIMULASI!$M$2,'R.UP3'!$B$5:$S$5,0),FALSE) -> #REF! | I32: =IF(OR(G32="N/A",H32="N/A"),"N/A",IF(AND(G32=0,H32=0),0,H32/G32*100)) -> #REF! | J32: =IF(I32="N/A",0,IF(I32>110,E32*110/100,E32*I32/100)) -> #REF! | K32: OK
B33: =T.UP3!B51 -> b. Usulan Penghapusan ATTB | C33: =T.UP3!C51 -> ñ | D33: =T.UP3!D51 -> Rp. Milyar | E33: =IF(OR(H33="N/A",G33="N/A"),0,T.UP3!F51) -> #N/A | F33: =T.UP3!H51 -> 3.16 | G33: =VLOOKUP(B33,T.UP3!$B$4:$T$69,MATCH(SIMULASI!$M$2,T.UP3!$B$5:$T$5,0),FALSE) -> #N/A | H33: =VLOOKUP(B33,'R.UP3'!$B$4:$S$54,MATCH(SIMULASI!$M$2,'R.UP3'!$B$5:$S$5,0),FALSE) -> #N/A | I33: 70 | J33: =IF(I33="N/A",0,IF(I33>110,E33*110/100,E33*I33/100)) -> #N/A | K33: OK
B34: =T.UP3!#REF! -> #REF! | C34: =T.UP3!#REF! -> #REF! | D34: =T.UP3!#REF! -> #REF! | E34: =IF(OR(H34="N/A",G34="N/A"),0,T.UP3!#REF!) -> #REF! | F34: =T.UP3!#REF! -> #REF! | G34: =VLOOKUP(B34,T.UP3!$B$4:$T$69,MATCH(SIMULASI!$M$2,T.UP3!$B$5:$T$5,0),FALSE) -> #REF! | H34: 5 | I34: =IF(OR(G34="N/A",H34="N/A"),"N/A",IF(AND(G34=0,H34=0),0,H34/G34*100)) -> #REF! | J34: =IF(I34="N/A",0,IF(I34>110,E34*110/100,E34*I34/100)) -> #REF! | K34: OK
A35: =T.UP3!A52 -> 0 | B35: =T.UP3!B52 -> c. Usulan Penghapusan PRR
B36: =T.UP3!B54 -> a. HCR, OCR, dan Produktivitas Pegawai | C36: =T.UP3!C54 -> ñ | D36: =T.UP3!D54 -> % | E36: =IF(OR(H36="N/A",G36="N/A"),0,T.UP3!F54) -> #N/A | F36: =T.UP3!H54 -> 100 | G36: =VLOOKUP(B36,T.UP3!$B$4:$T$69,MATCH(SIMULASI!$M$2,T.UP3!$B$5:$T$5,0),FALSE) -> #N/A | H36: 80 | I36: =IF(OR(G36="N/A",H36="N/A"),"N/A",IF(AND(G36=0,H36=0),0,H36/G36*100)) -> #N/A | J36: =IF(I36="N/A",0,IF(I36>110,E36*110/100,E36*I36/100)) -> #N/A | K36: OK
B37: =T.UP3!B55 -> b. Produktivitas Unit | C37: =T.UP3!C55 -> ñ | D37: =T.UP3!D55 -> % | E37: =IF(OR(H37="N/A",G37="N/A"),0,T.UP3!F55) -> #N/A | F37: =T.UP3!H55 -> 100 | G37: =VLOOKUP(B37,T.UP3!$B$4:$T$69,MATCH(SIMULASI!$M$2,T.UP3!$B$5:$T$5,0),FALSE) -> #N/A | H37: 80 | I37: =IF(OR(G37="N/A",H37="N/A"),"N/A",IF(AND(G37=0,H37=0),0,H37/G37*100)) -> #N/A | J37: =IF(I37="N/A",0,IF(I37>110,E37*110/100,E37*I37/100)) -> #N/A | K37: OK
A38: =T.UP3!A60 -> 0 | B38: =T.UP3!B60 -> b. Maturity Level Gudang
B39: =T.UP3!B61 -> c. Maturity Level Sustainbility | E39: =IF(H39="N/A",0,T.UP3!F61) -> 0
B40: =T.UP3!B62 -> d. Implementasi Roadmap Perbaikan Penerapan Manajemen Risiko dan Pencapaian Perlakuan Risiko | E40: =IF(H40="N/A",0,T.UP3!F62) -> 0
B41: =T.UP3!B66 -> c. Ketepatan penyampaian pelaporan dan Akurasi Data Kinerja | E41: =IF(H41="N/A",0,T.UP3!F66) -> Max-10
B42: =T.UP3!B68 -> e. Pencapaian Beyond RKAP | E42: =IF(H42="N/A",0,T.UP3!F68) -> Max-2 Max+2
B43: TOTAL BOBOT | E43: =E7+E11 -> #N/A | J43: =J7+J11 -> #N/A
B44: TOTAL BOBOT PROPORSIONAL | E44: 100 | J44: =E44/E43*J43 -> #N/A
A46: TOLITOLI, 08 JUNI 2022

Sheet PI
B1: KONTRAK MANAJEMEN 2024
B2: PT PLN (PERSERO) UNIT INDUK DISTRIBUSI SULUTTENGGO
B3: UNIT PELAKSANA PELAYANAN PELANGGAN TOLITOLI
B5: GANGGUAN TM | Q5: GANGGUAN TM | AF5: GANGGUAN TM
B6: TARGET | Q6: REALISASI BULANAN | AF6: REALISASI KOMULATIF
B7: Unit | D7: Jan | E7: Feb | F7: Mar | G7: Apr | H7: May | I7: Jun | J7: Jul | K7: Aug | L7: Sep | M7: Oct | N7: Nov | O7: Dec | Q7: Unit | S7: Jan | T7: Feb | U7: Mar | V7: Apr | W7: May | X7: Jun | Y7: Jul | Z7: Aug | AA7: Sep | AB7: Oct | AC7: Nov | AD7: Dec | AF7: Unit | AH7: Jan | AI7: Feb | AJ7: Mar | AK7: Apr | AL7: May | AM7: Jun | AN7: Jul | AO7: Aug | AP7: Sep | AQ7: Oct | AR7: Nov | AS7: Dec
B8: ULP Tolitoli | C8: Gangguan TM > 5 Menit | D8: 6 | E8: 11 | F8: 17 | G8: 22 | H8: 28 | I8: 33 | J8: 39 | K8: 44 | L8: 50 | M8: 55 | N8: 61 | O8: 62 | Q8: ULP Tolitoli | R8: Gangguan TM > 5 Menit | S8: 2 | T8: 1 | U8: 5 | V8: 3 | W8: 18 | X8: 2 | Y8: 7 | Z8: 0 | AA8: 8 | AB8: 8 | AF8: ULP Tolitoli | AG8: Gangguan TM > 5 Menit | AH8: 2 | AI8: 3 | AJ8: 8 | AK8: 11 | AL8: 29 | AM8: 31 | AN8: 38 | AO8: 38 | AP8: 46 | AQ8: 54 | AR8: 54 | AS8: 54
C9: Gangguan TM ≤ 5 Menit | D9: 7 | E9: 14 | F9: 22 | G9: 29 | H9: 36 | I9: 43 | J9: 50 | K9: 57 | L9: 65 | M9: 72 | N9: 79 | O9: 86 | R9: Gangguan TM ≤ 5 Menit | S9: 0 | T9: 6 | U9: 2 | V9: 0 | W9: 15 | X9: 11 | Y9: 8 | Z9: 2 | AA9: 11 | AB9: 10 | AG9: Gangguan TM ≤ 5 Menit | AH9: 0 | AI9: 6 | AJ9: 8 | AK9: 8 | AL9: 23 | AM9: 34 | AN9: 42 | AO9: 44 | AP9: 55 | AQ9: 65 | AR9: 65 | AS9: 65
B11: ULP Leok | C11: Gangguan TM > 5 Menit | D11: 3 | E11: 5 | F11: 8 | G11: 11 | H11: 13 | I11: 16 | J11: 19 | K11: 21 | L11: 24 | M11: 27 | N11: 29 | O11: 30 | Q11: ULP Leok | R11: Gangguan TM > 5 Menit | S11: 2 | T11: 3 | U11: 3 | V11: 2 | W11: 3 | X11: 0 | Y11: 2 | Z11: 0 | AA11: 1 | AB11: 4 | AF11: ULP Leok | AG11: Gangguan TM > 5 Menit | AH11: 2 | AI11: 5 | AJ11: 8 | AK11: 10 | AL11: 13 | AM11: 13 | AN11: 15 | AO11: 15 | AP11: 16 | AQ11: 20 | AR11: 20 | AS11: 20
C12: Gangguan TM ≤ 5 Menit | D12: 4 | E12: 7 | F12: 11 | G12: 15 | H12: 18 | I12: 22 | J12: 26 | K12: 29 | L12: 33 | M12: 37 | N12: 40 | O12: 44 | R12: Gangguan TM ≤ 5 Menit | S12: 0 | T12: 2 | U12: 1 | V12: 1 | W12: 11 | X12: 4 | Y12: 1 | Z12: 0 | AA12: 1 | AB12: 8 | AG12: Gangguan TM ≤ 5 Menit | AH12: 0 | AI12: 2 | AJ12: 3 | AK12: 4 | AL12: 15 | AM12: 19 | AN12: 20 | AO12: 20 | AP12: 21 | AQ12: 29 | AR12: 29 | AS12: 29
B14: ULP Bangkir | C14: Gangguan TM > 5 Menit | D14: 3 | E14: 6 | F14: 10 | G14: 13 | H14: 16 | I14: 19 | J14: 22 | K14: 26 | L14: 29 | M14: 32 | N14: 35 | O14: 36 | Q14: ULP Bangkir | R14: Gangguan TM > 5 Menit | S14: 0 | T14: 0 | U14: 8 | V14: 1 | W14: 2 | X14: 2 | Y14: 3 | Z14: 0 | AA14: 2 | AB14: 3 | AF14: ULP Bangkir | AG14: Gangguan TM > 5 Menit | AH14: 0 | AI14: 0 | AJ14: 8 | AK14: 9 | AL14: 11 | AM14: 13 | AN14: 16 | AO14: 16 | AP14: 18 | AQ14: 21 | AR14: 21 | AS14: 21
C15: Gangguan TM ≤ 5 Menit | D15: 2 | E15: 4 | F15: 5 | G15: 7 | H15: 9 | I15: 11 | J15: 13 | K15: 14 | L15: 16 | M15: 18 | N15: 20 | O15: 21 | R15: Gangguan TM ≤ 5 Menit | S15: 0 | T15: 4 | U15: 0 | V15: 0 | W15: 3 | X15: 2 | Y15: 2 | Z15: 0 | AA15: 1 | AB15: 3 | AG15: Gangguan TM ≤ 5 Menit | AH15: 0 | AI15: 4 | AJ15: 4 | AK15: 4 | AL15: 7 | AM15: 9 | AN15: 11 | AO15: 11 | AP15: 12 | AQ15: 15 | AR15: 15 | AS15: 15
B17: ULP Moutong | C17: Gangguan TM > 5 Menit | D17: 1 | E17: 2 | F17: 3 | G17: 4 | H17: 5 | I17: 6 | J17: 7 | K17: 9 | L17: 10 | M17: 11 | N17: 12 | O17: 12 | Q17: ULP Moutong | R17: Gangguan TM > 5 Menit | S17: 0 | T17: 1 | U17: 1 | V17: 1 | W17: 1 | X17: 1 | Y17: 2 | Z17: 0 | AA17: 0 | AB17: 2 | AF17: ULP Moutong | AG17: Gangguan TM > 5 Menit | AH17: 0 | AI17: 1 | AJ17: 2 | AK17: 3 | AL17: 4 | AM17: 5 | AN17: 7 | AO17: 7 | AP17: 7 | AQ17: 9 | AR17: 9 | AS17: 9
C18: Gangguan TM ≤ 5 Menit | D18: 2 | E18: 3 | F18: 5 | G18: 7 | H18: 8 | I18: 10 | J18: 12 | K18: 14 | L18: 15 | M18: 17 | N18: 19 | O18: 20 | R18: Gangguan TM ≤ 5 Menit | S18: 0 | T18: 2 | U18: 0 | V18: 0 | W18: 4 | X18: 1 | Y18: 3 | Z18: 1 | AA18: 1 | AB18: 2 | AG18: Gangguan TM ≤ 5 Menit | AH18: 0 | AI18: 2 | AJ18: 2 | AK18: 2 | AL18: 6 | AM18: 7 | AN18: 10 | AO18: 11 | AP18: 12 | AQ18: 14 | AR18: 14 | AS18: 14
B20: ULP Kotaraya | C20: Gangguan TM > 5 Menit | D20: 2 | E20: 5 | F20: 7 | G20: 9 | H20: 12 | I20: 14 | J20: 16 | K20: 19 | L20: 21 | M20: 23 | N20: 26 | O20: 26 | Q20: ULP Kotaraya | R20: Gangguan TM > 5 Menit | S20: 1 | T20: 0 | U20: 5 | V20: 1 | W20: 2 | X20: 2 | Y20: 0 | Z20: 0 | AA20: 0 | AB20: 0 | AF20: ULP Kotaraya | AG20: Gangguan TM > 5 Menit | AH20: 1 | AI20: 1 | AJ20: 6 | AK20: 7 | AL20: 9 | AM20: 11 | AN20: 11 | AO20: 11 | AP20: 11 | AQ20: 11 | AR20: 11 | AS20: 11
C21: Gangguan TM ≤ 5 Menit | D21: 2 | E21: 3 | F21: 5 | G21: 7 | H21: 8 | I21: 10 | J21: 12 | K21: 14 | L21: 15 | M21: 17 | N21: 19 | O21: 20 | R21: Gangguan TM ≤ 5 Menit | S21: 1 | T21: 3 | U21: 0 | V21: 0 | W21: 2 | X21: 1 | Y21: 3 | Z21: 0 | AA21: 2 | AB21: 0 | AG21: Gangguan TM ≤ 5 Menit | AH21: 1 | AI21: 4 | AJ21: 4 | AK21: 4 | AL21: 6 | AM21: 7 | AN21: 10 | AO21: 10 | AP21: 12 | AQ21: 12 | AR21: 12 | AS21: 12
B23: UP3 Tolitoli | C23: Gangguan TM > 5 Menit | D23: 15 | E23: 29 | F23: 45 | G23: 59 | H23: 74 | I23: 88 | J23: 103 | K23: 119 | L23: 134 | M23: 148 | N23: 163 | O23: 166 | Q23: UP3 Tolitoli | R23: Gangguan TM > 5 Menit | S23: 5 | T23: 5 | U23: 22 | V23: 8 | W23: 26 | X23: 7 | Y23: 14 | Z23: 0 | AA23: 11 | AB23: 17 | AC23: 0 | AD23: 0 | AF23: UP3 Tolitoli | AG23: Gangguan TM > 5 Menit | AH23: 5 | AI23: 10 | AJ23: 32 | AK23: 40 | AL23: 66 | AM23: 73 | AN23: 87 | AO23: 87 | AP23: 98 | AQ23: 115 | AR23: 115 | AS23: 115
C24: Gangguan TM ≤ 5 Menit | D24: 17 | E24: 31 | F24: 48 | G24: 65 | H24: 79 | I24: 96 | J24: 113 | K24: 128 | L24: 144 | M24: 161 | N24: 177 | O24: 191 | R24: Gangguan TM ≤ 5 Menit | S24: 1 | T24: 17 | U24: 3 | V24: 1 | W24: 35 | X24: 19 | Y24: 17 | Z24: 3 | AA24: 16 | AB24: 23 | AC24: 0 | AD24: 0 | AG24: Gangguan TM ≤ 5 Menit | AH24: 1 | AI24: 18 | AJ24: 21 | AK24: 22 | AL24: 57 | AM24: 76 | AN24: 93 | AO24: 96 | AP24: 112 | AQ24: 135 | AR24: 135 | AS24: 135
B28: KERUSAKAN PERALATAN DISTRIBUSI | Q28: KERUSAKAN PERALATAN DISTRIBUSI | AF28: KERUSAKAN PERALATAN DISTRIBUSI
B29: TARGET | Q29: REALISASI BULANAN | AF29: REALIASI KOMULATIF
B30: Unit | D30: Jan | E30: Feb | F30: Mar | G30: Apr | H30: May | I30: Jun | J30: Jul | K30: Aug | L30: Sep | M30: Oct | N30: Nov | O30: Dec | Q30: Unit | S30: Jan | T30: Feb | U30: Mar | V30: Apr | W30: May | X30: Jun | Y30: Jul | Z30: Aug | AA30: Sep | AB30: Oct | AC30: Nov | AD30: Dec | AF30: Unit | AH30: Jan | AI30: Feb | AJ30: Mar | AK30: Apr | AL30: May | AM30: Jun | AN30: Jul | AO30: Aug | AP30: Sep | AQ30: Oct | AR30: Nov | AS30: Dec
B31: ULP Tolitoli | C31: Kerusakan PHB - TM | Q31: ULP Tolitoli | R31: Kerusakan PHB - TM | S31: 0 | T31: 0 | U31: 0 | V31: 0 | W31: 0 | X31: 0 | Y31: 1 | Z31: 0 | AA31: 0 | AB31: 0 | AF31: ULP Tolitoli | AG31: Kerusakan PHB - TM | AH31: 0 | AI31: 0 | AJ31: 0 | AK31: 0 | AL31: 0 | AM31: 0 | AN31: 1 | AO31: 1 | AP31: 1 | AQ31: 1 | AR31: 1 | AS31: 1
C32: Kerusakan Trafo Distribusi | R32: Kerusakan Trafo Distribusi | S32: 0 | T32: 0 | U32: 0 | V32: 0 | W32: 1 | X32: 1 | Y32: 0 | Z32: 0 | AA32: 0 | AB32: 0 | AG32: Kerusakan Trafo Distribusi | AH32: 0 | AI32: 0 | AJ32: 0 | AK32: 0 | AL32: 1 | AM32: 2 | AN32: 2 | AO32: 2 | AP32: 2 | AQ32: 2 | AR32: 2 | AS32: 2
C33: Jumlah | D33: 0 | E33: 0 | F33: 1 | G33: 1 | H33: 1 | I33: 1 | J33: 1 | K33: 1 | L33: 1 | M33: 1 | N33: 1 | O33: 1 | R33: Jumlah | S33: 0 | T33: 0 | U33: 0 | V33: 0 | W33: 1 | X33: 1 | Y33: 1 | Z33: 0 | AA33: 0 | AB33: 0 | AC33: 0 | AD33: 0 | AG33: Jumlah | AH33: 0 | AI33: 0 | AJ33: 0 | AK33: 0 | AL33: 1 | AM33: 2 | AN33: 3 | AO33: 3 | AP33: 3 | AQ33: 3 | AR33: 3 | AS33: 3
B34: ULP Leok | C34: Kerusakan PHB - TM | Q34: ULP Leok | R34: Kerusakan PHB - TM | S34: 0 | T34: 0 | U34: 0 | V34: 0 | W34: 0 | X34: 0 | Y34: 0 | Z34: 0 | AA34: 0 | AB34: 0 | AF34: ULP Leok | AG34: Kerusakan PHB - TM | AH34: 0 | AI34: 0 | AJ34: 0 | AK34: 0 | AL34: 0 | AM34: 0 | AN34: 0 | AO34: 0 | AP34: 0 | AQ34: 0 | AR34: 0 | AS34: 0
C35: Kerusakan Trafo Distribusi | R35: Kerusakan Trafo Distribusi | S35: 0 | T35: 0 | U35: 0 | V35: 0 | W35: 0 | X35: 0 | Y35: 0 | Z35: 0 | AA35: 0 | AB35: 0 | AG35: Kerusakan Trafo Distribusi | AH35: 0 | AI35: 0 | AJ35: 0 | AK35: 0 | AL35: 0 | AM35: 0 | AN35: 0 | AO35: 0 | AP35: 0 | AQ35: 0 | AR35: 0 | AS35: 0
C36: Jumlah | D36: 0 | E36: 0 | F36: 1 | G36: 1 | H36: 1 | I36: 1 | J36: 1 | K36: 1 | L36: 1 | M36: 1 | N36: 1 | O36: 1 | R36: Jumlah | S36: 0 | T36: 0 | U36: 0 | V36: 0 | W36: 0 | X36: 0 | Y36: 0 | Z36: 0 | AA36: 0 | AB36: 0 | AC36: 0 | AD36: 0 | AG36: Jumlah | AH36: 0 | AI36: 0 | AJ36: 0 | AK36: 0 | AL36: 0 | AM36: 0 | AN36: 0 | AO36: 0 | AP36: 0 | AQ36: 0 | AR36: 0 | AS36: 0
B37: ULP Bangkir | C37: Kerusakan PHB - TM | Q37: ULP Bangkir | R37: Kerusakan PHB - TM | S37: 0 | T37: 0 | U37: 0 | V37: 0 | W37: 0 | X37: 0 | Y37: 0 | Z37: 0 | AA37: 0 | AB37: 0 | AF37: ULP Bangkir | AG37: Kerusakan PHB - TM | AH37: 0 | AI37: 0 | AJ37: 0 | AK37: 0 | AL37: 0 | AM37: 0 | AN37: 0 | AO37: 0 | AP37: 0 | AQ37: 0 | AR37: 0 | AS37: 0
C38: Kerusakan Trafo Distribusi | R38: Kerusakan Trafo Distribusi | S38: 0 | T38: 0 | U38: 0 | V38: 0 | W38: 0 | X38: 0 | Y38: 0 | Z38: 0 | AA38: 0 | AB38: 0 | AG38: Kerusakan Trafo Distribusi | AH38: 0 | AI38: 0 | AJ38: 0 | AK38: 0 | AL38: 0 | AM38: 0 | AN38: 0 | AO38: 0 | AP38: 0 | AQ38: 0 | AR38: 0 | AS38: 0
C39: Jumlah | D39: 0 | E39: 0 | F39: 1 | G39: 1 | H39: 1 | I39: 1 | J39: 1 | K39: 1 | L39: 1 | M39: 1 | N39: 1 | O39: 1 | R39: Jumlah | S39: 0 | T39: 0 | U39: 0 | V39: 0 | W39: 0 | X39: 0 | Y39: 0 | Z39: 0 | AA39: 0 | AB39: 0 | AC39: 0 | AD39: 0 | AG39: Jumlah | AH39: 0 | AI39: 0 | AJ39: 0 | AK39: 0 | AL39: 0 | AM39: 0 | AN39: 0 | AO39: 0 | AP39: 0 | AQ39: 0 | AR39: 0 | AS39: 0
B40: ULP Moutong | C40: Kerusakan PHB - TM | Q40: ULP Moutong | R40: Kerusakan PHB - TM | S40: 0 | T40: 0 | U40: 0 | V40: 0 | W40: 0 | X40: 0 | Y40: 0 | Z40: 0 | AA40: 0 | AB40: 0 | AF40: ULP Moutong | AG40: Kerusakan PHB - TM | AH40: 0 | AI40: 0 | AJ40: 0 | AK40: 0 | AL40: 0 | AM40: 0 | AN40: 0 | AO40: 0 | AP40: 0 | AQ40: 0 | AR40: 0 | AS40: 0
C41: Kerusakan Trafo Distribusi | R41: Kerusakan Trafo Distribusi | S41: 0 | T41: 0 | U41: 0 | V41: 0 | W41: 0 | X41: 0 | Y41: 0 | Z41: 0 | AA41: 0 | AB41: 0 | AG41: Kerusakan Trafo Distribusi | AH41: 0 | AI41: 0 | AJ41: 0 | AK41: 0 | AL41: 0 | AM41: 0 | AN41: 0 | AO41: 0 | AP41: 0 | AQ41: 0 | AR41: 0 | AS41: 0
C42: Jumlah | D42: 0 | E42: 0 | F42: 0 | G42: 0 | H42: 0 | I42: 1 | J42: 1 | K42: 1 | L42: 1 | M42: 1 | N42: 1 | O42: 1 | R42: Jumlah | S42: 0 | T42: 0 | U42: 0 | V42: 0 | W42: 0 | X42: 0 | Y42: 0 | Z42: 0 | AA42: 0 | AB42: 0 | AC42: 0 | AD42: 0 | AG42: Jumlah | AH42: 0 | AI42: 0 | AJ42: 0 | AK42: 0 | AL42: 0 | AM42: 0 | AN42: 0 | AO42: 0 | AP42: 0 | AQ42: 0 | AR42: 0 | AS42: 0
B43: ULP Kotaraya | C43: Kerusakan PHB - TM | Q43: ULP Kotaraya | R43: Kerusakan PHB - TM | S43: 0 | T43: 0 | U43: 0 | V43: 0 | W43: 0 | X43: 0 | Y43: 0 | Z43: 0 | AA43: 0 | AB43: 0 | AF43: ULP Kotaraya | AG43: Kerusakan PHB - TM | AH43: 0 | AI43: 0 | AJ43: 0 | AK43: 0 | AL43: 0 | AM43: 0 | AN43: 0 | AO43: 0 | AP43: 0 | AQ43: 0 | AR43: 0 | AS43: 0
C44: Kerusakan Trafo Distribusi | R44: Kerusakan Trafo Distribusi | S44: 0 | T44: 0 | U44: 0 | V44: 0 | W44: 0 | X44: 0 | Y44: 0 | Z44: 0 | AA44: 0 | AB44: 0 | AG44: Kerusakan Trafo Distribusi | AH44: 0 | AI44: 0 | AJ44: 0 | AK44: 0 | AL44: 0 | AM44: 0 | AN44: 0 | AO44: 0 | AP44: 0 | AQ44: 0 | AR44: 0 | AS44: 0
C45: Jumlah | D45: 0 | E45: 0 | F45: 1 | G45: 1 | H45: 1 | I45: 1 | J45: 1 | K45: 1 | L45: 1 | M45: 1 | N45: 1 | O45: 1 | R45: Jumlah | S45: 0 | T45: 0 | U45: 0 | V45: 0 | W45: 0 | X45: 0 | Y45: 0 | Z45: 0 | AA45: 0 | AB45: 0 | AC45: 0 | AD45: 0 | AG45: Jumlah | AH45: 0 | AI45: 0 | AJ45: 0 | AK45: 0 | AL45: 0 | AM45: 0 | AN45: 0 | AO45: 0 | AP45: 0 | AQ45: 0 | AR45: 0 | AS45: 0
B46: UP3 Tolitoli | C46: Kerusakan PHB - TM | Q46: ULP Kotaraya | R46: Kerusakan PHB - TM | S46: 0 | T46: 0 | U46: 0 | V46: 0 | W46: 0 | X46: 0 | Y46: 1 | Z46: 0 | AA46: 0 | AB46: 0 | AF46: ULP Kotaraya | AG46: Kerusakan PHB - TM | AH46: 0 | AI46: 0 | AJ46: 0 | AK46: 0 | AL46: 0 | AM46: 0 | AN46: 1 | AO46: 1 | AP46: 1 | AQ46: 1 | AR46: 1 | AS46: 1
C47: Kerusakan Trafo Distribusi | R47: Kerusakan Trafo Distribusi | S47: 0 | T47: 0 | U47: 0 | V47: 0 | W47: 1 | X47: 1 | Y47: 0 | Z47: 0 | AA47: 0 | AB47: 0 | AG47: Kerusakan Trafo Distribusi | AH47: 0 | AI47: 0 | AJ47: 0 | AK47: 0 | AL47: 1 | AM47: 2 | AN47: 2 | AO47: 2 | AP47: 2 | AQ47: 2 | AR47: 2 | AS47: 2
C48: Jumlah | D48: 0 | E48: 0 | F48: 5 | G48: 5 | H48: 5 | I48: 5 | J48: 5 | K48: 5 | L48: 5 | M48: 5 | N48: 5 | O48: 5 | R48: Jumlah | S48: 0 | T48: 0 | U48: 0 | V48: 0 | W48: 1 | X48: 1 | Y48: 1 | Z48: 0 | AA48: 0 | AB48: 0 | AC48: 0 | AD48: 0 | AG48: Jumlah | AH48: 0 | AI48: 0 | AJ48: 0 | AK48: 0 | AL48: 1 | AM48: 2 | AN48: 3 | AO48: 3 | AP48: 3 | AQ48: 3 | AR48: 3 | AS48: 3
A50: 4 | B50: PENURUNAN FEEDBACK RATING NEGATIF PADA PLN MOBILE - GANGGUAN | Q50: PENURUNAN FEEDBACK RATING NEGATIF PADA PLN MOBILE - GANGGUAN | AF50: PENURUNAN FEEDBACK RATING NEGATIF PADA PLN MOBILE - GANGGUAN
B51: TARGET | Q51: REALISASI BULANAN | AF51: REALISASI KOMULATIF
B52: Unit | D52: Jan | E52: Feb | F52: Mar | G52: Apr | H52: May | I52: Jun | J52: Jul | K52: Aug | L52: Sep | M52: Oct | N52: Nov | O52: Dec | Q52: Unit | S52: Jan | T52: Feb | U52: Mar | V52: Apr | W52: May | X52: Jun | Y52: Jul | Z52: Aug | AA52: Sep | AB52: Oct | AC52: Nov | AD52: Dec | AF52: Unit | AH52: Jan | AI52: Feb | AJ52: Mar | AK52: Apr | AL52: May | AM52: Jun | AN52: Jul | AO52: Aug | AP52: Sep | AQ52: Oct | AR52: Nov | AS52: Dec
B53: ULP Tolitoli | C53: Total WO Gangguan | Q53: ULP Tolitoli | R53: Total WO Gangguan | S53: 341 | T53: 292 | U53: 397 | V53: 339 | W53: 317 | X53: 299 | Y53: 390 | Z53: 320 | AA53: 300 | AB53: 300 | AF53: ULP Tolitoli | AG53: Total WO Gangguan | AH53: 341 | AI53: 633 | AJ53: 1030 | AK53: 1369 | AL53: 1686 | AM53: 1985 | AN53: 2375 | AO53: 2695 | AP53: 2995 | AQ53: 3295 | AR53: 3295 | AS53: 3295
C54: Rating Negatif Gangguan | R54: Rating Negatif Gangguan | S54: 0 | T54: 0 | U54: 0 | V54: 0 | W54: 0 | X54: 0 | Y54: 0 | Z54: 0 | AA54: 0 | AB54: 0 | AG54: Rating Negatif Gangguan | AH54: 0 | AI54: 0 | AJ54: 0 | AK54: 0 | AL54: 0 | AM54: 0 | AN54: 0 | AO54: 0 | AP54: 0 | AQ54: 0 | AR54: 0 | AS54: 0
C55: Feedback Rating Negatif | D55: 0.09 | E55: 0.09 | F55: 0.09 | G55: 0.09 | H55: 0.09 | I55: 0.09 | J55: 0.09 | K55: 0.09 | L55: 0.09 | M55: 0.09 | N55: 0.09 | O55: 0.09 | R55: Feedback Rating Negatif | S55: 0 | T55: 0 | U55: 0 | V55: 0 | W55: 0 | X55: 0 | Y55: 0 | Z55: 0 | AA55: 0 | AB55: 0 | AC55: #DIV/0! | AD55: #DIV/0! | AG55: Feedback Rating Negatif | AH55: 0 | AI55: 0 | AJ55: 0 | AK55: 0 | AL55: 0 | AM55: 0 | AN55: 0 | AO55: 0 | AP55: 0 | AQ55: 0 | AR55: 0 | AS55: 0
B56: ULP Leok | C56: Total WO Gangguan | Q56: ULP Leok | R56: Total WO Gangguan | S56: 466 | T56: 413 | U56: 389 | V56: 322 | W56: 319 | X56: 261 | Y56: 351 | Z56: 422 | AA56: 489 | AB56: 489 | AF56: ULP Leok | AG56: Total WO Gangguan | AH56: 466 | AI56: 879 | AJ56: 1268 | AK56: 1590 | AL56: 1909 | AM56: 2170 | AN56: 2521 | AO56: 2943 | AP56: 3432 | AQ56: 3921 | AR56: 3921 | AS56: 3921
C57: Rating Negatif Gangguan | R57: Rating Negatif Gangguan | S57: 0 | T57: 0 | U57: 0 | V57: 0 | W57: 0 | X57: 0 | Y57: 0 | Z57: 0 | AA57: 0 | AB57: 0 | AG57: Rating Negatif Gangguan | AH57: 0 | AI57: 0 | AJ57: 0 | AK57: 0 | AL57: 0 | AM57: 0 | AN57: 0 | AO57: 0 | AP57: 0 | AQ57: 0 | AR57: 0 | AS57: 0
C58: Feedback Rating Negatif | D58: 0.09 | E58: 0.09 | F58: 0.09 | G58: 0.09 | H58: 0.09 | I58: 0.09 | J58: 0.09 | K58: 0.09 | L58: 0.09 | M58: 0.09 | N58: 0.09 | O58: 0.09 | R58: Feedback Rating Negatif | S58: 0 | T58: 0 | U58: 0 | V58: 0 | W58: 0 | X58: 0 | Y58: 0 | Z58: 0 | AA58: 0 | AB58: 0 | AC58: #DIV/0! | AD58: #DIV/0! | AG58: Feedback Rating Negatif | AH58: 0 | AI58: 0 | AJ58: 0 | AK58: 0 | AL58: 0 | AM58: 0 | AN58: 0 | AO58: 0 | AP58: 0 | AQ58: 0 | AR58: 0 | AS58: 0
B59: ULP Bangkir | C59: Total WO Gangguan | Q59: ULP Bangkir | R59: Total WO Gangguan | S59: 351 | T59: 334 | U59: 431 | V59: 335 | W59: 299 | X59: 269 | Y59: 308 | Z59: 322 | AA59: 290 | AB59: 290 | AF59: ULP Bangkir | AG59: Total WO Gangguan | AH59: 351 | AI59: 685 | AJ59: 1116 | AK59: 1451 | AL59: 1750 | AM59: 2019 | AN59: 2327 | AO59: 2649 | AP59: 2939 | AQ59: 3229 | AR59: 3229 | AS59: 3229
C60: Rating Negatif Gangguan | R60: Rating Negatif Gangguan | S60: 0 | T60: 0 | U60: 0 | V60: 0 | W60: 0 | X60: 0 | Y60: 0 | Z60: 0 | AA60: 0 | AB60: 0 | AG60: Rating Negatif Gangguan | AH60: 0 | AI60: 0 | AJ60: 0 | AK60: 0 | AL60: 0 | AM60: 0 | AN60: 0 | AO60: 0 | AP60: 0 | AQ60: 0 | AR60: 0 | AS60: 0
C61: Feedback Rating Negatif | D61: 0.09 | E61: 0.09 | F61: 0.09 | G61: 0.09 | H61: 0.09 | I61: 0.09 | J61: 0.09 | K61: 0.09 | L61: 0.09 | M61: 0.09 | N61: 0.09 | O61: 0.09 | R61: Feedback Rating Negatif | S61: 0 | T61: 0 | U61: 0 | V61: 0 | W61: 0 | X61: 0 | Y61: 0 | Z61: 0 | AA61: 0 | AB61: 0 | AC61: #DIV/0! | AD61: #DIV/0! | AG61: Feedback Rating Negatif | AH61: 0 | AI61: 0 | AJ61: 0 | AK61: 0 | AL61: 0 | AM61: 0 | AN61: 0 | AO61: 0 | AP61: 0 | AQ61: 0 | AR61: 0 | AS61: 0
B62: ULP Moutong | C62: Total WO Gangguan | Q62: ULP Moutong | R62: Total WO Gangguan | S62: 209 | T62: 341 | U62: 351 | V62: 249 | W62: 213 | X62: 224 | Y62: 220 | Z62: 218 | AA62: 200 | AB62: 200 | AF62: ULP Moutong | AG62: Total WO Gangguan | AH62: 209 | AI62: 550 | AJ62: 901 | AK62: 1150 | AL62: 1363 | AM62: 1587 | AN62: 1807 | AO62: 2025 | AP62: 2225 | AQ62: 2425 | AR62: 2425 | AS62: 2425
C63: Rating Negatif Gangguan | R63: Rating Negatif Gangguan | S63: 0 | T63: 0 | U63: 0 | V63: 0 | W63: 0 | X63: 0 | Y63: 0 | Z63: 0 | AA63: 0 | AB63: 0 | AG63: Rating Negatif Gangguan | AH63: 0 | AI63: 0 | AJ63: 0 | AK63: 0 | AL63: 0 | AM63: 0 | AN63: 0 | AO63: 0 | AP63: 0 | AQ63: 0 | AR63: 0 | AS63: 0
C64: Feedback Rating Negatif | D64: 0.09 | E64: 0.09 | F64: 0.09 | G64: 0.09 | H64: 0.09 | I64: 0.09 | J64: 0.09 | K64: 0.09 | L64: 0.09 | M64: 0.09 | N64: 0.09 | O64: 0.09 | R64: Feedback Rating Negatif | S64: 0 | T64: 0 | U64: 0 | V64: 0 | W64: 0 | X64: 0 | Y64: 0 | Z64: 0 | AA64: 0 | AB64: 0 | AC64: #DIV/0! | AD64: #DIV/0! | AG64: Feedback Rating Negatif | AH64: 0 | AI64: 0 | AJ64: 0 | AK64: 0 | AL64: 0 | AM64: 0 | AN64: 0 | AO64: 0 | AP64: 0 | AQ64: 0 | AR64: 0 | AS64: 0
B65: ULP Kotaraya | C65: Total WO Gangguan | Q65: ULP Kotaraya | R65: Total WO Gangguan | S65: 947 | T65: 887 | U65: 975 | V65: 975 | W65: 892 | X65: 874 | Y65: 832 | Z65: 874 | AA65: 123 | AB65: 123 | AF65: ULP Kotaraya | AG65: Total WO Gangguan | AH65: 947 | AI65: 1834 | AJ65: 2809 | AK65: 3784 | AL65: 4676 | AM65: 5550 | AN65: 6382 | AO65: 7256 | AP65: 7379 | AQ65: 7502 | AR65: 7502 | AS65: 7502
C66: Rating Negatif Gangguan | R66: Rating Negatif Gangguan | S66: 0 | T66: 0 | U66: 0 | V66: 0 | W66: 0 | X66: 0 | Y66: 0 | Z66: 0 | AA66: 0 | AB66: 0 | AG66: Rating Negatif Gangguan | AH66: 0 | AI66: 0 | AJ66: 0 | AK66: 0 | AL66: 0 | AM66: 0 | AN66: 0 | AO66: 0 | AP66: 0 | AQ66: 0 | AR66: 0 | AS66: 0
C67: Feedback Rating Negatif | D67: 0.09 | E67: 0.09 | F67: 0.09 | G67: 0.09 | H67: 0.09 | I67: 0.09 | J67: 0.09 | K67: 0.09 | L67: 0.09 | M67: 0.09 | N67: 0.09 | O67: 0.09 | R67: Feedback Rating Negatif | S67: 0 | T67: 0 | U67: 0 | V67: 0 | W67: 0 | X67: 0 | Y67: 0 | Z67: 0 | AA67: 0 | AB67: 0 | AC67: #DIV/0! | AD67: #DIV/0! | AG67: Feedback Rating Negatif | AH67: 0 | AI67: 0 | AJ67: 0 | AK67: 0 | AL67: 0 | AM67: 0 | AN67: 0 | AO67: 0 | AP67: 0 | AQ67: 0 | AR67: 0 | AS67: 0
B68: UP3 Tolitoli | C68: Total WO Gangguan | Q68: UP3 Tolitoli | R68: Total WO Gangguan | S68: 2314 | T68: 2267 | U68: 2543 | V68: 2220 | W68: 2040 | X68: 1927 | Y68: 2101 | Z68: 2156 | AA68: 1402 | AB68: 1402 | AC68: 0 | AD68: 0 | AF68: UP3 Tolitoli | AG68: Total WO Gangguan | AH68: 2314 | AI68: 4581 | AJ68: 7124 | AK68: 9344 | AL68: 11384 | AM68: 13311 | AN68: 15412 | AO68: 17568 | AP68: 18970 | AQ68: 20372 | AR68: 20372 | AS68: 20372
C69: Rating Negatif Gangguan | R69: Rating Negatif Gangguan | S69: 0 | T69: 0 | U69: 0 | V69: 0 | W69: 0 | X69: 0 | Y69: 0 | Z69: 0 | AA69: 0 | AB69: 0 | AC69: 0 | AD69: 0 | AG69: Rating Negatif Gangguan | AH69: 0 | AI69: 0 | AJ69: 0 | AK69: 0 | AL69: 0 | AM69: 0 | AN69: 0 | AO69: 0 | AP69: 0 | AQ69: 0 | AR69: 0 | AS69: 0
C70: Feedback Rating Negatif | D70: 0.09 | E70: 0.09 | F70: 0.09 | G70: 0.09 | H70: 0.09 | I70: 0.09 | J70: 0.09 | K70: 0.09 | L70: 0.09 | M70: 0.09 | N70: 0.09 | O70: 0.09 | R70: Feedback Rating Negatif | S70: 0 | T70: 0 | U70: 0 | V70: 0 | W70: 0 | X70: 0 | Y70: 0 | Z70: 0 | AA70: 0 | AB70: 0 | AC70: #DIV/0! | AD70: #DIV/0! | AG70: Feedback Rating Negatif | AH70: 0 | AI70: 0 | AJ70: 0 | AK70: 0 | AL70: 0 | AM70: 0 | AN70: 0 | AO70: 0 | AP70: 0 | AQ70: 0 | AR70: 0 | AS70: 0
B72: PENURUNAN PENGADUAN GANGGUAN BERULANG PADA PLN MOBILE | Q72: PENURUNAN PENGADUAN GANGGUAN BERULANG PADA PLN MOBILE | AF72: PENURUNAN PENGADUAN GANGGUAN BERULANG PADA PLN MOBILE | AJ72: 0
B73: TARGET | Q73: REALISASI BULANAN | AF73: REALIASI KOMULATIF
B74: Unit | D74: Jan | E74: Feb | F74: Mar | G74: Apr | H74: May | I74: Jun | J74: Jul | K74: Aug | L74: Sep | M74: Oct | N74: Nov | O74: Dec | Q74: Unit | S74: Jan | T74: Feb | U74: Mar | V74: Apr | W74: May | X74: Jun | Y74: Jul | Z74: Aug | AA74: Sep | AB74: Oct | AC74: Nov | AD74: Dec | AF74: Unit | AH74: Jan | AI74: Feb | AJ74: Mar | AK74: Apr | AL74: May | AM74: Jun | AN74: Jul | AO74: Aug | AP74: Sep | AQ74: Oct | AR74: Nov | AS74: Dec
B75: ULP Tolitoli | C75: Total WO Gangguan | Q75: ULP Tolitoli | R75: Total WO Gangguan | S75: 341 | T75: 292 | U75: 397 | V75: 339 | W75: 317 | X75: 299 | Y75: 390 | Z75: 320 | AA75: 300 | AB75: 300 | AC75: 0 | AD75: 0 | AF75: ULP Tolitoli | AG75: Total WO Gangguan | AH75: 341 | AI75: 633 | AJ75: 1030 | AK75: 1369 | AL75: 1686 | AM75: 1985 | AN75: 2375 | AO75: 2695 | AP75: 2995 | AQ75: 3295 | AR75: 3295 | AS75: 3295
C76: Laporan Berulang | R76: Laporan Berulang | S76: 0 | T76: 0 | U76: 0 | V76: 0 | W76: 0 | X76: 0 | Y76: 0 | Z76: 0 | AA76: 0 | AB76: 0 | AC76: 1 | AD76: 0 | AG76: Laporan Berulang | AH76: 0 | AI76: 0 | AJ76: 0 | AK76: 0 | AL76: 0 | AM76: 0 | AN76: 0 | AO76: 0 | AP76: 0 | AQ76: 0 | AR76: 1 | AS76: 1
C77: Laporan Berulang | D77: 0.04 | E77: 0.04 | F77: 0.04 | G77: 0.04 | H77: 0.04 | I77: 0.04 | J77: 0.04 | K77: 0.04 | L77: 0.04 | M77: 0.04 | N77: 0.04 | O77: 0.04 | R77: Laporan Berulang | S77: 0 | T77: 0 | U77: 0 | V77: 0 | W77: 0 | X77: 0 | Y77: 0 | Z77: 0 | AA77: 0 | AB77: 0 | AC77: #DIV/0! | AD77: #DIV/0! | AG77: Laporan Berulang | AH77: 0 | AI77: 0 | AJ77: 0 | AK77: 0 | AL77: 0 | AM77: 0 | AN77: 0 | AO77: 0 | AP77: 0 | AQ77: 0 | AR77: 0.030349014 | AS77: 0.030349014
B78: ULP Leok | C78: Total WO Gangguan | Q78: ULP Leok | R78: Total WO Gangguan | S78: 466 | T78: 413 | U78: 389 | V78: 322 | W78: 319 | X78: 261 | Y78: 351 | Z78: 422 | AA78: 489 | AB78: 489 | AC78: 0 | AD78: 0 | AF78: ULP Leok | AG78: Total WO Gangguan | AH78: 466 | AI78: 879 | AJ78: 1268 | AK78: 1590 | AL78: 1909 | AM78: 2170 | AN78: 2521 | AO78: 2943 | AP78: 3432 | AQ78: 3921 | AR78: 3921 | AS78: 3921
C79: Laporan Berulang | R79: Laporan Berulang | S79: 0 | T79: 0 | U79: 0 | V79: 0 | W79: 0 | X79: 0 | Y79: 0 | Z79: 0 | AA79: 0 | AB79: 0 | AC79: 0 | AD79: 1 | AG79: Laporan Berulang | AH79: 0 | AI79: 0 | AJ79: 0 | AK79: 0 | AL79: 0 | AM79: 0 | AN79: 0 | AO79: 0 | AP79: 0 | AQ79: 0 | AR79: 0 | AS79: 1
C80: Laporan Berulang | D80: 0.04 | E80: 0.04 | F80: 0.04 | G80: 0.04 | H80: 0.04 | I80: 0.04 | J80: 0.04 | K80: 0.04 | L80: 0.04 | M80: 0.04 | N80: 0.04 | O80: 0.04 | R80: Laporan Berulang | S80: 0 | T80: 0 | U80: 0 | V80: 0 | W80: 0 | X80: 0 | Y80: 0 | Z80: 0 | AA80: 0 | AB80: 0 | AC80: #DIV/0! | AD80: #DIV/0! | AG80: Laporan Berulang | AH80: 0 | AI80: 0 | AJ80: 0 | AK80: 0 | AL80: 0 | AM80: 0 | AN80: 0 | AO80: 0 | AP80: 0 | AQ80: 0 | AR80: 0 | AS80: 0.025503698
B81: ULP Bangkir | C81: Total WO Gangguan | Q81: ULP Bangkir | R81: Total WO Gangguan | S81: 351 | T81: 334 | U81: 431 | V81: 335 | W81: 299 | X81: 269 | Y81: 308 | Z81: 322 | AA81: 290 | AB81: 290 | AC81: 0 | AD81: 0 | AF81: ULP Bangkir | AG81: Total WO Gangguan | AH81: 351 | AI81: 685 | AJ81: 1116 | AK81: 1451 | AL81: 1750 | AM81: 2019 | AN81: 2327 | AO81: 2649 | AP81: 2939 | AQ81: 3229 | AR81: 3229 | AS81: 3229
C82: Laporan Berulang | R82: Laporan Berulang | S82: 0 | T82: 0 | U82: 0 | V82: 0 | W82: 0 | X82: 0 | Y82: 0 | Z82: 0 | AA82: 0 | AB82: 0 | AC82: 1 | AD82: 0 | AG82: Laporan Berulang | AH82: 0 | AI82: 0 | AJ82: 0 | AK82: 0 | AL82: 0 | AM82: 0 | AN82: 0 | AO82: 0 | AP82: 0 | AQ82: 0 | AR82: 1 | AS82: 1
C83: Laporan Berulang | D83: 0.04 | E83: 0.04 | F83: 0.04 | G83: 0.04 | H83: 0.04 | I83: 0.04 | J83: 0.04 | K83: 0.04 | L83: 0.04 | M83: 0.04 | N83: 0.04 | O83: 0.04 | R83: Laporan Berulang | S83: 0 | T83: 0 | U83: 0 | V83: 0 | W83: 0 | X83: 0 | Y83: 0 | Z83: 0 | AA83: 0 | AB83: 0 | AC83: #DIV/0! | AD83: #DIV/0! | AG83: Laporan Berulang | AH83: 0 | AI83: 0 | AJ83: 0 | AK83: 0 | AL83: 0 | AM83: 0 | AN83: 0 | AO83: 0 | AP83: 0 | AQ83: 0 | AR83: 0.03096934 | AS83: 0.03096934
B84: ULP Moutong | C84: Total WO Gangguan | Q84: ULP Moutong | R84: Total WO Gangguan | S84: 209 | T84: 341 | U84: 351 | V84: 249 | W84: 213 | X84: 224 | Y84: 220 | Z84: 218 | AA84: 200 | AB84: 200 | AC84: 0 | AD84: 0 | AF84: ULP Moutong | AG84: Total WO Gangguan | AH84: 209 | AI84: 550 | AJ84: 901 | AK84: 1150 | AL84: 1363 | AM84: 1587 | AN84: 1807 | AO84: 2025 | AP84: 2225 | AQ84: 2425 | AR84: 2425 | AS84: 2425
C85: Laporan Berulang | R85: Laporan Berulang | S85: 0 | T85: 0 | U85: 0 | V85: 0 | W85: 0 | X85: 0 | Y85: 0 | Z85: 0 | AA85: 0 | AB85: 0 | AC85: 0 | AD85: 0 | AG85: Laporan Berulang | AH85: 0 | AI85: 0 | AJ85: 0 | AK85: 0 | AL85: 0 | AM85: 0 | AN85: 0 | AO85: 0 | AP85: 0 | AQ85: 0 | AR85: 0 | AS85: 0
C86: Laporan Berulang | D86: 0.04 | E86: 0.04 | F86: 0.04 | G86: 0.04 | H86: 0.04 | I86: 0.04 | J86: 0.04 | K86: 0.04 | L86: 0.04 | M86: 0.04 | N86: 0.04 | O86: 0.04 | R86: Laporan Berulang | S86: 0 | T86: 0 | U86: 0 | V86: 0 | W86: 0 | X86: 0 | Y86: 0 | Z86: 0 | AA86: 0 | AB86: 0 | AC86: #DIV/0! | AD86: #DIV/0! | AG86: Laporan Berulang | AH86: 0 | AI86: 0 | AJ86: 0 | AK86: 0 | AL86: 0 | AM86: 0 | AN86: 0 | AO86: 0 | AP86: 0 | AQ86: 0 | AR86: 0 | AS86: 0
B87: ULP Kotaraya | C87: Total WO Gangguan | Q87: ULP Kotaraya | R87: Total WO Gangguan | S87: 947 | T87: 887 | U87: 975 | V87: 975 | W87: 892 | X87: 874 | Y87: 832 | Z87: 874 | AA87: 123 | AB87: 123 | AC87: 0 | AD87: 0 | AF87: ULP Kotaraya | AG87: Total WO Gangguan | AH87: 947 | AI87: 1834 | AJ87: 2809 | AK87: 3784 | AL87: 4676 | AM87: 5550 | AN87: 6382 | AO87: 7256 | AP87: 7379 | AQ87: 7502 | AR87: 7502 | AS87: 7502
C88: Laporan Berulang | R88: Laporan Berulang | S88: 0 | T88: 0 | U88: 0 | V88: 0 | W88: 0 | X88: 0 | Y88: 0 | Z88: 0 | AA88: 0 | AB88: 0 | AC88: 0 | AD88: 0 | AG88: Laporan Berulang | AH88: 0 | AI88: 0 | AJ88: 0 | AK88: 0 | AL88: 0 | AM88: 0 | AN88: 0 | AO88: 0 | AP88: 0 | AQ88: 0 | AR88: 0 | AS88: 0
C89: Laporan Berulang | D89: 0.04 | E89: 0.04 | F89: 0.04 | G89: 0.04 | H89: 0.04 | I89: 0.04 | J89: 0.04 | K89: 0.04 | L89: 0.04 | M89: 0.04 | N89: 0.04 | O89: 0.04 | R89: Laporan Berulang | S89: 0 | T89: 0 | U89: 0 | V89: 0 | W89: 0 | X89: 0 | Y89: 0 | Z89: 0 | AA89: 0 | AB89: 0 | AC89: #DIV/0! | AD89: #DIV/0! | AG89: Laporan Berulang | AH89: 0 | AI89: 0 | AJ89: 0 | AK89: 0 | AL89: 0 | AM89: 0 | AN89: 0 | AO89: 0 | AP89: 0 | AQ89: 0 | AR89: 0 | AS89: 0
B90: UP3 Tolitoli | C90: Total WO Gangguan | Q90: UP3 Tolitoli | R90: Total WO Gangguan | S90: 2314 | T90: 2267 | U90: 2543 | V90: 2220 | W90: 2040 | X90: 1927 | Y90: 2101 | Z90: 2156 | AA90: 1402 | AB90: 1402 | AC90: 0 | AD90: 0 | AF90: UP3 Tolitoli | AG90: Total WO Gangguan | AH90: 2314 | AI90: 4581 | AJ90: 7124 | AK90: 9344 | AL90: 11384 | AM90: 13311 | AN90: 15412 | AO90: 17568 | AP90: 18970 | AQ90: 20372 | AR90: 20372 | AS90: 20372
C91: Laporan Berulang | R91: Laporan Berulang | S91: 0 | T91: 0 | U91: 0 | V91: 0 | W91: 0 | X91: 0 | Y91: 0 | Z91: 0 | AA91: 0 | AB91: 0 | AC91: 0 | AD91: 1 | AG91: Laporan Berulang | AH91: 0 | AI91: 0 | AJ91: 0 | AK91: 0 | AL91: 0 | AM91: 0 | AN91: 0 | AO91: 0 | AP91: 0 | AQ91: 0 | AR91: 0 | AS91: 1
C92: Laporan Berulang | D92: 0.04 | E92: 0.04 | F92: 0.04 | G92: 0.04 | H92: 0.04 | I92: 0.04 | J92: 0.04 | K92: 0.04 | L92: 0.04 | M92: 0.04 | N92: 0.04 | O92: 0.04 | R92: Laporan Berulang | S92: 0 | T92: 0 | U92: 0 | V92: 0 | W92: 0 | X92: 0 | Y92: 0 | Z92: 0 | AA92: 0 | AB92: 0 | AC92: #DIV/0! | AD92: #DIV/0! | AG92: Laporan Berulang | AH92: 0 | AI92: 0 | AJ92: 0 | AK92: 0 | AL92: 0 | AM92: 0 | AN92: 0 | AO92: 0 | AP92: 0 | AQ92: 0 | AR92: 0 | AS92: 0.0049086982
B94: RATING PLN MOBILE | Q94: RATING PLN MOBILE | AF94: RATING PLN MOBILE
B95: TARGET | Q95: REALISASI BULANAN | AF95: REALIASI KOMULATIF
B96: Unit | D96: Jan | E96: Feb | F96: Mar | G96: Apr | H96: May | I96: Jun | J96: Jul | K96: Aug | L96: Sep | M96: Oct | N96: Nov | O96: Dec | Q96: Unit | S96: Jan | T96: Feb | U96: Mar | V96: Apr | W96: May | X96: Jun | Y96: Jul | Z96: Aug | AA96: Sep | AB96: Oct | AC96: Nov | AD96: Dec | AF96: Unit | AH96: Jan | AI96: Feb | AJ96: Mar | AK96: Apr | AL96: May | AM96: Jun | AN96: Jul | AO96: Aug | AP96: Sep | AQ96: Oct | AR96: Nov | AS96: Dec
B97: Semua Unit | C97: Rating | D97: 4.9 | E97: 4.9 | F97: 4.9 | G97: 4.9 | H97: 4.9 | I97: 4.9 | J97: 4.9 | K97: 4.9 | L97: 4.9 | M97: 4.9 | N97: 4.9 | O97: 4.9 | Q97: Semua Unit | R97: Rating | S97: 4.91 | T97: 4.91 | U97: 4.91 | V97: 4.91 | W97: 4.9 | X97: 4.9 | Y97: 4.9 | Z97: 4.9 | AA97: 4.9 | AB97: 4.9 | AC97: 4.9 | AD97: 4.9 | AF97: Semua Unit | AG97: Rating | AH97: 4.91 | AI97: 4.91 | AJ97: 4.91 | AK97: 4.91 | AL97: 4.9 | AM97: 4.9 | AN97: 4.9 | AO97: 4.9 | AP97: 4.9 | AQ97: 4.9 | AR97: 4.9 | AS97: 4.9
AF98: JUMLAH PENGGUNA SWACAM
B99: JUMLAH KALI TRANSAKSI KEUANGAN PLN MOBILE - TOTAL | Q99: JUMLAH KALI TRANSAKSI KEUANGAN PLN MOBILE - TOTAL | AF99: JUMLAH KALI TRANSAKSI KEUANGAN PLN MOBILE - TOTAL
B100: TARGET | Q100: REALISASI BULANAN | AF100: REALIASI KOMULATIF
B101: Unit | D101: Jan | E101: Feb | F101: Mar | G101: Apr | H101: May | I101: Jun | J101: Jul | K101: Aug | L101: Sep | M101: Oct | N101: Nov | O101: Dec | Q101: Unit | S101: Jan | T101: Feb | U101: Mar | V101: Apr | W101: May | X101: Jun | Y101: Jul | Z101: Aug | AA101: Sep | AB101: Oct | AC101: Nov | AD101: Dec | AF101: Unit | AH101: Jan | AI101: Feb | AJ101: Mar | AK101: Apr | AL101: May | AM101: Jun | AN101: Jul | AO101: Aug | AP101: Sep | AQ101: Oct | AR101: Nov | AS101: Dec
B102: ULP Tolitoli | C102: Jumlah Kali Transaksi | D102: 1598 | E102: 3042 | F102: 4641 | G102: 6188 | H102: 7786 | I102: 9333 | J102: 10381 | K102: 11430 | L102: 12444 | M102: 13492 | N102: 14507 | O102: 15555 | Q102: ULP Tolitoli | R102: Jumlah Kali Transaksi | S102: 859 | T102: 1155 | U102: 1832 | V102: 2510 | W102: 2246 | X102: 1704 | Y102: 1965 | Z102: 1940 | AA102: 1898 | AB102: 1826 | AF102: ULP Tolitoli | AG102: Jumlah Kali Transaksi | AH102: 859 | AI102: 2014 | AJ102: 3846 | AK102: 6356 | AL102: 8602 | AM102: 10306 | AN102: 12271 | AO102: 14211 | AP102: 16109 | AQ102: 17935 | AR102: 0 | AS102: 0
B103: ULP Leok | C103: Jumlah Kali Transaksi | D103: 1826 | E103: 3476 | F103: 5303 | G103: 7070 | H103: 8896 | I103: 10664 | J103: 11862 | K103: 13060 | L103: 14219 | M103: 15417 | N103: 16576 | O103: 17774 | Q103: ULP Leok | R103: Jumlah Kali Transaksi | S103: 1054 | T103: 1117 | U103: 3018 | V103: 2434 | W103: 2576 | X103: 2432 | Y103: 2646 | Z103: 1661 | AA103: 1615 | AB103: 1565 | AF103: ULP Leok | AG103: Jumlah Kali Transaksi | AH103: 1054 | AI103: 2171 | AJ103: 5189 | AK103: 7623 | AL103: 10199 | AM103: 12631 | AN103: 15277 | AO103: 16938 | AP103: 18553 | AQ103: 20118 | AR103: 0 | AS103: 0
B104: ULP Bangkir | C104: Jumlah Kali Transaksi | D104: 841 | E104: 1601 | F104: 2442 | G104: 3257 | H104: 4098 | I104: 4912 | J104: 5740 | K104: 6567 | L104: 7368 | M104: 8196 | N104: 8996 | O104: 9824 | Q104: ULP Bangkir | R104: Jumlah Kali Transaksi | S104: 293 | T104: 222 | U104: 1609 | V104: 1844 | W104: 1467 | X104: 830 | Y104: 976 | Z104: 873 | AA104: 1374 | AB104: 986 | AF104: ULP Bangkir | AG104: Jumlah Kali Transaksi | AH104: 293 | AI104: 515 | AJ104: 2124 | AK104: 3968 | AL104: 5435 | AM104: 6265 | AN104: 7241 | AO104: 8114 | AP104: 9488 | AQ104: 10474 | AR104: 0 | AS104: 0
B105: ULP Moutong | C105: Jumlah Kali Transaksi | D105: 987 | E105: 1878 | F105: 2865 | G105: 3820 | H105: 4807 | I105: 5762 | J105: 6409 | K105: 7056 | L105: 7683 | M105: 8330 | N105: 8956 | O105: 9603 | Q105: ULP Moutong | R105: Jumlah Kali Transaksi | S105: 239 | T105: 388 | U105: 1743 | V105: 1778 | W105: 2124 | X105: 2399 | Y105: 2001 | Z105: 1572 | AA105: 1058 | AB105: 1059 | AF105: ULP Moutong | AG105: Jumlah Kali Transaksi | AH105: 239 | AI105: 627 | AJ105: 2370 | AK105: 4148 | AL105: 6272 | AM105: 8671 | AN105: 10672 | AO105: 12244 | AP105: 13302 | AQ105: 14361 | AR105: 0 | AS105: 0
B106: ULP Kotaraya | C106: Jumlah Kali Transaksi | D106: 1043 | E106: 1985 | F106: 3029 | G106: 4038 | H106: 5081 | I106: 6091 | J106: 6775 | K106: 7459 | L106: 8122 | M106: 8806 | N106: 9468 | O106: 10152 | Q106: ULP Kotaraya | R106: Jumlah Kali Transaksi | S106: 336 | T106: 500 | U106: 1984 | V106: 1752 | W106: 1469 | X106: 1147 | Y106: 917 | Z106: 1060 | AA106: 1473 | AB106: 1474 | AF106: ULP Kotaraya | AG106: Jumlah Kali Transaksi | AH106: 336 | AI106: 836 | AJ106: 2820 | AK106: 4572 | AL106: 6041 | AM106: 7188 | AN106: 8105 | AO106: 9165 | AP106: 10638 | AQ106: 12112 | AR106: 0 | AS106: 0
B107: UP3 Tolitoli | C107: Jumlah Kali Transaksi | D107: 5386 | E107: 10253 | F107: 15641 | G107: 20855 | H107: 26242 | I107: 31455 | J107: 36754 | K107: 42054 | L107: 47183 | M107: 52481 | N107: 57609 | O107: 62908 | Q107: UP3 Tolitoli | R107: Jumlah Kali Transaksi | S107: 2781 | T107: 3382 | U107: 10186 | V107: 10318 | W107: 9882 | X107: 8512 | Y107: 8505 | Z107: 7106 | AA107: 7418 | AB107: 6910 | AC107: 0 | AD107: 0 | AF107: UP3 Tolitoli | AG107: Jumlah Kali Transaksi | AH107: 2781 | AI107: 6163 | AJ107: 16349 | AK107: 26667 | AL107: 36549 | AM107: 45061 | AN107: 53566 | AO107: 60672 | AP107: 68090 | AQ107: 75000 | AR107: 0 | AS107: 0
A110: 5 | B110: RCT DAN RPT GANGGUAN (MENIT) | Q110: RCT DAN RPT GANGGUAN (MENIT) | AF110: RCT DAN RPT GANGGUAN (MENIT)
B111: TARGET | Q111: REALISASI BULANAN | AF111: REALISASI KOMULATIF
B112: Unit | D112: Jan | E112: Feb | F112: Mar | G112: Apr | H112: May | I112: Jun | J112: Jul | K112: Aug | L112: Sep | M112: Oct | N112: Nov | O112: Dec | Q112: Unit | S112: Jan | T112: Feb | U112: Mar | V112: Apr | W112: May | X112: Jun | Y112: Jul | Z112: Aug | AA112: Sep | AB112: Oct | AC112: Nov | AD112: Dec | AF112: Unit | AH112: Jan | AI112: Feb | AJ112: Mar | AK112: Apr | AL112: May | AM112: Jun | AN112: Jul | AO112: Aug | AP112: Sep | AQ112: Oct | AR112: Nov | AS112: Dec
B113: ULP Tolitoli | C113: Respond Time (RPT) | D113: 30 | E113: 30 | F113: 30 | G113: 30 | H113: 30 | I113: 30 | J113: 30 | K113: 30 | L113: 30 | M113: 30 | N113: 30 | O113: 30 | Q113: ULP Tolitoli | R113: Respond Time (RPT) | S113: 11.47716 | T113: 11.275 | U113: 11.162054 | V113: 11.401995 | W113: 14.48 | X113: 13.31789 | Y113: 13.31789 | Z113: 14.690741 | AA113: 14.942134 | AB113: 14.70729 | AF113: ULP Tolitoli | AG113: Respond Time (RPT) | AH113: 11.47716 | AI113: 11.37608 | AJ113: 11.304738 | AK113: 11.329052 | AL113: 11.959242 | AM113: 12.185683 | AN113: 12.347427 | AO113: 12.640341 | AP113: 12.896096 | AQ113: 13.077215 | AR113: 13.077215 | AS113: 13.077215
C114: Recovery Time (RCT) | R114: Recovery Time (RCT) | AG114: Recovery Time (RCT)
...

Sheet UP3
B1: KONTRAK MANAJEMEN 2025
B2: PT PLN (PERSERO) UID SULUTTENGGO | M2: OCT | N2: PILIH BULAN LAPORAN
B3: UP3 TOLITOLI
A4: NO | B4: KPI | D4: SATUAN | E4: BOBOT | F4: TARGET 2025 | G4: =VLOOKUP(M2,M7:N18,2,FALSE) -> S.D. OKTOBER
G5: TARGET | H5: REALISASI | I5: PENCAPAIAN | J5: NILAI
A6: 1 | B6: 2 | D6: 3 | E6: 4 | F6: 5 | G6: 6 | H6: 7 | I6: 8 | J6: 9
A7: =T.UP3!A7 -> I | B7: =T.UP3!B7 -> Key Performance Indikator | E7: =SUM(E8:E16) -> 40 | J7: =SUM(J8:J16) -> 41.76 | M7: JAN | N7: S.D. JANUARI | R7: =R8+R9+R10 -> 40.96 | S7: =S8+S9+S10 -> 41.25
A8: =T.UP3!A8 -> 1 | B8: =T.UP3!B8 -> Penjualan Tenaga Listrik | C8: =T.UP3!C8 -> ñ | D8: =T.UP3!D8 -> GWh | E8: =T.UP3!F8 -> 14 | F8: =T.UP3!H8 -> 231.47 | G8: =VLOOKUP(B8,T.UP3!$B$4:$T$69,MATCH('UP3'!$M$2,T.UP3!$B$5:$T$5,0),FALSE) -> 191.42 | H8: =VLOOKUP(B8,'R.UP3'!$B$4:$T$67,MATCH('UP3'!$M$2,'R.UP3'!$B$5:$T$5,0),FALSE) -> 185.5369 | I8: =IF(OR(G8="N/A",H8="N/A"),"N/A",IF((H8/G8*100)>=110,110,(H8/G8*100))) -> 96.9266 | J8: =ROUNDDOWN(IF(I8="N/A",0,IF(I8>110,E8*110/100,E8*I8/100)),2) -> 13.56 | M8: FEB | N8: S.D. FEBRUARI | R8: 13.56 | S8: 13.53 | T8: =R8-S8 -> 0.03
A9: =T.UP3!A9 -> 2 | B9: =T.UP3!B9 -> Keandalan Sistem | E9: =IF(OR(H9="N/A",G9="N/A"),0,T.UP3!F9) -> 14 | I9: =AVERAGE(I10:I12) -> 110 | J9: =ROUNDDOWN(IF(I9="N/A",0,IF(I9>110,E9*110/100,E9*I9/100)),2) -> 15.4 | M9: MAR | N9: S.D. MARET | R9: 15.4 | S9: 15.4 | T9: =R9-S9 -> 0
B10: =T.UP3!B10 -> a. SAIDI Sesuai Kewenangannya | C10: =T.UP3!C10 -> ò | D10: =T.UP3!D10 -> Menit/Plg | F10: =T.UP3!H10 -> 280.67 | G10: =VLOOKUP(B10,T.UP3!$B$4:$T$69,MATCH('UP3'!$M$2,T.UP3!$B$5:$T$5,0),FALSE) -> 233.89 | H10: =VLOOKUP(B10,'R.UP3'!$B$4:$T$67,MATCH('UP3'!$M$2,'R.UP3'!$B$5:$T$5,0),FALSE) -> 196.05712 | I10: =IF(OR(G10="N/A",H10="N/A"),"N/A",IF((2-(H10/G10))*100>=110,110,(2-(H10/G10))*100)) -> 110 | M10: APT | N10: S.D. APRIL | R10: 12 | S10: 12.32 | T10: =R10-S10 -> -0.32
B11: =T.UP3!B11 -> b. SAIFI Sesuai Kewenangannya | C11: =T.UP3!C11 -> ò | D11: =T.UP3!D11 -> Kali/Plg | F11: =T.UP3!H11 -> 2.97 | G11: =VLOOKUP(B11,T.UP3!$B$4:$T$69,MATCH('UP3'!$M$2,T.UP3!$B$5:$T$5,0),FALSE) -> 2.47 | H11: =VLOOKUP(B11,'R.UP3'!$B$4:$T$67,MATCH('UP3'!$M$2,'R.UP3'!$B$5:$T$5,0),FALSE) -> 2.1759568 | I11: =IF(OR(G11="N/A",H11="N/A"),"N/A",IF((2-(H11/G11))*100>=110,110,(2-(H11/G11))*100)) -> 110 | M11: MAY | N11: S.D. MEI
B12: =T.UP3!B12 -> c. ENS | C12: =T.UP3!C12 -> ò | D12: =T.UP3!D12 -> MWh | F12: =T.UP3!H12 -> 107.87 | G12: =VLOOKUP(B12,T.UP3!$B$4:$T$69,MATCH('UP3'!$M$2,T.UP3!$B$5:$T$5,0),FALSE) -> 89.89 | H12: =VLOOKUP(B12,'R.UP3'!$B$4:$T$67,MATCH('UP3'!$M$2,'R.UP3'!$B$5:$T$5,0),FALSE) -> 60.972 | I12: =IF(G12=0,0,IF(((G12-(H12-G12))/G12)*100<=0,0,IF(((G12-(H12-G12))/G12)*100>=110,110,((G12-(H12-G12))/G12)*100))) -> 110 | M12: JUN | N12: S.D. JUNI
A13: =T.UP3!A13 -> 3 | B13: =T.UP3!B13 -> Efisiensi Jaringan Distribusi | E13: =IF(OR(H13="N/A",G13="N/A"),0,T.UP3!F13) -> 12 | I13: =AVERAGE(I14:I16) -> 106.66884 | J13: =ROUNDDOWN(IF(I13="N/A",0,IF(I13>110,E13*110/100,E13*I13/100)),2) -> 12.8 | M13: JUL | N13: S.D. JULI
B14: =T.UP3!B14 -> a. Susut Distribusi Tanpa E-min (sesuai kewenangan) | C14: =T.UP3!C14 -> ò | D14: =T.UP3!D14 -> % | F14: =T.UP3!H14 -> 9 | G14: =VLOOKUP(B14,T.UP3!$B$4:$T$69,MATCH('UP3'!$M$2,T.UP3!$B$5:$T$5,0),FALSE) -> 9.14 | H14: =VLOOKUP(B14,'R.UP3'!$B$4:$T$67,MATCH('UP3'!$M$2,'R.UP3'!$B$5:$T$5,0),FALSE) -> 8.2408737 | I14: =IF(OR(G14="N/A",H14="N/A"),"N/A",IF((2-(H14/G14))*100>=110,110,(2-(H14/G14))*100)) -> 109.83727 | M14: AUG | N14: S.D. AGUSTUS
B15: =T.UP3!B15 -> b. Penyelesaian Temuan P2TL | C15: =T.UP3!C15 -> ñ | D15: =T.UP3!D15 -> % | F15: =T.UP3!H15 -> 100 | G15: =VLOOKUP(B15,T.UP3!$B$4:$T$69,MATCH('UP3'!$M$2,T.UP3!$B$5:$T$5,0),FALSE) -> 80 | H15: =VLOOKUP(B15,'R.UP3'!$B$4:$T$67,MATCH('UP3'!$M$2,'R.UP3'!$B$5:$T$5,0),FALSE) -> 98.245663 | I15: =IF(OR(G15="N/A",H15="N/A"),"N/A",IF((H15/G15*100)>=110,110,(H15/G15*100))) -> 110 | M15: SEP | N15: S.D. SEPTEMBER
B16: =T.UP3!B16 -> c. Penyelesaian Ganti Meter | C16: =T.UP3!C16 -> ñ | D16: =T.UP3!D16 -> Unit | F16: =T.UP3!H16 -> 4727 | G16: =VLOOKUP(B16,T.UP3!$B$4:$T$69,MATCH('UP3'!$M$2,T.UP3!$B$5:$T$5,0),FALSE) -> 4727 | H16: =VLOOKUP(B16,'R.UP3'!$B$4:$T$67,MATCH('UP3'!$M$2,'R.UP3'!$B$5:$T$5,0),FALSE) -> 4735 | I16: =IF(OR(G16="N/A",H16="N/A"),"N/A",IF((H16/G16*100)>=110,110,(H16/G16*100))) -> 100.16924 | M16: OCT | N16: S.D. OKTOBER
A17: =T.UP3!A17 -> II | B17: =T.UP3!B17 -> Perfomance Indicators | E17: =SUM(E18:E68) -> 60 | J17: =SUM(J18,J22,J27,J30,J33,J35,J42,J45,J49,J53,J58) -> 61.08 | M17: NOV | N17: S.D. NOVEMBER
A18: =T.UP3!A18 -> 4 | B18: =T.UP3!B18 -> Keandalan Jaringan Distribusi | E18: =T.UP3!F18 -> 6 | I18: =AVERAGE(I19:I21) -> 110 | J18: =ROUNDDOWN(IF(I18="N/A",0,IF(I18>110,E18*110/100,E18*I18/100)),2) -> 6.6 | M18: DEC | N18: S.D. DESEMBER | R18: =SUM(R19:R70) -> 48.4 | S18: =SUM(S19:S70) -> 53.07
B19: =T.UP3!B19 -> a. Gangguan TM > 5 Menit | C19: =T.UP3!C19 -> ò | D19: =T.UP3!D19 -> Kali | F19: =T.UP3!H19 -> 166 | G19: =VLOOKUP(B19,T.UP3!$B$4:$T$69,MATCH('UP3'!$M$2,T.UP3!$B$5:$T$5,0),FALSE) -> 148 | H19: =VLOOKUP(B19,'R.UP3'!$B$4:$T$67,MATCH('UP3'!$M$2,'R.UP3'!$B$5:$T$5,0),FALSE) -> 115 | I19: =IF(G19=0,0,IF(((G19-(H19-G19))/G19)*100<=0,0,IF(((G19-(H19-G19))/G19)*100>=110,110,((G19-(H19-G19))/G19)*100))) -> 110 | R19: 6.42 | S19: 6.56 | T19: =R19-S19 -> -0.14
B20: =T.UP3!B20 -> b. Gangguan TM ≤ 5 Menit | C20: =T.UP3!C20 -> ò | D20: =T.UP3!D20 -> Kali | F20: =T.UP3!H20 -> 191 | G20: =VLOOKUP(B20,T.UP3!$B$4:$T$69,MATCH('UP3'!$M$2,T.UP3!$B$5:$T$5,0),FALSE) -> 161 | H20: =VLOOKUP(B20,'R.UP3'!$B$4:$T$67,MATCH('UP3'!$M$2,'R.UP3'!$B$5:$T$5,0),FALSE) -> 135 | I20: =IF(OR(G20="N/A",H20="N/A"),"N/A",IF((2-(H20/G20))*100>=110,110,(2-(H20/G20))*100)) -> 110 | R20: 6.22 | S20: 6.22 | T20: =R20-S20 -> 0
B21: =T.UP3!B21 -> c. Kerusakan Peralatan Distribusi (PHB TM dan Trafo) Sesuai Kewenangan | C21: =T.UP3!C21 -> ò | D21: =T.UP3!D21 -> Unit | F21: =T.UP3!H21 -> 5 | G21: =VLOOKUP(B21,T.UP3!$B$4:$T$69,MATCH('UP3'!$M$2,T.UP3!$B$5:$T$5,0),FALSE) -> 5 | H21: =VLOOKUP(B21,'R.UP3'!$B$4:$T$67,MATCH('UP3'!$M$2,'R.UP3'!$B$5:$T$5,0),FALSE) -> 3 | I21: =IFERROR(IF(OR(G21="N/A",H21="N/A"),"N/A",IF((2-(H21/G21))*100>=110,110,(2-(H21/G21))*100)),100) -> 110
A22: =T.UP3!A22 -> 5 | B22: =T.UP3!B22 -> Peningkatan Layanan | E22: =T.UP3!F22 -> 6 | I22: =AVERAGE(I23:I26) -> 107.5 | J22: =ROUNDDOWN(IF(I22="N/A",0,IF(I22>110,E22*110/100,E22*I22/100)),2) -> 6.45 | R22: 4.4 | S22: 4.4 | T22: =R22-S22 -> 0
B23: =T.UP3!B23 -> a. Feedback Rating Negatif pada PLN Mobile - Gangguan | C23: =T.UP3!C23 -> ò | D23: =T.UP3!D23 -> % | F23: =T.UP3!H23 -> 0.09 | G23: =VLOOKUP(B23,T.UP3!$B$4:$T$69,MATCH('UP3'!$M$2,T.UP3!$B$5:$T$5,0),FALSE) -> 0.09 | H23: =VLOOKUP(B23,'R.UP3'!$B$4:$T$67,MATCH('UP3'!$M$2,'R.UP3'!$B$5:$T$5,0),FALSE) -> 0 | I23: =IF(OR(G23="N/A",H23="N/A"),"N/A",IF((2-(H23/G23))*100>=110,110,(2-(H23/G23))*100)) -> 110 | R23: 4.4 | S23: 4.4 | T23: =R23-S23 -> 0
B24: =T.UP3!B24 -> b. Pengaduan Gangguan Berulang pada PLN Mobile | C24: =T.UP3!C24 -> ò | D24: =T.UP3!D24 -> % | F24: =T.UP3!H24 -> 0.04 | G24: =VLOOKUP(B24,T.UP3!$B$4:$T$69,MATCH('UP3'!$M$2,T.UP3!$B$5:$T$5,0),FALSE) -> 0.04 | H24: =VLOOKUP(B24,'R.UP3'!$B$4:$T$67,MATCH('UP3'!$M$2,'R.UP3'!$B$5:$T$5,0),FALSE) -> 0 | I24: =IF(OR(G24="N/A",H24="N/A"),"N/A",IF((2-(H24/G24))*100>=110,110,(2-(H24/G24))*100)) -> 110
B25: =T.UP3!B25 -> c. Rating PLN Mobile | C25: =T.UP3!C25 -> ñ | D25: =T.UP3!D25 -> Rating | F25: =T.UP3!H25 -> 4.9 | G25: =VLOOKUP(B25,T.UP3!$B$4:$T$69,MATCH('UP3'!$M$2,T.UP3!$B$5:$T$5,0),FALSE) -> 4.9 | H25: =VLOOKUP(B25,'R.UP3'!$B$4:$T$67,MATCH('UP3'!$M$2,'R.UP3'!$B$5:$T$5,0),FALSE) -> 4.9 | I25: =IF(OR(G25="N/A",H25="N/A"),"N/A",IF((H25/G25*100)>=110,110,(H25/G25*100))) -> 100 | R25: 0 | S25: 2.2 | T25: =R25-S25 -> -2.2
B26: =T.UP3!B26 -> d. Jumlah Kali Transaksi Keuangan melalui PLN Mobile | C26: =T.UP3!C26 -> ñ | D26: =T.UP3!D26 -> Kali Transaksi | F26: =T.UP3!H26 -> 62908 | G26: =VLOOKUP(B26,T.UP3!$B$4:$T$69,MATCH('UP3'!$M$2,T.UP3!$B$5:$T$5,0),FALSE) -> 52481 | H26: =VLOOKUP(B26,'R.UP3'!$B$4:$T$67,MATCH('UP3'!$M$2,'R.UP3'!$B$5:$T$5,0),FALSE) -> 75000 | I26: =IF(OR(G26="N/A",H26="N/A"),"N/A",IF((H26/G26*100)>=110,110,(H26/G26*100))) -> 110 | R26: 3.3 | S26: 3.3 | T26: =R26-S26 -> 0
A27: =T.UP3!A27 -> 6 | B27: =T.UP3!B27 -> Dispatch Respon Time | E27: =T.UP3!F27 -> 3 | I27: =AVERAGE(I28:I29) -> 105 | J27: =ROUNDDOWN(IF(I27="N/A",0,IF(I27>110,E27*110/100,E27*I27/100)),2) -> 3.15
B28: =T.UP3!B28 -> a. Response Time atas Gangguan (diluar Clear Tamper) | C28: =T.UP3!C28 -> ò | D28: =T.UP3!D28 -> Menit | F28: =T.UP3!H28 -> 30 | G28: =VLOOKUP(B28,T.UP3!$B$4:$T$69,MATCH('UP3'!$M$2,T.UP3!$B$5:$T$5,0),FALSE) -> 30 | H28: =VLOOKUP(B28,'R.UP3'!$B$4:$T$67,MATCH('UP3'!$M$2,'R.UP3'!$B$5:$T$5,0),FALSE) -> 10.140176 | I28: =IF(OR(G28="N/A",H28="N/A"),"N/A",IF((2-(H28/G28))*100<0,0,IF((2-(H28/G28))*100>=110,110,(2-(H28/G28))*100))) -> 110
B29: =T.UP3!B29 -> b. Success Rate Auto Dispatch Gangguan Individual (diluar Clear Tamper) | C29: =T.UP3!C29 -> ñ | D29: =T.UP3!D29 -> % | F29: =T.UP3!H29 -> 0 | G29: =VLOOKUP(B29,T.UP3!$B$4:$T$69,MATCH('UP3'!$M$2,T.UP3!$B$5:$T$5,0),FALSE) -> 0 | H29: =VLOOKUP(B29,'R.UP3'!$B$4:$T$67,MATCH('UP3'!$M$2,'R.UP3'!$B$5:$T$5,0),FALSE) -> 0 | I29: =IF(G29=0,100,(IF((H29/G29*100)>110,110,(H29/G29*100)))) -> 100
A30: =T.UP3!A30 -> 7 | B30: =T.UP3!B30 -> Sistem Recovery : | E30: =T.UP3!F30 -> 4 | I30: =AVERAGE(I31:I32) -> 110 | J30: =ROUNDDOWN(IF(I30="N/A",0,IF(I30>110,E30*110/100,E30*I30/100)),2) -> 4.4
B31: =T.UP3!B31 -> a. Recovery Time Gangguan Meluas TM | C31: =T.UP3!C31 -> ñ | D31: =T.UP3!D31 -> % | F31: =T.UP3!H31 -> 100 | G31: =VLOOKUP(B31,T.UP3!$B$4:$T$69,MATCH('UP3'!$M$2,T.UP3!$B$5:$T$5,0),FALSE) -> 100 | H31: =VLOOKUP(B31,'R.UP3'!$B$4:$T$67,MATCH('UP3'!$M$2,'R.UP3'!$B$5:$T$5,0),FALSE) -> 110 | I31: =IF(OR(G31="N/A",H31="N/A"),"N/A",IF((H31/G31*100)>=110,110,(H31/G31*100))) -> 110
B32: =T.UP3!B32 -> b. Penormalan Siaga 1 Gangguan TM | C32: =T.UP3!C32 -> ñ | D32: =T.UP3!D32 -> % | F32: =T.UP3!H32 -> 100 | G32: =VLOOKUP(B32,T.UP3!$B$4:$T$69,MATCH('UP3'!$M$2,T.UP3!$B$5:$T$5,0),FALSE) -> 100 | H32: =VLOOKUP(B32,'R.UP3'!$B$4:$T$67,MATCH('UP3'!$M$2,'R.UP3'!$B$5:$T$5,0),FALSE) -> 110 | I32: =IF(OR(G32="N/A",H32="N/A"),"N/A",IF((H32/G32*100)>=110,110,(H32/G32*100))) -> 110
A33: =T.UP3!A33 -> 8 | B33: =T.UP3!B33 -> Digitalisasi Aplikasi Korporat | E33: =T.UP3!F33 -> 6 | I33: =AVERAGE(I34) -> 101.95 | J33: =ROUNDDOWN(IF(I33="N/A",0,IF(I33>110,E33*110/100,E33*I33/100)),2) -> 6.11
B34: =T.UP3!B34 -> a. Pengembangan EAM Distribusi | C34: =T.UP3!C34 -> ñ | D34: =T.UP3!D34 -> % | F34: =T.UP3!H34 -> 100 | G34: =VLOOKUP(B34,T.UP3!$B$4:$T$69,MATCH('UP3'!$M$2,T.UP3!$B$5:$T$5,0),FALSE) -> 100 | H34: =VLOOKUP(B34,'R.UP3'!$B$4:$T$67,MATCH('UP3'!$M$2,'R.UP3'!$B$5:$T$5,0),FALSE) -> 101.95 | I34: =IF(G34=0,100,(IF((H34/G34*100)>110,110,(H34/G34*100)))) -> 101.95 | R34: 4.5 | S34: 4.5 | T34: =R34-S34 -> 0
A35: =T.UP3!A35 -> 9 | B35: =T.UP3!B35 -> Percepatan Penyambungan Pelanggan | I35: =AVERAGE(I36:I41) -> 91.302287 | J35: =SUM(J36:J41) -> 8.8
B36: =T.UP3!B36 -> a. Penambahan Daya Tersambung | C36: =T.UP3!C36 -> ñ | D36: =T.UP3!D36 -> MVA | E36: =T.UP3!F36 -> 2 | F36: =T.UP3!H36 -> 13.36 | G36: =VLOOKUP(B36,T.UP3!$B$4:$T$69,MATCH('UP3'!$M$2,T.UP3!$B$5:$T$5,0),FALSE) -> 9.91 | H36: =VLOOKUP(B36,'R.UP3'!$B$4:$T$67,MATCH('UP3'!$M$2,'R.UP3'!$B$5:$T$5,0),FALSE) -> 6.7730833 | I36: =IF(G36=0,110,(IF((H36/G36*100)>110,110,(H36/G36*100)))) -> 68.345947 | J36: =ROUNDDOWN(IF(I36="N/A",0,IF(I36>110,E36*110/100,E36*I36/100)),2) -> 1.36
B37: =T.UP3!B37 -> b. Penambahan Jumlah Pelanggan | C37: =T.UP3!C37 -> ñ | D37: =T.UP3!D37 -> Pelanggan | E37: =T.UP3!F37 -> 2 | F37: =T.UP3!H37 -> 10632 | G37: =VLOOKUP(B37,T.UP3!$B$4:$T$69,MATCH('UP3'!$M$2,T.UP3!$B$5:$T$5,0),FALSE) -> 8638 | H37: =VLOOKUP(B37,'R.UP3'!$B$4:$T$67,MATCH('UP3'!$M$2,'R.UP3'!$B$5:$T$5,0),FALSE) -> 4387 | I37: =IF(G37=0,110,(IF((H37/G37*100)>110,110,(H37/G37*100)))) -> 50.787219 | J37: =ROUNDDOWN(IF(I37="N/A",0,IF(I37>110,E37*110/100,E37*I37/100)),2) -> 1.01
B38: =T.UP3!B38 -> c. Jumlah Penambahan Pelanggan Produk Tematik | C38: =T.UP3!C38 -> ñ | D38: =T.UP3!D38 -> Pelanggan | E38: =T.UP3!F38 -> 1.5 | F38: =T.UP3!H38 -> 996 | G38: =VLOOKUP(B38,T.UP3!$B$4:$T$69,MATCH('UP3'!$M$2,T.UP3!$B$5:$T$5,0),FALSE) -> 864 | H38: =VLOOKUP(B38,'R.UP3'!$B$4:$T$67,MATCH('UP3'!$M$2,'R.UP3'!$B$5:$T$5,0),FALSE) -> 939 | I38: =IF(G38=0,110,(IF((H38/G38*100)>110,110,(H38/G38*100)))) -> 108.68056 | J38: =ROUNDDOWN(IF(I38="N/A",0,IF(I38>110,E38*110/100,E38*I38/100)),2) -> 1.63
B39: =T.UP3!B39 -> d. Implementasi Kesesuaian Sektor Bisnis sesuai KBLI 2020 | C39: =T.UP3!C39 -> ñ | D39: =T.UP3!D39 -> Pelanggan | E39: =T.UP3!F39 -> 1.5 | F39: =T.UP3!H39 -> 8 | G39: =VLOOKUP(B39,T.UP3!$B$4:$T$69,MATCH('UP3'!$M$2,T.UP3!$B$5:$T$5,0),FALSE) -> 8 | H39: =VLOOKUP(B39,'R.UP3'!$B$4:$T$67,MATCH('UP3'!$M$2,'R.UP3'!$B$5:$T$5,0),FALSE) -> 8 | I39: =IF(G39=0,100,(IF((H39/G39*100)>110,110,(H39/G39*100)))) -> 100 | J39: =ROUNDDOWN(IF(I39="N/A",0,IF(I39>110,E39*110/100,E39*I39/100)),2) -> 1.5 | AE39: =IF(AC39>=100,110,IF(AC39>=95,100,AC39)) -> 0
B40: =T.UP3!B40 -> e. Penambahan Jumlah Pelanggan Rumah Tangga Lisdes | C40: =T.UP3!C40 -> ñ | D40: =T.UP3!D40 -> Pelanggan | E40: =T.UP3!F40 -> 1.5 | F40: =T.UP3!H40 -> 441 | G40: =VLOOKUP(B40,T.UP3!$B$4:$T$69,MATCH('UP3'!$M$2,T.UP3!$B$5:$T$5,0),FALSE) -> 161 | H40: =VLOOKUP(B40,'R.UP3'!$B$4:$T$67,MATCH('UP3'!$M$2,'R.UP3'!$B$5:$T$5,0),FALSE) -> 186 | I40: =IF(G40=0,110,(IF((H40/G40*100)>110,110,(H40/G40*100)))) -> 110 | J40: =ROUNDDOWN(IF(I40="N/A",0,IF(I40>110,E40*110/100,E40*I40/100)),2) -> 1.65 | R40: 1.97 | S40: 1.97 | T40: =R40-S40 -> 0
B41: =T.UP3!B41 -> f. Peningkatan kWh Penjualan dari Pelanggan Rumah Tangga Lisdes | C41: =T.UP3!C41 -> ñ | D41: =T.UP3!D41 -> KWh | E41: =T.UP3!F41 -> 1.5 | F41: =T.UP3!H41 -> 58950.99 | G41: =VLOOKUP(B41,T.UP3!$B$4:$T$69,MATCH('UP3'!$M$2,T.UP3!$B$5:$T$5,0),FALSE) -> 21521.791 | H41: =VLOOKUP(B41,'R.UP3'!$B$4:$T$67,MATCH('UP3'!$M$2,'R.UP3'!$B$5:$T$5,0),FALSE) -> 74417.7 | I41: =IF(OR(G41="N/A",H41="N/A"),"N/A",IF((H41/G41*100)>=110,110,(H41/G41*100))) -> 110 | J41: =ROUNDDOWN(IF(I41="N/A",0,IF(I41>110,E41*110/100,E41*I41/100)),2) -> 1.65
A42: =T.UP3!A42 -> 10 | B42: =T.UP3!B42 -> Pengelolaan Pembacaan Meter | E42: =T.UP3!F42 -> 4 | I42: =AVERAGE(I43:I44) -> 105 | J42: =ROUNDDOWN(IF(I42="N/A",0,IF(I42>110,E42*110/100,E42*I42/100)),2) -> 4.2 | R42: 1.61 | S42: 1.61 | T42: =R42-S42 -> 0
B43: =T.UP3!B43 -> a. Jumlah Pengguna Swa Cam | C43: =T.UP3!C43 -> ñ | D43: =T.UP3!D43 -> Pelanggan | F43: =T.UP3!H43 -> 4728 | G43: =VLOOKUP(B43,T.UP3!$B$4:$T$69,MATCH('UP3'!$M$2,T.UP3!$B$5:$T$5,0),FALSE) -> 4728 | H43: =VLOOKUP(B43,'R.UP3'!$B$4:$T$67,MATCH('UP3'!$M$2,'R.UP3'!$B$5:$T$5,0),FALSE) -> 5532 | I43: =IF(OR(G43="N/A",H43="N/A"),"N/A",IF((H43/G43*100)>=110,110,(H43/G43*100))) -> 110 | R43: 1.77 | S43: 1.91 | T43: =R43-S43 -> -0.14
B44: =T.UP3!B44 -> b. Tindak Lanjut LBKB (Laporan Bulanan Kelainan Baca Meter) | C44: =T.UP3!C44 -> ò | D44: =T.UP3!D44 -> Pelanggan | F44: =T.UP3!H44 -> 0 | G44: =VLOOKUP(B44,T.UP3!$B$4:$T$69,MATCH('UP3'!$M$2,T.UP3!$B$5:$T$5,0),FALSE) -> 0 | H44: =VLOOKUP(B44,'R.UP3'!$B$4:$T$67,MATCH('UP3'!$M$2,'R.UP3'!$B$5:$T$5,0),FALSE) -> 0 | I44: =IF(G44=0,100,(IF((H44/G44*100)>110,110,(H44/G44*100)))) -> 100
A45: =T.UP3!A45 -> 11 | B45: =T.UP3!B45 -> Percepatan Cash In | D45: =T.UP3!D45 -> % | E45: =T.UP3!F45 -> 6 | I45: =AVERAGE(I46:I48) -> 106.2138 | J45: =ROUNDDOWN(IF(I45="N/A",0,IF(I45>110,E45*110/100,E45*I45/100)),2) -> 6.37 | R45: 4.4 | S45: 4.4 | T45: =R45-S45 -> 0
B46: =T.UP3!B46 -> a. Pencapaian Rata-Rata Saldo Tanggal 20 diluar Konsumen Instansi (Kementerian & Lembaga) | C46: =T.UP3!C46 -> ò | D46: =T.UP3!D46 -> Rp. Juta | E46: =T.UP3!F46 -> 0 | F46: =T.UP3!H46 -> 1175 | G46: =VLOOKUP(B46,T.UP3!$B$4:$T$69,MATCH('UP3'!$M$2,T.UP3!$B$5:$T$5,0),FALSE) -> 1175 | H46: =VLOOKUP(B46,'R.UP3'!$B$4:$T$67,MATCH('UP3'!$M$2,'R.UP3'!$B$5:$T$5,0),FALSE) -> 1001.412 | I46: =IF(OR(G46="N/A",H46="N/A"),"N/A",IF((2-(H46/G46))*100>=110,110,(2-(H46/G46))*100)) -> 110
B47: =T.UP3!B47 -> b. Pencapaian Saldo Rata-Rata Akhir Bulan diluar Konsumen Instansi (Kementerian & Lembaga) | C47: =T.UP3!C47 -> ò | D47: =T.UP3!D47 -> Rp. Juta | F47: =T.UP3!H47 -> 286.27 | G47: =VLOOKUP(B47,T.UP3!$B$4:$T$69,MATCH('UP3'!$M$2,T.UP3!$B$5:$T$5,0),FALSE) -> 286.27 | H47: =VLOOKUP(B47,'R.UP3'!$B$4:$T$67,MATCH('UP3'!$M$2,'R.UP3'!$B$5:$T$5,0),FALSE) -> 290.15922 | I47: =IF(OR(G47="N/A",H47="N/A"),"N/A",IF((2-(H47/G47))*100>=110,110,(2-(H47/G47))*100)) -> 98.641414
B48: =T.UP3!B48 -> c. Pencapaian Pelunasan PRR | C48: =T.UP3!C48 -> ñ | D48: =T.UP3!D48 -> Rp. Juta | F48: =T.UP3!H48 -> 9.31 | G48: =VLOOKUP(B48,T.UP3!$B$4:$T$69,MATCH('UP3'!$M$2,T.UP3!$B$5:$T$5,0),FALSE) -> 7.45 | H48: =VLOOKUP(B48,'R.UP3'!$B$4:$T$67,MATCH('UP3'!$M$2,'R.UP3'!$B$5:$T$5,0),FALSE) -> 16.981306 | I48: =IF(OR(G48="N/A",H48="N/A"),"N/A",IF((H48/G48*100)>=110,110,(H48/G48*100))) -> 110
A49: =T.UP3!A49 -> 12 | B49: =T.UP3!B49 -> Pengendalian Anggaran | E49: =T.UP3!F49 -> 6 | I49: =AVERAGE(I50:I52) -> 98.350877 | J49: =ROUNDDOWN(IF(I49="N/A",0,IF(I49>110,E49*110/100,E49*I49/100)),2) -> 5.9
B50: =T.UP3!B50 -> a. Pengendalian Penggunaan Anggaran Investasi sesuai RKAP | C50: =T.UP3!C50 -> ó | D50: =T.UP3!D50 -> % | F50: =T.UP3!H50 -> 95-100 | G50: =VLOOKUP(B50,T.UP3!$B$4:$T$69,MATCH('UP3'!$M$2,T.UP3!$B$5:$T$5,0),FALSE) -> 95-100 | H50: =VLOOKUP(B50,'R.UP3'!$B$4:$T$67,MATCH('UP3'!$M$2,'R.UP3'!$B$5:$T$5,0),FALSE) -> 90.3 | I50: =MAX(0,_xlfn.IFS(H50<95,H50/95, AND(H50>=95,H50<=100),1+((H50-95)/(100-95))*0.1,H50> 100,1-(H50-100)/(190-100)))*100 -> 95.052632
B51: =T.UP3!B51 -> b. Usulan Penghapusan ATTB | C51: =T.UP3!C51 -> ñ | D51: =T.UP3!D51 -> Rp. Milyar | F51: =T.UP3!H51 -> 3.16 | G51: =VLOOKUP(B51,T.UP3!$B$4:$T$69,MATCH('UP3'!$M$2,T.UP3!$B$5:$T$5,0),FALSE) -> 0 | H51: =VLOOKUP(B51,'R.UP3'!$B$4:$T$67,MATCH('UP3'!$M$2,'R.UP3'!$B$5:$T$5,0),FALSE) -> 0 | I51: =IF(G51=0,100,(IF((H51/G51*100)>110,110,(H51/G51*100)))) -> 100
B52: =T.UP3!B52 -> c. Usulan Penghapusan PRR | C52: =T.UP3!C52 -> ñ | D52: =T.UP3!D52 -> Rp. Milyar | F52: =T.UP3!H52 -> 34.29 | G52: =VLOOKUP(B52,T.UP3!$B$4:$T$69,MATCH('UP3'!$M$2,T.UP3!$B$5:$T$5,0),FALSE) -> 0 | H52: =VLOOKUP(B52,'R.UP3'!$B$4:$T$67,MATCH('UP3'!$M$2,'R.UP3'!$B$5:$T$5,0),FALSE) -> 0 | I52: =IF(OR(G52="N/A",H52="N/A"),"N/A",IF(AND(G52=0,H52=0),100,H52/G52*100)) -> 100 | R52: 0.81 | S52: 1.1 | T52: =R52-S52 -> -0.29
A53: =T.UP3!A53 -> 13 | B53: =T.UP3!B53 -> Manajemen SDM, Komunikasi, dan TJSL | I53: =AVERAGE(I54:I57) -> 100 | J53: =SUM(J54:J57) -> 5 | R53: 1.1 | S53: 1.1 | T53: =R53-S53 -> 0
B54: =T.UP3!B54 -> a. HCR, OCR, dan Produktivitas Pegawai | C54: =T.UP3!C54 -> ñ | D54: =T.UP3!D54 -> % | E54: 2 | F54: =T.UP3!H54 -> 100 | G54: =VLOOKUP(B54,T.UP3!$B$4:$T$69,MATCH('UP3'!$M$2,T.UP3!$B$5:$T$5,0),FALSE) -> 100 | H54: =VLOOKUP(B54,'R.UP3'!$B$4:$T$67,MATCH('UP3'!$M$2,'R.UP3'!$B$5:$T$5,0),FALSE) -> 100 | I54: =IF(G54=0,100,(IF((H54/G54*100)>110,110,(H54/G54*100)))) -> 100 | J54: =ROUNDDOWN(IF(I54="N/A",0,IF(I54>110,E54*110/100,E54*I54/100)),2) -> 2 | R54: 1.1 | S54: 1.1 | T54: =R54-S54 -> 0
B55: =T.UP3!B55 -> b. Produktivitas Unit | C55: =T.UP3!C55 -> ñ | D55: =T.UP3!D55 -> % | E55: 1 | F55: =T.UP3!H55 -> 100 | G55: =VLOOKUP(B55,T.UP3!$B$4:$T$69,MATCH('UP3'!$M$2,T.UP3!$B$5:$T$5,0),FALSE) -> 100 | H55: =VLOOKUP(B55,'R.UP3'!$B$4:$T$67,MATCH('UP3'!$M$2,'R.UP3'!$B$5:$T$5,0),FALSE) -> 90 | I55: =IF(G55=0,100,(IF((H55/G55*100)>110,110,(H55/G55*100)))) -> 90 | J55: =ROUNDDOWN(IF(I55="N/A",0,IF(I55>110,E55*110/100,E55*I55/100)),2) -> 0.9 | R55: 2.2 | S55: 2.2 | T55: =R55-S55 -> 0
B56: =T.UP3!B56 -> c. Pengelolaan Komunikasi dan TJSL | C56: =T.UP3!C56 -> ñ | D56: =T.UP3!D56 -> % | E56: 1 | F56: =T.UP3!H56 -> 100 | G56: =VLOOKUP(B56,T.UP3!$B$4:$T$69,MATCH('UP3'!$M$2,T.UP3!$B$5:$T$5,0),FALSE) -> 100 | H56: =VLOOKUP(B56,'R.UP3'!$B$4:$T$67,MATCH('UP3'!$M$2,'R.UP3'!$B$5:$T$5,0),FALSE) -> 110 | I56: =IF(OR(G56="N/A",H56="N/A"),"N/A",IF(AND(G56=0,H56=0),100,H56/G56*100)) -> 110 | J56: =ROUNDDOWN(IF(I56="N/A",0,IF(I56>110,E56*110/100,E56*I56/100)),2) -> 1.1
B57: =T.UP3!B57 -> d. Peningkatan Layanan dan Budaya K3 | C57: =T.UP3!C57 -> ñ | D57: =T.UP3!D57 -> % | E57: 1 | F57: =T.UP3!H57 -> 100 | G57: =VLOOKUP(B57,T.UP3!$B$4:$T$69,MATCH('UP3'!$M$2,T.UP3!$B$5:$T$5,0),FALSE) -> 100 | H57: =VLOOKUP(B57,'R.UP3'!$B$4:$T$67,MATCH('UP3'!$M$2,'R.UP3'!$B$5:$T$5,0),FALSE) -> 100 | I57: =IF(OR(G57="N/A",H57="N/A"),"N/A",IF(AND(G57=0,H57=0),100,H57/G57*100)) -> 100 | J57: =ROUNDDOWN(IF(I57="N/A",0,IF(I57>110,E57*110/100,E57*I57/100)),2) -> 1 | R57: 2.2 | S57: 2.2 | T57: =R57-S57 -> 0
A58: =T.UP3!A58 -> 14 | B58: =T.UP3!B58 -> Perbaikan Proses Bisnis dan Keberlanjutan | E58: =T.UP3!F58 -> 4 | I58: =AVERAGE(I59:I62) -> 102.5 | J58: =ROUNDDOWN(IF(I58="N/A",0,IF(I58>110,E58*110/100,E58*I58/100)),2) -> 4.1 | R58: 2 | S58: 2 | T58: =R58-S58 -> 0
B59: =T.UP3!B59 -> a. Implementasi PLN Bisnis Ekselen | C59: =T.UP3!C59 -> ñ | D59: =T.UP3!D59 -> % | F59: =T.UP3!H59 -> 100 | G59: =VLOOKUP(B59,T.UP3!$B$4:$T$69,MATCH('UP3'!$M$2,T.UP3!$B$5:$T$5,0),FALSE) -> 100 | H59: =VLOOKUP(B59,'R.UP3'!$B$4:$T$67,MATCH('UP3'!$M$2,'R.UP3'!$B$5:$T$5,0),FALSE) -> 100 | I59: =IF(OR(G59="N/A",H59="N/A"),"N/A",IF(AND(G59=0,H59=0),100,H59/G59*100)) -> 100
B60: =T.UP3!B60 -> b. Maturity Level Gudang | C60: =T.UP3!C60 -> ñ | D60: =T.UP3!D60 -> Skor | F60: =T.UP3!H57 -> 100 | G60: =VLOOKUP(B60,T.UP3!$B$4:$T$69,MATCH('UP3'!$M$2,T.UP3!$B$5:$T$5,0),FALSE) -> 3.65 | H60: =VLOOKUP(B60,'R.UP3'!$B$4:$T$67,MATCH('UP3'!$M$2,'R.UP3'!$B$5:$T$5,0),FALSE) -> 3.65 | I60: =IFERROR(IF(OR(G60="N/A",H60="N/A"),"N/A",IF((H60/G60*100)>=110,110,(H60/G60*100))),100) -> 100
B61: =T.UP3!B61 -> c. Maturity Level Sustainbility | C61: =T.UP3!C61 -> ñ | D61: =T.UP3!D61 -> % | F61: =T.UP3!H58 -> 0 | G61: =VLOOKUP(B61,T.UP3!$B$4:$T$69,MATCH('UP3'!$M$2,T.UP3!$B$5:$T$5,0),FALSE) -> 100 | H61: =VLOOKUP(B61,'R.UP3'!$B$4:$T$67,MATCH('UP3'!$M$2,'R.UP3'!$B$5:$T$5,0),FALSE) -> 110 | I61: =IF(OR(G61="N/A",H61="N/A"),"N/A",IF((H61/G61*100)>=110,110,(H61/G61*100))) -> 110
B62: =T.UP3!B62 -> d. Implementasi Roadmap Perbaikan Penerapan Manajemen Risiko dan Pencapaian Perlakuan Risiko | C62: =T.UP3!C62 -> ñ | D62: =T.UP3!D62 -> % | F62: =T.UP3!H59 -> 100 | G62: =VLOOKUP(B62,T.UP3!$B$4:$T$69,MATCH('UP3'!$M$2,T.UP3!$B$5:$T$5,0),FALSE) -> 100 | H62: =VLOOKUP(B62,'R.UP3'!$B$4:$T$67,MATCH('UP3'!$M$2,'R.UP3'!$B$5:$T$5,0),FALSE) -> 100 | I62: =IF(OR(G62="N/A",H62="N/A"),"N/A",IF((H62/G62*100)>=110,110,(H62/G62*100))) -> 100
A63: =T.UP3!A63 -> 15 | B63: =T.UP3!B63 -> Kepatuhan : | R63: 0 | S63: 0.9 | T63: =R63-S63 -> -0.9
B64: =T.UP3!B64 -> a. Pengelolaan K3, Keamanan dan Lingkungan Hidup | E64: =T.UP3!F64 -> Max-8 | R64: 0 | S64: 1 | T64: =R64-S64 -> -1
B65: =T.UP3!B65 -> b. Maturity Level Implementasi Sistem Manajemen Anti Penyuapan (SMAP) | E65: =T.UP3!F65 -> Max-4
B66: =T.UP3!B66 -> c. Ketepatan penyampaian pelaporan dan Akurasi Data Kinerja | E66: =T.UP3!F66 -> Max-10
B67: =T.UP3!B67 -> d. Tindak Lanjut Temuan Auditor | E67: =T.UP3!F67 -> Max-5
B68: =T.UP3!B68 -> e. Pencapaian Beyond RKAP | E68: =T.UP3!F68 -> Max-2 Max+2
B69: TOTAL BOBOT | E69: =E7+E17 -> 100 | J69: =J7+J17 -> 102.84
B70: TOTAL BOBOT PROPORSIONAL | E70: 100 | J70: =E70/E69*J69 -> 102.84
R71: 98.61 | S71: 103.58
R72: 102.71875 | S72: 103.58

Sheet PROG. JUNI
B1: KONTRAK MANAJEMEN 2024
B2: PT PLN (PERSERO) UID SULUTTENGGO | M2: AUG | N2: PILIH BULAN LAPORAN
B3: UP3 TOLITOLI
A4: NO | B4: KPI | D4: SATUAN | E4: BOBOT | F4: TARGET 2023 | G4: =VLOOKUP(M2,M7:N18,2,FALSE) -> S.D. AGUSTUS
G5: TARGET | H5: REALISASI | I5: PENCAPAIAN | J5: NILAI
A6: 1 | B6: 2 | D6: 3 | E6: 4 | F6: 5 | G6: 6 | H6: 7 | I6: 8 | J6: 9
A7: =T.UP3!A7 -> I | B7: =T.UP3!B7 -> Key Performance Indikator | E7: =SUM(E8:E15) -> #REF! | J7: =SUM(J8:J15) -> #REF! | M7: JAN | N7: S.D. JANUARI | R7: =R8+R9+R10 -> 40.96 | S7: =S8+S9+S10 -> 41.25
A8: =T.UP3!A8 -> 1 | B8: =T.UP3!B8 -> Penjualan Tenaga Listrik | C8: =T.UP3!C8 -> ñ | D8: =T.UP3!D8 -> GWh | E8: =IF(OR(H8="N/A",G8="N/A"),0,T.UP3!F8) -> 14 | F8: =T.UP3!H8 -> 231.47 | G8: =VLOOKUP(B8,T.UP3!$B$4:$T$69,MATCH('PROG. JUNI'!$M$2,T.UP3!$B$5:$T$5,0),FALSE) -> 151.71 | H8: =VLOOKUP(B8,'R.UP3'!$B$4:$S$54,MATCH('PROG. JUNI'!$M$2,'R.UP3'!$B$5:$S$5,0),FALSE) -> 148.05998 | I8: =IF(OR(G8="N/A",H8="N/A"),"N/A",IF(AND(G8=0,H8=0),0,H8/G8*100)) -> 97.594079 | J8: =ROUNDDOWN(IF(I8="N/A",0,IF(I8>110,E8*110/100,E8*I8/100)),2) -> 13.66 | K8: OK | M8: FEB | N8: S.D. FEBRUARI | R8: 13.56 | S8: 13.53 | T8: =R8-S8 -> 0.03
A9: =T.UP3!A9 -> 2 | B9: =T.UP3!B9 -> Keandalan Sistem | E9: =IF(OR(H9="N/A",G9="N/A"),0,T.UP3!F9) -> 14 | I9: =AVERAGE(I10:I12) -> 110 | J9: =ROUNDDOWN(IF(I9="N/A",0,IF(I9>110,E9*110/100,E9*I9/100)),2) -> 15.4 | M9: MAR | N9: S.D. MARET | R9: 15.4 | S9: 15.4 | T9: =R9-S9 -> 0
B10: =T.UP3!B10 -> a. SAIDI Sesuai Kewenangannya | C10: =T.UP3!C10 -> ò | D10: =T.UP3!D10 -> Menit/Plg | F10: =T.UP3!H10 -> 280.67 | G10: =VLOOKUP(B10,T.UP3!$B$4:$T$69,MATCH('PROG. JUNI'!$M$2,T.UP3!$B$5:$T$5,0),FALSE) -> 187.11 | H10: =VLOOKUP(B10,'R.UP3'!$B$4:$S$54,MATCH('PROG. JUNI'!$M$2,'R.UP3'!$B$5:$S$5,0),FALSE) -> 149.85371 | I10: 110 | K10: OK | M10: APRIL | N10: S.D. APRIL | R10: 12 | S10: 12.32 | T10: =R10-S10 -> -0.32
B11: =T.UP3!B11 -> b. SAIFI Sesuai Kewenangannya | C11: =T.UP3!C11 -> ò | D11: =T.UP3!D11 -> Kali/Plg | F11: =T.UP3!H11 -> 2.97 | G11: =VLOOKUP(B11,T.UP3!$B$4:$T$69,MATCH('PROG. JUNI'!$M$2,T.UP3!$B$5:$T$5,0),FALSE) -> 1.98 | H11: =VLOOKUP(B11,'R.UP3'!$B$4:$S$54,MATCH('PROG. JUNI'!$M$2,'R.UP3'!$B$5:$S$5,0),FALSE) -> 1.5900799 | I11: 110 | K11: OK | M11: MEI | N11: S.D. MEI
B12: =T.UP3!B12 -> c. ENS | C12: =T.UP3!C12 -> ò | D12: =T.UP3!D12 -> MWh | F12: =T.UP3!H12 -> 107.87 | G12: =VLOOKUP(B12,T.UP3!$B$4:$T$69,MATCH('PROG. JUNI'!$M$2,T.UP3!$B$5:$T$5,0),FALSE) -> 71.91 | H12: =VLOOKUP(B12,'R.UP3'!$B$4:$S$54,MATCH('PROG. JUNI'!$M$2,'R.UP3'!$B$5:$S$5,0),FALSE) -> 46.248 | I12: 110 | K12: OK | M12: JUNI | N12: S.D. JUNI
A13: =T.UP3!#REF! -> #REF! | B13: =T.UP3!#REF! -> #REF! | E13: =IF(OR(H13="N/A",G13="N/A"),0,T.UP3!#REF!) -> #REF! | I13: =AVERAGE(I14:I15) -> 101.29791 | J13: =ROUNDDOWN(IF(I13="N/A",0,IF(I13>110,E13*110/100,E13*I13/100)),2) -> #REF! | M13: JULI | N13: S.D. JULI
B14: =T.UP3!B16 -> c. Penyelesaian Ganti Meter | C14: =T.UP3!C16 -> ñ | D14: =T.UP3!D16 -> Unit | F14: =T.UP3!H16 -> 4727 | G14: =VLOOKUP(B14,T.UP3!$B$4:$T$69,MATCH('PROG. JUNI'!$M$2,T.UP3!$B$5:$T$5,0),FALSE) -> 3444 | H14: =VLOOKUP(B14,'R.UP3'!$B$4:$S$54,MATCH('PROG. JUNI'!$M$2,'R.UP3'!$B$5:$S$5,0),FALSE) -> 3699 | I14: =IF(OR(G14="N/A",H14="N/A"),"N/A",IF(AND(G14=0,H14=0),0,(2-H14/G14)*100)) -> 92.595819 | K14: OK | M14: AUG | N14: S.D. AGUSTUS
B15: =T.UP3!#REF! -> #REF! | C15: =T.UP3!#REF! -> #REF! | D15: =T.UP3!#REF! -> #REF! | F15: =T.UP3!#REF! -> #REF! | G15: =VLOOKUP(B15,T.UP3!$B$4:$T$69,MATCH('PROG. JUNI'!$M$2,T.UP3!$B$5:$T$5,0),FALSE) -> #REF! | H15: =VLOOKUP(B15,'R.UP3'!$B$4:$S$54,MATCH('PROG. JUNI'!$M$2,'R.UP3'!$B$5:$S$5,0),FALSE) -> #REF! | I15: 110 | K15: OK | M15: SEP | N15: S.D. SEPTEMBER
A16: =T.UP3!A17 -> II | B16: =T.UP3!B17 -> Perfomance Indicators | E16: =SUM(E17:E49) -> #REF! | J16: =SUM(J17:J49) -> #REF! | M16: OKT | N16: S.D. OKTOBER | R16: =SUM(R17:R47) -> 57.65 | S16: =SUM(S17:S47) -> 62.33
A17: =T.UP3!#REF! -> #REF! | B17: =T.UP3!#REF! -> #REF! | E17: =IF(OR(H17="N/A",G17="N/A"),0,T.UP3!F18) -> 6 | I17: =AVERAGE(I18:I21) -> 107.5 | J17: =ROUNDDOWN(IF(I17="N/A",0,IF(I17>110,E17*110/100,E17*I17/100)),2) -> 6.45 | M17: NOV | N17: S.D. NOVEMBER | R17: 5.95 | S17: 5.96 | T17: =R17-S17 -> -0.01
A18: =T.UP3!A18 -> 4 | B18: =T.UP3!B18 -> Keandalan Jaringan Distribusi | C18: =T.UP3!C19 -> ò | D18: =T.UP3!D19 -> Kali | F18: =T.UP3!H19 -> 166 | G18: =VLOOKUP(B18,T.UP3!$B$4:$T$69,MATCH('PROG. JUNI'!$M$2,T.UP3!$B$5:$T$5,0),FALSE) -> 0 | H18: =VLOOKUP(B18,'R.UP3'!$B$4:$S$54,MATCH('PROG. JUNI'!$M$2,'R.UP3'!$B$5:$S$5,0),FALSE) -> 0 | I18: 110 | K18: OK | M18: DES | N18: S.D. DESEMBER | R18: 6.42 | S18: 6.56 | T18: =R18-S18 -> -0.14
A19: =T.UP3!A19 -> 0 | B19: =T.UP3!B19 -> a. Gangguan TM > 5 Menit | C19: =T.UP3!C20 -> ò | D19: =T.UP3!D20 -> Kali | F19: =T.UP3!H20 -> 191 | G19: =VLOOKUP(B19,T.UP3!$B$4:$T$69,MATCH('PROG. JUNI'!$M$2,T.UP3!$B$5:$T$5,0),FALSE) -> 119 | H19: =VLOOKUP(B19,'R.UP3'!$B$4:$S$54,MATCH('PROG. JUNI'!$M$2,'R.UP3'!$B$5:$S$5,0),FALSE) -> 87 | I19: 110 | K19: OK | R19: 6.22 | S19: 6.22 | T19: =R19-S19 -> 0
A20: =T.UP3!A20 -> 0 | B20: =T.UP3!B20 -> b. Gangguan TM ≤ 5 Menit | C20: =T.UP3!C21 -> ò | D20: =T.UP3!D21 -> Unit | F20: =T.UP3!H21 -> 5 | G20: =VLOOKUP(B20,T.UP3!$B$4:$T$69,MATCH('PROG. JUNI'!$M$2,T.UP3!$B$5:$T$5,0),FALSE) -> 128 | H20: =VLOOKUP(B20,'R.UP3'!$B$4:$S$54,MATCH('PROG. JUNI'!$M$2,'R.UP3'!$B$5:$S$5,0),FALSE) -> 96 | I20: 110 | K20: OK
A21: =T.UP3!A21 -> 0 | B21: =T.UP3!B21 -> c. Kerusakan Peralatan Distribusi (PHB TM dan Trafo) Sesuai Kewenangan | C21: =T.UP3!C22 -> 0 | D21: =T.UP3!D22 -> 0 | F21: =T.UP3!H22 -> 0 | G21: =VLOOKUP(B21,T.UP3!$B$4:$T$69,MATCH('PROG. JUNI'!$M$2,T.UP3!$B$5:$T$5,0),FALSE) -> 5 | H21: =VLOOKUP(B21,'R.UP3'!$B$4:$S$54,MATCH('PROG. JUNI'!$M$2,'R.UP3'!$B$5:$S$5,0),FALSE) -> 3 | I21: 100 | K21: OK | R21: 4.4 | S21: 4.4 | T21: =R21-S21 -> 0
A22: =T.UP3!A22 -> 5 | B22: =T.UP3!B22 -> Peningkatan Layanan | E22: =IF(OR(H22="N/A",G22="N/A"),0,T.UP3!F24) -> 0 | I22: =AVERAGE(I23:I26) -> 116.43209 | J22: =ROUNDDOWN(IF(I22="N/A",0,IF(I22>110,E22*110/100,E22*I22/100)),2) -> 0 | L22: =E22-J22 -> 0 | R22: 4.4 | S22: 4.4 | T22: =R22-S22 -> 0
A23: =T.UP3!A24 -> 0 | B23: =T.UP3!B24 -> b. Pengaduan Gangguan Berulang pada PLN Mobile | C23: =T.UP3!C25 -> ñ | D23: =T.UP3!D25 -> Rating | F23: =T.UP3!H25 -> 4.9 | G23: =VLOOKUP(B23,T.UP3!$B$4:$T$69,MATCH('PROG. JUNI'!$M$2,T.UP3!$B$5:$T$5,0),FALSE) -> 0.04 | H23: =VLOOKUP(B23,'R.UP3'!$B$4:$S$54,MATCH('PROG. JUNI'!$M$2,'R.UP3'!$B$5:$S$5,0),FALSE) -> 0 | I23: =IF(OR(G23="N/A",H23="N/A"),"N/A",IF(AND(G23=0,H23=0),0,(2-H23/G23)*100)) -> 200 | K23: OK | R23: 0 | S23: 2.2 | T23: =R23-S23 -> -2.2
A24: =T.UP3!A25 -> 0 | B24: =T.UP3!B25 -> c. Rating PLN Mobile | C24: =T.UP3!#REF! -> #REF! | D24: =T.UP3!#REF! -> #REF! | F24: =T.UP3!#REF! -> #REF! | G24: =VLOOKUP(B24,T.UP3!$B$4:$T$69,MATCH('PROG. JUNI'!$M$2,T.UP3!$B$5:$T$5,0),FALSE) -> 4.9 | H24: =VLOOKUP(B24,'R.UP3'!$B$4:$S$54,MATCH('PROG. JUNI'!$M$2,'R.UP3'!$B$5:$S$5,0),FALSE) -> 4.9 | I24: =IF(OR(G24="N/A",H24="N/A"),"N/A",IF(AND(G24=0,H24=0),0,(2-H24/G24)*100)) -> 100 | K24: OK
A25: =T.UP3!A26 -> 0 | B25: =T.UP3!B26 -> d. Jumlah Kali Transaksi Keuangan melalui PLN Mobile | C25: =T.UP3!C26 -> ñ | D25: =T.UP3!D26 -> Kali Transaksi | F25: =T.UP3!H26 -> 62908 | G25: =VLOOKUP(B25,T.UP3!$B$4:$T$69,MATCH('PROG. JUNI'!$M$2,T.UP3!$B$5:$T$5,0),FALSE) -> 42054 | H25: =VLOOKUP(B25,'R.UP3'!$B$4:$S$54,MATCH('PROG. JUNI'!$M$2,'R.UP3'!$B$5:$S$5,0),FALSE) -> 60672 | I25: =IF(OR(G25="N/A",H25="N/A"),"N/A",IF(AND(G25=0,H25=0),0,(2-H25/G25)*100)) -> 55.728349 | K25: OK | R25: 3.3 | S25: 3.3 | T25: =R25-S25 -> 0
A26: =T.UP3!A30 -> 7 | B26: =T.UP3!B30 -> Sistem Recovery : | C26: =T.UP3!#REF! -> #REF! | D26: =T.UP3!#REF! -> #REF! | F26: =T.UP3!#REF! -> #REF! | G26: =VLOOKUP(B26,T.UP3!$B$4:$T$69,MATCH('PROG. JUNI'!$M$2,T.UP3!$B$5:$T$5,0),FALSE) -> 0 | H26: =VLOOKUP(B26,'R.UP3'!$B$4:$S$54,MATCH('PROG. JUNI'!$M$2,'R.UP3'!$B$5:$S$5,0),FALSE) -> 0 | I26: 110 | R26: 3.3 | S26: 3.3 | T26: =R26-S26 -> 0
A27: =T.UP3!A31 -> 0 | B27: =T.UP3!B31 -> a. Recovery Time Gangguan Meluas TM | C27: =T.UP3!C37 -> ñ | D27: =T.UP3!D37 -> Pelanggan | E27: =IF(OR(H27="N/A",G27="N/A"),0,T.UP3!F37) -> 2 | F27: =T.UP3!H37 -> 10632 | G27: =VLOOKUP(B27,T.UP3!$B$4:$T$69,MATCH('PROG. JUNI'!$M$2,T.UP3!$B$5:$T$5,0),FALSE) -> 100 | H27: =VLOOKUP(B27,'R.UP3'!$B$4:$S$54,MATCH('PROG. JUNI'!$M$2,'R.UP3'!$B$5:$S$5,0),FALSE) -> 110 | I27: =IF(OR(G27="N/A",H27="N/A"),"N/A",IF(AND(G27=0,H27=0),0,H27/G27*100)) -> 110 | J27: =ROUNDDOWN(IF(I27="N/A",0,IF(I27>110,E27*110/100,E27*I27/100)),2) -> 2.2 | K27: OK | R27: 4.5 | S27: 4.5 | T27: =R27-S27 -> 0
A28: =T.UP3!A32 -> 0 | B28: =T.UP3!B32 -> b. Penormalan Siaga 1 Gangguan TM | E28: =IF(OR(H28="N/A",G28="N/A"),0,T.UP3!F40) -> 1.5 | I28: =AVERAGE(I29:I32) -> 102.90984 | J28: =ROUNDDOWN(IF(I28="N/A",0,IF(I28>110,E28*110/100,E28*I28/100)),2) -> 1.54 | L28: =E28-J28 -> -0.04 | R28: 1.97 | S28: 1.97 | T28: =R28-S28 -> 0
A29: =T.UP3!A33 -> 8 | B29: =T.UP3!B33 -> Digitalisasi Aplikasi Korporat | C29: =T.UP3!C41 -> ñ | D29: =T.UP3!D41 -> KWh | F29: =T.UP3!H41 -> 58950.99 | G29: =VLOOKUP(B29,T.UP3!$B$4:$T$69,MATCH('PROG. JUNI'!$M$2,T.UP3!$B$5:$T$5,0),FALSE) -> 0 | H29: =VLOOKUP(B29,'R.UP3'!$B$4:$S$54,MATCH('PROG. JUNI'!$M$2,'R.UP3'!$B$5:$S$5,0),FALSE) -> 0 | I29: 110 | K29: OK | R29: 1.61 | S29: 1.61 | T29: =R29-S29 -> 0
A30: =T.UP3!A36 -> 0 | B30: =T.UP3!B36 -> a. Penambahan Daya Tersambung | C30: =T.UP3!C42 -> 0 | D30: =T.UP3!D42 -> 0 | F30: =T.UP3!H42 -> 0 | G30: =VLOOKUP(B30,T.UP3!$B$4:$T$69,MATCH('PROG. JUNI'!$M$2,T.UP3!$B$5:$T$5,0),FALSE) -> 7.62 | H30: =VLOOKUP(B30,'R.UP3'!$B$4:$S$54,MATCH('PROG. JUNI'!$M$2,'R.UP3'!$B$5:$S$5,0),FALSE) -> 4.2161333 | I30: 100 | K30: OK | R30: 1.77 | S30: 1.91 | T30: =R30-S30 -> -0.14
A31: =T.UP3!A37 -> 0 | B31: =T.UP3!B37 -> b. Penambahan Jumlah Pelanggan | C31: =T.UP3!C43 -> ñ | D31: =T.UP3!D43 -> Pelanggan | F31: =T.UP3!H43 -> 4728 | G31: =VLOOKUP(B31,T.UP3!$B$4:$T$69,MATCH('PROG. JUNI'!$M$2,T.UP3!$B$5:$T$5,0),FALSE) -> 6645 | H31: =VLOOKUP(B31,'R.UP3'!$B$4:$S$54,MATCH('PROG. JUNI'!$M$2,'R.UP3'!$B$5:$S$5,0),FALSE) -> 3293 | I31: 100 | K31: OK
A32: =T.UP3!A38 -> 0 | B32: =T.UP3!B38 -> c. Jumlah Penambahan Pelanggan Produk Tematik | C32: =T.UP3!#REF! -> #REF! | D32: =T.UP3!#REF! -> #REF! | F32: =T.UP3!#REF! -> #REF! | G32: =VLOOKUP(B32,T.UP3!$B$4:$T$69,MATCH('PROG. JUNI'!$M$2,T.UP3!$B$5:$T$5,0),FALSE) -> 732 | H32: =VLOOKUP(B32,'R.UP3'!$B$4:$S$54,MATCH('PROG. JUNI'!$M$2,'R.UP3'!$B$5:$S$5,0),FALSE) -> 744 | I32: =IF(OR(G32="N/A",H32="N/A"),"N/A",IF(AND(G32=0,H32=0),0,H32/G32*100)) -> 101.63934 | K32: OK | R32: 4.4 | S32: 4.4 | T32: =R32-S32 -> 0
A33: =T.UP3!A40 -> 0 | B33: =T.UP3!B40 -> e. Penambahan Jumlah Pelanggan Rumah Tangga Lisdes | C33: =T.UP3!C46 -> ò | D33: =T.UP3!D46 -> Rp. Juta | E33: =IF(OR(H33="N/A",G33="N/A"),0,T.UP3!F46) -> 0 | F33: =T.UP3!H46 -> 1175 | G33: =VLOOKUP(B33,T.UP3!$B$4:$T$69,MATCH('PROG. JUNI'!$M$2,T.UP3!$B$5:$T$5,0),FALSE) -> 61 | H33: =VLOOKUP(B33,'R.UP3'!$B$4:$S$54,MATCH('PROG. JUNI'!$M$2,'R.UP3'!$B$5:$S$5,0),FALSE) -> 159 | I33: =IF(OR(G33="N/A",H33="N/A"),"N/A",IF(AND(G33=0,H33=0),0,H33/G33*100)) -> 260.65574 | J33: =ROUNDDOWN(IF(I33="N/A",0,IF(I33>110,E33*110/100,E33*I33/100)),2) -> 0 | K33: OK
A34: =T.UP3!A41 -> 0 | B34: =T.UP3!B41 -> f. Peningkatan kWh Penjualan dari Pelanggan Rumah Tangga Lisdes | E34: =IF(OR(H34="N/A",G34="N/A"),0,T.UP3!F50) -> 0 | I34: =AVERAGE(I35:I37) -> 106.66667 | J34: =ROUNDDOWN(IF(I34="N/A",0,IF(I34>110,E34*110/100,E34*I34/100)),2) -> 0 | R34: 0.81 | S34: 1.1 | T34: =R34-S34 -> -0.29
A35: =T.UP3!A42 -> 10 | B35: =T.UP3!B42 -> Pengelolaan Pembacaan Meter | C35: =T.UP3!#REF! -> #REF! | D35: =T.UP3!#REF! -> #REF! | F35: =T.UP3!#REF! -> #REF! | G35: =VLOOKUP(B35,T.UP3!$B$4:$T$69,MATCH('PROG. JUNI'!$M$2,T.UP3!$B$5:$T$5,0),FALSE) -> 0 | H35: =VLOOKUP(B35,'R.UP3'!$B$4:$S$54,MATCH('PROG. JUNI'!$M$2,'R.UP3'!$B$5:$S$5,0),FALSE) -> 0 | I35: 110 | K35: OK | R35: 1.1 | S35: 1.1 | T35: =R35-S35 -> 0
A36: =T.UP3!A43 -> 0 | B36: =T.UP3!B43 -> a. Jumlah Pengguna Swa Cam | C36: =T.UP3!#REF! -> #REF! | D36: =T.UP3!#REF! -> #REF! | F36: =T.UP3!#REF! -> #REF! | G36: =VLOOKUP(B36,T.UP3!$B$4:$T$69,MATCH('PROG. JUNI'!$M$2,T.UP3!$B$5:$T$5,0),FALSE) -> 4728 | H36: =VLOOKUP(B36,'R.UP3'!$B$4:$S$54,MATCH('PROG. JUNI'!$M$2,'R.UP3'!$B$5:$S$5,0),FALSE) -> 5376 | I36: 110 | K36: OK | R36: 1.1 | S36: 1.1 | T36: =R36-S36 -> 0
A37: =T.UP3!A46 -> 0 | B37: =T.UP3!B46 -> a. Pencapaian Rata-Rata Saldo Tanggal 20 diluar Konsumen Instansi (Kementerian & Lembaga) | C37: =T.UP3!#REF! -> #REF! | D37: =T.UP3!#REF! -> #REF! | F37: =T.UP3!#REF! -> #REF! | G37: =VLOOKUP(B37,T.UP3!$B$4:$T$69,MATCH('PROG. JUNI'!$M$2,T.UP3!$B$5:$T$5,0),FALSE) -> 1175 | H37: 671.68885 | I37: 100 | K37: OK | R37: 2.2 | S37: 2.2 | T37: =R37-S37 -> 0
A38: =T.UP3!#REF! -> #REF! | B38: =T.UP3!#REF! -> #REF! | C38: =T.UP3!C51 -> ñ | D38: =T.UP3!D51 -> Rp. Milyar | E38: =IF(OR(H38="N/A",G38="N/A"),0,T.UP3!F51) -> #REF! | F38: =T.UP3!H51 -> 3.16 | G38: =VLOOKUP(B38,T.UP3!$B$4:$T$69,MATCH('PROG. JUNI'!$M$2,T.UP3!$B$5:$T$5,0),FALSE) -> #REF! | H38: 69 | I38: =IF(OR(G38="N/A",H38="N/A"),"N/A",IF(AND(G38=0,H38=0),0,H38/100*100)) -> #REF! | J38: =ROUNDDOWN(IF(I38="N/A",0,IF(I38>110,E38*110/100,E38*I38/100)),2) -> #REF! | R38: 2.2 | S38: 2.2 | T38: =R38-S38 -> 0
A39: =T.UP3!A47 -> 0 | B39: =T.UP3!B47 -> b. Pencapaian Saldo Rata-Rata Akhir Bulan diluar Konsumen Instansi (Kementerian & Lembaga) | C39: =T.UP3!#REF! -> #REF! | D39: =T.UP3!#REF! -> #REF! | E39: =IF(OR(H39="N/A",G39="N/A"),0,T.UP3!#REF!) -> #REF! | F39: =T.UP3!#REF! -> #REF! | G39: =VLOOKUP(B39,T.UP3!$B$4:$T$69,MATCH('PROG. JUNI'!$M$2,T.UP3!$B$5:$T$5,0),FALSE) -> 286.27 | H39: =VLOOKUP(B39,'R.UP3'!$B$4:$S$54,MATCH('PROG. JUNI'!$M$2,'R.UP3'!$B$5:$S$5,0),FALSE) -> 356.95072 | I39: 110 | J39: =ROUNDDOWN(IF(I39="N/A",0,IF(I39>110,E39*110/100,E39*I39/100)),2) -> #REF! | K39: OK | R39: 2 | S39: 2 | T39: =R39-S39 -> 0
A40: =T.UP3!A48 -> 0 | B40: =T.UP3!B48 -> c. Pencapaian Pelunasan PRR | C40: =T.UP3!C52 -> ñ | D40: =T.UP3!D52 -> Rp. Milyar | E40: =IF(OR(H40="N/A",G40="N/A"),0,T.UP3!F52) -> 0 | F40: =T.UP3!H52 -> 34.29 | G40: =VLOOKUP(B40,T.UP3!$B$4:$T$69,MATCH('PROG. JUNI'!$M$2,T.UP3!$B$5:$T$5,0),FALSE) -> 5.59 | H40: 100 | I40: =IF(OR(G40="N/A",H40="N/A"),"N/A",IF(AND(G40=0,H40=0),0,H40/G40*100)) -> 1788.9088 | J40: =ROUNDDOWN(IF(I40="N/A",0,IF(I40>110,E40*110/100,E40*I40/100)),2) -> 0 | K40: OK
A41: =T.UP3!A49 -> 12 | B41: =T.UP3!B49 -> Pengendalian Anggaran | C41: =T.UP3!C54 -> ñ | D41: =T.UP3!D54 -> % | E41: =IF(OR(H41="N/A",G41="N/A"),0,T.UP3!F54) -> 0 | F41: =T.UP3!H54 -> 100 | G41: 4.05 | H41: 3.3 | I41: =IF(OR(G41="N/A",H41="N/A"),"N/A",IF(AND(G41=0,H41=0),0,H41/G41*100)) -> 81.481481 | J41: =ROUNDDOWN(IF(I41="N/A",0,IF(I41>110,E41*110/100,E41*I41/100)),2) -> 0 | K41: OK | R41: 0 | S41: 0.9 | T41: =R41-S41 -> -0.9
A42: =T.UP3!A50 -> 0 | B42: =T.UP3!B50 -> a. Pengendalian Penggunaan Anggaran Investasi sesuai RKAP | R42: 0 | S42: 1 | T42: =R42-S42 -> -1
A43: =T.UP3!A51 -> 0 | B43: =T.UP3!B51 -> b. Usulan Penghapusan ATTB | C43: =T.UP3!C57 -> ñ | D43: =T.UP3!D57 -> % | E43: 2 | F43: =T.UP3!H57 -> 100 | G43: =VLOOKUP(B43,T.UP3!$B$4:$T$69,MATCH('PROG. JUNI'!$M$2,T.UP3!$B$5:$T$5,0),FALSE) -> 0 | H43: =VLOOKUP(B43,'R.UP3'!$B$4:$S$54,MATCH('PROG. JUNI'!$M$2,'R.UP3'!$B$5:$S$5,0),FALSE) -> 0 | I43: =IF(OR(G43="N/A",H43="N/A"),"N/A",IF(AND(G43=0,H43=0),0,H43/G43*100)) -> 0 | J43: =ROUNDDOWN(IF(I43="N/A",0,IF(I43>110,E43*110/100,E43*I43/100)),2) -> 0 | K43: OK
A44: =T.UP3!A52 -> 0 | B44: =T.UP3!B58 -> Perbaikan Proses Bisnis dan Keberlanjutan | C44: =T.UP3!C58 -> 0 | D44: =T.UP3!D58 -> 0 | E44: 2 | F44: =T.UP3!H58 -> 0 | G44: 100 | H44: 100 | I44: =IF(OR(G44="N/A",H44="N/A"),"N/A",IF(AND(G44=0,H44=0),0,H44/G44*100)) -> 100 | J44: =ROUNDDOWN(IF(I44="N/A",0,IF(I44>110,E44*110/100,E44*I44/100)),2) -> 2 | K44: OK
A45: =T.UP3!A53 -> 13 | B45: =T.UP3!B60 -> b. Maturity Level Gudang
A46: =T.UP3!A54 -> 0 | B46: =T.UP3!B61 -> c. Maturity Level Sustainbility | D46: =T.UP3!D61 -> %
A47: =T.UP3!A55 -> 0 | B47: =T.UP3!B62 -> d. Implementasi Roadmap Perbaikan Penerapan Manajemen Risiko dan Pencapaian Perlakuan Risiko | D47: =T.UP3!D62 -> %
A48: =T.UP3!A56 -> 0 | B48: =T.UP3!B66 -> c. Ketepatan penyampaian pelaporan dan Akurasi Data Kinerja | D48: =T.UP3!D66 -> 0
A49: =T.UP3!A57 -> 0 | B49: =T.UP3!B68 -> e. Pencapaian Beyond RKAP | D49: =T.UP3!D68 -> 0
B50: TOTAL BOBOT | E50: =E7+E16 -> #REF! | J50: =J7+J16 -> #REF! | R50: 98.61 | S50: 103.58
B51: TOTAL BOBOT PROPORSIONAL | E51: 100 | J51: =E51/E50*J50 -> #REF! | R51: 102.71875 | S51: 103.58
A53: TOLITOLI, 08 JUNI 2023

Sheet ULP
A1: AUG | C1: PILIH BULAN LAPORAN
D3: REALISASI KINERJA UNIT TAHUN 2025 | O3: =$D$3 -> REALISASI KINERJA UNIT TAHUN 2025 | Z3: =$D$3 -> REALISASI KINERJA UNIT TAHUN 2025 | AK3: =$D$3 -> REALISASI KINERJA UNIT TAHUN 2025 | AV3: =$D$3 -> REALISASI KINERJA UNIT TAHUN 2025
D4: PT PLN (PERSERO) ULP TOLITOLI | O4: PT PLN (PERSERO) ULP LEOK | Z4: PT PLN (PERSERO) ULP BANGKIR | AK4: PT PLN (PERSERO) ULP MOUTONG | AV4: PT PLN (PERSERO) ULP KOTARAYA
A5: PILIH
C6: NO | D6: KPI UNIT 2023 | F6: SATUAN | G6: BOBOT | H6: TARGET 2025 | I6: =VLOOKUP($A$1,$K$74:$L$85,2,FALSE) -> S.D. AGUSTUS | N6: NO | O6: KPI UNIT 2023 | Q6: SATUAN | R6: BOBOT | S6: TARGET 2025 | T6: =VLOOKUP($A$1,$K$74:$L$85,2,FALSE) -> S.D. AGUSTUS | Y6: NO | Z6: KPI UNIT 2023 | AB6: SATUAN | AC6: BOBOT | AD6: TARGET 2025 | AE6: =VLOOKUP($A$1,$K$74:$L$85,2,FALSE) -> S.D. AGUSTUS | AJ6: NO | AK6: KPI UNIT 2023 | AM6: SATUAN | AN6: BOBOT | AO6: TARGET 2025 | AP6: =VLOOKUP($A$1,$K$74:$L$85,2,FALSE) -> S.D. AGUSTUS | AU6: NO | AV6: KPI UNIT 2023 | AX6: SATUAN | AY6: BOBOT | AZ6: TARGET 2025 | BA6: =VLOOKUP($A$1,$K$74:$L$85,2,FALSE) -> S.D. AGUSTUS
I7: TARGET | J7: REALISASI | K7: PENCAPAIAN | L7: NILAI | T7: TARGET | U7: REALISASI | V7: PENCAPAIAN | W7: NILAI | AE7: TARGET | AF7: REALISASI | AG7: PENCAPAIAN | AH7: NILAI | AP7: TARGET | AQ7: REALISASI | AR7: PENCAPAIAN | AS7: NILAI | BA7: TARGET | BB7: REAL | BC7: PENCAPAIAN | BD7: NILAI
C8: 1 | D8: 2 | F8: 3 | G8: 4 | H8: 5 | I8: 6 | J8: 7 | K8: 8 | L8: 9 | N8: 1 | O8: 2 | Q8: 3 | R8: 4 | S8: 5 | T8: 6 | U8: 7 | V8: 8 | W8: 9 | Y8: 1 | Z8: 2 | AB8: 3 | AC8: 4 | AD8: 5 | AE8: 6 | AF8: 7 | AG8: 8 | AH8: 9 | AJ8: 1 | AK8: 2 | AM8: 3 | AN8: 4 | AO8: 5 | AP8: 6 | AQ8: 7 | AR8: 8 | AS8: 9 | AU8: 1 | AV8: 2 | AX8: 3 | AY8: 4 | AZ8: 5 | BA8: 6 | BB8: 7 | BC8: 8 | BD8: 9
C9: I | D9: =T.TOLIS!$B$7 -> Key Performance Indicators | G9: =SUM(G10:G18) -> 40 | L9: =SUM(L10,L11,L15) -> 41.69 | N9: =$C$9 -> I | O9: =$D$9 -> Key Performance Indicators | R9: =SUM(R10:R18) -> 40 | W9: =SUM(W10,W11,W15) -> 41.04 | Y9: =$C$9 -> I | Z9: =$D$9 -> Key Performance Indicators | AC9: =SUM(AC10:AC18) -> 40 | AH9: =SUM(AH10,AH11,AH15) -> 42.64 | AJ9: =$C$9 -> I | AK9: =$D$9 -> Key Performance Indicators | AN9: =SUM(AN10:AN18) -> 40 | AS9: =SUM(AS10,AS11,AS15) -> 41.63 | AU9: I | AV9: =O9 -> Key Performance Indicators | AY9: =SUM(AY10:AY18) -> 40 | BD9: =SUM(BD10,BD11,BD15) -> 42.88
